Workbook

Sheet Monthly Sales
L1: =SUBTOTAL(9,L4:L18) -> 1 | M1: =SUBTOTAL(9,M4:M18) -> 1 | N1: =1-L1/M1 -> 0 | P1: =SUBTOTAL(9,P4:P20) -> 1 | Q1: =SUBTOTAL(9,Q4:Q20) -> 1 | R1: =1-P1/Q1 -> 0 | T1: =SUBTOTAL(9,T4:T29) -> 376 | U1: =SUBTOTAL(9,U4:U29) -> 450 | V1: =1-T1/U1 -> 0.16444444 | X1: =SUBTOTAL(9,X4:X63) -> 384 | Y1: =SUBTOTAL(9,Y4:Y63) -> 493 | Z1: =1-X1/Y1 -> 0.22109533 | AB1: =SUBTOTAL(9,AB4:AB63) -> 272 | AC1: =SUBTOTAL(9,AC4:AC63) -> 456 | AD1: =1-AB1/AC1 -> 0.40350877 | AF1: =SUBTOTAL(9,AF4:AF76) -> 327 | AG1: =SUBTOTAL(9,AG4:AG76) -> 394 | AH1: =1-AF1/AG1 -> 0.17005076 | AJ1: =SUBTOTAL(9,AJ4:AJ76) -> 639 | AK1: =SUBTOTAL(9,AK4:AK76) -> 781 | AL1: =1-AJ1/AK1 -> 0.18181818 | AN1: =SUBTOTAL(9,AN4:AN76) -> 1272 | AO1: =SUBTOTAL(9,AO4:AO76) -> 1559 | AP1: =1-AN1/AO1 -> 0.18409237 | AR1: =SUBTOTAL(9,AR4:AR76) -> 1640 | AS1: =SUBTOTAL(9,AS4:AS76) -> 1883 | AT1: =1-AR1/AS1 -> 0.12904939 | AV1: =SUBTOTAL(9,AV4:AV76) -> 3295 | AW1: =SUBTOTAL(9,AW4:AW76) -> 3922 | AZ1: =SUBTOTAL(9,AZ4:AZ76) -> 5280 | BA1: =SUBTOTAL(9,BA4:BA76) -> 6213 | BB1: =1-AZ1/BA1 -> 0.150169 | BD1: =SUBTOTAL(9,BD4:BD76) -> 5791 | BE1: =SUBTOTAL(9,BE4:BE76) -> 7417 | BF1: =1-BD1/BE1 -> 0.2192261 | BH1: =SUBTOTAL(9,BH4:BH96) -> 9440 | BI1: =SUBTOTAL(9,BI4:BI96) -> 10654 | BJ1: =1-BH1/BI1 -> 0.11394781 | BK1: =SUBTOTAL(9,BK4:BK96) -> 462097 | BL1: =SUBTOTAL(9,BL4:BL96) -> 6744 | BM1: =SUBTOTAL(9,BM4:BM96) -> 12278407 | BN1: =SUBTOTAL(9,BN4:BN96) -> 5905526.3 | BO1: =SUBTOTAL(9,BO4:BO96) -> 7836 | BP1: =SUBTOTAL(9,BP4:BP96) -> 13703901 | BQ1: =1-BL1/BO1 -> 0.13935681 | BR1: =SUBTOTAL(9,BR4:BR96) -> 1 | BT1: =SUBTOTAL(9,BT4:BT96) -> 22592 | BU1: =SUBTOTAL(9,BU4:BU96) -> 37467 | BV1: =SUBTOTAL(9,BV4:BV96) -> 15648 | BW1: =BT1+BU1+BV1 -> 75707 | BX1: =SUBTOTAL(9,BX4:BX96) -> 63188946 | BY1: =SUBTOTAL(9,BY4:BY96) -> 26150 | BZ1: =SUBTOTAL(9,BZ4:BZ96) -> 28664665 | CA1: =SUBTOTAL(9,CA4:CA96) -> 101857 | CB1: =SUBTOTAL(9,CB4:CB96) -> 91853611 | CG1: =SUBTOTAL(9,CG4:CG96) -> 402043 | CH1: =SUBTOTAL(9,CH4:CH96) -> 5869 | CI1: =SUBTOTAL(9,CI4:CI96) -> 11349955 | CJ1: =SUBTOTAL(9,CJ4:CJ96) -> 5442057.3 | CK1: =SUBTOTAL(9,CK4:CK96) -> 6843 | CL1: =SUBTOTAL(9,CL4:CL96) -> 12719046 | CM1: =1-CH1/CK1 -> 0.14233523 | CN1: =SUBTOTAL(9,CN4:CN96) -> 1 | CP1: =SUBTOTAL(9,CP4:CP96) -> 26111 | CQ1: =SUBTOTAL(9,CQ4:CQ96) -> 42042 | CR1: =SUBTOTAL(9,CR4:CR96) -> 15648 | CS1: =CP1+CQ1+CR1 -> 83801 | CT1: =SUBTOTAL(9,CT4:CT96) -> 72873566 | CU1: =SUBTOTAL(9,CU4:CU96) -> 26150 | CV1: =SUBTOTAL(9,CV4:CV96) -> 28664665 | CW1: =SUBTOTAL(9,CW4:CW96) -> 109951 | CX1: =SUBTOTAL(9,CX4:CX96) -> 1.0153823e+08 | DC1: =SUBTOTAL(9,DC4:DC96) -> 551472 | DD1: =SUBTOTAL(9,DD4:DD96) -> 6889 | DE1: =SUBTOTAL(9,DE4:DE96) -> 12611721 | DF1: =SUBTOTAL(9,DF4:DF96) -> 5998498.8 | DG1: =SUBTOTAL(9,DG4:DG96) -> 8113 | DH1: =SUBTOTAL(9,DH4:DH96) -> 14405977 | DI1: =1-DD1/DG1 -> 0.15086898 | DJ1: =SUBTOTAL(9,DJ4:DJ96) -> 1 | DL1: =SUBTOTAL(9,DL4:DL96) -> 23327 | DM1: =SUBTOTAL(9,DM4:DM96) -> 52543 | DN1: =SUBTOTAL(9,DN4:DN96) -> 15648 | DO1: =DL1+DM1+DN1 -> 91518 | DP1: =SUBTOTAL(9,DP4:DP96) -> 81641762 | DQ1: =SUBTOTAL(9,DQ4:DQ96) -> 26150 | DR1: =SUBTOTAL(9,DR4:DR96) -> 28664665 | DS1: =SUBTOTAL(9,DS4:DS96) -> 117668 | DT1: =SUBTOTAL(9,DT4:DT96) -> 1.1030643e+08 | DY1: =SUBTOTAL(9,DY4:DY96) -> 448589 | DZ1: =SUBTOTAL(9,DZ4:DZ96) -> 4589 | EA1: =SUBTOTAL(9,EA4:EA96) -> 8786637.3 | EB1: =SUBTOTAL(9,EB4:EB96) -> 4099840.1 | EC1: =SUBTOTAL(9,EC4:EC96) -> 5383 | ED1: =SUBTOTAL(9,ED4:ED96) -> 2024841 | EE1: =1-DZ1/EC1 -> 0.14750139 | EF1: =SUBTOTAL(9,EF4:EF96) -> 1 | EH1: =SUBTOTAL(9,EH4:EH96) -> 18351 | EI1: =SUBTOTAL(9,EI4:EI96) -> 59585 | EJ1: =SUBTOTAL(9,EJ4:EJ96) -> 15648 | EK1: =EH1+EI1+EJ1 -> 93584 | EL1: =SUBTOTAL(9,EL4:EL96) -> 84119944 | EM1: =SUBTOTAL(9,EM4:EM96) -> 26150 | EN1: =SUBTOTAL(9,EN4:EN96) -> 28664665 | EO1: =SUBTOTAL(9,EO4:EO96) -> 119734 | EP1: =SUBTOTAL(9,EP4:EP96) -> 1.1278461e+08 | EU1: =SUBTOTAL(9,EU4:EU96) -> 520803 | EV1: =SUBTOTAL(9,EV4:EV96) -> 2896 | EW1: =SUBTOTAL(9,EW4:EW96) -> 6663805.7 | EX1: =SUBTOTAL(9,EX4:EX96) -> 3142093.7 | EY1: =SUBTOTAL(9,EY4:EY96) -> 3554 | EZ1: =SUBTOTAL(9,EZ4:EZ96) -> 1379651 | FA1: =1-EV1/EY1 -> 0.1851435 | FB1: =SUBTOTAL(9,FB4:FB96) -> 1 | FD1: =SUBTOTAL(9,FD4:FD96) -> 13986 | FE1: =SUBTOTAL(9,FE4:FE96) -> 58160 | FF1: =SUBTOTAL(9,FF4:FF96) -> 15648 | FG1: =FD1+FE1+FF1 -> 87794 | FH1: =SUBTOTAL(9,FH4:FH96) -> 77473660 | FI1: =SUBTOTAL(9,FI4:FI96) -> 26150 | FJ1: =SUBTOTAL(9,FJ4:FJ96) -> 28664665 | FK1: =SUBTOTAL(9,FK4:FK96) -> 113944 | FL1: =SUBTOTAL(9,FL4:FL96) -> 1.0613833e+08 | FQ1: =SUBTOTAL(9,FQ4:FQ96) -> 492024 | FV1: =SUBTOTAL(9,FV4:FV96) -> 5068 | FW1: =SUBTOTAL(9,FW4:FW96) -> 9367096 | FX1: =SUBTOTAL(9,FX4:FX96) -> 4530373.1 | FY1: =SUBTOTAL(9,FY4:FY96) -> 1 | GA1: =SUBTOTAL(9,GA4:GA96) -> 4256 | GB1: =SUBTOTAL(9,GB4:GB96) -> 54221 | GC1: =SUBTOTAL(9,GC4:GC96) -> 15648 | GD1: =GA1+GB1+GC1 -> 74125 | GE1: =SUBTOTAL(9,GE4:GE96) -> 67007188 | GF1: =SUBTOTAL(9,GF4:GF96) -> 26150 | GG1: =SUBTOTAL(9,GG4:GG96) -> 28664665 | GH1: =SUBTOTAL(9,GH4:GH96) -> 100275 | GI1: =SUBTOTAL(9,GI4:GI96) -> 95671853 | GN1: =SUBTOTAL(9,GN4:GN96) -> 457793 | GS1: =SUBTOTAL(9,GS4:GS96) -> 5017 | GT1: =SUBTOTAL(9,GT4:GT96) -> 9464370.1 | GU1: =SUBTOTAL(9,GU4:GU96) -> 4573113.8 | GV1: =SUBTOTAL(9,GV4:GV96) -> 1 | GX1: =SUBTOTAL(9,GX4:GX96) -> 9285 | GY1: =SUBTOTAL(9,GY4:GY96) -> 50578 | GZ1: =SUBTOTAL(9,GZ4:GZ96) -> 15648 | HA1: =GX1+GY1+GZ1 -> 75511 | HB1: =SUBTOTAL(9,HB4:HB96) -> 68989445 | HC1: =SUBTOTAL(9,HC4:HC96) -> 26150 | HD1: =SUBTOTAL(9,HD4:HD96) -> 28664665 | HE1: =SUBTOTAL(9,HE4:HE96) -> 101661 | HF1: =SUBTOTAL(9,HF4:HF96) -> 97654110 | HK1: =SUBTOTAL(9,HK4:HK118) -> 557516 | HP1: =SUBTOTAL(9,HP4:HP118) -> 5112 | HQ1: =SUBTOTAL(9,HQ4:HQ118) -> 10951496 | HR1: =SUBTOTAL(9,HR4:HR118) -> 5248434.8 | HS1: =SUBTOTAL(9,HS4:HS118) -> 1 | HU1: =SUBTOTAL(9,HU4:HU118) -> 13334 | HV1: =SUBTOTAL(9,HV4:HV118) -> 44532 | HW1: =SUBTOTAL(9,HW4:HW118) -> 15648 | HX1: =HU1+HV1+HW1 -> 73514 | HY1: =SUBTOTAL(9,HY4:HY118) -> 69516329 | HZ1: =SUBTOTAL(9,HZ4:HZ118) -> 26150 | IA1: =SUBTOTAL(9,IA4:IA118) -> 28664665 | IB1: =SUBTOTAL(9,IB4:IB118) -> 95105 | IC1: =SUBTOTAL(9,IC4:IC118) -> 98180994 | IH1: =SUBTOTAL(9,IH4:IH118) -> 540913 | II1: =SUBTOTAL(9,II4:II222) -> 3890 | IJ1: =SUBTOTAL(9,IJ4:IJ222) -> 9290801.4 | IK1: =SUBTOTAL(9,IK4:IK222) -> 1491 | IL1: =SUBTOTAL(9,IL4:IL222) -> 2047482.8 | IM1: =SUBTOTAL(9,IM4:IM222) -> 5381 | IN1: =SUBTOTAL(9,IN4:IN222) -> 11338284 | IO1: =SUBTOTAL(9,IO4:IO222) -> 5377810.2 | IP1: =SUBTOTAL(9,IP4:IP222) -> 1 | IR1: =SUBTOTAL(9,IR4:IR118) -> 26926 | IS1: =SUBTOTAL(9,IS4:IS118) -> 47576 | IT1: =SUBTOTAL(9,IT4:IT118) -> 15648 | IU1: =IR1+IS1+IT1 -> 90150 | IV1: =SUBTOTAL(9,IV4:IV118) -> 86416412 | IW1: =SUBTOTAL(9,IW4:IW118) -> 26150 | IX1: =SUBTOTAL(9,IX4:IX118) -> 28664665 | IY1: =SUBTOTAL(9,IY4:IY118) -> 110697 | IZ1: =SUBTOTAL(9,IZ4:IZ118) -> 1.1508108e+08 | JE1: =SUBTOTAL(9,JE4:JE121) -> 527871 | JF1: =SUBTOTAL(9,JF4:JF222) -> 3181 | JG1: =SUBTOTAL(9,JG4:JG222) -> 7626892.6 | JH1: =SUBTOTAL(9,JH4:JH222) -> 963 | JI1: =SUBTOTAL(9,JI4:JI222) -> 1414888 | JJ1: =SUBTOTAL(9,JJ4:JJ222) -> 4144 | JK1: =SUBTOTAL(9,JK4:JK222) -> 9041780.6 | JL1: =SUBTOTAL(9,JL4:JL222) -> 4246671.4 | JM1: =SUBTOTAL(9,JM4:JM222) -> 1 | JO1: =SUBTOTAL(9,JO4:JO118) -> 26926 | JP1: =SUBTOTAL(9,JP4:JP118) -> 47576 | JQ1: =SUBTOTAL(9,JQ4:JQ118) -> 15648 | JR1: =JO1+JP1+JQ1 -> 90150 | JS1: =SUBTOTAL(9,JS4:JS118) -> 361230 | JT1: =SUBTOTAL(9,JT4:JT118) -> 26150 | JU1: =SUBTOTAL(9,JU4:JU118) -> 372000 | JV1: =SUBTOTAL(9,JV4:JV118) -> 110697 | JW1: =SUBTOTAL(9,JW4:JW118) -> 733230 | KB1: =SUBTOTAL(9,KB4:KB121) -> 800146 | KC1: =SUBTOTAL(9,KC4:KC222) -> 4408 | KD1: =SUBTOTAL(9,KD4:KD222) -> 11052673 | KE1: =SUBTOTAL(9,KE4:KE222) -> 475 | KF1: =SUBTOTAL(9,KF4:KF222) -> 747624.35 | KG1: =SUBTOTAL(9,KG4:KG222) -> 4883 | KH1: =SUBTOTAL(9,KH4:KH222) -> 11800298 | KI1: =SUBTOTAL(9,KI4:KI222) -> 5508667.7 | KJ1: =SUBTOTAL(9,KJ4:KJ222) -> 1 | KL1: =SUBTOTAL(9,KL4:KL118) -> 26926 | KM1: =SUBTOTAL(9,KM4:KM118) -> 47576 | KN1: =SUBTOTAL(9,KN4:KN118) -> 15648 | KO1: =KL1+KM1+KN1 -> 90150 | KP1: =SUBTOTAL(9,KP4:KP118) -> 8936142 | KQ1: =SUBTOTAL(9,KQ4:KQ118) -> 26150 | KR1: =SUBTOTAL(9,KR4:KR118) -> 5950438 | KS1: =SUBTOTAL(9,KS4:KS118) -> 110697 | KT1: =SUBTOTAL(9,KT4:KT118) -> 14886580 | KY1: =SUBTOTAL(9,KY4:KY121) -> 666302 | KZ1: =SUBTOTAL(9,KZ4:KZ222) -> 5338 | LA1: =SUBTOTAL(9,LA4:LA222) -> 13164314 | LB1: =SUBTOTAL(9,LB4:LB222) -> 198 | LC1: =SUBTOTAL(9,LC4:LC222) -> 282761.19 | LD1: =SUBTOTAL(9,LD4:LD222) -> 5536 | LE1: =SUBTOTAL(9,LE4:LE222) -> 13447076 | LF1: =SUBTOTAL(9,LF4:LF222) -> 6474650.8 | LG1: =SUBTOTAL(9,LG4:LG222) -> 1 | LI1: =SUBTOTAL(9,LI4:LI118) -> 26926 | LJ1: =SUBTOTAL(9,LJ4:LJ118) -> 47576 | LK1: =SUBTOTAL(9,LK4:LK118) -> 15648 | LL1: =LI1+LJ1+LK1 -> 90150 | LM1: =SUBTOTAL(9,LM4:LM118) -> 147398063 | LN1: =SUBTOTAL(9,LN4:LN118) -> 26150 | LO1: =SUBTOTAL(9,LO4:LO118) -> 94087948 | LP1: =SUBTOTAL(9,LP4:LP118) -> 110697 | LQ1: =SUBTOTAL(9,LQ4:LQ118) -> 241486011 | LV1: =SUBTOTAL(9,LV4:LV125) -> 1585414 | LW1: =SUBTOTAL(9,LW4:LW222) -> 3960 | LX1: =SUBTOTAL(9,LX4:LX222) -> 9409199.3 | LY1: =SUBTOTAL(9,LY4:LY222) -> 159 | LZ1: =SUBTOTAL(9,LZ4:LZ222) -> 176692.81 | MA1: =SUBTOTAL(9,MA4:MA222) -> 3973 | MB1: =SUBTOTAL(9,MB4:MB222) -> 9486413.4 | MC1: =SUBTOTAL(9,MC4:MC222) -> 4336977.2 | MD1: =SUBTOTAL(9,MD4:MD222) -> 1 | MF1: =SUBTOTAL(9,MF4:MF118) -> 26926 | MG1: =SUBTOTAL(9,MG4:MG118) -> 47576 | MH1: =SUBTOTAL(9,MH4:MH118) -> 15648 | MI1: =MF1+MG1+MH1 -> 90150 | MJ1: =SUBTOTAL(9,MJ4:MJ118) -> 1.6799388e+11 | MK1: =SUBTOTAL(9,MK4:MK118) -> 26150 | ML1: =SUBTOTAL(9,ML4:ML118) -> 1.0419171e+11 | MM1: =SUBTOTAL(9,MM4:MM118) -> 110697 | MN1: =SUBTOTAL(9,MN4:MN118) -> 2.7218559e+11 | MS1: =SUBTOTAL(9,MS4:MS146) -> 1467707 | MT1: =SUBTOTAL(9,MT4:MT222) -> 5672 | MU1: =SUBTOTAL(9,MU4:MU222) -> 12443129 | MV1: =SUBTOTAL(9,MV4:MV222) -> 93 | MW1: =SUBTOTAL(9,MW4:MW222) -> 111229.69 | MX1: =SUBTOTAL(9,MX4:MX222) -> 5765 | MY1: =SUBTOTAL(9,MY4:MY222) -> 12554359 | MZ1: =SUBTOTAL(9,MZ4:MZ222) -> 6016751.5 | NA1: =SUBTOTAL(9,NA4:NA222) -> 1 | NC1: =SUBTOTAL(9,NC4:NC118) -> 26926 | ND1: =SUBTOTAL(9,ND4:ND118) -> 47576 | NE1: =SUBTOTAL(9,NE4:NE118) -> 15648 | NF1: =NC1+ND1+NE1 -> 90150 | NG1: =SUBTOTAL(9,NG4:NG118) -> #VALUE! | NH1: =SUBTOTAL(9,NH4:NH118) -> 26150 | NI1: =SUBTOTAL(9,NI4:NI118) -> #VALUE! | NJ1: =SUBTOTAL(9,NJ4:NJ118) -> 110697 | NK1: =SUBTOTAL(9,NK4:NK118) -> #VALUE! | NP1: =SUBTOTAL(9,NP4:NP146) -> 1137447 | NQ1: =SUBTOTAL(9,NQ4:NQ222) -> 4953 | NR1: =SUBTOTAL(9,NR4:NR222) -> 9617223.4 | NS1: =SUBTOTAL(9,NS4:NS222) -> 10 | NT1: =SUBTOTAL(9,NT4:NT222) -> 9226.28 | NU1: =SUBTOTAL(9,NU4:NU222) -> 4963 | NV1: =SUBTOTAL(9,NV4:NV222) -> 9626449.7 | NW1: =SUBTOTAL(9,NW4:NW222) -> 4759220.8 | NX1: =SUBTOTAL(9,NX4:NX222) -> 1 | NZ1: =SUBTOTAL(9,NZ4:NZ118) -> 26926 | OA1: =SUBTOTAL(9,OA4:OA118) -> 47576 | OB1: =SUBTOTAL(9,OB4:OB118) -> 15648 | OC1: =NZ1+OA1+OB1 -> 90150 | OD1: =SUBTOTAL(9,OD4:OD118) -> #VALUE! | OE1: =SUBTOTAL(9,OE4:OE118) -> 26150 | OF1: =SUBTOTAL(9,OF4:OF118) -> #VALUE! | OG1: =SUBTOTAL(9,OG4:OG118) -> 110697 | OH1: =SUBTOTAL(9,OH4:OH118) -> #VALUE!
K2: 45200 | O2: 45231 | S2: Dec-23(1-31st) | W2: Jan-24(1-30th) | AA2: Feb-24(1-29th) | AE2: March-24(1-30th) | AI2: April-24(1-30th) | AM2: May-24(1-31st) | AQ2: June-24 (1-30th) | AU2: July-24 (1-31st) | AY2: Aug-24 (1-31st) | BC2: Sept-24 (1-30th) | BG2: Oct-24 (1-31st) | BK2: Nov-24 (1-30th) | BT2: 02nd Dec | BU2: 02nd Dec | BV2: 28th Nov | BY2: 28th Nov | CG2: Dec-24 (1-31st) | CP2: 19th Dec | CQ2: 19th Dec | CR2: 28th Nov | CU2: 28th Nov | DC2: Jan - 25 (1-31st) | DL2: 19th Dec | DM2: 19th Dec | DN2: 28th Nov | DQ2: 28th Nov | DY2: Feb - 25 (1-28th) | EU2: Mar - 25 (1-31st) | FQ2: Apr - 25 (1-30th) | GN2: May - 25 (1-31st) | HK2: June - 25 (1-30th) | IH2: July - 25 (1-31st) | JE2: Aug - 25 (1-31st) | KB2: Sept - 25 (1-30th) | KY2: Oct - 25 (1-31st) | LV2: Nov - 25 (1-30th) | MS2: Dec - 25 (1-31st) | NP2: Jan - 26 (1-31st)
A3: FBA SKU | B3: Model | C3: SKU | D3: Category | E3: Main Category | F3: Brand | G3: ASIN | H3: Description | I3: DP | J3: NLC | K3: Sessions | L3: Net Units | M3: Gross Units | N3: Ops to Net Cancellation % | O3: Sessions | P3: Net Units | Q3: Gross Units | R3: Gross to Net Cancellation % | S3: Sessions | T3: Net Units | U3: Gross Units | V3: Gross to Net Cancellation % | W3: Sessions | X3: Net Units | Y3: Gross Units | Z3: Gross to Net Cancellation % | AA3: Sessions | AB3: Net Units | AC3: Gross Units | AD3: Gross to Net Cancellation % | AE3: Sessions | AF3: Net Units | AG3: Gross Units | AH3: Gross to Net Cancellation % | AI3: Sessions | AJ3: Net Units | AK3: Gross Units | AL3: Gross to Net Cancellation % | AM3: Sessions | AN3: Net Units | AO3: Gross Units | AP3: Gross to Net Cancellation % | AQ3: Sessions | AR3: Net Units | AS3: Gross Units | AT3: Gross to Net Cancellation % | AU3: Sessions | AV3: Net Units | AW3: Gross Units | AX3: Gross to Net Cancellation % | AY3: Sessions | AZ3: Net Units | BA3: Gross Units | BB3: Gross to Net Cancellation % | BC3: Sessions | BD3: Net Units | BE3: Gross Units | BF3: Gross to Net Cancellation % | BG3: Sessions | BH3: Net Units | BI3: Gross Units | BJ3: Gross to Net Cancellation % | BK3: Sessions | BL3: Net Units Sold | BM3: Net Units Value at SP | BN3: Net Units Value at NLC | BO3: Gross Units Sold | BP3: Gross Units Value | BQ3: Gross to Net Cancellation % | BR3: Contribution to sales | BS3: Model no | BT3: Current Amazon Inventory | BU3: AMPM Inventory | BV3: Pipeline Inventory | BW3: Total Inventory (Amazon+AMPM+Pipeline) | BX3: Total Inventory (Amazon+AMPM+Pipeline) Value | BY3: Open Order | BZ3: Open Order Value | CA3: Total SOH | CB3: Total SOH Value at NLC | CC3: Model | CD3: =C3 -> SKU | CE3: ASIN | CF3: Model | CG3: Sessions | CH3: Net Units Sold | CI3: Net Units Value at SP | CJ3: Net Units Value at NLC | CK3: Gross Units Sold | CL3: Gross Units Value | CM3: Gross to Net Cancellation % | CN3: Contribution to sales | CO3: Model no | CP3: Current Amazon Inventory | CQ3: AMPM Inventory | CR3: Pipeline Inventory | CS3: Total Inventory (Amazon+AMPM+Pipeline) | CT3: Total Inventory (Amazon+AMPM+Pipeline) Value | CU3: Open Order | CV3: Open Order Value | CW3: Total SOH | CX3: Total SOH Value at NLC | CY3: Model | CZ3: =C3 -> SKU | DA3: ASIN | DB3: Model | DC3: Sessions | DD3: Net Units Sold | DE3: Net Units Value at SP | DF3: Net Units Value at NLC | DG3: Gross Units Sold | DH3: Gross Units Value | DI3: Gross to Net Cancellation % | DJ3: Contribution to sales | DK3: Model no | DL3: Current Amazon Inventory | DM3: AMPM Inventory | DN3: Pipeline Inventory | DO3: Total Inventory (Amazon+AMPM+Pipeline) | DP3: Total Inventory (Amazon+AMPM+Pipeline) Value | DQ3: Open Order | DR3: Open Order Value | DS3: Total SOH | DT3: Total SOH Value at NLC | DU3: Model | DV3: SKU | DW3: ASIN | DX3: Model | DY3: Sessions | DZ3: Net Units Sold | EA3: Net Units Value at SP | EB3: Net Units Value at NLC | EC3: Gross Units Sold | ED3: Gross Units Value | EE3: Gross to Net Cancellation % | EF3: Contribution to sales | EG3: Model no | EH3: Current Amazon Inventory | EI3: AMPM Inventory | EJ3: Pipeline Inventory | EK3: Total Inventory (Amazon+AMPM+Pipeline) | EL3: Total Inventory (Amazon+AMPM+Pipeline) Value | EM3: Open Order | EN3: Open Order Value | EO3: Total SOH | EP3: Total SOH Value at NLC | EQ3: Model | ER3: SKU | ES3: ASIN | ET3: Model | EU3: Sessions | EV3: Net Units Sold | EW3: Net Units Value at SP | EX3: Net Units Value at NLC | EY3: Gross Units Sold | EZ3: Gross Units Value | FA3: Gross to Net Cancellation % | FB3: Contribution to sales | FC3: Model no | FD3: Current Amazon Inventory | FE3: AMPM Inventory | FF3: Pipeline Inventory | FG3: Total Inventory (Amazon+AMPM+Pipeline) | FH3: Total Inventory (Amazon+AMPM+Pipeline) Value | FI3: Open Order | FJ3: Open Order Value | FK3: Total SOH | FL3: Total SOH Value at NLC | FM3: Model | FN3: SKU | FO3: ASIN | FP3: Model | FQ3: Sessions | FR3: Amazon Sales Unit | FS3: Amazon Sales Value | FT3: EB Sales Units | FU3: EB Sales Value | FV3: Net Units Sold | FW3: Net Units Value at SP | FX3: Net Units Value at NLC | FY3: Contribution to sales | FZ3: Model no | GA3: Current Amazon Inventory | GB3: AMPM Inventory | GC3: Pipeline Inventory | GD3: Total Inventory (Amazon+AMPM+Pipeline) | GE3: Total Inventory (Amazon+AMPM+Pipeline) Value | GF3: Open Order | GG3: Open Order Value | GH3: Total SOH | GI3: Total SOH Value at NLC | GJ3: Model | GK3: SKU | GL3: ASIN | GM3: Model | GN3: Sessions | GO3: Amazon Sales Unit | GP3: Amazon Sales Value | GQ3: EB Sales Units | GR3: EB Sales Value | GS3: Net Units Sold | GT3: Net Units Value at SP | GU3: Net Units Value at NLC | GV3: Contribution to sales | GW3: Model no | GX3: Current Amazon Inventory | GY3: AMPM Inventory | GZ3: Pipeline Inventory | HA3: Total Inventory (Amazon+AMPM+Pipeline) | HB3: Total Inventory (Amazon+AMPM+Pipeline) Value | HC3: Open Order | HD3: Open Order Value | HE3: Total SOH | HF3: Total SOH Value at NLC | HG3: Model | HH3: SKU | HI3: ASIN | HJ3: Model | HK3: Sessions | HL3: Amazon Sales Unit | HM3: Amazon Sales Value | HN3: EB Sales Units | HO3: EB Sales Value | HP3: Net Units Sold | HQ3: Net Units Value at SP | HR3: Net Units Value at NLC | HS3: Contribution to sales | HT3: Model no | HU3: Current Amazon Inventory | HV3: AMPM Inventory | HW3: Pipeline Inventory | HX3: Total Inventory (Amazon+AMPM+Pipeline) | HY3: Total Inventory (Amazon+AMPM+Pipeline) Value | HZ3: Open Order | IA3: Open Order Value | IB3: Total SOH | IC3: Total SOH Value at NLC | ID3: Model | IE3: SKU | IF3: ASIN | IG3: Model | IH3: Sessions | II3: Amazon Sales Unit | IJ3: Amazon Sales Value | IK3: EB Sales Units | IL3: EB Sales Value | IM3: Net Units Sold | IN3: Net Units Value at SP | IO3: Net Units Value at NLC | IP3: Contribution to sales | IQ3: Model no | IR3: Current Amazon Inventory | IS3: AMPM Inventory | IT3: Pipeline Inventory | IU3: Total Inventory (Amazon+AMPM+Pipeline) | IV3: Total Inventory (Amazon+AMPM+Pipeline) Value | IW3: Open Order | IX3: Open Order Value | IY3: Total SOH | IZ3: Total SOH Value at NLC | JA3: Model | JB3: SKU | JC3: ASIN | JD3: Model | JE3: Sessions | JF3: Amazon Sales Unit | JG3: Amazon Sales Value | JH3: EB Sales Units | JI3: EB Sales Value | JJ3: Net Units Sold | JK3: Net Units Value at SP | JL3: Net Units Value at NLC | JM3: Contribution to sales | JN3: Model no | JO3: Current Amazon Inventory | JP3: AMPM Inventory | JQ3: Pipeline Inventory | JR3: Total Inventory (Amazon+AMPM+Pipeline) | JS3: Total Inventory (Amazon+AMPM+Pipeline) Value | JT3: Open Order | JU3: Open Order Value | JV3: Total SOH | JW3: Total SOH Value at NLC | JX3: Model | JY3: SKU | JZ3: ASIN | KA3: Model | KB3: Sessions | KC3: Amazon Sales Unit | KD3: Amazon Sales Value | KE3: EB Sales Units | KF3: EB Sales Value | KG3: Net Units Sold | KH3: Net Units Value at SP | KI3: Net Units Value at NLC | KJ3: Contribution to sales | KK3: Model no | KL3: Current Amazon Inventory | KM3: AMPM Inventory | KN3: Pipeline Inventory | KO3: Total Inventory (Amazon+AMPM+Pipeline) | KP3: Total Inventory (Amazon+AMPM+Pipeline) Value | KQ3: Open Order | KR3: Open Order Value | KS3: Total SOH | KT3: Total SOH Value at NLC | KU3: Model | KV3: SKU | KW3: ASIN | KX3: Model | KY3: Sessions | KZ3: Amazon Sales Unit | LA3: Amazon Sales Value | LB3: EB Sales Units | LC3: EB Sales Value | LD3: Net Units Sold | LE3: Net Units Value at SP | LF3: Net Units Value at NLC | LG3: Contribution to sales | LH3: Model no | LI3: Current Amazon Inventory | LJ3: AMPM Inventory | LK3: Pipeline Inventory | LL3: Total Inventory (Amazon+AMPM+Pipeline) | LM3: Total Inventory (Amazon+AMPM+Pipeline) Value | LN3: Open Order | LO3: Open Order Value | LP3: Total SOH | LQ3: Total SOH Value at NLC | LR3: Model | LS3: SKU | LT3: ASIN | LU3: Model | LV3: Sessions | LW3: Amazon Sales Unit | LX3: Amazon Sales Value | LY3: EB Sales Units | LZ3: EB Sales Value | MA3: Net Units Sold | MB3: Net Units Value at SP | MC3: Net Units Value at NLC | MD3: Contribution to sales | ME3: Model no | MF3: Current Amazon Inventory | MG3: AMPM Inventory | MH3: Pipeline Inventory | MI3: Total Inventory (Amazon+AMPM+Pipeline) | MJ3: Total Inventory (Amazon+AMPM+Pipeline) Value | MK3: Open Order | ML3: Open Order Value | MM3: Total SOH | MN3: Total SOH Value at NLC | MO3: Model | MP3: SKU | MQ3: ASIN | MR3: Model | MS3: Sessions | MT3: Amazon Sales Unit | MU3: Amazon Sales Value | MV3: EB Sales Units | MW3: EB Sales Value | MX3: Net Units Sold | MY3: Net Units Value at SP | MZ3: Net Units Value at NLC | NA3: Contribution to sales | NB3: Model no | NC3: Current Amazon Inventory | ND3: AMPM Inventory | NE3: Pipeline Inventory | NF3: Total Inventory (Amazon+AMPM+Pipeline) | NG3: Total Inventory (Amazon+AMPM+Pipeline) Value | NH3: Open Order | NI3: Open Order Value | NJ3: Total SOH | NK3: Total SOH Value at NLC | NL3: Model | NM3: SKU | NN3: ASIN | NO3: Model | NP3: Sessions | NQ3: Amazon Sales Unit | NR3: Amazon Sales Value | NS3: EB Sales Units | NT3: EB Sales Value | NU3: Net Units Sold | NV3: Net Units Value at SP | NW3: Net Units Value at NLC | NX3: Contribution to sales | NY3: Model no | NZ3: Current Amazon Inventory | OA3: AMPM Inventory | OB3: Pipeline Inventory | OC3: Total Inventory (Amazon+AMPM+Pipeline) | OD3: Total Inventory (Amazon+AMPM+Pipeline) Value | OE3: Open Order | OF3: Open Order Value | OG3: Total SOH | OH3: Total SOH Value at NLC | OI3: Model | OJ3: SKU | OK3: ASIN | OL3: Model
A4: FBA79262 | B4: SC-02 | C4: FBA79262 | D4: Home & Kitchen | E4: Cleaning & Vacumming | F4: Nexlev | G4: B0CYSMBCB8 | H4: Nexlev Steam Cleaner | I4: 1088.3211 | J4: 1284.2189 | K4: 0 | L4: 0 | M4: 0 | N4: =1-L4/M4 -> #DIV/0! | O4: 0 | P4: 0 | Q4: 0 | R4: =1-P4/Q4 -> #DIV/0! | S4: 0 | T4: 0 | U4: 0 | V4: =1-T4/U4 -> #DIV/0! | W4: 0 | X4: 0 | Y4: 0 | Z4: =1-X4/Y4 -> #DIV/0! | AA4: 0 | AB4: 0 | AC4: 0 | AD4: =1-AB4/AC4 -> #DIV/0! | AE4: 0 | AF4: 0 | AG4: 0 | AH4: =1-AF4/AG4 -> #DIV/0! | AI4: 3385 | AJ4: 15 | AK4: 29 | AL4: =1-AJ4/AK4 -> 0.48275862 | AM4: 27847 | AN4: 367 | AO4: 486 | AP4: =1-AN4/AO4 -> 0.24485597 | AQ4: 31212 | AR4: 306 | AS4: 362 | AT4: =1-AR4/AS4 -> 0.15469613 | AU4: 30179 | AV4: 294 | AW4: 349 | AX4: =1-AV4/AW4 -> 0.15759312 | AY4: 44123 | AZ4: 306 | BA4: 371 | BB4: =1-AZ4/BA4 -> 0.17520216 | BC4: 25535 | BD4: 286 | BE4: 393 | BF4: =1-BD4/BE4 -> 0.27226463 | BG4: 91824 | BH4: 1086 | BI4: 1345 | BJ4: =1-BH4/BI4 -> 0.19256506 | BK4: 62353 | BL4: 652 | BM4: 1853003 | BN4: =BL4*J4 -> 837310.74 | BO4: 833 | BP4: 2069171 | BQ4: =1-BL4/BO4 -> 0.21728691 | BR4: =BM4/$BM$1 -> 0.15091559 | BS4: =B4 -> SC-02 | BT4: 870 | BU4: 1691 | BV4: 0 | BW4: =BT4+BU4+BV4 -> 2561 | BX4: =BW4*J4 -> 3288884.7 | BY4: 3000 | BZ4: =BY4*J4 -> 3852656.8 | CA4: =BW4+BY4 -> 5561 | CB4: =BX4+BZ4 -> 7141541.5 | CC4: =B4 -> SC-02 | CD4: =C4 -> FBA79262 | CE4: =G4 -> B0CYSMBCB8 | CF4: =B4 -> SC-02 | CG4: 26982 | CH4: 338 | CI4: 911996.11 | CJ4: =CH4*J4 -> 434066 | CK4: 402 | CL4: 979531 | CM4: =1-CH4/CK4 -> 0.15920398 | CN4: =CI4/$CI$1 -> 0.080352397 | CO4: =B4 -> SC-02 | CP4: 1099 | CQ4: 1164 | CR4: 0 | CS4: =CP4+CQ4+CR4 -> 2263 | CT4: =CS4*J4 -> 2906187.4 | CU4: 3000 | CV4: =CU4*J4 -> 3852656.8 | CW4: =CS4+CU4 -> 5263 | CX4: =CT4+CV4 -> 6758844.2 | CY4: =B4 -> SC-02 | CZ4: =C4 -> FBA79262 | DA4: =G4 -> B0CYSMBCB8 | DB4: =B4 -> SC-02 | DC4: 28319 | DD4: 275 | DE4: 737395.51 | DF4: =DD4*J4 -> 353160.21 | DG4: 336 | DH4: 851483 | DI4: =1-DD4/DG4 -> 0.18154762 | DJ4: =DE4/$DE$1 -> 0.058469064 | DK4: =B4 -> SC-02 | DL4: 893 | DM4: 1057 | DN4: 0 | DO4: =DL4+DM4+DN4 -> 1950 | DP4: =DO4*J4 -> 2504226.9 | DQ4: 3000 | DR4: =DQ4*J4 -> 3852656.8 | DS4: =DO4+DQ4 -> 4950 | DT4: =DP4+DR4 -> 6356883.7 | DU4: =B4 -> SC-02 | DV4: =C4 -> FBA79262 | DW4: =G4 -> B0CYSMBCB8 | DX4: =B4 -> SC-02 | DY4: 13255 | DZ4: 138 | EA4: 364807.16 | EB4: =DZ4*J4 -> 177222.21 | EC4: 169 | ED4: 4,08,945.00 | EE4: =1-DZ4/EC4 -> 0.18343195 | EF4: =EA4/$EA$1 -> 0.041518404 | EG4: =B4 -> SC-02 | EH4: 658 | EI4: 992 | EJ4: 0 | EK4: =EH4+EI4+EJ4 -> 1650 | EL4: =EK4*J4 -> 2118961.2 | EM4: 3000 | EN4: =EM4*J4 -> 3852656.8 | EO4: =EK4+EM4 -> 4650 | EP4: =EL4+EN4 -> 5971618 | EQ4: =B4 -> SC-02 | ER4: =C4 -> FBA79262 | ES4: =G4 -> B0CYSMBCB8 | ET4: =B4 -> SC-02 | EU4: 20601 | EV4: 120 | EW4: 300059 | EX4: =EV4*J4 -> 154106.27 | EY4: 149 | EZ4: 3,22,499 | FA4: =1-EV4/EY4 -> 0.19463087 | FB4: =EW4/$EW$1 -> 0.045028174 | FC4: =B4 -> SC-02 | FD4: 526 | FE4: 837 | FF4: 0 | FG4: =FD4+FE4+FF4 -> 1363 | FH4: =FG4*J4 -> 1750390.4 | FI4: 3000 | FJ4: =FI4*J4 -> 3852656.8 | FK4: =FG4+FI4 -> 4363 | FL4: =FH4+FJ4 -> 5603047.2 | FM4: =B4 -> SC-02 | FN4: =C4 -> FBA79262 | FO4: =G4 -> B0CYSMBCB8 | FP4: =B4 -> SC-02 | FQ4: 25575 | FR4: 128 | FS4: 304792 | FT4: 0 | FU4: 0 | FV4: =FR4+FT4 -> 128 | FW4: =FS4+FU4 -> 304792 | FX4: =FV4*J4 -> 164380.02 | FY4: =FW4/$FW$1 -> 0.03253858 | FZ4: =B4 -> SC-02 | GA4: 0 | GB4: 775 | GC4: 0 | GD4: =GA4+GB4+GC4 -> 775 | GE4: =GD4*J4 -> 995269.67 | GF4: 3000 | GG4: =GF4*J4 -> 3852656.8 | GH4: =GD4+GF4 -> 3775 | GI4: =GE4+GG4 -> 4847926.5 | GJ4: =B4 -> SC-02 | GK4: =C4 -> FBA79262 | GL4: =G4 -> B0CYSMBCB8 | GM4: =B4 -> SC-02 | GN4: 30592 | GO4: 155 | GP4: 366411 | GQ4: 0 | GR4: 0 | GS4: =GO4+GQ4 -> 155 | GT4: =GP4+GR4 -> 366411 | GU4: =GS4*J4 -> 199053.93 | GV4: =GT4/$GT$1 -> 0.038714779 | GW4: =B4 -> SC-02 | GX4: 239 | GY4: 771 | GZ4: 0 | HA4: =GX4+GY4+GZ4 -> 1010 | HB4: =HA4*J4 -> 1297061.1 | HC4: 3000 | HD4: =HC4*J4 -> 3852656.8 | HE4: =HA4+HC4 -> 4010 | HF4: =HB4+HD4 -> 5149717.9 | HG4: =B4 -> SC-02 | HH4: =C4 -> FBA79262 | HI4: =G4 -> B0CYSMBCB8 | HJ4: =B4 -> SC-02 | HK4: 23433 | HL4: 163 | HM4: 395912 | HN4: 0 | HO4: 0 | HP4: =HL4+HN4 -> 163 | HQ4: =HM4+HO4 -> 395912 | HR4: =HP4*J4 -> 209327.69 | HS4: =HQ4/$HQ$1 -> 0.036151409 | HT4: =B4 -> SC-02 | HU4: 571 | HV4: 162 | HW4: 0 | HX4: =HU4+HV4+HW4 -> 733 | HY4: =HX4*J4 -> 941332.48 | HZ4: 3000 | IA4: =HZ4*J4 -> 3852656.8 | IB4: =HX4+HZ4 -> 3733 | IC4: =HY4+IA4 -> 4793989.3 | ID4: =B4 -> SC-02 | IE4: =C4 -> FBA79262 | IF4: =G4 -> B0CYSMBCB8 | IG4: =B4 -> SC-02 | IH4: 9913 | II4: 148 | IJ4: 356074.7 | IK4: 0 | IL4: 0 | IM4: =II4+IK4 -> 148 | IN4: =IJ4+IL4 -> 356074.7 | IO4: =IM4*J4 -> 190064.4 | IP4: =IN4/$IN$1 -> 0.031404637 | IQ4: =B4 -> SC-02 | IR4: 694 | IS4: 75 | IT4: 0 | IU4: =IR4+IS4+IT4 -> 769 | IV4: =IU4*J4 -> 987564.36 | IW4: 3000 | IX4: =IW4*J4 -> 3852656.8 | IY4: =IU4+IW4 -> 3769 | IZ4: =IV4+IX4 -> 4840221.2 | JA4: =B4 -> SC-02 | JB4: =C4 -> FBA79262 | JC4: =G4 -> B0CYSMBCB8 | JD4: =B4 -> SC-02 | JE4: 29846 | JF4: 117 | JG4: 280182.04 | JH4: 0 | JI4: 0 | JJ4: =JF4+JH4 -> 117 | JK4: =JG4+JI4 -> 280182.04 | JL4: =JJ4*J4 -> 150253.62 | JM4: =JK4/$JK$1 -> 0.030987485 | JN4: =B4 -> SC-02 | JO4: 694 | JP4: 75 | JQ4: 0 | JR4: =JO4+JP4+JQ4 -> 769 | JS4: =JR4*AG4 -> 0 | JT4: 3000 | JU4: =JT4*AG4 -> 0 | JV4: =JR4+JT4 -> 3769 | JW4: =JS4+JU4 -> 0 | JX4: =B4 -> SC-02 | JY4: =C4 -> FBA79262 | JZ4: =G4 -> B0CYSMBCB8 | KA4: =B4 -> SC-02 | KB4: 13951 | KC4: 160 | KD4: 376393.12 | KE4: 0 | KF4: 0 | KG4: =KC4+KE4 -> 160 | KH4: =KD4+KF4 -> 376393.12 | KI4: =KG4*J4 -> 205475.03 | KJ4: =KH4/$KH$1 -> 0.031896917 | KK4: =B4 -> SC-02 | KL4: 694 | KM4: 75 | KN4: 0 | KO4: =KL4+KM4+KN4 -> 769 | KP4: =KO4*BD4 -> 219934 | KQ4: 3000 | KR4: =KQ4*BD4 -> 858000 | KS4: =KO4+KQ4 -> 3769 | KT4: =KP4+KR4 -> 1077934 | KU4: =B4 -> SC-02 | KV4: =C4 -> FBA79262 | KW4: =G4 -> B0CYSMBCB8 | KX4: =B4 -> SC-02 | KY4: 17904 | KZ4: 267 | LA4: 624729.36 | LB4: 0 | LC4: 0 | LD4: =KZ4+LB4 -> 267 | LE4: =LA4+LC4 -> 624729.36 | LF4: =LD4*J4 -> 342886.46 | LG4: =LE4/$LE$1 -> 0.046458381 | LH4: =B4 -> SC-02 | LI4: 694 | LJ4: 75 | LK4: 0 | LL4: =LI4+LJ4+LK4 -> 769 | LM4: =LL4*CA4 -> 4276409 | LN4: 3000 | LO4: =LN4*CA4 -> 16683000 | LP4: =LL4+LN4 -> 3769 | LQ4: =LM4+LO4 -> 20959409 | LR4: =B4 -> SC-02 | LS4: =C4 -> FBA79262 | LT4: =G4 -> B0CYSMBCB8 | LU4: =B4 -> SC-02 | LV4: 9617 | LW4: 31 | LX4: 81841.26 | LY4: 0 | LZ4: 0 | MA4: =LW4+LY4 -> 31 | MB4: =LX4+LZ4 -> 81841.26 | MC4: =MA4*J4 -> 39810.787 | MD4: =MB4/$MB$1 -> 0.0086272078 | ME4: =B4 -> SC-02 | MF4: 694 | MG4: 75 | MH4: 0 | MI4: =MF4+MG4+MH4 -> 769 | MJ4: =MI4*CX4 -> 5.1975512e+09 | MK4: 3000 | ML4: =MK4*CX4 -> 2.0276533e+10 | MM4: =MI4+MK4 -> 3769 | MN4: =MJ4+ML4 -> 2.5474084e+10 | MO4: =B4 -> SC-02 | MP4: =C4 -> FBA79262 | MQ4: =G4 -> B0CYSMBCB8 | MR4: =B4 -> SC-02 | MS4: 10790 | MT4: 69 | MU4: 148161.62 | MV4: 0 | MW4: 0 | MX4: =MT4+MV4 -> 69 | MY4: =MU4+MW4 -> 148161.62 | MZ4: =MX4*J4 -> 88611.106 | NA4: =MY4/$MY$1 -> 0.011801608 | NB4: =B4 -> SC-02 | NC4: 694 | ND4: 75 | NE4: 0 | NF4: =NC4+ND4+NE4 -> 769 | NG4: =NF4*DU4 -> #VALUE! | NH4: 3000 | NI4: =NH4*DU4 -> #VALUE! | NJ4: =NF4+NH4 -> 3769 | NK4: =NG4+NI4 -> #VALUE! | NL4: =B4 -> SC-02 | NM4: =C4 -> FBA79262 | NN4: =G4 -> B0CYSMBCB8 | NO4: =B4 -> SC-02 | NP4: 1841 | NQ4: 29 | NR4: 62289.4 | NS4: 0 | NT4: 0 | NU4: =NQ4+NS4 -> 29 | NV4: =NR4+NT4 -> 62289.4 | NW4: =NU4*J4 -> 37242.349 | NX4: =NV4/$NV$1 -> 0.0064706514 | NY4: =B4 -> SC-02 | NZ4: 694 | OA4: 75 | OB4: 0 | OC4: =NZ4+OA4+OB4 -> 769 | OD4: =OC4*ER4 -> #VALUE! | OE4: 3000 | OF4: =OE4*ER4 -> #VALUE! | OG4: =OC4+OE4 -> 3769 | OH4: =OD4+OF4 -> #VALUE! | OI4: =B4 -> SC-02 | OJ4: =C4 -> FBA79262 | OK4: =G4 -> B0CYSMBCB8 | OL4: =B4 -> SC-02
A5: FBA79263 | B5: MR-01 | C5: FBA79263 | D5: Home & Kitchen | E5: Cleaning & Vacumming | F5: Nexlev | G5: B0CYSLCRQS | H5: Nexlev Dust Mite UV | I5: 908.87355 | J5: 1072.4708 | K5: 0 | L5: 0 | M5: 0 | N5: =1-L5/M5 -> #DIV/0! | O5: 0 | P5: 0 | Q5: 0 | R5: =1-P5/Q5 -> #DIV/0! | S5: 0 | T5: 0 | U5: 0 | V5: =1-T5/U5 -> #DIV/0! | W5: 0 | X5: 0 | Y5: 0 | Z5: =1-X5/Y5 -> #DIV/0! | AA5: 0 | AB5: 0 | AC5: 0 | AD5: =1-AB5/AC5 -> #DIV/0! | AE5: 0 | AF5: 0 | AG5: 0 | AH5: =1-AF5/AG5 -> #DIV/0! | AI5: 8884 | AJ5: 7 | AK5: 18 | AL5: =1-AJ5/AK5 -> 0.61111111 | AM5: 17432 | AN5: 262 | AO5: 302 | AP5: =1-AN5/AO5 -> 0.13245033 | AQ5: 16574 | AR5: 350 | AS5: 385 | AT5: =1-AR5/AS5 -> 0.090909091 | AU5: 25278 | AV5: 476 | AW5: 531 | AX5: =1-AV5/AW5 -> 0.10357815 | AY5: 32573 | AZ5: 550 | BA5: 434 | BB5: =1-AZ5/BA5 -> -0.26728111 | BC5: 77021 | BD5: 519 | BE5: 651 | BF5: =1-BD5/BE5 -> 0.20276498 | BG5: 112340 | BH5: 1116 | BI5: 1266 | BJ5: =1-BH5/BI5 -> 0.11848341 | BK5: 62354 | BL5: 331 | BM5: 1154626 | BN5: =BL5*J5 -> 354987.83 | BO5: 385 | BP5: 1248208 | BQ5: =1-BL5/BO5 -> 0.14025974 | BR5: =BM5/$BM$1 -> 0.094037117 | BS5: =B5 -> MR-01 | BT5: 1000 | BU5: 1680 | BV5: 0 | BW5: =BT5+BU5+BV5 -> 2680 | BX5: =BW5*J5 -> 2874221.7 | BY5: 3130 | BZ5: =BY5*J5 -> 3356833.6 | CA5: =BW5+BY5 -> 5810 | CB5: =BX5+BZ5 -> 6231055.3 | CC5: =B5 -> MR-01 | CD5: =C5 -> FBA79263 | CE5: =G5 -> B0CYSLCRQS | CF5: =B5 -> MR-01 | CG5: 37362 | CH5: 462 | CI5: 1409678.7 | CJ5: =CH5*J5 -> 495481.5 | CK5: 532 | CL5: 1513843 | CM5: =1-CH5/CK5 -> 0.13157895 | CN5: =CI5/$CI$1 -> 0.12420126 | CO5: =B5 -> MR-01 | CP5: 1017 | CQ5: 1191 | CR5: 0 | CS5: =CP5+CQ5+CR5 -> 2208 | CT5: =CS5*J5 -> 2368015.5 | CU5: 3130 | CV5: =CU5*J5 -> 3356833.6 | CW5: =CS5+CU5 -> 5338 | CX5: =CT5+CV5 -> 5724849.1 | CY5: =B5 -> MR-01 | CZ5: =C5 -> FBA79263 | DA5: =G5 -> B0CYSLCRQS | DB5: =B5 -> MR-01 | DC5: 47410 | DD5: 351 | DE5: 1047736.7 | DF5: =DD5*J5 -> 376437.25 | DG5: 420 | DH5: 1165980 | DI5: =1-DD5/DG5 -> 0.16428571 | DJ5: =DE5/$DE$1 -> 0.083076424 | DK5: =B5 -> MR-01 | DL5: 1283 | DM5: 3388 | DN5: 0 | DO5: =DL5+DM5+DN5 -> 4671 | DP5: =DO5*J5 -> 5009511.1 | DQ5: 3130 | DR5: =DQ5*J5 -> 3356833.6 | DS5: =DO5+DQ5 -> 7801 | DT5: =DP5+DR5 -> 8366344.6 | DU5: =B5 -> MR-01 | DV5: =C5 -> FBA79263 | DW5: =G5 -> B0CYSLCRQS | DX5: =B5 -> MR-01 | DY5: 57506 | DZ5: 210 | EA5: 626706 | EB5: =DZ5*J5 -> 225218.87 | EC5: 242 | ED5: 6,83,020.00 | EE5: =1-DZ5/EC5 -> 0.1322314 | EF5: =EA5/$EA$1 -> 0.071324897 | EG5: =B5 -> MR-01 | EH5: 1041 | EI5: 1743 | EJ5: 0 | EK5: =EH5+EI5+EJ5 -> 2784 | EL5: =EK5*J5 -> 2985758.7 | EM5: 3130 | EN5: =EM5*J5 -> 3356833.6 | EO5: =EK5+EM5 -> 5914 | EP5: =EL5+EN5 -> 6342592.2 | EQ5: =B5 -> MR-01 | ER5: =C5 -> FBA79263 | ES5: =G5 -> B0CYSLCRQS | ET5: =B5 -> MR-01 | EU5: 45013 | EV5: 163 | EW5: 482445 | EX5: =EV5*J5 -> 174812.74 | EY5: 198 | EZ5: 5,19,097 | FA5: =1-EV5/EY5 -> 0.17676768 | FB5: =EW5/$EW$1 -> 0.072397819 | FC5: =B5 -> MR-01 | FD5: 894 | FE5: 3002 | FF5: 0 | FG5: =FD5+FE5+FF5 -> 3896 | FH5: =FG5*J5 -> 4178346.2 | FI5: 3130 | FJ5: =FI5*J5 -> 3356833.6 | FK5: =FG5+FI5 -> 7026 | FL5: =FH5+FJ5 -> 7535179.8 | FM5: =B5 -> MR-01 | FN5: =C5 -> FBA79263 | FO5: =G5 -> B0CYSLCRQS | FP5: =B5 -> MR-01 | FQ5: 36377 | FR5: 243 | FS5: 693251 | FT5: 0 | FU5: 0 | FV5: =FR5+FT5 -> 243 | FW5: =FS5+FU5 -> 693251 | FX5: =FV5*J5 -> 260610.4 | FY5: =FW5/$FW$1 -> 0.07400917 | FZ5: =B5 -> MR-01 | GA5: 0 | GB5: 2827 | GC5: 0 | GD5: =GA5+GB5+GC5 -> 2827 | GE5: =GD5*J5 -> 3031874.9 | GF5: 3130 | GG5: =GF5*J5 -> 3356833.6 | GH5: =GD5+GF5 -> 5957 | GI5: =GE5+GG5 -> 6388708.5 | GJ5: =B5 -> MR-01 | GK5: =C5 -> FBA79263 | GL5: =G5 -> B0CYSLCRQS | GM5: =B5 -> MR-01 | GN5: 52917 | GO5: 271 | GP5: 777402 | GQ5: 0 | GR5: 0 | GS5: =GO5+GQ5 -> 271 | GT5: =GP5+GR5 -> 777402 | GU5: =GS5*J5 -> 290639.58 | GV5: =GT5/$GT$1 -> 0.082139856 | GW5: =B5 -> MR-01 | GX5: 417 | GY5: 2707 | GZ5: 0 | HA5: =GX5+GY5+GZ5 -> 3124 | HB5: =HA5*J5 -> 3350398.7 | HC5: 3130 | HD5: =HC5*J5 -> 3356833.6 | HE5: =HA5+HC5 -> 6254 | HF5: =HB5+HD5 -> 6707232.3 | HG5: =B5 -> MR-01 | HH5: =C5 -> FBA79263 | HI5: =G5 -> B0CYSLCRQS | HJ5: =B5 -> MR-01 | HK5: 31808 | HL5: 227 | HM5: 650447 | HN5: 0 | HO5: 0 | HP5: =HL5+HN5 -> 227 | HQ5: =HM5+HO5 -> 650447 | HR5: =HP5*J5 -> 243450.87 | HS5: =HQ5/$HQ$1 -> 0.059393439 | HT5: =B5 -> MR-01 | HU5: 392 | HV5: 2548 | HW5: 0 | HX5: =HU5+HV5+HW5 -> 2940 | HY5: =HX5*J5 -> 3153064.1 | HZ5: 3130 | IA5: =HZ5*J5 -> 3356833.6 | IB5: =HX5+HZ5 -> 6070 | IC5: =HY5+IA5 -> 6509897.7 | ID5: =B5 -> MR-01 | IE5: =C5 -> FBA79263 | IF5: =G5 -> B0CYSLCRQS | IG5: =B5 -> MR-01 | IH5: 57544 | II5: 267 | IJ5: 762248.02 | IK5: 0 | IL5: 0 | IM5: =II5+IK5 -> 267 | IN5: =IJ5+IL5 -> 762248.02 | IO5: =IM5*J5 -> 286349.7 | IP5: =IN5/$IN$1 -> 0.06722781 | IQ5: =B5 -> MR-01 | IR5: 772 | IS5: 2101 | IT5: 0 | IU5: =IR5+IS5+IT5 -> 2873 | IV5: =IU5*J5 -> 3081208.6 | IW5: 3130 | IX5: =IW5*J5 -> 3356833.6 | IY5: =IU5+IW5 -> 6003 | IZ5: =IV5+IX5 -> 6438042.1 | JA5: =B5 -> MR-01 | JB5: =C5 -> FBA79263 | JC5: =G5 -> B0CYSLCRQS | JD5: =B5 -> MR-01 | JE5: 58494 | JF5: 239 | JG5: 690999.26 | JH5: 0 | JI5: 0 | JJ5: =JF5+JH5 -> 239 | JK5: =JG5+JI5 -> 690999.26 | JL5: =JJ5*J5 -> 256320.52 | JM5: =JK5/$JK$1 -> 0.076422918 | JN5: =B5 -> MR-01 | JO5: 772 | JP5: 2101 | JQ5: 0 | JR5: =JO5+JP5+JQ5 -> 2873 | JS5: =JR5*AG5 -> 0 | JT5: 3130 | JU5: =JT5*AG5 -> 0 | JV5: =JR5+JT5 -> 6003 | JW5: =JS5+JU5 -> 0 | JX5: =B5 -> MR-01 | JY5: =C5 -> FBA79263 | JZ5: =G5 -> B0CYSLCRQS | KA5: =B5 -> MR-01 | KB5: 297966 | KC5: 519 | KD5: 1461641.5 | KE5: 0 | KF5: 0 | KG5: =KC5+KE5 -> 519 | KH5: =KD5+KF5 -> 1461641.5 | KI5: =KG5*J5 -> 556612.34 | KJ5: =KH5/$KH$1 -> 0.12386479 | KK5: =B5 -> MR-01 | KL5: 772 | KM5: 2101 | KN5: 0 | KO5: =KL5+KM5+KN5 -> 2873 | KP5: =KO5*BD5 -> 1491087 | KQ5: 3130 | KR5: =KQ5*BD5 -> 1624470 | KS5: =KO5+KQ5 -> 6003 | KT5: =KP5+KR5 -> 3115557 | KU5: =B5 -> MR-01 | KV5: =C5 -> FBA79263 | KW5: =G5 -> B0CYSLCRQS | KX5: =B5 -> MR-01 | KY5: 197065 | KZ5: 656 | LA5: 1807157.4 | LB5: 0 | LC5: 0 | LD5: =KZ5+LB5 -> 656 | LE5: =LA5+LC5 -> 1807157.4 | LF5: =LD5*J5 -> 703540.84 | LG5: =LE5/$LE$1 -> 0.13439036 | LH5: =B5 -> MR-01 | LI5: 772 | LJ5: 2101 | LK5: 0 | LL5: =LI5+LJ5+LK5 -> 2873 | LM5: =LL5*CA5 -> 16692130 | LN5: 3130 | LO5: =LN5*CA5 -> 18185300 | LP5: =LL5+LN5 -> 6003 | LQ5: =LM5+LO5 -> 34877430 | LR5: =B5 -> MR-01 | LS5: =C5 -> FBA79263 | LT5: =G5 -> B0CYSLCRQS | LU5: =B5 -> MR-01 | LV5: 482976 | LW5: 278 | LX5: 802320.94 | LY5: 0 | LZ5: 0 | MA5: =LW5+LY5 -> 278 | MB5: =LX5+LZ5 -> 802320.94 | MC5: =MA5*J5 -> 298146.88 | MD5: =MB5/$MB$1 -> 0.084575793 | ME5: =B5 -> MR-01 | MF5: 772 | MG5: 2101 | MH5: 0 | MI5: =MF5+MG5+MH5 -> 2873 | MJ5: =MI5*CX5 -> 1.6447491e+10 | MK5: 3130 | ML5: =MK5*CX5 -> 1.7918778e+10 | MM5: =MI5+MK5 -> 6003 | MN5: =MJ5+ML5 -> 3.4366269e+10 | MO5: =B5 -> MR-01 | MP5: =C5 -> FBA79263 | MQ5: =G5 -> B0CYSLCRQS | MR5: =B5 -> MR-01 | MS5: 486322 | MT5: 225 | MU5: 619000 | MV5: 0 | MW5: 0 | MX5: =MT5+MV5 -> 225 | MY5: =MU5+MW5 -> 619000 | MZ5: =MX5*J5 -> 241305.93 | NA5: =MY5/$MY$1 -> 0.049305583 | NB5: =B5 -> MR-01 | NC5: 772 | ND5: 2101 | NE5: 0 | NF5: =NC5+ND5+NE5 -> 2873 | NG5: =NF5*DU5 -> #VALUE! | NH5: 3130 | NI5: =NH5*DU5 -> #VALUE! | NJ5: =NF5+NH5 -> 6003 | NK5: =NG5+NI5 -> #VALUE! | NL5: =B5 -> MR-01 | NM5: =C5 -> FBA79263 | NN5: =G5 -> B0CYSLCRQS | NO5: =Y5 -> 0 | NP5: 454966 | NQ5: 275 | NR5: 699828 | NS5: 0 | NT5: 0 | NU5: =NQ5+NS5 -> 275 | NV5: =NR5+NT5 -> 699828 | NW5: =NU5*J5 -> 294929.47 | NX5: =NV5/$NV$1 -> 0.072698453 | NY5: =B5 -> MR-01 | NZ5: 772 | OA5: 2101 | OB5: 0 | OC5: =NZ5+OA5+OB5 -> 2873 | OD5: =OC5*ER5 -> #VALUE! | OE5: 3130 | OF5: =OE5*ER5 -> #VALUE! | OG5: =OC5+OE5 -> 6003 | OH5: =OD5+OF5 -> #VALUE! | OI5: =B5 -> MR-01 | OJ5: =C5 -> FBA79263 | OK5: =G5 -> B0CYSLCRQS | OL5: =B5 -> MR-01
A6: FBA79452 | B6: VC-01 | C6: FBA79452 | D6: Home & Kitchen | E6: Cleaning & Vacumming | F6: Nexlev | G6: B0DCGHVN81 | H6: Nexlev Handheld Vacuum Cleaner | I6: 832.33683 | J6: 982.15746 | K6: 0 | L6: 0 | M6: 0 | N6: =1-L6/M6 -> #DIV/0! | O6: 0 | P6: 0 | Q6: 0 | R6: =1-P6/Q6 -> #DIV/0! | S6: 0 | T6: 0 | U6: 0 | V6: =1-T6/U6 -> #DIV/0! | W6: 0 | X6: 0 | Y6: 0 | Z6: =1-X6/Y6 -> #DIV/0! | AA6: 0 | AB6: 0 | AC6: 0 | AD6: =1-AB6/AC6 -> #DIV/0! | AE6: 0 | AF6: 0 | AG6: 0 | AH6: =1-AF6/AG6 -> #DIV/0! | AI6: 0 | AJ6: 0 | AK6: 0 | AL6: =1-AJ6/AK6 -> #DIV/0! | AM6: 0 | AN6: 0 | AO6: 0 | AP6: =1-AN6/AO6 -> #DIV/0! | AQ6: 0 | AR6: 0 | AS6: 0 | AT6: =1-AR6/AS6 -> #DIV/0! | AU6: 0 | AV6: 0 | AW6: 0 | AX6: =1-AV6/AW6 -> #DIV/0! | AY6: 0 | AZ6: 0 | BA6: 0 | BB6: =1-AZ6/BA6 -> #DIV/0! | BC6: 9002 | BD6: 65 | BE6: 94 | BF6: =1-BD6/BE6 -> 0.30851064 | BG6: 24619 | BH6: 319 | BI6: 384 | BJ6: =1-BH6/BI6 -> 0.16927083 | BK6: 22634 | BL6: 493 | BM6: 1037136 | BN6: =BL6*J6 -> 484203.63 | BO6: 533 | BP6: 1067228 | BQ6: =1-BL6/BO6 -> 0.075046904 | BR6: =BM6/$BM$1 -> 0.084468286 | BS6: =B6 -> VC-01 | BT6: 6 | BU6: 1 | BV6: 0 | BW6: =BT6+BU6+BV6 -> 7 | BX6: =BW6*J6 -> 6875.1022 | BY6: 2004 | BZ6: =BY6*J6 -> 1968243.5 | CA6: =BW6+BY6 -> 2011 | CB6: =BX6+BZ6 -> 1975118.7 | CC6: =B6 -> VC-01 | CD6: =C6 -> FBA79452 | CE6: =G6 -> B0DCGHVN81 | CF6: =B6 -> VC-01 | CG6: 135 | CH6: 7 | CI6: 15393 | CJ6: =CH6*J6 -> 6875.1022 | CK6: 5 | CL6: 10995 | CM6: =1-CH6/CK6 -> -0.4 | CN6: =CI6/$CI$1 -> 0.0013562168 | CO6: =B6 -> VC-01 | CP6: 1206 | CQ6: 3 | CR6: 0 | CS6: =CP6+CQ6+CR6 -> 1209 | CT6: =CS6*J6 -> 1187428.4 | CU6: 2004 | CV6: =CU6*J6 -> 1968243.5 | CW6: =CS6+CU6 -> 3213 | CX6: =CT6+CV6 -> 3155671.9 | CY6: =B6 -> VC-01 | CZ6: =C6 -> FBA79452 | DA6: =G6 -> B0DCGHVN81 | DB6: =B6 -> VC-01 | DC6: 11523 | DD6: 76 | DE6: 157582 | DF6: =DD6*J6 -> 74643.967 | DG6: 90 | DH6: 173741 | DI6: =1-DD6/DG6 -> 0.15555556 | DJ6: =DE6/$DE$1 -> 0.012494885 | DK6: =B6 -> VC-01 | DL6: 345 | DM6: 1570 | DN6: 0 | DO6: =DL6+DM6+DN6 -> 1915 | DP6: =DO6*J6 -> 1880831.5 | DQ6: 2004 | DR6: =DQ6*J6 -> 1968243.5 | DS6: =DO6+DQ6 -> 3919 | DT6: =DP6+DR6 -> 3849075.1 | DU6: =B6 -> VC-01 | DV6: =C6 -> FBA79452 | DW6: =G6 -> B0DCGHVN81 | DX6: =B6 -> VC-01 | DY6: 14778 | DZ6: 108 | EA6: 225050 | EB6: =DZ6*J6 -> 106073.01 | EC6: 149 | ED6: 2,66,182.00 | EE6: =1-DZ6/EC6 -> 0.27516779 | EF6: =EA6/$EA$1 -> 0.025612756 | EG6: =B6 -> VC-01 | EH6: 414 | EI6: 1375 | EJ6: 0 | EK6: =EH6+EI6+EJ6 -> 1789 | EL6: =EK6*J6 -> 1757079.7 | EM6: 2004 | EN6: =EM6*J6 -> 1968243.5 | EO6: =EK6+EM6 -> 3793 | EP6: =EL6+EN6 -> 3725323.2 | EQ6: =B6 -> VC-01 | ER6: =C6 -> FBA79452 | ES6: =G6 -> B0DCGHVN81 | ET6: =B6 -> VC-01 | EU6: 20648 | EV6: 140 | EW6: 280479.58 | EX6: =EV6*J6 -> 137502.04 | EY6: 170 | EZ6: 3,01,863 | FA6: =1-EV6/EY6 -> 0.17647059 | FB6: =EW6/$EW$1 -> 0.04209 | FC6: =B6 -> VC-01 | FD6: 246 | FE6: 1297 | FF6: 0 | FG6: =FD6+FE6+FF6 -> 1543 | FH6: =FG6*J6 -> 1515469 | FI6: 2004 | FJ6: =FI6*J6 -> 1968243.5 | FK6: =FG6+FI6 -> 3547 | FL6: =FH6+FJ6 -> 3483712.5 | FM6: =B6 -> VC-01 | FN6: =C6 -> FBA79452 | FO6: =G6 -> B0DCGHVN81 | FP6: =B6 -> VC-01 | FQ6: 18612 | FR6: 145 | FS6: 261090 | FT6: 0 | FU6: 0 | FV6: =FR6+FT6 -> 145 | FW6: =FS6+FU6 -> 261090 | FX6: =FV6*J6 -> 142412.83 | FY6: =FW6/$FW$1 -> 0.027873099 | FZ6: =B6 -> VC-01 | GA6: 0 | GB6: 1015 | GC6: 0 | GD6: =GA6+GB6+GC6 -> 1015 | GE6: =GD6*J6 -> 996889.82 | GF6: 2004 | GG6: =GF6*J6 -> 1968243.5 | GH6: =GD6+GF6 -> 3019 | GI6: =GE6+GG6 -> 2965133.4 | GJ6: =B6 -> VC-01 | GK6: =C6 -> FBA79452 | GL6: =G6 -> B0DCGHVN81 | GM6: =B6 -> VC-01 | GN6: 25662 | GO6: 277 | GP6: 513101.58 | GQ6: 0 | GR6: 0 | GS6: =GO6+GQ6 -> 277 | GT6: =GP6+GR6 -> 513101.58 | GU6: =GS6*J6 -> 272057.62 | GV6: =GT6/$GT$1 -> 0.054214023 | GW6: =B6 -> VC-01 | GX6: 463 | GY6: 118 | GZ6: 0 | HA6: =GX6+GY6+GZ6 -> 581 | HB6: =HA6*J6 -> 570633.48 | HC6: 2004 | HD6: =HC6*J6 -> 1968243.5 | HE6: =HA6+HC6 -> 2585 | HF6: =HB6+HD6 -> 2538877 | HG6: =B6 -> VC-01 | HH6: =C6 -> FBA79452 | HI6: =G6 -> B0DCGHVN81 | HJ6: =B6 -> VC-01 | HK6: 23567 | HL6: 205 | HM6: 409043 | HN6: 0 | HO6: 0 | HP6: =HL6+HN6 -> 205 | HQ6: =HM6+HO6 -> 409043 | HR6: =HP6*J6 -> 201342.28 | HS6: =HQ6/$HQ$1 -> 0.037350423 | HT6: =B6 -> VC-01 | HU6: 475 | HV6: 1404 | HW6: 0 | HX6: =HU6+HV6+HW6 -> 1879 | HY6: =HX6*J6 -> 1845473.9 | HZ6: 2004 | IA6: =HZ6*J6 -> 1968243.5 | IB6: =HX6+HZ6 -> 3883 | IC6: =HY6+IA6 -> 3813717.4 | ID6: =B6 -> VC-01 | IE6: =C6 -> FBA79452 | IF6: =G6 -> B0DCGHVN81 | IG6: =B6 -> VC-01 | IH6: 19726 | II6: 195 | IJ6: 383503.77 | IK6: 0 | IL6: 0 | IM6: =II6+IK6 -> 195 | IN6: =IJ6+IL6 -> 383503.77 | IO6: =IM6*J6 -> 191520.7 | IP6: =IN6/$IN$1 -> 0.033823792 | IQ6: =B6 -> VC-01 | IR6: 601 | IS6: 1270 | IT6: 0 | IU6: =IR6+IS6+IT6 -> 1871 | IV6: =IU6*J6 -> 1837616.6 | IW6: 2004 | IX6: =IW6*J6 -> 1968243.5 | IY6: =IU6+IW6 -> 3875 | IZ6: =IV6+IX6 -> 3805860.2 | JA6: =B6 -> VC-01 | JB6: =C6 -> FBA79452 | JC6: =G6 -> B0DCGHVN81 | JD6: =B6 -> VC-01 | JE6: 19816 | JF6: 106 | JG6: 210160.3 | JH6: 0 | JI6: 0 | JJ6: =JF6+JH6 -> 106 | JK6: =JG6+JI6 -> 210160.3 | JL6: =JJ6*J6 -> 104108.69 | JM6: =JK6/$JK$1 -> 0.023243243 | JN6: =B6 -> VC-01 | JO6: 601 | JP6: 1270 | JQ6: 0 | JR6: =JO6+JP6+JQ6 -> 1871 | JS6: =JR6*AG6 -> 0 | JT6: 2004 | JU6: =JT6*AG6 -> 0 | JV6: =JR6+JT6 -> 3875 | JW6: =JS6+JU6 -> 0 | JX6: =B6 -> VC-01 | JY6: =C6 -> FBA79452 | JZ6: =G6 -> B0DCGHVN81 | KA6: =B6 -> VC-01 | KB6: 32376 | KC6: 164 | KD6: 318413.02 | KE6: 0 | KF6: 0 | KG6: =KC6+KE6 -> 164 | KH6: =KD6+KF6 -> 318413.02 | KI6: =KG6*J6 -> 161073.82 | KJ6: =KH6/$KH$1 -> 0.026983473 | KK6: =B6 -> VC-01 | KL6: 601 | KM6: 1270 | KN6: 0 | KO6: =KL6+KM6+KN6 -> 1871 | KP6: =KO6*BD6 -> 121615 | KQ6: 2004 | KR6: =KQ6*BD6 -> 130260 | KS6: =KO6+KQ6 -> 3875 | KT6: =KP6+KR6 -> 251875 | KU6: =B6 -> VC-01 | KV6: =C6 -> FBA79452 | KW6: =G6 -> B0DCGHVN81 | KX6: =B6 -> VC-01 | KY6: 25198 | KZ6: 250 | LA6: 478149.44 | LB6: 0 | LC6: 0 | LD6: =KZ6+LB6 -> 250 | LE6: =LA6+LC6 -> 478149.44 | LF6: =LD6*J6 -> 245539.36 | LG6: =LE6/$LE$1 -> 0.035557875 | LH6: =B6 -> VC-01 | LI6: 601 | LJ6: 1270 | LK6: 0 | LL6: =LI6+LJ6+LK6 -> 1871 | LM6: =LL6*CA6 -> 3762581 | LN6: 2004 | LO6: =LN6*CA6 -> 4030044 | LP6: =LL6+LN6 -> 3875 | LQ6: =LM6+LO6 -> 7792625 | LR6: =B6 -> VC-01 | LS6: =C6 -> FBA79452 | LT6: =G6 -> B0DCGHVN81 | LU6: =B6 -> VC-01 | LV6: 36838 | LW6: 99 | LX6: 196467.15 | LY6: 0 | LZ6: 0 | MA6: =LW6+LY6 -> 99 | MB6: =LX6+LZ6 -> 196467.15 | MC6: =MA6*J6 -> 97233.588 | MD6: =MB6/$MB$1 -> 0.020710372 | ME6: =B6 -> VC-01 | MF6: 601 | MG6: 1270 | MH6: 0 | MI6: =MF6+MG6+MH6 -> 1871 | MJ6: =MI6*CX6 -> 5.9042622e+09 | MK6: 2004 | ML6: =MK6*CX6 -> 6.3239665e+09 | MM6: =MI6+MK6 -> 3875 | MN6: =MJ6+ML6 -> 1.2228229e+10 | MO6: =B6 -> VC-01 | MP6: =C6 -> FBA79452 | MQ6: =G6 -> B0DCGHVN81 | MR6: =B6 -> VC-01 | MS6: 26737 | MT6: 173 | MU6: 322713 | MV6: 0 | MW6: 0 | MX6: =MT6+MV6 -> 173 | MY6: =MU6+MW6 -> 322713 | MZ6: =MX6*J6 -> 169913.24 | NA6: =MY6/$MY$1 -> 0.025705255 | NB6: =B6 -> VC-01 | NC6: 601 | ND6: 1270 | NE6: 0 | NF6: =NC6+ND6+NE6 -> 1871 | NG6: =NF6*DU6 -> #VALUE! | NH6: 2004 | NI6: =NH6*DU6 -> #VALUE! | NJ6: =NF6+NH6 -> 3875 | NK6: =NG6+NI6 -> #VALUE! | NL6: =B6 -> VC-01 | NM6: =C6 -> FBA79452 | NN6: =G6 -> B0DCGHVN81 | NO6: =Y6 -> 0 | NP6: 28712 | NQ6: 193 | NR6: 337698 | NS6: 0 | NT6: 0 | NU6: =NQ6+NS6 -> 193 | NV6: =NR6+NT6 -> 337698 | NW6: =NU6*J6 -> 189556.39 | NX6: =NV6/$NV$1 -> 0.035080223 | NY6: =B6 -> VC-01 | NZ6: 601 | OA6: 1270 | OB6: 0 | OC6: =NZ6+OA6+OB6 -> 1871 | OD6: =OC6*ER6 -> #VALUE! | OE6: 2004 | OF6: =OE6*ER6 -> #VALUE! | OG6: =OC6+OE6 -> 3875 | OH6: =OD6+OF6 -> #VALUE! | OI6: =B6 -> VC-01 | OJ6: =C6 -> FBA79452 | OK6: =G6 -> B0DCGHVN81 | OL6: =B6 -> VC-01
A7: FBA79439 | B7: MR-02 | C7: FBA79439 | D7: Home & Kitchen | E7: Cleaning & Vacumming | F7: Nexlev | G7: B0DCK7ZH5P | H7: Nexlev Cordless Mite Remover | I7: 999.7609 | J7: 1179.7179 | K7: 0 | L7: 0 | M7: 0 | N7: =1-L7/M7 -> #DIV/0! | O7: 0 | P7: 0 | Q7: 0 | R7: =1-P7/Q7 -> #DIV/0! | S7: 0 | T7: 0 | U7: 0 | V7: =1-T7/U7 -> #DIV/0! | W7: 0 | X7: 0 | Y7: 0 | Z7: =1-X7/Y7 -> #DIV/0! | AA7: 0 | AB7: 0 | AC7: 0 | AD7: =1-AB7/AC7 -> #DIV/0! | AE7: 0 | AF7: 0 | AG7: 0 | AH7: =1-AF7/AG7 -> #DIV/0! | AI7: 0 | AJ7: 0 | AK7: 0 | AL7: =1-AJ7/AK7 -> #DIV/0! | AM7: 0 | AN7: 0 | AO7: 0 | AP7: =1-AN7/AO7 -> #DIV/0! | AQ7: 0 | AR7: 0 | AS7: 0 | AT7: =1-AR7/AS7 -> #DIV/0! | AU7: 0 | AV7: 0 | AW7: 0 | AX7: =1-AV7/AW7 -> #DIV/0! | AY7: 0 | AZ7: 0 | BA7: 0 | BB7: =1-AZ7/BA7 -> #DIV/0! | BC7: 14548 | BD7: 217 | BE7: 286 | BF7: =1-BD7/BE7 -> 0.24125874 | BG7: 43903 | BH7: 376 | BI7: 402 | BJ7: =1-BH7/BI7 -> 0.064676617 | BK7: 22383 | BL7: 247 | BM7: 976155 | BN7: =BL7*J7 -> 291390.31 | BO7: 266 | BP7: 1027819 | BQ7: =1-BL7/BO7 -> 0.071428571 | BR7: =BM7/$BM$1 -> 0.079501763 | BS7: =B7 -> MR-02 | BT7: 89 | BU7: 17 | BV7: 1500 | BW7: =BT7+BU7+BV7 -> 1606 | BX7: =BW7*J7 -> 1894626.9 | BY7: 1500 | BZ7: =BY7*J7 -> 1769576.8 | CA7: =BW7+BY7 -> 3106 | CB7: =BX7+BZ7 -> 3664203.7 | CC7: =B7 -> MR-02 | CD7: =C7 -> FBA79439 | CE7: =G7 -> B0DCK7ZH5P | CF7: =B7 -> MR-02 | CG7: 18851 | CH7: 159 | CI7: 641339.1 | CJ7: =CH7*J7 -> 187575.14 | CK7: 185 | CL7: 725892 | CM7: =1-CH7/CK7 -> 0.14054054 | CN7: =CI7/$CI$1 -> 0.05650587 | CO7: =B7 -> MR-02 | CP7: 596 | CQ7: 870 | CR7: 1500 | CS7: =CP7+CQ7+CR7 -> 2966 | CT7: =CS7*J7 -> 3499043.2 | CU7: 1500 | CV7: =CU7*J7 -> 1769576.8 | CW7: =CS7+CU7 -> 4466 | CX7: =CT7+CV7 -> 5268620 | CY7: =B7 -> MR-02 | CZ7: =C7 -> FBA79439 | DA7: =G7 -> B0DCK7ZH5P | DB7: =B7 -> MR-02 | DC7: 39422 | DD7: 347 | DE7: 1225063.9 | DF7: =DD7*J7 -> 409362.1 | DG7: 401 | DH7: 1380570 | DI7: =1-DD7/DG7 -> 0.13466334 | DJ7: =DE7/$DE$1 -> 0.097136934 | DK7: =B7 -> MR-02 | DL7: 567 | DM7: 569 | DN7: 1500 | DO7: =DL7+DM7+DN7 -> 2636 | DP7: =DO7*J7 -> 3109736.3 | DQ7: 1500 | DR7: =DQ7*J7 -> 1769576.8 | DS7: =DO7+DQ7 -> 4136 | DT7: =DP7+DR7 -> 4879313.1 | DU7: =B7 -> MR-02 | DV7: =C7 -> FBA79439 | DW7: =G7 -> B0DCK7ZH5P | DX7: =B7 -> MR-02 | DY7: 28955 | DZ7: 134 | EA7: 474622 | EB7: =DZ7*J7 -> 158082.19 | EC7: 163 | ED7: 5,58,203.00 | EE7: =1-DZ7/EC7 -> 0.17791411 | EF7: =EA7/$EA$1 -> 0.054016342 | EG7: =B7 -> MR-02 | EH7: 490 | EI7: 1664 | EJ7: 1500 | EK7: =EH7+EI7+EJ7 -> 3654 | EL7: =EK7*J7 -> 4310689.1 | EM7: 1500 | EN7: =EM7*J7 -> 1769576.8 | EO7: =EK7+EM7 -> 5154 | EP7: =EL7+EN7 -> 6080265.9 | EQ7: =B7 -> MR-02 | ER7: =C7 -> FBA79439 | ES7: =G7 -> B0DCK7ZH5P | ET7: =B7 -> MR-02 | EU7: 31297 | EV7: 108 | EW7: 351934 | EX7: =EV7*J7 -> 127409.53 | EY7: 132 | EZ7: 4,12,191 | FA7: =1-EV7/EY7 -> 0.18181818 | FB7: =EW7/$EW$1 -> 0.052812764 | FC7: =B7 -> MR-02 | FD7: 373 | FE7: 1549 | FF7: 1500 | FG7: =FD7+FE7+FF7 -> 3422 | FH7: =FG7*J7 -> 4036994.5 | FI7: 1500 | FJ7: =FI7*J7 -> 1769576.8 | FK7: =FG7+FI7 -> 4922 | FL7: =FH7+FJ7 -> 5806571.3 | FM7: =B7 -> MR-02 | FN7: =C7 -> FBA79439 | FO7: =G7 -> B0DCK7ZH5P | FP7: =B7 -> MR-02 | FQ7: 28460 | FR7: 181 | FS7: 588256 | FT7: 0 | FU7: 0 | FV7: =FR7+FT7 -> 181 | FW7: =FS7+FU7 -> 588256 | FX7: =FV7*J7 -> 213528.93 | FY7: =FW7/$FW$1 -> 0.062800253 | FZ7: =B7 -> MR-02 | GA7: 0 | GB7: 1259 | GC7: 1500 | GD7: =GA7+GB7+GC7 -> 2759 | GE7: =GD7*J7 -> 3254841.6 | GF7: 1500 | GG7: =GF7*J7 -> 1769576.8 | GH7: =GD7+GF7 -> 4259 | GI7: =GE7+GG7 -> 5024418.4 | GJ7: =B7 -> MR-02 | GK7: =C7 -> FBA79439 | GL7: =G7 -> B0DCK7ZH5P | GM7: =B7 -> MR-02 | GN7: 28472 | GO7: 185 | GP7: 599956 | GQ7: 0 | GR7: 0 | GS7: =GO7+GQ7 -> 185 | GT7: =GP7+GR7 -> 599956 | GU7: =GS7*J7 -> 218247.81 | GV7: =GT7/$GT$1 -> 0.063391012 | GW7: =B7 -> MR-02 | GX7: 148 | GY7: 1222 | GZ7: 1500 | HA7: =GX7+GY7+GZ7 -> 2870 | HB7: =HA7*J7 -> 3385790.3 | HC7: 1500 | HD7: =HC7*J7 -> 1769576.8 | HE7: =HA7+HC7 -> 4370 | HF7: =HB7+HD7 -> 5155367.1 | HG7: =B7 -> MR-02 | HH7: =C7 -> FBA79439 | HI7: =G7 -> B0DCK7ZH5P | HJ7: =B7 -> MR-02 | HK7: 39511 | HL7: 132 | HM7: 437850 | HN7: 0 | HO7: 0 | HP7: =HL7+HN7 -> 132 | HQ7: =HM7+HO7 -> 437850 | HR7: =HP7*J7 -> 155722.76 | HS7: =HQ7/$HQ$1 -> 0.03998084 | HT7: =B7 -> MR-02 | HU7: 549 | HV7: 552 | HW7: 1500 | HX7: =HU7+HV7+HW7 -> 2601 | HY7: =HX7*J7 -> 3068446.2 | HZ7: 1500 | IA7: =HZ7*J7 -> 1769576.8 | IB7: =HX7+HZ7 -> 4101 | IC7: =HY7+IA7 -> 4838023 | ID7: =B7 -> MR-02 | IE7: =C7 -> FBA79439 | IF7: =G7 -> B0DCK7ZH5P | IG7: =B7 -> MR-02 | IH7: 48112 | II7: 265 | IJ7: 842524.23 | IK7: 0 | IL7: 0 | IM7: =II7+IK7 -> 265 | IN7: =IJ7+IL7 -> 842524.23 | IO7: =IM7*J7 -> 312625.23 | IP7: =IN7/$IN$1 -> 0.074307912 | IQ7: =B7 -> MR-02 | IR7: 641 | IS7: 414 | IT7: 1500 | IU7: =IR7+IS7+IT7 -> 2555 | IV7: =IU7*J7 -> 3014179.2 | IW7: 1500 | IX7: =IW7*J7 -> 1769576.8 | IY7: =IU7+IW7 -> 4055 | IZ7: =IV7+IX7 -> 4783756 | JA7: =B7 -> MR-02 | JB7: =C7 -> FBA79439 | JC7: =G7 -> B0DCK7ZH5P | JD7: =B7 -> MR-02 | JE7: 48864 | JF7: 202 | JG7: 651632.62 | JH7: 0 | JI7: 0 | JJ7: =JF7+JH7 -> 202 | JK7: =JG7+JI7 -> 651632.62 | JL7: =JJ7*J7 -> 238303.01 | JM7: =JK7/$JK$1 -> 0.072069059 | JN7: =B7 -> MR-02 | JO7: 641 | JP7: 414 | JQ7: 1500 | JR7: =JO7+JP7+JQ7 -> 2555 | JS7: =JR7*AG7 -> 0 | JT7: 1500 | JU7: =JT7*AG7 -> 0 | JV7: =JR7+JT7 -> 4055 | JW7: =JS7+JU7 -> 0 | JX7: =B7 -> MR-02 | JY7: =C7 -> FBA79439 | JZ7: =G7 -> B0DCK7ZH5P | KA7: =B7 -> MR-02 | KB7: 74655 | KC7: 332 | KD7: 1067157.1 | KE7: 0 | KF7: 0 | KG7: =KC7+KE7 -> 332 | KH7: =KD7+KF7 -> 1067157.1 | KI7: =KG7*J7 -> 391666.33 | KJ7: =KH7/$KH$1 -> 0.090434756 | KK7: =B7 -> MR-02 | KL7: 641 | KM7: 414 | KN7: 1500 | KO7: =KL7+KM7+KN7 -> 2555 | KP7: =KO7*BD7 -> 554435 | KQ7: 1500 | KR7: =KQ7*BD7 -> 325500 | KS7: =KO7+KQ7 -> 4055 | KT7: =KP7+KR7 -> 879935 | KU7: =B7 -> MR-02 | KV7: =C7 -> FBA79439 | KW7: =G7 -> B0DCK7ZH5P | KX7: =B7 -> MR-02 | KY7: 38750 | KZ7: 279 | LA7: 871760.31 | LB7: 0 | LC7: 0 | LD7: =KZ7+LB7 -> 279 | LE7: =LA7+LC7 -> 871760.31 | LF7: =LD7*J7 -> 329141.29 | LG7: =LE7/$LE$1 -> 0.064828988 | LH7: =B7 -> MR-02 | LI7: 641 | LJ7: 414 | LK7: 1500 | LL7: =LI7+LJ7+LK7 -> 2555 | LM7: =LL7*CA7 -> 7935830 | LN7: 1500 | LO7: =LN7*CA7 -> 4659000 | LP7: =LL7+LN7 -> 4055 | LQ7: =LM7+LO7 -> 12594830 | LR7: =B7 -> MR-02 | LS7: =C7 -> FBA79439 | LT7: =G7 -> B0DCK7ZH5P | LU7: =B7 -> MR-02 | LV7: 100155 | LW7: 192 | LX7: 627659.8 | LY7: 0 | LZ7: 0 | MA7: =LW7+LY7 -> 192 | MB7: =LX7+LZ7 -> 627659.8 | MC7: =MA7*J7 -> 226505.83 | MD7: =MB7/$MB$1 -> 0.066164078 | ME7: =B7 -> MR-02 | MF7: 641 | MG7: 414 | MH7: 1500 | MI7: =MF7+MG7+MH7 -> 2555 | MJ7: =MI7*CX7 -> 1.3461324e+10 | MK7: 1500 | ML7: =MK7*CX7 -> 7.90293e+09 | MM7: =MI7+MK7 -> 4055 | MN7: =MJ7+ML7 -> 2.1364254e+10 | MO7: =B7 -> MR-02 | MP7: =C7 -> FBA79439 | MQ7: =G7 -> B0DCK7ZH5P | MR7: =B7 -> MR-02 | MS7: 68949 | MT7: 166 | MU7: 536530 | MV7: 0 | MW7: 0 | MX7: =MT7+MV7 -> 166 | MY7: =MU7+MW7 -> 536530 | MZ7: =MX7*J7 -> 195833.17 | NA7: =MY7/$MY$1 -> 0.04273655 | NB7: =B7 -> MR-02 | NC7: 641 | ND7: 414 | NE7: 1500 | NF7: =NC7+ND7+NE7 -> 2555 | NG7: =NF7*DU7 -> #VALUE! | NH7: 1500 | NI7: =NH7*DU7 -> #VALUE! | NJ7: =NF7+NH7 -> 4055 | NK7: =NG7+NI7 -> #VALUE! | NL7: =B7 -> MR-02 | NM7: =C7 -> FBA79439 | NN7: =G7 -> B0DCK7ZH5P | NO7: =Y7 -> 0 | NP7: 61086 | NQ7: 119 | NR7: 394747 | NS7: 0 | NT7: 0 | NU7: =NQ7+NS7 -> 119 | NV7: =NR7+NT7 -> 394747 | NW7: =NU7*J7 -> 140386.43 | NX7: =NV7/$NV$1 -> 0.041006499 | NY7: =B7 -> MR-02 | NZ7: 641 | OA7: 414 | OB7: 1500 | OC7: =NZ7+OA7+OB7 -> 2555 | OD7: =OC7*ER7 -> #VALUE! | OE7: 1500 | OF7: =OE7*ER7 -> #VALUE! | OG7: =OC7+OE7 -> 4055 | OH7: =OD7+OF7 -> #VALUE! | OI7: =B7 -> MR-02 | OJ7: =C7 -> FBA79439 | OK7: =G7 -> B0DCK7ZH5P | OL7: =B7 -> MR-02
A8: FBA78980 | B8: GS-02 | C8: FBA78980 | D8: Home & Kitchen | E8: Fabric Care | F8: Nexlev | G8: B0CDPMX152 | H8: Nexlev Garment Steamer | I8: 1001.1721 | J8: 1181.3831 | K8: 46 | L8: 0 | M8: 0 | N8: =1-L8/M8 -> #DIV/0! | O8: 95 | P8: 0 | Q8: 0 | R8: =1-P8/Q8 -> #DIV/0! | S8: 6202 | T8: 210 | U8: 240 | V8: =1-T8/U8 -> 0.125 | W8: 7915 | X8: 79 | Y8: 198 | Z8: =1-X8/Y8 -> 0.6010101 | AA8: 4838 | AB8: 82 | AC8: 96 | AD8: =1-AB8/AC8 -> 0.14583333 | AE8: 1623 | AF8: 34 | AG8: 39 | AH8: =1-AF8/AG8 -> 0.12820513 | AI8: 953 | AJ8: 93 | AK8: 130 | AL8: =1-AJ8/AK8 -> 0.28461538 | AM8: 4664 | AN8: 44 | AO8: 56 | AP8: =1-AN8/AO8 -> 0.21428571 | AQ8: 3849 | AR8: 82 | AS8: 93 | AT8: =1-AR8/AS8 -> 0.11827957 | AU8: 5976 | AV8: 122 | AW8: 154 | AX8: =1-AV8/AW8 -> 0.20779221 | AY8: 6875 | AZ8: 216 | BA8: 262 | BB8: =1-AZ8/BA8 -> 0.17557252 | BC8: 7405 | BD8: 210 | BE8: 285 | BF8: =1-BD8/BE8 -> 0.26315789 | BG8: 8336 | BH8: 258 | BI8: 283 | BJ8: =1-BH8/BI8 -> 0.088339223 | BK8: 17167 | BL8: 450 | BM8: 897774 | BN8: =BL8*J8 -> 531622.41 | BO8: 554 | BP8: 1027865 | BQ8: =1-BL8/BO8 -> 0.18772563 | BR8: =BM8/$BM$1 -> 0.073118117 | BS8: =B8 -> GS-02 | BT8: 138 | BU8: 68 | BV8: 0 | BW8: =BT8+BU8+BV8 -> 206 | BX8: =BW8*J8 -> 243364.92 | BY8: 1000 | BZ8: =BY8*J8 -> 1181383.1 | CA8: =BW8+BY8 -> 1206 | CB8: =BX8+BZ8 -> 1424748.1 | CC8: =B8 -> GS-02 | CD8: =C8 -> FBA78980 | CE8: =G8 -> B0CDPMX152 | CF8: =B8 -> GS-02 | CG8: 6917 | CH8: 187 | CI8: 387791 | CJ8: =CH8*J8 -> 220918.65 | CK8: 204 | CL8: 389113 | CM8: =1-CH8/CK8 -> 0.083333333 | CN8: =CI8/$CI$1 -> 0.034166743 | CO8: =B8 -> GS-02 | CP8: 6 | CQ8: 16 | CR8: 0 | CS8: =CP8+CQ8+CR8 -> 22 | CT8: =CS8*J8 -> 25990.429 | CU8: 1000 | CV8: =CU8*J8 -> 1181383.1 | CW8: =CS8+CU8 -> 1022 | CX8: =CT8+CV8 -> 1207373.6 | CY8: =B8 -> GS-02 | CZ8: =C8 -> FBA78980 | DA8: =G8 -> B0CDPMX152 | DB8: =B8 -> GS-02 | DC8: 2055 | DD8: 28 | DE8: 57504.06 | DF8: =DD8*J8 -> 33078.728 | DG8: 37 | DH8: 75559.8 | DI8: =1-DD8/DG8 -> 0.24324324 | DJ8: =DE8/$DE$1 -> 0.0045595729 | DK8: =B8 -> GS-02 | DL8: 239 | DM8: 754 | DN8: 0 | DO8: =DL8+DM8+DN8 -> 993 | DP8: =DO8*J8 -> 1173113.4 | DQ8: 1000 | DR8: =DQ8*J8 -> 1181383.1 | DS8: =DO8+DQ8 -> 1993 | DT8: =DP8+DR8 -> 2354496.6 | DU8: =B8 -> GS-02 | DV8: =C8 -> FBA78980 | DW8: =G8 -> B0CDPMX152 | DX8: =B8 -> GS-02 | DY8: 5656 | DZ8: 49 | EA8: 106058 | EB8: =DZ8*J8 -> 57887.773 | EC8: 57 | ED8: 1,12,318.00 | EE8: =1-DZ8/EC8 -> 0.14035088 | EF8: =EA8/$EA$1 -> 0.012070374 | EG8: =B8 -> GS-02 | EH8: 228 | EI8: 743 | EJ8: 0 | EK8: =EH8+EI8+EJ8 -> 971 | EL8: =EK8*J8 -> 1147123 | EM8: 1000 | EN8: =EM8*J8 -> 1181383.1 | EO8: =EK8+EM8 -> 1971 | EP8: =EL8+EN8 -> 2328506.1 | EQ8: =B8 -> GS-02 | ER8: =C8 -> FBA78980 | ES8: =G8 -> B0CDPMX152 | ET8: =B8 -> GS-02 | EU8: 3898 | EV8: 18 | EW8: 38182 | EX8: =EV8*J8 -> 21264.896 | EY8: 22 | EZ8: 44429 | FA8: =1-EV8/EY8 -> 0.18181818 | FB8: =EW8/$EW$1 -> 0.0057297589 | FC8: =B8 -> GS-02 | FD8: 207 | FE8: 681 | FF8: 0 | FG8: =FD8+FE8+FF8 -> 888 | FH8: =FG8*J8 -> 1049068.2 | FI8: 1000 | FJ8: =FI8*J8 -> 1181383.1 | FK8: =FG8+FI8 -> 1888 | FL8: =FH8+FJ8 -> 2230451.3 | FM8: =B8 -> GS-02 | FN8: =C8 -> FBA78980 | FO8: =G8 -> B0CDPMX152 | FP8: =B8 -> GS-02 | FQ8: 2491 | FR8: 62 | FS8: 130296 | FT8: 0 | FU8: 0 | FV8: =FR8+FT8 -> 62 | FW8: =FS8+FU8 -> 130296 | FX8: =FV8*J8 -> 73245.754 | FY8: =FW8/$FW$1 -> 0.013909967 | FZ8: =B8 -> GS-02 | GA8: 0 | GB8: 646 | GC8: 0 | GD8: =GA8+GB8+GC8 -> 646 | GE8: =GD8*J8 -> 763173.5 | GF8: 1000 | GG8: =GF8*J8 -> 1181383.1 | GH8: =GD8+GF8 -> 1646 | GI8: =GE8+GG8 -> 1944556.6 | GJ8: =B8 -> GS-02 | GK8: =C8 -> FBA78980 | GL8: =G8 -> B0CDPMX152 | GM8: =B8 -> GS-02 | GN8: 3414 | GO8: 52 | GP8: 108799.58 | GQ8: 0 | GR8: 0 | GS8: =GO8+GQ8 -> 52 | GT8: =GP8+GR8 -> 108799.58 | GU8: =GS8*J8 -> 61431.923 | GV8: =GT8/$GT$1 -> 0.011495702 | GW8: =B8 -> GS-02 | GX8: 126 | GY8: 599 | GZ8: 0 | HA8: =GX8+GY8+GZ8 -> 725 | HB8: =HA8*J8 -> 856502.77 | HC8: 1000 | HD8: =HC8*J8 -> 1181383.1 | HE8: =HA8+HC8 -> 1725 | HF8: =HB8+HD8 -> 2037885.9 | HG8: =B8 -> GS-02 | HH8: =C8 -> FBA78980 | HI8: =G8 -> B0CDPMX152 | HJ8: =B8 -> GS-02 | HK8: 3210 | HL8: 76 | HM8: 159397 | HN8: 0 | HO8: 0 | HP8: =HL8+HN8 -> 76 | HQ8: =HM8+HO8 -> 159397 | HR8: =HP8*J8 -> 89785.118 | HS8: =HQ8/$HQ$1 -> 0.014554815 | HT8: =B8 -> GS-02 | HU8: 195 | HV8: 374 | HW8: 0 | HX8: =HU8+HV8+HW8 -> 569 | HY8: =HX8*J8 -> 672207 | HZ8: 1000 | IA8: =HZ8*J8 -> 1181383.1 | IB8: =HX8+HZ8 -> 1569 | IC8: =HY8+IA8 -> 1853590.1 | ID8: =B8 -> GS-02 | IE8: =C8 -> FBA78980 | IF8: =G8 -> B0CDPMX152 | IG8: =B8 -> GS-02 | IH8: 5431 | II8: 84 | IJ8: 175307.67 | IK8: 0 | IL8: 0 | IM8: =II8+IK8 -> 84 | IN8: =IJ8+IL8 -> 175307.67 | IO8: =IM8*J8 -> 99236.183 | IP8: =IN8/$IN$1 -> 0.015461569 | IQ8: =B8 -> GS-02 | IR8: 308 | IS8: 3246 | IT8: 0 | IU8: =IR8+IS8+IT8 -> 3554 | IV8: =IU8*J8 -> 4198635.6 | IW8: 1000 | IX8: =IW8*J8 -> 1181383.1 | IY8: =IU8+IW8 -> 4554 | IZ8: =IV8+IX8 -> 5380018.8 | JA8: =B8 -> GS-02 | JB8: =C8 -> FBA78980 | JC8: =G8 -> B0CDPMX152 | JD8: =B8 -> GS-02 | JE8: 13634 | JF8: 109 | JG8: 225310.9 | JH8: 0 | JI8: 0 | JJ8: =JF8+JH8 -> 109 | JK8: =JG8+JI8 -> 225310.9 | JL8: =JJ8*J8 -> 128770.76 | JM8: =JK8/$JK$1 -> 0.024918864 | JN8: =B8 -> GS-02 | JO8: 308 | JP8: 3246 | JQ8: 0 | JR8: =JO8+JP8+JQ8 -> 3554 | JS8: =JR8*AG8 -> 138606 | JT8: 1000 | JU8: =JT8*AG8 -> 39000 | JV8: =JR8+JT8 -> 4554 | JW8: =JS8+JU8 -> 177606 | JX8: =B8 -> GS-02 | JY8: =C8 -> FBA78980 | JZ8: =G8 -> B0CDPMX152 | KA8: =B8 -> GS-02 | KB8: 23997 | KC8: 137 | KD8: 277621.08 | KE8: 0 | KF8: 0 | KG8: =KC8+KE8 -> 137 | KH8: =KD8+KF8 -> 277621.08 | KI8: =KG8*J8 -> 161849.49 | KJ8: =KH8/$KH$1 -> 0.023526616 | KK8: =B8 -> GS-02 | KL8: 308 | KM8: 3246 | KN8: 0 | KO8: =KL8+KM8+KN8 -> 3554 | KP8: =KO8*BD8 -> 746340 | KQ8: 1000 | KR8: =KQ8*BD8 -> 210000 | KS8: =KO8+KQ8 -> 4554 | KT8: =KP8+KR8 -> 956340 | KU8: =B8 -> GS-02 | KV8: =C8 -> FBA78980 | KW8: =G8 -> B0CDPMX152 | KX8: =B8 -> GS-02 | KY8: 48149 | KZ8: 154 | LA8: 295445.03 | LB8: 0 | LC8: 0 | LD8: =KZ8+LB8 -> 154 | LE8: =LA8+LC8 -> 295445.03 | LF8: =LD8*J8 -> 181933 | LG8: =LE8/$LE$1 -> 0.02197095 | LH8: =B8 -> GS-02 | LI8: 308 | LJ8: 3246 | LK8: 0 | LL8: =LI8+LJ8+LK8 -> 3554 | LM8: =LL8*CA8 -> 4286124 | LN8: 1000 | LO8: =LN8*CA8 -> 1206000 | LP8: =LL8+LN8 -> 4554 | LQ8: =LM8+LO8 -> 5492124 | LR8: =B8 -> GS-02 | LS8: =C8 -> FBA78980 | LT8: =G8 -> B0CDPMX152 | LU8: =B8 -> GS-02 | LV8: 59017 | LW8: 225 | LX8: 460171.62 | LY8: 0 | LZ8: 0 | MA8: =LW8+LY8 -> 225 | MB8: =LX8+LZ8 -> 460171.62 | MC8: =MA8*J8 -> 265811.2 | MD8: =MB8/$MB$1 -> 0.048508493 | ME8: =B8 -> GS-02 | MF8: 308 | MG8: 3246 | MH8: 0 | MI8: =MF8+MG8+MH8 -> 3554 | MJ8: =MI8*CX8 -> 4.2910056e+09 | MK8: 1000 | ML8: =MK8*CX8 -> 1.2073736e+09 | MM8: =MI8+MK8 -> 4554 | MN8: =MJ8+ML8 -> 5.4983792e+09 | MO8: =B8 -> GS-02 | MP8: =C8 -> FBA78980 | MQ8: =G8 -> B0CDPMX152 | MR8: =B8 -> GS-02 | MS8: 38661 | MT8: 238 | MU8: 469297 | MV8: 0 | MW8: 0 | MX8: =MT8+MV8 -> 238 | MY8: =MU8+MW8 -> 469297 | MZ8: =MX8*J8 -> 281169.18 | NA8: =MY8/$MY$1 -> 0.037381199 | NB8: =B8 -> GS-02 | NC8: 308 | ND8: 3246 | NE8: 0 | NF8: =NC8+ND8+NE8 -> 3554 | NG8: =NF8*DU8 -> #VALUE! | NH8: 1000 | NI8: =NH8*DU8 -> #VALUE! | NJ8: =NF8+NH8 -> 4554 | NK8: =NG8+NI8 -> #VALUE! | NL8: =B8 -> GS-02 | NM8: =C8 -> FBA78980 | NN8: =G8 -> B0CDPMX152 | NO8: =Y8 -> 198 | NP8: 26968 | NQ8: 212 | NR8: 417027 | NS8: 0 | NT8: 0 | NU8: =NQ8+NS8 -> 212 | NV8: =NR8+NT8 -> 417027 | NW8: =NU8*J8 -> 250453.22 | NX8: =NV8/$NV$1 -> 0.043320956 | NY8: =B8 -> GS-02 | NZ8: 308 | OA8: 3246 | OB8: 0 | OC8: =NZ8+OA8+OB8 -> 3554 | OD8: =OC8*ER8 -> #VALUE! | OE8: 1000 | OF8: =OE8*ER8 -> #VALUE! | OG8: =OC8+OE8 -> 4554 | OH8: =OD8+OF8 -> #VALUE! | OI8: =B8 -> GS-02 | OJ8: =C8 -> FBA78980 | OK8: =G8 -> B0CDPMX152 | OL8: =B8 -> GS-02
A9: FBA78981 | B9: SC-01 | C9: FBA78981 | D9: Home & Kitchen | E9: Cleaning & Vacumming | F9: Nexlev | G9: B0CDPP45BM | H9: Nexlev Steam Cleaner | I9: 1439.2728 | J9: 1698.342 | K9: 2 | L9: 0 | M9: 0 | N9: =1-L9/M9 -> #DIV/0! | O9: 287 | P9: 1 | Q9: 1 | R9: =1-P9/Q9 -> 0 | S9: 5489 | T9: 101 | U9: 129 | V9: =1-T9/U9 -> 0.21705426 | W9: 10658 | X9: 120 | Y9: 125 | Z9: =1-X9/Y9 -> 0.04 | AA9: 12687 | AB9: 75 | AC9: 144 | AD9: =1-AB9/AC9 -> 0.47916667 | AE9: 6619 | AF9: 75 | AG9: 111 | AH9: =1-AF9/AG9 -> 0.32432432 | AI9: 0 | AJ9: 1 | AK9: 2 | AL9: =1-AJ9/AK9 -> 0.5 | AM9: 1197 | AN9: 0 | AO9: 2 | AP9: =1-AN9/AO9 -> 1 | AQ9: 16129 | AR9: 65 | AS9: 70 | AT9: =1-AR9/AS9 -> 0.071428571 | AU9: 62371 | AV9: 307 | AW9: 363 | AX9: =1-AV9/AW9 -> 0.15426997 | AY9: 45806 | AZ9: 305 | BA9: 359 | BB9: =1-AZ9/BA9 -> 0.15041783 | BC9: 45114 | BD9: 481 | BE9: 633 | BF9: =1-BD9/BE9 -> 0.24012638 | BG9: 42043 | BH9: 615 | BI9: 654 | BJ9: =1-BH9/BI9 -> 0.059633028 | BK9: 31862 | BL9: 194 | BM9: 663164 | BN9: =BL9*J9 -> 329478.34 | BO9: 241 | BP9: 805783 | BQ9: =1-BL9/BO9 -> 0.19502075 | BR9: =BM9/$BM$1 -> 0.054010589 | BS9: =B9 -> SC-01 | BT9: 626 | BU9: 734 | BV9: 0 | BW9: =BT9+BU9+BV9 -> 1360 | BX9: =BW9*J9 -> 2309745.1 | BY9: 3000 | BZ9: =BY9*J9 -> 5095025.9 | CA9: =BW9+BY9 -> 4360 | CB9: =BX9+BZ9 -> 7404770.9 | CC9: =B9 -> SC-01 | CD9: =C9 -> FBA78981 | CE9: =G9 -> B0CDPP45BM | CF9: =B9 -> SC-01 | CG9: 32610 | CH9: 376 | CI9: 1273843 | CJ9: =CH9*J9 -> 638576.57 | CK9: 431 | CL9: 1404032 | CM9: =1-CH9/CK9 -> 0.12761021 | CN9: =CI9/$CI$1 -> 0.11223331 | CO9: =B9 -> SC-01 | CP9: 651 | CQ9: 306 | CR9: 0 | CS9: =CP9+CQ9+CR9 -> 957 | CT9: =CS9*J9 -> 1625313.3 | CU9: 3000 | CV9: =CU9*J9 -> 5095025.9 | CW9: =CS9+CU9 -> 3957 | CX9: =CT9+CV9 -> 6720339.1 | CY9: =B9 -> SC-01 | CZ9: =C9 -> FBA78981 | DA9: =G9 -> B0CDPP45BM | DB9: =B9 -> SC-01 | DC9: 32939 | DD9: 371 | DE9: 1243698.3 | DF9: =DD9*J9 -> 630084.87 | DG9: 438 | DH9: 1423496 | DI9: =1-DD9/DG9 -> 0.15296804 | DJ9: =DE9/$DE$1 -> 0.098614481 | DK9: =B9 -> SC-01 | DL9: 788 | DM9: 1812 | DN9: 0 | DO9: =DL9+DM9+DN9 -> 2600 | DP9: =DO9*J9 -> 4415689.1 | DQ9: 3000 | DR9: =DQ9*J9 -> 5095025.9 | DS9: =DO9+DQ9 -> 5600 | DT9: =DP9+DR9 -> 9510714.9 | DU9: =B9 -> SC-01 | DV9: =C9 -> FBA78981 | DW9: =G9 -> B0CDPP45BM | DX9: =B9 -> SC-01 | DY9: 29420 | DZ9: 288 | EA9: 979578.59 | EB9: =DZ9*J9 -> 489122.48 | EC9: 338 | ED9: 11,35,606.00 | EE9: =1-DZ9/EC9 -> 0.14792899 | EF9: =EA9/$EA$1 -> 0.11148504 | EG9: =B9 -> SC-01 | EH9: 597 | EI9: 1245 | EJ9: 0 | EK9: =EH9+EI9+EJ9 -> 1842 | EL9: =EK9*J9 -> 3128345.9 | EM9: 3000 | EN9: =EM9*J9 -> 5095025.9 | EO9: =EK9+EM9 -> 4842 | EP9: =EL9+EN9 -> 8223371.7 | EQ9: =B9 -> SC-01 | ER9: =C9 -> FBA78981 | ES9: =G9 -> B0CDPP45BM | ET9: =B9 -> SC-01 | EU9: 33204 | EV9: 264 | EW9: 897310 | EX9: =EV9*J9 -> 448362.28 | EY9: 344 | EZ9: 11,45,843 | FA9: =1-EV9/EY9 -> 0.23255814 | FB9: =EW9/$EW$1 -> 0.13465429 | FC9: =B9 -> SC-01 | FD9: 427 | FE9: 929 | FF9: 0 | FG9: =FD9+FE9+FF9 -> 1356 | FH9: =FG9*J9 -> 2302951.7 | FI9: 3000 | FJ9: =FI9*J9 -> 5095025.9 | FK9: =FG9+FI9 -> 4356 | FL9: =FH9+FJ9 -> 7397977.6 | FM9: =B9 -> SC-01 | FN9: =C9 -> FBA78981 | FO9: =G9 -> B0CDPP45BM | FP9: =B9 -> SC-01 | FQ9: 32543 | FR9: 281 | FS9: 948743 | FT9: 0 | FU9: 0 | FV9: =FR9+FT9 -> 281 | FW9: =FS9+FU9 -> 948743 | FX9: =FV9*J9 -> 477234.09 | FY9: =FW9/$FW$1 -> 0.10128465 | FZ9: =B9 -> SC-01 | GA9: 0 | GB9: 624 | GC9: 0 | GD9: =GA9+GB9+GC9 -> 624 | GE9: =GD9*J9 -> 1059765.4 | GF9: 3000 | GG9: =GF9*J9 -> 5095025.9 | GH9: =GD9+GF9 -> 3624 | GI9: =GE9+GG9 -> 6154791.2 | GJ9: =B9 -> SC-01 | GK9: =C9 -> FBA78981 | GL9: =G9 -> B0CDPP45BM | GM9: =B9 -> SC-01 | GN9: 36810 | GO9: 240 | GP9: 803855 | GQ9: 0 | GR9: 0 | GS9: =GO9+GQ9 -> 240 | GT9: =GP9+GR9 -> 803855 | GU9: =GS9*J9 -> 407602.07 | GV9: =GT9/$GT$1 -> 0.084934865 | GW9: =B9 -> SC-01 | GX9: 464 | GY9: 459 | GZ9: 0 | HA9: =GX9+GY9+GZ9 -> 923 | HB9: =HA9*J9 -> 1567569.6 | HC9: 3000 | HD9: =HC9*J9 -> 5095025.9 | HE9: =HA9+HC9 -> 3923 | HF9: =HB9+HD9 -> 6662595.5 | HG9: =B9 -> SC-01 | HH9: =C9 -> FBA78981 | HI9: =G9 -> B0CDPP45BM | HJ9: =B9 -> SC-01 | HK9: 36704 | HL9: 306 | HM9: 1034497 | HN9: 0 | HO9: 0 | HP9: =HL9+HN9 -> 306 | HQ9: =HM9+HO9 -> 1034497 | HR9: =HP9*J9 -> 519692.64 | HS9: =HQ9/$HQ$1 -> 0.094461708 | HT9: =B9 -> SC-01 | HU9: 418 | HV9: 0 | HW9: 0 | HX9: =HU9+HV9+HW9 -> 418 | HY9: =HX9*J9 -> 709906.94 | HZ9: 3000 | IA9: =HZ9*J9 -> 5095025.9 | IB9: =HX9+HZ9 -> 3418 | IC9: =HY9+IA9 -> 5804932.8 | ID9: =B9 -> SC-01 | IE9: =C9 -> FBA78981 | IF9: =G9 -> B0CDPP45BM | IG9: =B9 -> SC-01 | IH9: 41310 | II9: 316 | IJ9: 1061984.1 | IK9: 0 | IL9: 0 | IM9: =II9+IK9 -> 316 | IN9: =IJ9+IL9 -> 1061984.1 | IO9: =IM9*J9 -> 536676.06 | IP9: =IN9/$IN$1 -> 0.093663559 | IQ9: =B9 -> SC-01 | IR9: 708 | IS9: 634 | IT9: 0 | IU9: =IR9+IS9+IT9 -> 1342 | IV9: =IU9*J9 -> 2279174.9 | IW9: 3000 | IX9: =IW9*J9 -> 5095025.9 | IY9: =IU9+IW9 -> 4342 | IZ9: =IV9+IX9 -> 7374200.8 | JA9: =B9 -> SC-01 | JB9: =C9 -> FBA78981 | JC9: =G9 -> B0CDPP45BM | JD9: =B9 -> SC-01 | JE9: 30549 | JF9: 273 | JG9: 915590.88 | JH9: 0 | JI9: 0 | JJ9: =JF9+JH9 -> 273 | JK9: =JG9+JI9 -> 915590.88 | JL9: =JJ9*J9 -> 463647.35 | JM9: =JK9/$JK$1 -> 0.10126223 | JN9: =B9 -> SC-01 | JO9: 708 | JP9: 634 | JQ9: 0 | JR9: =JO9+JP9+JQ9 -> 1342 | JS9: =JR9*AG9 -> 148962 | JT9: 3000 | JU9: =JT9*AG9 -> 333000 | JV9: =JR9+JT9 -> 4342 | JW9: =JS9+JU9 -> 481962 | JX9: =B9 -> SC-01 | JY9: =C9 -> FBA78981 | JZ9: =G9 -> B0CDPP45BM | KA9: =B9 -> SC-01 | KB9: 64288 | KC9: 556 | KD9: 1818704.1 | KE9: 0 | KF9: 0 | KG9: =KC9+KE9 -> 556 | KH9: =KD9+KF9 -> 1818704.1 | KI9: =KG9*J9 -> 944278.13 | KJ9: =KH9/$KH$1 -> 0.15412358 | KK9: =B9 -> SC-01 | KL9: 708 | KM9: 634 | KN9: 0 | KO9: =KL9+KM9+KN9 -> 1342 | KP9: =KO9*BD9 -> 645502 | KQ9: 3000 | KR9: =KQ9*BD9 -> 1443000 | KS9: =KO9+KQ9 -> 4342 | KT9: =KP9+KR9 -> 2088502 | KU9: =B9 -> SC-01 | KV9: =C9 -> FBA78981 | KW9: =G9 -> B0CDPP45BM | KX9: =B9 -> SC-01 | KY9: 41538 | KZ9: 677 | LA9: 2150674.9 | LB9: 0 | LC9: 0 | LD9: =KZ9+LB9 -> 677 | LE9: =LA9+LC9 -> 2150674.9 | LF9: =LD9*J9 -> 1149777.5 | LG9: =LE9/$LE$1 -> 0.15993625 | LH9: =B9 -> SC-01 | LI9: 708 | LJ9: 634 | LK9: 0 | LL9: =LI9+LJ9+LK9 -> 1342 | LM9: =LL9*CA9 -> 5851120 | LN9: 3000 | LO9: =LN9*CA9 -> 13080000 | LP9: =LL9+LN9 -> 4342 | LQ9: =LM9+LO9 -> 18931120 | LR9: =B9 -> SC-01 | LS9: =C9 -> FBA78981 | LT9: =G9 -> B0CDPP45BM | LU9: =B9 -> SC-01 | LV9: 104034 | LW9: 336 | LX9: 1154561.7 | LY9: 0 | LZ9: 0 | MA9: =LW9+LY9 -> 336 | MB9: =LX9+LZ9 -> 1154561.7 | MC9: =MA9*J9 -> 570642.9 | MD9: =MB9/$MB$1 -> 0.12170687 | ME9: =B9 -> SC-01 | MF9: 708 | MG9: 634 | MH9: 0 | MI9: =MF9+MG9+MH9 -> 1342 | MJ9: =MI9*CX9 -> 9.0186951e+09 | MK9: 3000 | ML9: =MK9*CX9 -> 2.0161017e+10 | MM9: =MI9+MK9 -> 4342 | MN9: =MJ9+ML9 -> 2.9179712e+10 | MO9: =B9 -> SC-01 | MP9: =C9 -> FBA78981 | MQ9: =G9 -> B0CDPP45BM | MR9: =B9 -> SC-01 | MS9: 128830 | MT9: 492 | MU9: 1718494 | MV9: 0 | MW9: 0 | MX9: =MT9+MV9 -> 492 | MY9: =MU9+MW9 -> 1718494 | MZ9: =MX9*J9 -> 835584.24 | NA9: =MY9/$MY$1 -> 0.13688425 | NB9: =B9 -> SC-01 | NC9: 708 | ND9: 634 | NE9: 0 | NF9: =NC9+ND9+NE9 -> 1342 | NG9: =NF9*DU9 -> #VALUE! | NH9: 3000 | NI9: =NH9*DU9 -> #VALUE! | NJ9: =NF9+NH9 -> 4342 | NK9: =NG9+NI9 -> #VALUE! | NL9: =B9 -> SC-01 | NM9: =C9 -> FBA78981 | NN9: =G9 -> B0CDPP45BM | NO9: =Y9 -> 125 | NP9: 63780 | NQ9: 283 | NR9: 929336 | NS9: 0 | NT9: 0 | NU9: =NQ9+NS9 -> 283 | NV9: =NR9+NT9 -> 929336 | NW9: =NU9*J9 -> 480630.77 | NX9: =NV9/$NV$1 -> 0.096539849 | NY9: =B9 -> SC-01 | NZ9: 708 | OA9: 634 | OB9: 0 | OC9: =NZ9+OA9+OB9 -> 1342 | OD9: =OC9*ER9 -> #VALUE! | OE9: 3000 | OF9: =OE9*ER9 -> #VALUE! | OG9: =OC9+OE9 -> 4342 | OH9: =OD9+OF9 -> #VALUE! | OI9: =B9 -> SC-01 | OJ9: =C9 -> FBA78981 | OK9: =G9 -> B0CDPP45BM | OL9: =B9 -> SC-01
A10: FBA78979 | B10: GS-01 | C10: FBK78979 | D10: Home & Kitchen | E10: Fabric Care | F10: Nexlev | G10: B0CDPQXPC1 | H10: Nexlev Premium Garment Steamer | I10: 1231.0628 | J10: 1452.6542 | K10: 58 | L10: 1 | M10: 1 | N10: =1-L10/M10 -> 0 | O10: 77 | P10: 0 | Q10: 0 | R10: =1-P10/Q10 -> #DIV/0! | S10: 2066 | T10: 65 | U10: 81 | V10: =1-T10/U10 -> 0.19753086 | W10: 3043 | X10: 151 | Y10: 112 | Z10: =1-X10/Y10 -> -0.34821429 | AA10: 3689 | AB10: 86 | AC10: 164 | AD10: =1-AB10/AC10 -> 0.47560976 | AE10: 2343 | AF10: 57 | AG10: 62 | AH10: =1-AF10/AG10 -> 0.080645161 | AI10: 711 | AJ10: 69 | AK10: 78 | AL10: =1-AJ10/AK10 -> 0.11538462 | AM10: 711 | AN10: 10 | AO10: 14 | AP10: =1-AN10/AO10 -> 0.28571429 | AQ10: 956 | AR10: 16 | AS10: 25 | AT10: =1-AR10/AS10 -> 0.36 | AU10: 614 | AV10: 14 | AW10: 31 | AX10: =1-AV10/AW10 -> 0.5483871 | AY10: 1697 | AZ10: 73 | BA10: 88 | BB10: =1-AZ10/BA10 -> 0.17045455 | BC10: 2150 | BD10: 65 | BE10: 81 | BF10: =1-BD10/BE10 -> 0.19753086 | BG10: 2982 | BH10: 75 | BI10: 87 | BJ10: =1-BH10/BI10 -> 0.13793103 | BK10: 7833 | BL10: 250 | BM10: 602178 | BN10: =BL10*J10 -> 363163.54 | BO10: 296 | BP10: 669722 | BQ10: =1-BL10/BO10 -> 0.15540541 | BR10: =BM10/$BM$1 -> 0.049043659 | BS10: =B10 -> GS-01 | BT10: 170 | BU10: 296 | BV10: 0 | BW10: =BT10+BU10+BV10 -> 466 | BX10: =BW10*J10 -> 676936.84 | BY10: 0 | BZ10: =BY10*J10 -> 0 | CA10: =BW10+BY10 -> 466 | CB10: =BX10+BZ10 -> 676936.84 | CC10: =B10 -> GS-01 | CD10: =C10 -> FBK78979 | CE10: =G10 -> B0CDPQXPC1 | CF10: =B10 -> GS-01 | CG10: 4391 | CH10: 163 | CI10: 408936.62 | CJ10: =CH10*J10 -> 236782.63 | CK10: 181 | CL10: 427680 | CM10: =1-CH10/CK10 -> 0.099447514 | CN10: =CI10/$CI$1 -> 0.0360298 | CO10: =B10 -> GS-01 | CP10: 423 | CQ10: 8 | CR10: 0 | CS10: =CP10+CQ10+CR10 -> 431 | CT10: =CS10*J10 -> 626093.94 | CU10: 0 | CV10: =CU10*J10 -> 0 | CW10: =CS10+CU10 -> 431 | CX10: =CT10+CV10 -> 626093.94 | CY10: =B10 -> GS-01 | CZ10: =C10 -> FBK78979 | DA10: =G10 -> B0CDPQXPC1 | DB10: =B10 -> GS-01 | DC10: 3602 | DD10: 82 | DE10: 205075.18 | DF10: =DD10*J10 -> 119117.64 | DG10: 96 | DH10: 232857 | DI10: =1-DD10/DG10 -> 0.14583333 | DJ10: =DE10/$DE$1 -> 0.016260682 | DK10: =B10 -> GS-01 | DL10: 176 | DM10: 5 | DN10: 0 | DO10: =DL10+DM10+DN10 -> 181 | DP10: =DO10*J10 -> 262930.4 | DQ10: 0 | DR10: =DQ10*J10 -> 0 | DS10: =DO10+DQ10 -> 181 | DT10: =DP10+DR10 -> 262930.4 | DU10: =B10 -> GS-01 | DV10: =C10 -> FBK78979 | DW10: =G10 -> B0CDPQXPC1 | DX10: =B10 -> GS-01 | DY10: 1757 | DZ10: 48 | EA10: 120040.16 | EB10: =DZ10*J10 -> 69727.399 | EC10: 60 | ED10: 1,27,449.00 | EE10: =1-DZ10/EC10 -> 0.2 | EF10: =EA10/$EA$1 -> 0.013661672 | EG10: =B10 -> GS-01 | EH10: 126 | EI10: 5 | EJ10: 0 | EK10: =EH10+EI10+EJ10 -> 131 | EL10: =EK10*J10 -> 190297.69 | EM10: 0 | EN10: =EM10*J10 -> 0 | EO10: =EK10+EM10 -> 131 | EP10: =EL10+EN10 -> 190297.69 | EQ10: =B10 -> GS-01 | ER10: =C10 -> FBK78979 | ES10: =G10 -> B0CDPQXPC1 | ET10: =B10 -> GS-01 | EU10: 3315 | EV10: 37 | EW10: 88757 | EX10: =EV10*J10 -> 53748.204 | EY10: 52 | EZ10: 1,17,143 | FA10: =1-EV10/EY10 -> 0.28846154 | FB10: =EW10/$EW$1 -> 0.013319266 | FC10: =B10 -> GS-01 | FD10: 79 | FE10: 5 | FF10: 0 | FG10: =FD10+FE10+FF10 -> 84 | FH10: =FG10*J10 -> 122022.95 | FI10: 0 | FJ10: =FI10*J10 -> 0 | FK10: =FG10+FI10 -> 84 | FL10: =FH10+FJ10 -> 122022.95 | FM10: =B10 -> GS-01 | FN10: =C10 -> FBK78979 | FO10: =G10 -> B0CDPQXPC1 | FP10: =B10 -> GS-01 | FQ10: 1834 | FR10: 37 | FS10: 85063 | FT10: 0 | FU10: 0 | FV10: =FR10+FT10 -> 37 | FW10: =FS10+FU10 -> 85063 | FX10: =FV10*J10 -> 53748.204 | FY10: =FW10/$FW$1 -> 0.0090810428 | FZ10: =B10 -> GS-01 | GA10: 0 | GB10: 8 | GC10: 0 | GD10: =GA10+GB10+GC10 -> 8 | GE10: =GD10*J10 -> 11621.233 | GF10: 0 | GG10: =GF10*J10 -> 0 | GH10: =GD10+GF10 -> 8 | GI10: =GE10+GG10 -> 11621.233 | GJ10: =B10 -> GS-01 | GK10: =C10 -> FBK78979 | GL10: =G10 -> B0CDPQXPC1 | GM10: =B10 -> GS-01 | GN10: 1008 | GO10: 0 | GP10: 0 | GQ10: 0 | GR10: 0 | GS10: =GO10+GQ10 -> 0 | GT10: =GP10+GR10 -> 0 | GU10: =GS10*J10 -> 0 | GV10: =GT10/$GT$1 -> 0 | GW10: =B10 -> GS-01 | GX10: 0 | GY10: 0 | GZ10: 0 | HA10: =GX10+GY10+GZ10 -> 0 | HB10: =HA10*J10 -> 0 | HC10: 0 | HD10: =HC10*J10 -> 0 | HE10: =HA10+HC10 -> 0 | HF10: =HB10+HD10 -> 0 | HG10: =B10 -> GS-01 | HH10: =C10 -> FBK78979 | HI10: =G10 -> B0CDPQXPC1 | HJ10: =B10 -> GS-01 | HK10: 1095 | HL10: 26 | HM10: 59774 | HN10: 0 | HO10: 0 | HP10: =HL10+HN10 -> 26 | HQ10: =HM10+HO10 -> 59774 | HR10: =HP10*J10 -> 37769.008 | HS10: =HQ10/$HQ$1 -> 0.0054580672 | HT10: =B10 -> GS-01 | HU10: 1 | HV10: 0 | HW10: 0 | HX10: =HU10+HV10+HW10 -> 1 | HY10: =HX10*J10 -> 1452.6542 | HZ10: 0 | IA10: =HZ10*J10 -> 0 | IB10: =HX10+HZ10 -> 1 | IC10: =HY10+IA10 -> 1452.6542 | ID10: =B10 -> GS-01 | IE10: =C10 -> FBK78979 | IF10: =G10 -> B0CDPQXPC1 | IG10: =B10 -> GS-01 | IH10: 100 | II10: 4 | IJ10: 9334 | IK10: 0 | IL10: 0 | IM10: =II10+IK10 -> 4 | IN10: =IJ10+IL10 -> 9334 | IO10: =IM10*J10 -> 5810.6166 | IP10: =IN10/$IN$1 -> 0.00082322861 | IQ10: =B10 -> GS-01 | IR10: 2 | IS10: 0 | IT10: 0 | IU10: =IR10+IS10+IT10 -> 2 | IV10: =IU10*J10 -> 2905.3083 | IW10: 0 | IX10: =IW10*J10 -> 0 | IY10: =IU10+IW10 -> 2 | IZ10: =IV10+IX10 -> 2905.3083 | JA10: =B10 -> GS-01 | JB10: =C10 -> FBK78979 | JC10: =G10 -> B0CDPQXPC1 | JD10: =B10 -> GS-01 | JE10: 205 | JF10: 1 | JG10: 2437 | JH10: 0 | JI10: 0 | JJ10: =JF10+JH10 -> 1 | JK10: =JG10+JI10 -> 2437 | JL10: =JJ10*J10 -> 1452.6542 | JM10: =JK10/$JK$1 -> 0.00026952656 | JN10: =B10 -> GS-01 | JO10: 2 | JP10: 0 | JQ10: 0 | JR10: =JO10+JP10+JQ10 -> 2 | JS10: =JR10*AG10 -> 124 | JT10: 0 | JU10: =JT10*AG10 -> 0 | JV10: =JR10+JT10 -> 2 | JW10: =JS10+JU10 -> 124 | JX10: =B10 -> GS-01 | JY10: =C10 -> FBK78979 | JZ10: =G10 -> B0CDPQXPC1 | KA10: =B10 -> GS-01 | KB10: NA | KC10: 0 | KD10: 0 | KE10: 0 | KF10: 0 | KG10: =KC10+KE10 -> 0 | KH10: =KD10+KF10 -> 0 | KI10: =KG10*J10 -> 0 | KJ10: =KH10/$KH$1 -> 0 | KK10: =B10 -> GS-01 | KL10: 2 | KM10: 0 | KN10: 0 | KO10: =KL10+KM10+KN10 -> 2 | KP10: =KO10*BD10 -> 130 | KQ10: 0 | KR10: =KQ10*BD10 -> 0 | KS10: =KO10+KQ10 -> 2 | KT10: =KP10+KR10 -> 130 | KU10: =B10 -> GS-01 | KV10: =C10 -> FBK78979 | KW10: =G10 -> B0CDPQXPC1 | KX10: =B10 -> GS-01 | KY10: 10 | KZ10: 0 | LA10: 0 | LB10: 0 | LC10: 0 | LD10: =KZ10+LB10 -> 0 | LE10: =LA10+LC10 -> 0 | LF10: =LD10*J10 -> 0 | LG10: =LE10/$LE$1 -> 0 | LH10: =B10 -> GS-01 | LI10: 2 | LJ10: 0 | LK10: 0 | LL10: =LI10+LJ10+LK10 -> 2 | LM10: =LL10*CA10 -> 932 | LN10: 0 | LO10: =LN10*CA10 -> 0 | LP10: =LL10+LN10 -> 2 | LQ10: =LM10+LO10 -> 932 | LR10: =B10 -> GS-01 | LS10: =C10 -> FBK78979 | LT10: =G10 -> B0CDPQXPC1 | LU10: =B10 -> GS-01 | LV10: 0 | LW10: 0 | LX10: 0 | LY10: 0 | LZ10: 0 | MA10: =LW10+LY10 -> 0 | MB10: =LX10+LZ10 -> 0 | MC10: =MA10*J10 -> 0 | MD10: =MB10/$MB$1 -> 0 | ME10: =B10 -> GS-01 | MF10: 2 | MG10: 0 | MH10: 0 | MI10: =MF10+MG10+MH10 -> 2 | MJ10: =MI10*CX10 -> 1252187.9 | MK10: 0 | ML10: =MK10*CX10 -> 0 | MM10: =MI10+MK10 -> 2 | MN10: =MJ10+ML10 -> 1252187.9 | MO10: =B10 -> GS-01 | MP10: =C10 -> FBK78979 | MQ10: =G10 -> B0CDPQXPC1 | MR10: =B10 -> GS-01 | MS10: 0 | MT10: 0 | MU10: 0 | MV10: 0 | MW10: 0 | MX10: =MT10+MV10 -> 0 | MY10: =MU10+MW10 -> 0 | MZ10: =MX10*J10 -> 0 | NA10: =MY10/$MY$1 -> 0 | NB10: =B10 -> GS-01 | NC10: 2 | ND10: 0 | NE10: 0 | NF10: =NC10+ND10+NE10 -> 2 | NG10: =NF10*DU10 -> #VALUE! | NH10: 0 | NI10: =NH10*DU10 -> #VALUE! | NJ10: =NF10+NH10 -> 2 | NK10: =NG10+NI10 -> #VALUE! | NL10: =B10 -> GS-01 | NM10: =C10 -> FBK78979 | NN10: =G10 -> B0CDPQXPC1 | NO10: =Y10 -> 112 | NP10: 0 | NQ10: 0 | NR10: 0 | NS10: 0 | NT10: 0 | NU10: =NQ10+NS10 -> 0 | NV10: =NR10+NT10 -> 0 | NW10: =NU10*J10 -> 0 | NX10: =NV10/$NV$1 -> 0 | NY10: =B10 -> GS-01 | NZ10: 2 | OA10: 0 | OB10: 0 | OC10: =NZ10+OA10+OB10 -> 2 | OD10: =OC10*ER10 -> #VALUE! | OE10: 0 | OF10: =OE10*ER10 -> #VALUE! | OG10: =OC10+OE10 -> 2 | OH10: =OD10+OF10 -> #VALUE! | OI10: =B10 -> GS-01 | OJ10: =C10 -> FBK78979 | OK10: =G10 -> B0CDPQXPC1 | OL10: =B10 -> GS-01
A11: FBA79280 | B11: LR-02 | C11: FBA79280 | D11: Home & Kitchen | E11: Fabric Care | F11: Nexlev | G11: B0D845B2DG | H11: Nexlev Lint Remover | I11: 715.03224 | J11: 843.73804 | K11: 0 | L11: 0 | M11: 0 | N11: =1-L11/M11 -> #DIV/0! | O11: 0 | P11: 0 | Q11: 0 | R11: =1-P11/Q11 -> #DIV/0! | S11: 0 | T11: 0 | U11: 0 | V11: =1-T11/U11 -> #DIV/0! | W11: 0 | X11: 0 | Y11: 0 | Z11: =1-X11/Y11 -> #DIV/0! | AA11: 0 | AB11: 0 | AC11: 0 | AD11: =1-AB11/AC11 -> #DIV/0! | AE11: 0 | AF11: 0 | AG11: 0 | AH11: =1-AF11/AG11 -> #DIV/0! | AI11: 0 | AJ11: 0 | AK11: 0 | AL11: =1-AJ11/AK11 -> #DIV/0! | AM11: 0 | AN11: 0 | AO11: 0 | AP11: =1-AN11/AO11 -> #DIV/0! | AQ11: 0 | AR11: 0 | AS11: 0 | AT11: =1-AR11/AS11 -> #DIV/0! | AU11: 588 | AV11: 10 | AW11: 13 | AX11: =1-AV11/AW11 -> 0.23076923 | AY11: 2063 | AZ11: 58 | BA11: 71 | BB11: =1-AZ11/BA11 -> 0.18309859 | BC11: 4853 | BD11: 96 | BE11: 104 | BF11: =1-BD11/BE11 -> 0.076923077 | BG11: 14825 | BH11: 178 | BI11: 197 | BJ11: =1-BH11/BI11 -> 0.096446701 | BK11: 7943 | BL11: 348 | BM11: 502801 | BN11: =BL11*J11 -> 293620.84 | BO11: 380 | BP11: 544973 | BQ11: =1-BL11/BO11 -> 0.084210526 | BR11: =BM11/$BM$1 -> 0.040950019 | BS11: =B11 -> LR-02 | BT11: 377 | BU11: 362 | BV11: 0 | BW11: =BT11+BU11+BV11 -> 739 | BX11: =BW11*J11 -> 623522.41 | BY11: 1500 | BZ11: =BY11*J11 -> 1265607.1 | CA11: =BW11+BY11 -> 2239 | CB11: =BX11+BZ11 -> 1889129.5 | CC11: =B11 -> LR-02 | CD11: =C11 -> FBA79280 | CE11: =G11 -> B0D845B2DG | CF11: =B11 -> LR-02 | CG11: 11928 | CH11: 537 | CI11: 834411.14 | CJ11: =CH11*J11 -> 453087.33 | CK11: 596 | CL11: 923037 | CM11: =1-CH11/CK11 -> 0.098993289 | CN11: =CI11/$CI$1 -> 0.07351669 | CO11: =B11 -> LR-02 | CP11: 204 | CQ11: 19 | CR11: 0 | CS11: =CP11+CQ11+CR11 -> 223 | CT11: =CS11*J11 -> 188153.58 | CU11: 1500 | CV11: =CU11*J11 -> 1265607.1 | CW11: =CS11+CU11 -> 1723 | CX11: =CT11+CV11 -> 1453760.6 | CY11: =B11 -> LR-02 | CZ11: =C11 -> FBA79280 | DA11: =G11 -> B0D845B2DG | DB11: =B11 -> LR-02 | DC11: 7847 | DD11: 198 | DE11: 296341.7 | DF11: =DD11*J11 -> 167060.13 | DG11: 226 | DH11: 328380 | DI11: =1-DD11/DG11 -> 0.12389381 | DJ11: =DE11/$DE$1 -> 0.023497325 | DK11: =B11 -> LR-02 | DL11: 395 | DM11: 12 | DN11: 0 | DO11: =DL11+DM11+DN11 -> 407 | DP11: =DO11*J11 -> 343401.38 | DQ11: 1500 | DR11: =DQ11*J11 -> 1265607.1 | DS11: =DO11+DQ11 -> 1907 | DT11: =DP11+DR11 -> 1609008.4 | DU11: =B11 -> LR-02 | DV11: =C11 -> FBA79280 | DW11: =G11 -> B0D845B2DG | DX11: =B11 -> LR-02 | DY11: 6478 | DZ11: 109 | EA11: 174449 | EB11: =DZ11*J11 -> 91967.447 | EC11: 123 | ED11: 1,91,880.00 | EE11: =1-DZ11/EC11 -> 0.11382114 | EF11: =EA11/$EA$1 -> 0.019853898 | EG11: =B11 -> LR-02 | EH11: 350 | EI11: 808 | EJ11: 0 | EK11: =EH11+EI11+EJ11 -> 1158 | EL11: =EK11*J11 -> 977048.65 | EM11: 1500 | EN11: =EM11*J11 -> 1265607.1 | EO11: =EK11+EM11 -> 2658 | EP11: =EL11+EN11 -> 2242655.7 | EQ11: =B11 -> LR-02 | ER11: =C11 -> FBA79280 | ES11: =G11 -> B0D845B2DG | ET11: =B11 -> LR-02 | EU11: 12426 | EV11: 133 | EW11: 207905.5 | EX11: =EV11*J11 -> 112217.16 | EY11: 146 | EZ11: 2,24,804 | FA11: =1-EV11/EY11 -> 0.089041096 | FB11: =EW11/$EW$1 -> 0.031199214 | FC11: =B11 -> LR-02 | FD11: 276 | FE11: 708 | FF11: 0 | FG11: =FD11+FE11+FF11 -> 984 | FH11: =FG11*J11 -> 830238.23 | FI11: 1500 | FJ11: =FI11*J11 -> 1265607.1 | FK11: =FG11+FI11 -> 2484 | FL11: =FH11+FJ11 -> 2095845.3 | FM11: =B11 -> LR-02 | FN11: =C11 -> FBA79280 | FO11: =G11 -> B0D845B2DG | FP11: =B11 -> LR-02 | FQ11: 11680 | FR11: 153 | FS11: 228695.44 | FT11: 0 | FU11: 0 | FV11: =FR11+FT11 -> 153 | FW11: =FS11+FU11 -> 228695.44 | FX11: =FV11*J11 -> 129091.92 | FY11: =FW11/$FW$1 -> 0.024414764 | FZ11: =B11 -> LR-02 | GA11: 0 | GB11: 1944 | GC11: 0 | GD11: =GA11+GB11+GC11 -> 1944 | GE11: =GD11*J11 -> 1640226.8 | GF11: 1500 | GG11: =GF11*J11 -> 1265607.1 | GH11: =GD11+GF11 -> 3444 | GI11: =GE11+GG11 -> 2905833.8 | GJ11: =B11 -> LR-02 | GK11: =C11 -> FBA79280 | GL11: =G11 -> B0D845B2DG | GM11: =B11 -> LR-02 | GN11: 6186 | GO11: 104 | GP11: 157835 | GQ11: 0 | GR11: 0 | GS11: =GO11+GQ11 -> 104 | GT11: =GP11+GR11 -> 157835 | GU11: =GS11*J11 -> 87748.756 | GV11: =GT11/$GT$1 -> 0.016676757 | GW11: =B11 -> LR-02 | GX11: 222 | GY11: 1890 | GZ11: 0 | HA11: =GX11+GY11+GZ11 -> 2112 | HB11: =HA11*J11 -> 1781974.7 | HC11: 1500 | HD11: =HC11*J11 -> 1265607.1 | HE11: =HA11+HC11 -> 3612 | HF11: =HB11+HD11 -> 3047581.8 | HG11: =B11 -> LR-02 | HH11: =C11 -> FBA79280 | HI11: =G11 -> B0D845B2DG | HJ11: =B11 -> LR-02 | HK11: 2019 | HL11: 100 | HM11: 149603.58 | HN11: 0 | HO11: 0 | HP11: =HL11+HN11 -> 100 | HQ11: =HM11+HO11 -> 149603.58 | HR11: =HP11*J11 -> 84373.804 | HS11: =HQ11/$HQ$1 -> 0.013660561 | HT11: =B11 -> LR-02 | HU11: 374 | HV11: 1648 | HW11: 0 | HX11: =HU11+HV11+HW11 -> 2022 | HY11: =HX11*J11 -> 1706038.3 | HZ11: 1500 | IA11: =HZ11*J11 -> 1265607.1 | IB11: =HX11+HZ11 -> 3522 | IC11: =HY11+IA11 -> 2971645.4 | ID11: =B11 -> LR-02 | IE11: =C11 -> FBA79280 | IF11: =G11 -> B0D845B2DG | IG11: =B11 -> LR-02 | IH11: 3592 | II11: 101 | IJ11: 149382.31 | IK11: 0 | IL11: 0 | IM11: =II11+IK11 -> 101 | IN11: =IJ11+IL11 -> 149382.31 | IO11: =IM11*J11 -> 85217.542 | IP11: =IN11/$IN$1 -> 0.013175037 | IQ11: =B11 -> LR-02 | IR11: 403 | IS11: 1649 | IT11: 0 | IU11: =IR11+IS11+IT11 -> 2052 | IV11: =IU11*J11 -> 1731350.5 | IW11: 1500 | IX11: =IW11*J11 -> 1265607.1 | IY11: =IU11+IW11 -> 3552 | IZ11: =IV11+IX11 -> 2996957.5 | JA11: =B11 -> LR-02 | JB11: =C11 -> FBA79280 | JC11: =G11 -> B0D845B2DG | JD11: =B11 -> LR-02 | JE11: 2959 | JF11: 81 | JG11: 118750.18 | JH11: 0 | JI11: 0 | JJ11: =JF11+JH11 -> 81 | JK11: =JG11+JI11 -> 118750.18 | JL11: =JJ11*J11 -> 68342.781 | JM11: =JK11/$JK$1 -> 0.013133495 | JN11: =B11 -> LR-02 | JO11: 403 | JP11: 1649 | JQ11: 0 | JR11: =JO11+JP11+JQ11 -> 2052 | JS11: =JR11*AG11 -> 0 | JT11: 1500 | JU11: =JT11*AG11 -> 0 | JV11: =JR11+JT11 -> 3552 | JW11: =JS11+JU11 -> 0 | JX11: =B11 -> LR-02 | JY11: =C11 -> FBA79280 | JZ11: =G11 -> B0D845B2DG | KA11: =B11 -> LR-02 | KB11: 4852 | KC11: 70 | KD11: 103753.4 | KE11: 0 | KF11: 0 | KG11: =KC11+KE11 -> 70 | KH11: =KD11+KF11 -> 103753.4 | KI11: =KG11*J11 -> 59061.663 | KJ11: =KH11/$KH$1 -> 0.0087924391 | KK11: =B11 -> LR-02 | KL11: 403 | KM11: 1649 | KN11: 0 | KO11: =KL11+KM11+KN11 -> 2052 | KP11: =KO11*BD11 -> 196992 | KQ11: 1500 | KR11: =KQ11*BD11 -> 144000 | KS11: =KO11+KQ11 -> 3552 | KT11: =KP11+KR11 -> 340992 | KU11: =B11 -> LR-02 | KV11: =C11 -> FBA79280 | KW11: =G11 -> B0D845B2DG | KX11: =B11 -> LR-02 | KY11: 1376 | KZ11: 82 | LA11: 116879.44 | LB11: 0 | LC11: 0 | LD11: =KZ11+LB11 -> 82 | LE11: =LA11+LC11 -> 116879.44 | LF11: =LD11*J11 -> 69186.52 | LG11: =LE11/$LE$1 -> 0.008691811 | LH11: =B11 -> LR-02 | LI11: 403 | LJ11: 1649 | LK11: 0 | LL11: =LI11+LJ11+LK11 -> 2052 | LM11: =LL11*CA11 -> 4594428 | LN11: 1500 | LO11: =LN11*CA11 -> 3358500 | LP11: =LL11+LN11 -> 3552 | LQ11: =LM11+LO11 -> 7952928 | LR11: =B11 -> LR-02 | LS11: =C11 -> FBA79280 | LT11: =G11 -> B0D845B2DG | LU11: =B11 -> LR-02 | LV11: 9309 | LW11: 75 | LX11: 112875 | LY11: 0 | LZ11: 0 | MA11: =LW11+LY11 -> 75 | MB11: =LX11+LZ11 -> 112875 | MC11: =MA11*J11 -> 63280.353 | MD11: =MB11/$MB$1 -> 0.011898596 | ME11: =B11 -> LR-02 | MF11: 403 | MG11: 1649 | MH11: 0 | MI11: =MF11+MG11+MH11 -> 2052 | MJ11: =MI11*CX11 -> 2.9831169e+09 | MK11: 1500 | ML11: =MK11*CX11 -> 2.180641e+09 | MM11: =MI11+MK11 -> 3552 | MN11: =MJ11+ML11 -> 5.1637578e+09 | MO11: =B11 -> LR-02 | MP11: =C11 -> FBA79280 | MQ11: =G11 -> B0D845B2DG | MR11: =B11 -> LR-02 | MS11: 6243 | MT11: 127 | MU11: 183241 | MV11: 0 | MW11: 0 | MX11: =MT11+MV11 -> 127 | MY11: =MU11+MW11 -> 183241 | MZ11: =MX11*J11 -> 107154.73 | NA11: =MY11/$MY$1 -> 0.014595807 | NB11: =B11 -> LR-02 | NC11: 403 | ND11: 1649 | NE11: 0 | NF11: =NC11+ND11+NE11 -> 2052 | NG11: =NF11*DU11 -> #VALUE! | NH11: 1500 | NI11: =NH11*DU11 -> #VALUE! | NJ11: =NF11+NH11 -> 3552 | NK11: =NG11+NI11 -> #VALUE! | NL11: =B11 -> LR-02 | NM11: =C11 -> FBA79280 | NN11: =G11 -> B0D845B2DG | NO11: =Y11 -> 0 | NP11: 4978 | NQ11: 134 | NR11: 188602 | NS11: 0 | NT11: 0 | NU11: =NQ11+NS11 -> 134 | NV11: =NR11+NT11 -> 188602 | NW11: =NU11*J11 -> 113060.9 | NX11: =NV11/$NV$1 -> 0.019592062 | NY11: =B11 -> LR-02 | NZ11: 403 | OA11: 1649 | OB11: 0 | OC11: =NZ11+OA11+OB11 -> 2052 | OD11: =OC11*ER11 -> #VALUE! | OE11: 1500 | OF11: =OE11*ER11 -> #VALUE! | OG11: =OC11+OE11 -> 3552 | OH11: =OD11+OF11 -> #VALUE! | OI11: =B11 -> LR-02 | OJ11: =C11 -> FBA79280 | OK11: =G11 -> B0D845B2DG | OL11: =B11 -> LR-02
A12: FBA79333 | B12: HM-02 | C12: FBA79333 | D12: HPC | E12: Hair Care | F12: Nexlev | G12: B0D63DTKQB | H12: Scalp Massager Pro | I12: 544.83767 | J12: 642.90845 | K12: 0 | L12: 0 | M12: 0 | N12: =1-L12/M12 -> #DIV/0! | O12: 0 | P12: 0 | Q12: 0 | R12: =1-P12/Q12 -> #DIV/0! | S12: 0 | T12: 0 | U12: 0 | V12: =1-T12/U12 -> #DIV/0! | W12: 0 | X12: 0 | Y12: 0 | Z12: =1-X12/Y12 -> #DIV/0! | AA12: 0 | AB12: 0 | AC12: 0 | AD12: =1-AB12/AC12 -> #DIV/0! | AE12: 0 | AF12: 0 | AG12: 0 | AH12: =1-AF12/AG12 -> #DIV/0! | AI12: 0 | AJ12: 0 | AK12: 0 | AL12: =1-AJ12/AK12 -> #DIV/0! | AM12: 0 | AN12: 0 | AO12: 0 | AP12: =1-AN12/AO12 -> #DIV/0! | AQ12: 248 | AR12: 11 | AS12: 16 | AT12: =1-AR12/AS12 -> 0.3125 | AU12: 11757 | AV12: 358 | AW12: 407 | AX12: =1-AV12/AW12 -> 0.12039312 | AY12: 17499 | AZ12: 515 | BA12: 588 | BB12: =1-AZ12/BA12 -> 0.12414966 | BC12: 17299 | BD12: 405 | BE12: 504 | BF12: =1-BD12/BE12 -> 0.19642857 | BG12: 18552 | BH12: 539 | BI12: 579 | BJ12: =1-BH12/BI12 -> 0.069084629 | BK12: 9028 | BL12: 231 | BM12: 332311 | BN12: =BL12*J12 -> 148511.85 | BO12: 240 | BP12: 331677 | BQ12: =1-BL12/BO12 -> 0.0375 | BR12: =BM12/$BM$1 -> 0.027064667 | BS12: =B12 -> HM-02 | BT12: 993 | BU12: 1777 | BV12: 0 | BW12: =BT12+BU12+BV12 -> 2770 | BX12: =BW12*J12 -> 1780856.4 | BY12: 0 | BZ12: =BY12*J12 -> 0 | CA12: =BW12+BY12 -> 2770 | CB12: =BX12+BZ12 -> 1780856.4 | CC12: =B12 -> HM-02 | CD12: =C12 -> FBA79333 | CE12: =G12 -> B0D63DTKQB | CF12: =B12 -> HM-02 | CG12: 8206 | CH12: 116 | CI12: 172750.5 | CJ12: =CH12*J12 -> 74577.38 | CK12: 133 | CL12: 189323 | CM12: =1-CH12/CK12 -> 0.12781955 | CN12: =CI12/$CI$1 -> 0.015220368 | CO12: =B12 -> HM-02 | CP12: 883 | CQ12: 1762 | CR12: 0 | CS12: =CP12+CQ12+CR12 -> 2645 | CT12: =CS12*J12 -> 1700492.8 | CU12: 0 | CV12: =CU12*J12 -> 0 | CW12: =CS12+CU12 -> 2645 | CX12: =CT12+CV12 -> 1700492.8 | CY12: =B12 -> HM-02 | CZ12: =C12 -> FBA79333 | DA12: =G12 -> B0D63DTKQB | DB12: =B12 -> HM-02 | DC12: 9916 | DD12: 150 | DE12: 208634.52 | DF12: =DD12*J12 -> 96436.267 | DG12: 177 | DH12: 232483 | DI12: =1-DD12/DG12 -> 0.15254237 | DJ12: =DE12/$DE$1 -> 0.016542907 | DK12: =B12 -> HM-02 | DL12: 709 | DM12: 1695 | DN12: 0 | DO12: =DL12+DM12+DN12 -> 2404 | DP12: =DO12*J12 -> 1545551.9 | DQ12: 0 | DR12: =DQ12*J12 -> 0 | DS12: =DO12+DQ12 -> 2404 | DT12: =DP12+DR12 -> 1545551.9 | DU12: =B12 -> HM-02 | DV12: =C12 -> FBA79333 | DW12: =G12 -> B0D63DTKQB | DX12: =B12 -> HM-02 | DY12: 6095 | DZ12: 57 | EA12: 85537 | EB12: =DZ12*J12 -> 36645.782 | EC12: 76 | ED12: 97480 | EE12: =1-DZ12/EC12 -> 0.25 | EF12: =EA12/$EA$1 -> 0.009734896 | EG12: =B12 -> HM-02 | EH12: 644 | EI12: 1276 | EJ12: 0 | EK12: =EH12+EI12+EJ12 -> 1920 | EL12: =EK12*J12 -> 1234384.2 | EM12: 0 | EN12: =EM12*J12 -> 0 | EO12: =EK12+EM12 -> 1920 | EP12: =EL12+EN12 -> 1234384.2 | EQ12: =B12 -> HM-02 | ER12: =C12 -> FBA79333 | ES12: =G12 -> B0D63DTKQB | ET12: =B12 -> HM-02 | EU12: 4481 | EV12: 11 | EW12: 13564 | EX12: =EV12*J12 -> 7071.9929 | EY12: 16 | EZ12: 15531 | FA12: =1-EV12/EY12 -> 0.3125 | FB12: =EW12/$EW$1 -> 0.0020354735 | FC12: =B12 -> HM-02 | FD12: 146 | FE12: 1239 | FF12: 0 | FG12: =FD12+FE12+FF12 -> 1385 | FH12: =FG12*J12 -> 890428.2 | FI12: 0 | FJ12: =FI12*J12 -> 0 | FK12: =FG12+FI12 -> 1385 | FL12: =FH12+FJ12 -> 890428.2 | FM12: =B12 -> HM-02 | FN12: =C12 -> FBA79333 | FO12: =G12 -> B0D63DTKQB | FP12: =B12 -> HM-02 | FQ12: 2899 | FR12: 30 | FS12: 32165 | FT12: 82 | FU12: 81918.231 | FV12: =FR12+FT12 -> 112 | FW12: =FS12+FU12 -> 114083.23 | FX12: =FV12*J12 -> 72005.746 | FY12: =FW12/$FW$1 -> 0.012179146 | FZ12: =B12 -> HM-02 | GA12: 168 | GB12: 953 | GC12: 0 | GD12: =GA12+GB12+GC12 -> 1121 | GE12: =GD12*J12 -> 720700.37 | GF12: 0 | GG12: =GF12*J12 -> 0 | GH12: =GD12+GF12 -> 1121 | GI12: =GE12+GG12 -> 720700.37 | GJ12: =B12 -> HM-02 | GK12: =C12 -> FBA79333 | GL12: =G12 -> B0D63DTKQB | GM12: =B12 -> HM-02 | GN12: 2499 | GO12: 9 | GP12: 9165.81 | GQ12: 90 | GR12: 89910.301 | GS12: =GO12+GQ12 -> 99 | GT12: =GP12+GR12 -> 99076.111 | GU12: =GS12*J12 -> 63647.936 | GV12: =GT12/$GT$1 -> 0.010468326 | GW12: =B12 -> HM-02 | GX12: 109 | GY12: 1172 | GZ12: 0 | HA12: =GX12+GY12+GZ12 -> 1281 | HB12: =HA12*J12 -> 823565.72 | HC12: 0 | HD12: =HC12*J12 -> 0 | HE12: =HA12+HC12 -> 1281 | HF12: =HB12+HD12 -> 823565.72 | HG12: =B12 -> HM-02 | HH12: =C12 -> FBA79333 | HI12: =G12 -> B0D63DTKQB | HJ12: =B12 -> HM-02 | HK12: 3272 | HL12: 6 | HM12: 8040 | HN12: 68 | HO12: 88732.035 | HP12: =HL12+HN12 -> 74 | HQ12: =HM12+HO12 -> 96772.035 | HR12: =HP12*J12 -> 47575.225 | HS12: =HQ12/$HQ$1 -> 0.0088364217 | HT12: =B12 -> HM-02 | HU12: 175 | HV12: 888 | HW12: 0 | HX12: =HU12+HV12+HW12 -> 1063 | HY12: =HX12*J12 -> 683411.68 | HZ12: 0 | IA12: =HZ12*J12 -> 0 | IB12: =HX12+HZ12 -> 1063 | IC12: =HY12+IA12 -> 683411.68 | ID12: =B12 -> HM-02 | IE12: =C12 -> FBA79333 | IF12: =G12 -> B0D63DTKQB | IG12: =B12 -> HM-02 | IH12: 3140 | II12: 7 | IJ12: 7541 | IK12: 99 | IL12: 128937.93 | IM12: =II12+IK12 -> 106 | IN12: =IJ12+IL12 -> 136478.93 | IO12: =IM12*J12 -> 68148.295 | IP12: =IN12/$IN$1 -> 0.012037 | IQ12: =B12 -> HM-02 | IR12: 211 | IS12: 763 | IT12: 0 | IU12: =IR12+IS12+IT12 -> 974 | IV12: =IU12*J12 -> 626192.83 | IW12: 0 | IX12: =IW12*J12 -> 0 | IY12: =IU12+IW12 -> 974 | IZ12: =IV12+IX12 -> 626192.83 | JA12: =B12 -> HM-02 | JB12: =C12 -> FBA79333 | JC12: =G12 -> B0D63DTKQB | JD12: =B12 -> HM-02 | JE12: 2162 | JF12: 4 | JG12: 5932 | JH12: 38 | JI12: 52167.942 | JJ12: =JF12+JH12 -> 42 | JK12: =JG12+JI12 -> 58099.942 | JL12: =JJ12*J12 -> 27002.155 | JM12: =JK12/$JK$1 -> 0.006425719 | JN12: =B12 -> HM-02 | JO12: 211 | JP12: 763 | JQ12: 0 | JR12: =JO12+JP12+JQ12 -> 974 | JS12: =JR12*AG12 -> 0 | JT12: 0 | JU12: =JT12*AG12 -> 0 | JV12: =JR12+JT12 -> 974 | JW12: =JS12+JU12 -> 0 | JX12: =B12 -> HM-02 | JY12: =C12 -> FBA79333 | JZ12: =G12 -> B0D63DTKQB | KA12: =B12 -> HM-02 | KB12: 2176 | KC12: 3 | KD12: 4207 | KE12: 33 | KF12: 40146.916 | KG12: =KC12+KE12 -> 36 | KH12: =KD12+KF12 -> 44353.916 | KI12: =KG12*J12 -> 23144.704 | KJ12: =KH12/$KH$1 -> 0.0037587116 | KK12: =B12 -> HM-02 | KL12: 211 | KM12: 763 | KN12: 0 | KO12: =KL12+KM12+KN12 -> 974 | KP12: =KO12*BD12 -> 394470 | KQ12: 0 | KR12: =KQ12*BD12 -> 0 | KS12: =KO12+KQ12 -> 974 | KT12: =KP12+KR12 -> 394470 | KU12: =B12 -> HM-02 | KV12: =C12 -> FBA79333 | KW12: =G12 -> B0D63DTKQB | KX12: =B12 -> HM-02 | KY12: 1963 | KZ12: 15 | LA12: 20996.18 | LB12: 25 | LC12: 28067.091 | LD12: =KZ12+LB12 -> 40 | LE12: =LA12+LC12 -> 49063.271 | LF12: =LD12*J12 -> 25716.338 | LG12: =LE12/$LE$1 -> 0.0036486201 | LH12: =B12 -> HM-02 | LI12: 211 | LJ12: 763 | LK12: 0 | LL12: =LI12+LJ12+LK12 -> 974 | LM12: =LL12*CA12 -> 2697980 | LN12: 0 | LO12: =LN12*CA12 -> 0 | LP12: =LL12+LN12 -> 974 | LQ12: =LM12+LO12 -> 2697980 | LR12: =B12 -> HM-02 | LS12: =C12 -> FBA79333 | LT12: =G12 -> B0D63DTKQB | LU12: =B12 -> HM-02 | LV12: 4503 | LW12: 19 | LX12: 26794.45 | LY12: 6 | LZ12: 7659.04 | MA12: =LW12+LY12 -> 25 | MB12: =LX12+LZ12 -> 34453.49 | MC12: =MA12*J12 -> 16072.711 | MD12: =MB12/$MB$1 -> 0.0036318773 | ME12: =B12 -> HM-02 | MF12: 211 | MG12: 763 | MH12: 0 | MI12: =MF12+MG12+MH12 -> 974 | MJ12: =MI12*CX12 -> 1.65628e+09 | MK12: 0 | ML12: =MK12*CX12 -> 0 | MM12: =MI12+MK12 -> 974 | MN12: =MJ12+ML12 -> 1.65628e+09 | MO12: =B12 -> HM-02 | MP12: =C12 -> FBA79333 | MQ12: =G12 -> B0D63DTKQB | MR12: =B12 -> HM-02 | MS12: 3762 | MT12: 32 | MU12: 40581 | MV12: 0 | MW12: 0 | MX12: =MT12+MV12 -> 32 | MY12: =MU12+MW12 -> 40581 | MZ12: =MX12*J12 -> 20573.07 | NA12: =MY12/$MY$1 -> 0.0032324231 | NB12: =B12 -> HM-02 | NC12: 211 | ND12: 763 | NE12: 0 | NF12: =NC12+ND12+NE12 -> 974 | NG12: =NF12*DU12 -> #VALUE! | NH12: 0 | NI12: =NH12*DU12 -> #VALUE! | NJ12: =NF12+NH12 -> 974 | NK12: =NG12+NI12 -> #VALUE! | NL12: =B12 -> HM-02 | NM12: =C12 -> FBA79333 | NN12: =G12 -> B0D63DTKQB | NO12: =Y12 -> 0 | NP12: 1164 | NQ12: 27 | NR12: 39191 | NS12: 0 | NT12: 0 | NU12: =NQ12+NS12 -> 27 | NV12: =NR12+NT12 -> 39191 | NW12: =NU12*J12 -> 17358.528 | NX12: =NV12/$NV$1 -> 0.004071179 | NY12: =B12 -> HM-02 | NZ12: 211 | OA12: 763 | OB12: 0 | OC12: =NZ12+OA12+OB12 -> 974 | OD12: =OC12*ER12 -> #VALUE! | OE12: 0 | OF12: =OE12*ER12 -> #VALUE! | OG12: =OC12+OE12 -> 974 | OH12: =OD12+OF12 -> #VALUE! | OI12: =B12 -> HM-02 | OJ12: =C12 -> FBA79333 | OK12: =G12 -> B0D63DTKQB | OL12: =B12 -> HM-02
A13: FBA79266 | B13: T-01 | C13: FBA79266 | D13: HPC | E13: Trimmers & Body Groomers | F13: Nexlev | G13: B0D2LGR3GG | H13: Velvet Vibe Multi-Trimmer | I13: 416.40113 | J13: 491.35333 | K13: 0 | L13: 0 | M13: 0 | N13: =1-L13/M13 -> #DIV/0! | O13: 0 | P13: 0 | Q13: 0 | R13: =1-P13/Q13 -> #DIV/0! | S13: 0 | T13: 0 | U13: 0 | V13: =1-T13/U13 -> #DIV/0! | W13: 0 | X13: 0 | Y13: 0 | Z13: =1-X13/Y13 -> #DIV/0! | AA13: 0 | AB13: 0 | AC13: 0 | AD13: =1-AB13/AC13 -> #DIV/0! | AE13: 0 | AF13: 0 | AG13: 0 | AH13: =1-AF13/AG13 -> #DIV/0! | AI13: 0 | AJ13: 0 | AK13: 0 | AL13: =1-AJ13/AK13 -> #DIV/0! | AM13: 68 | AN13: 0 | AO13: 1 | AP13: =1-AN13/AO13 -> 1 | AQ13: 1338 | AR13: 42 | AS13: 44 | AT13: =1-AR13/AS13 -> 0.045454545 | AU13: 4436 | AV13: 222 | AW13: 258 | AX13: =1-AV13/AW13 -> 0.13953488 | AY13: 5076 | AZ13: 216 | BA13: 246 | BB13: =1-AZ13/BA13 -> 0.12195122 | BC13: 6215 | BD13: 276 | BE13: 334 | BF13: =1-BD13/BE13 -> 0.17365269 | BG13: 10474 | BH13: 555 | BI13: 558 | BJ13: =1-BH13/BI13 -> 0.0053763441 | BK13: 8108 | BL13: 350 | BM13: 297229 | BN13: =BL13*J13 -> 171973.67 | BO13: 373 | BP13: 315828 | BQ13: =1-BL13/BO13 -> 0.061662198 | BR13: =BM13/$BM$1 -> 0.024207456 | BS13: =B13 -> T-01 | BT13: 785 | BU13: 1443 | BV13: 0 | BW13: =BT13+BU13+BV13 -> 2228 | BX13: =BW13*J13 -> 1094735.2 | BY13: 0 | BZ13: =BY13*J13 -> 0 | CA13: =BW13+BY13 -> 2228 | CB13: =BX13+BZ13 -> 1094735.2 | CC13: =B13 -> T-01 | CD13: =C13 -> FBA79266 | CE13: =G13 -> B0D2LGR3GG | CF13: =B13 -> T-01 | CG13: 5797 | CH13: 205 | CI13: 182684.03 | CJ13: =CH13*J13 -> 100727.43 | CK13: 213 | CL13: 189355 | CM13: =1-CH13/CK13 -> 0.037558685 | CN13: =CI13/$CI$1 -> 0.016095573 | CO13: =B13 -> T-01 | CP13: 1006 | CQ13: 1037 | CR13: 0 | CS13: =CP13+CQ13+CR13 -> 2043 | CT13: =CS13*J13 -> 1003834.9 | CU13: 0 | CV13: =CU13*J13 -> 0 | CW13: =CS13+CU13 -> 2043 | CX13: =CT13+CV13 -> 1003834.9 | CY13: =B13 -> T-01 | CZ13: =C13 -> FBA79266 | DA13: =G13 -> B0D2LGR3GG | DB13: =B13 -> T-01 | DC13: 4096 | DD13: 151 | DE13: 127803.1 | DF13: =DD13*J13 -> 74194.353 | DG13: 165 | DH13: 138092 | DI13: =1-DD13/DG13 -> 0.084848485 | DJ13: =DE13/$DE$1 -> 0.010133677 | DK13: =B13 -> T-01 | DL13: 825 | DM13: 1023 | DN13: 0 | DO13: =DL13+DM13+DN13 -> 1848 | DP13: =DO13*J13 -> 908020.96 | DQ13: 0 | DR13: =DQ13*J13 -> 0 | DS13: =DO13+DQ13 -> 1848 | DT13: =DP13+DR13 -> 908020.96 | DU13: =B13 -> T-01 | DV13: =C13 -> FBA79266 | DW13: =G13 -> B0D2LGR3GG | DX13: =B13 -> T-01 | DY13: 3390 | DZ13: 87 | EA13: 78438 | EB13: =DZ13*J13 -> 42747.74 | EC13: 97 | ED13: 87455 | EE13: =1-DZ13/EC13 -> 0.10309278 | EF13: =EA13/$EA$1 -> 0.0089269646 | EG13: =B13 -> T-01 | EH13: 745 | EI13: 845 | EJ13: 0 | EK13: =EH13+EI13+EJ13 -> 1590 | EL13: =EK13*J13 -> 781251.8 | EM13: 0 | EN13: =EM13*J13 -> 0 | EO13: =EK13+EM13 -> 1590 | EP13: =EL13+EN13 -> 781251.8 | EQ13: =B13 -> T-01 | ER13: =C13 -> FBA79266 | ES13: =G13 -> B0D2LGR3GG | ET13: =B13 -> T-01 | EU13: 5583 | EV13: 14 | EW13: 12658 | EX13: =EV13*J13 -> 6878.9466 | EY13: 14 | EZ13: 12640 | FA13: =1-EV13/EY13 -> 0 | FB13: =EW13/$EW$1 -> 0.0018995152 | FC13: =B13 -> T-01 | FD13: 718 | FE13: 762 | FF13: 0 | FG13: =FD13+FE13+FF13 -> 1480 | FH13: =FG13*J13 -> 727202.93 | FI13: 0 | FJ13: =FI13*J13 -> 0 | FK13: =FG13+FI13 -> 1480 | FL13: =FH13+FJ13 -> 727202.93 | FM13: =B13 -> T-01 | FN13: =C13 -> FBA79266 | FO13: =G13 -> B0D2LGR3GG | FP13: =B13 -> T-01 | FQ13: 4503 | FR13: 20 | FS13: 18075 | FT13: 155 | FU13: 138644.57 | FV13: =FR13+FT13 -> 175 | FW13: =FS13+FU13 -> 156719.57 | FX13: =FV13*J13 -> 85986.833 | FY13: =FW13/$FW$1 -> 0.01673086 | FZ13: =B13 -> T-01 | GA13: 276 | GB13: 409 | GC13: 0 | GD13: =GA13+GB13+GC13 -> 685 | GE13: =GD13*J13 -> 336577.03 | GF13: 0 | GG13: =GF13*J13 -> 0 | GH13: =GD13+GF13 -> 685 | GI13: =GE13+GG13 -> 336577.03 | GJ13: =B13 -> T-01 | GK13: =C13 -> FBA79266 | GL13: =G13 -> B0D2LGR3GG | GM13: =B13 -> T-01 | GN13: 6527 | GO13: 11 | GP13: 9777.54 | GQ13: 243 | GR13: 215833.94 | GS13: =GO13+GQ13 -> 254 | GT13: =GP13+GR13 -> 225611.48 | GU13: =GS13*J13 -> 124803.75 | GV13: =GT13/$GT$1 -> 0.023837982 | GW13: =B13 -> T-01 | GX13: 145 | GY13: 107 | GZ13: 0 | HA13: =GX13+GY13+GZ13 -> 252 | HB13: =HA13*J13 -> 123821.04 | HC13: 0 | HD13: =HC13*J13 -> 0 | HE13: =HA13+HC13 -> 252 | HF13: =HB13+HD13 -> 123821.04 | HG13: =B13 -> T-01 | HH13: =C13 -> FBA79266 | HI13: =G13 -> B0D2LGR3GG | HJ13: =B13 -> T-01 | HK13: 4024 | HL13: 8 | HM13: 7246 | HN13: 149 | HO13: 133842.18 | HP13: =HL13+HN13 -> 157 | HQ13: =HM13+HO13 -> 141088.18 | HR13: =HP13*J13 -> 77142.473 | HS13: =HQ13/$HQ$1 -> 0.012883006 | HT13: =B13 -> T-01 | HU13: 46 | HV13: 218 | HW13: 0 | HX13: =HU13+HV13+HW13 -> 264 | HY13: =HX13*J13 -> 129717.28 | HZ13: 0 | IA13: =HZ13*J13 -> 0 | IB13: =HX13+HZ13 -> 264 | IC13: =HY13+IA13 -> 129717.28 | ID13: =B13 -> T-01 | IE13: =C13 -> FBA79266 | IF13: =G13 -> B0D2LGR3GG | IG13: =B13 -> T-01 | IH13: 3798 | II13: 37 | IJ13: 33269 | IK13: 91 | IL13: 80982.255 | IM13: =II13+IK13 -> 128 | IN13: =IJ13+IL13 -> 114251.26 | IO13: =IM13*J13 -> 62893.226 | IP13: =IN13/$IN$1 -> 0.010076591 | IQ13: =B13 -> T-01 | IR13: 114 | IS13: 37 | IT13: 0 | IU13: =IR13+IS13+IT13 -> 151 | IV13: =IU13*J13 -> 74194.353 | IW13: 0 | IX13: =IW13*J13 -> 0 | IY13: =IU13+IW13 -> 151 | IZ13: =IV13+IX13 -> 74194.353 | JA13: =B13 -> T-01 | JB13: =C13 -> FBA79266 | JC13: =G13 -> B0D2LGR3GG | JD13: =B13 -> T-01 | JE13: 1313 | JF13: 5 | JG13: 4709 | JH13: 38 | JI13: 35740.123 | JJ13: =JF13+JH13 -> 43 | JK13: =JG13+JI13 -> 40449.123 | JL13: =JJ13*J13 -> 21128.193 | JM13: =JK13/$JK$1 -> 0.0044735794 | JN13: =B13 -> T-01 | JO13: 114 | JP13: 37 | JQ13: 0 | JR13: =JO13+JP13+JQ13 -> 151 | JS13: =JR13*AG13 -> 0 | JT13: 0 | JU13: =JT13*AG13 -> 0 | JV13: =JR13+JT13 -> 151 | JW13: =JS13+JU13 -> 0 | JX13: =B13 -> T-01 | JY13: =C13 -> FBA79266 | JZ13: =G13 -> B0D2LGR3GG | KA13: =B13 -> T-01 | KB13: 1091 | KC13: 3 | KD13: 3087 | KE13: 16 | KF13: 15149.041 | KG13: =KC13+KE13 -> 19 | KH13: =KD13+KF13 -> 18236.041 | KI13: =KG13*J13 -> 9335.7133 | KJ13: =KH13/$KH$1 -> 0.0015453882 | KK13: =B13 -> T-01 | KL13: 114 | KM13: 37 | KN13: 0 | KO13: =KL13+KM13+KN13 -> 151 | KP13: =KO13*BD13 -> 41676 | KQ13: 0 | KR13: =KQ13*BD13 -> 0 | KS13: =KO13+KQ13 -> 151 | KT13: =KP13+KR13 -> 41676 | KU13: =B13 -> T-01 | KV13: =C13 -> FBA79266 | KW13: =G13 -> B0D2LGR3GG | KX13: =B13 -> T-01 | KY13: 991 | KZ13: 1 | LA13: 899 | LB13: 20 | LC13: 18825.272 | LD13: =KZ13+LB13 -> 21 | LE13: =LA13+LC13 -> 19724.272 | LF13: =LD13*J13 -> 10318.42 | LG13: =LE13/$LE$1 -> 0.0014668075 | LH13: =B13 -> T-01 | LI13: 114 | LJ13: 37 | LK13: 0 | LL13: =LI13+LJ13+LK13 -> 151 | LM13: =LL13*CA13 -> 336428 | LN13: 0 | LO13: =LN13*CA13 -> 0 | LP13: =LL13+LN13 -> 151 | LQ13: =LM13+LO13 -> 336428 | LR13: =B13 -> T-01 | LS13: =C13 -> FBA79266 | LT13: =G13 -> B0D2LGR3GG | LU13: =B13 -> T-01 | LV13: 955 | LW13: 0 | LX13: 0 | LY13: 13 | LZ13: 10692.51 | MA13: =LW13+LY13 -> 13 | MB13: =LX13+LZ13 -> 10692.51 | MC13: =MA13*J13 -> 6387.5933 | MD13: =MB13/$MB$1 -> 0.0011271394 | ME13: =B13 -> T-01 | MF13: 114 | MG13: 37 | MH13: 0 | MI13: =MF13+MG13+MH13 -> 151 | MJ13: =MI13*CX13 -> 1.5157906e+08 | MK13: 0 | ML13: =MK13*CX13 -> 0 | MM13: =MI13+MK13 -> 151 | MN13: =MJ13+ML13 -> 1.5157906e+08 | MO13: =B13 -> T-01 | MP13: =C13 -> FBA79266 | MQ13: =G13 -> B0D2LGR3GG | MR13: =B13 -> T-01 | MS13: 576 | MT13: 1 | MU13: 987 | MV13: 13 | MW13: 12622.389 | MX13: =MT13+MV13 -> 14 | MY13: =MU13+MW13 -> 13609.389 | MZ13: =MX13*J13 -> 6878.9466 | NA13: =MY13/$MY$1 -> 0.001084037 | NB13: =B13 -> T-01 | NC13: 114 | ND13: 37 | NE13: 0 | NF13: =NC13+ND13+NE13 -> 151 | NG13: =NF13*DU13 -> #VALUE! | NH13: 0 | NI13: =NH13*DU13 -> #VALUE! | NJ13: =NF13+NH13 -> 151 | NK13: =NG13+NI13 -> #VALUE! | NL13: =B13 -> T-01 | NM13: =C13 -> FBA79266 | NN13: =G13 -> B0D2LGR3GG | NO13: =Y13 -> 0 | NP13: 762 | NQ13: 0 | NR13: 0 | NS13: 5 | NT13: 4233.06 | NU13: =NQ13+NS13 -> 5 | NV13: =NR13+NT13 -> 4233.06 | NW13: =NU13*J13 -> 2456.7667 | NX13: =NV13/$NV$1 -> 0.00043973221 | NY13: =B13 -> T-01 | NZ13: 114 | OA13: 37 | OB13: 0 | OC13: =NZ13+OA13+OB13 -> 151 | OD13: =OC13*ER13 -> #VALUE! | OE13: 0 | OF13: =OE13*ER13 -> #VALUE! | OG13: =OC13+OE13 -> 151 | OH13: =OD13+OF13 -> #VALUE! | OI13: =B13 -> T-01 | OJ13: =C13 -> FBA79266 | OK13: =G13 -> B0D2LGR3GG | OL13: =B13 -> T-01
A14: FBA79229 | B14: GS-04 | C14: FBA79229 | D14: Home & Kitchen | E14: Fabric Care | F14: Nexlev | G14: B0CQX9ZZMH | H14: Nexlev Garment Steamer with Touch Screen | I14: 1212.5066 | J14: 1430.7578 | K14: 0 | L14: 0 | M14: 0 | N14: =1-L14/M14 -> #DIV/0! | O14: 0 | P14: 0 | Q14: 0 | R14: =1-P14/Q14 -> #DIV/0! | S14: 0 | T14: 0 | U14: 0 | V14: =1-T14/U14 -> #DIV/0! | W14: 0 | X14: 0 | Y14: 0 | Z14: =1-X14/Y14 -> #DIV/0! | AA14: 0 | AB14: 0 | AC14: 0 | AD14: =1-AB14/AC14 -> #DIV/0! | AE14: 554 | AF14: 19 | AG14: 21 | AH14: =1-AF14/AG14 -> 0.095238095 | AI14: 1332 | AJ14: 52 | AK14: 63 | AL14: =1-AJ14/AK14 -> 0.17460317 | AM14: 7189 | AN14: 70 | AO14: 89 | AP14: =1-AN14/AO14 -> 0.21348315 | AQ14: 1762 | AR14: 24 | AS14: 43 | AT14: =1-AR14/AS14 -> 0.44186047 | AU14: 781 | AV14: 8 | AW14: 13 | AX14: =1-AV14/AW14 -> 0.38461538 | AY14: 861 | AZ14: 16 | BA14: 20 | BB14: =1-AZ14/BA14 -> 0.2 | BC14: 1835 | BD14: 11 | BE14: 18 | BF14: =1-BD14/BE14 -> 0.38888889 | BG14: 679 | BH14: 27 | BI14: 31 | BJ14: =1-BH14/BI14 -> 0.12903226 | BK14: 22066 | BL14: 124 | BM14: 285375 | BN14: =BL14*J14 -> 177413.97 | BO14: 160 | BP14: 331208 | BQ14: =1-BL14/BO14 -> 0.225 | BR14: =BM14/$BM$1 -> 0.023242022 | BS14: =B14 -> GS-04 | BT14: 272 | BU14: 752 | BV14: 0 | BW14: =BT14+BU14+BV14 -> 1024 | BX14: =BW14*J14 -> 1465096 | BY14: 0 | BZ14: =BY14*J14 -> 0 | CA14: =BW14+BY14 -> 1024 | CB14: =BX14+BZ14 -> 1465096 | CC14: =B14 -> GS-04 | CD14: =C14 -> FBA79229 | CE14: =G14 -> B0CQX9ZZMH | CF14: =B14 -> GS-04 | CG14: 7904 | CH14: 80 | CI14: 184070.04 | CJ14: =CH14*J14 -> 114460.63 | CK14: 94 | CL14: 202324 | CM14: =1-CH14/CK14 -> 0.14893617 | CN14: =CI14/$CI$1 -> 0.016217689 | CO14: =B14 -> GS-04 | CP14: 429 | CQ14: 494 | CR14: 0 | CS14: =CP14+CQ14+CR14 -> 923 | CT14: =CS14*J14 -> 1320589.5 | CU14: 0 | CV14: =CU14*J14 -> 0 | CW14: =CS14+CU14 -> 923 | CX14: =CT14+CV14 -> 1320589.5 | CY14: =B14 -> GS-04 | CZ14: =C14 -> FBA79229 | DA14: =G14 -> B0CQX9ZZMH | DB14: =B14 -> GS-04 | DC14: 6561 | DD14: 96 | DE14: 219400.88 | DF14: =DD14*J14 -> 137352.75 | DG14: 118 | DH14: 246522 | DI14: =1-DD14/DG14 -> 0.18644068 | DJ14: =DE14/$DE$1 -> 0.017396586 | DK14: =B14 -> GS-04 | DL14: 395 | DM14: 292 | DN14: 0 | DO14: =DL14+DM14+DN14 -> 687 | DP14: =DO14*J14 -> 982930.64 | DQ14: 0 | DR14: =DQ14*J14 -> 0 | DS14: =DO14+DQ14 -> 687 | DT14: =DP14+DR14 -> 982930.64 | DU14: =B14 -> GS-04 | DV14: =C14 -> FBA79229 | DW14: =G14 -> B0CQX9ZZMH | DX14: =B14 -> GS-04 | DY14: 3710 | DZ14: 54 | EA14: 124146 | EB14: =DZ14*J14 -> 77260.923 | EC14: 69 | ED14: 1,44,837.00 | EE14: =1-DZ14/EC14 -> 0.2173913 | EF14: =EA14/$EA$1 -> 0.014128955 | EG14: =B14 -> GS-04 | EH14: 335 | EI14: 251 | EJ14: 0 | EK14: =EH14+EI14+EJ14 -> 586 | EL14: =EK14*J14 -> 838424.09 | EM14: 0 | EN14: =EM14*J14 -> 0 | EO14: =EK14+EM14 -> 586 | EP14: =EL14+EN14 -> 838424.09 | EQ14: =B14 -> GS-04 | ER14: =C14 -> FBA79229 | ES14: =G14 -> B0CQX9ZZMH | ET14: =B14 -> GS-04 | EU14: 1439 | EV14: 32 | EW14: 73532 | EX14: =EV14*J14 -> 45784.251 | EY14: 43 | EZ14: 89623 | FA14: =1-EV14/EY14 -> 0.25581395 | FB14: =EW14/$EW$1 -> 0.011034535 | FC14: =B14 -> GS-04 | FD14: 301 | FE14: 167 | FF14: 0 | FG14: =FD14+FE14+FF14 -> 468 | FH14: =FG14*J14 -> 669594.67 | FI14: 0 | FJ14: =FI14*J14 -> 0 | FK14: =FG14+FI14 -> 468 | FL14: =FH14+FJ14 -> 669594.67 | FM14: =B14 -> GS-04 | FN14: =C14 -> FBA79229 | FO14: =G14 -> B0CQX9ZZMH | FP14: =B14 -> GS-04 | FQ14: 924 | FR14: 23 | FS14: 50715 | FT14: 0 | FU14: 0 | FV14: =FR14+FT14 -> 23 | FW14: =FS14+FU14 -> 50715 | FX14: =FV14*J14 -> 32907.43 | FY14: =FW14/$FW$1 -> 0.0054141646 | FZ14: =B14 -> GS-04 | GA14: 0 | GB14: 162 | GC14: 0 | GD14: =GA14+GB14+GC14 -> 162 | GE14: =GD14*J14 -> 231782.77 | GF14: 0 | GG14: =GF14*J14 -> 0 | GH14: =GD14+GF14 -> 162 | GI14: =GE14+GG14 -> 231782.77 | GJ14: =B14 -> GS-04 | GK14: =C14 -> FBA79229 | GL14: =G14 -> B0CQX9ZZMH | GM14: =B14 -> GS-04 | GN14: 2807 | GO14: 33 | GP14: 72919 | GQ14: 0 | GR14: 0 | GS14: =GO14+GQ14 -> 33 | GT14: =GP14+GR14 -> 72919 | GU14: =GS14*J14 -> 47215.009 | GV14: =GT14/$GT$1 -> 0.0077045804 | GW14: =B14 -> GS-04 | GX14: 198 | GY14: 110 | GZ14: 0 | HA14: =GX14+GY14+GZ14 -> 308 | HB14: =HA14*J14 -> 440673.41 | HC14: 0 | HD14: =HC14*J14 -> 0 | HE14: =HA14+HC14 -> 308 | HF14: =HB14+HD14 -> 440673.41 | HG14: =B14 -> GS-04 | HH14: =C14 -> FBA79229 | HI14: =G14 -> B0CQX9ZZMH | HJ14: =B14 -> GS-04 | HK14: 1191 | HL14: 26 | HM14: 57325 | HN14: 0 | HO14: 0 | HP14: =HL14+HN14 -> 26 | HQ14: =HM14+HO14 -> 57325 | HR14: =HP14*J14 -> 37199.704 | HS14: =HQ14/$HQ$1 -> 0.0052344448 | HT14: =B14 -> GS-04 | HU14: 196 | HV14: 38 | HW14: 0 | HX14: =HU14+HV14+HW14 -> 234 | HY14: =HX14*J14 -> 334797.33 | HZ14: 0 | IA14: =HZ14*J14 -> 0 | IB14: =HX14+HZ14 -> 234 | IC14: =HY14+IA14 -> 334797.33 | ID14: =B14 -> GS-04 | IE14: =C14 -> FBA79229 | IF14: =G14 -> B0CQX9ZZMH | IG14: =B14 -> GS-04 | IH14: 1728 | II14: 66 | IJ14: 143966.49 | IK14: 0 | IL14: 0 | IM14: =II14+IK14 -> 66 | IN14: =IJ14+IL14 -> 143966.49 | IO14: =IM14*J14 -> 94430.017 | IP14: =IN14/$IN$1 -> 0.012697379 | IQ14: =B14 -> GS-04 | IR14: 127 | IS14: 5 | IT14: 0 | IU14: =IR14+IS14+IT14 -> 132 | IV14: =IU14*J14 -> 188860.03 | IW14: 0 | IX14: =IW14*J14 -> 0 | IY14: =IU14+IW14 -> 132 | IZ14: =IV14+IX14 -> 188860.03 | JA14: =B14 -> GS-04 | JB14: =C14 -> FBA79229 | JC14: =G14 -> B0CQX9ZZMH | JD14: =B14 -> GS-04 | JE14: 810 | JF14: 28 | JG14: 60166.96 | JH14: 0 | JI14: 0 | JJ14: =JF14+JH14 -> 28 | JK14: =JG14+JI14 -> 60166.96 | JL14: =JJ14*J14 -> 40061.219 | JM14: =JK14/$JK$1 -> 0.0066543265 | JN14: =B14 -> GS-04 | JO14: 127 | JP14: 5 | JQ14: 0 | JR14: =JO14+JP14+JQ14 -> 132 | JS14: =JR14*AG14 -> 2772 | JT14: 0 | JU14: =JT14*AG14 -> 0 | JV14: =JR14+JT14 -> 132 | JW14: =JS14+JU14 -> 2772 | JX14: =B14 -> GS-04 | JY14: =C14 -> FBA79229 | JZ14: =G14 -> B0CQX9ZZMH | KA14: =B14 -> GS-04 | KB14: 990 | KC14: 18 | KD14: 37109.74 | KE14: 0 | KF14: 0 | KG14: =KC14+KE14 -> 18 | KH14: =KD14+KF14 -> 37109.74 | KI14: =KG14*J14 -> 25753.641 | KJ14: =KH14/$KH$1 -> 0.0031448138 | KK14: =B14 -> GS-04 | KL14: 127 | KM14: 5 | KN14: 0 | KO14: =KL14+KM14+KN14 -> 132 | KP14: =KO14*BD14 -> 1452 | KQ14: 0 | KR14: =KQ14*BD14 -> 0 | KS14: =KO14+KQ14 -> 132 | KT14: =KP14+KR14 -> 1452 | KU14: =B14 -> GS-04 | KV14: =C14 -> FBA79229 | KW14: =G14 -> B0CQX9ZZMH | KX14: =B14 -> GS-04 | KY14: 1150 | KZ14: 40 | LA14: 82372.96 | LB14: 0 | LC14: 0 | LD14: =KZ14+LB14 -> 40 | LE14: =LA14+LC14 -> 82372.96 | LF14: =LD14*J14 -> 57230.314 | LG14: =LE14/$LE$1 -> 0.0061257155 | LH14: =B14 -> GS-04 | LI14: 127 | LJ14: 5 | LK14: 0 | LL14: =LI14+LJ14+LK14 -> 132 | LM14: =LL14*CA14 -> 135168 | LN14: 0 | LO14: =LN14*CA14 -> 0 | LP14: =LL14+LN14 -> 132 | LQ14: =LM14+LO14 -> 135168 | LR14: =B14 -> GS-04 | LS14: =C14 -> FBA79229 | LT14: =G14 -> B0CQX9ZZMH | LU14: =B14 -> GS-04 | LV14: 868 | LW14: 5 | LX14: 11212 | LY14: 0 | LZ14: 0 | MA14: =LW14+LY14 -> 5 | MB14: =LX14+LZ14 -> 11212 | MC14: =MA14*J14 -> 7153.7892 | MD14: =MB14/$MB$1 -> 0.0011819008 | ME14: =B14 -> GS-04 | MF14: 127 | MG14: 5 | MH14: 0 | MI14: =MF14+MG14+MH14 -> 132 | MJ14: =MI14*CX14 -> 1.7431781e+08 | MK14: 0 | ML14: =MK14*CX14 -> 0 | MM14: =MI14+MK14 -> 132 | MN14: =MJ14+ML14 -> 1.7431781e+08 | MO14: =B14 -> GS-04 | MP14: =C14 -> FBA79229 | MQ14: =G14 -> B0CQX9ZZMH | MR14: =B14 -> GS-04 | MS14: 599 | MT14: 12 | MU14: 19902 | MV14: 0 | MW14: 0 | MX14: =MT14+MV14 -> 12 | MY14: =MU14+MW14 -> 19902 | MZ14: =MX14*J14 -> 17169.094 | NA14: =MY14/$MY$1 -> 0.0015852661 | NB14: =B14 -> GS-04 | NC14: 127 | ND14: 5 | NE14: 0 | NF14: =NC14+ND14+NE14 -> 132 | NG14: =NF14*DU14 -> #VALUE! | NH14: 0 | NI14: =NH14*DU14 -> #VALUE! | NJ14: =NF14+NH14 -> 132 | NK14: =NG14+NI14 -> #VALUE! | NL14: =B14 -> GS-04 | NM14: =C14 -> FBA79229 | NN14: =G14 -> B0CQX9ZZMH | NO14: =Y14 -> 0 | NP14: 240 | NQ14: 13 | NR14: 26112 | NS14: 0 | NT14: 0 | NU14: =NQ14+NS14 -> 13 | NV14: =NR14+NT14 -> 26112 | NW14: =NU14*J14 -> 18599.852 | NX14: =NV14/$NV$1 -> 0.0027125265 | NY14: =B14 -> GS-04 | NZ14: 127 | OA14: 5 | OB14: 0 | OC14: =NZ14+OA14+OB14 -> 132 | OD14: =OC14*ER14 -> #VALUE! | OE14: 0 | OF14: =OE14*ER14 -> #VALUE! | OG14: =OC14+OE14 -> 132 | OH14: =OD14+OF14 -> #VALUE! | OI14: =B14 -> GS-04 | OJ14: =C14 -> FBA79229 | OK14: =G14 -> B0CQX9ZZMH | OL14: =B14 -> GS-04
A15: FBA79451 | B15: SS-01 | C15: FBA79451 | D15: Home & Kitchen | E15: Cleaning & Vacumming | F15: Nexlev | G15: B0D9KCKY9F | H15: Nexlev Spin Scrubber | I15: 1219.7609 | J15: 1439.3178 | K15: 0 | L15: 0 | M15: 0 | N15: =1-L15/M15 -> #DIV/0! | O15: 0 | P15: 0 | Q15: 0 | R15: =1-P15/Q15 -> #DIV/0! | S15: 0 | T15: 0 | U15: 0 | V15: =1-T15/U15 -> #DIV/0! | W15: 0 | X15: 0 | Y15: 0 | Z15: =1-X15/Y15 -> #DIV/0! | AA15: 0 | AB15: 0 | AC15: 0 | AD15: =1-AB15/AC15 -> #DIV/0! | AE15: 0 | AF15: 0 | AG15: 0 | AH15: =1-AF15/AG15 -> #DIV/0! | AI15: 0 | AJ15: 0 | AK15: 0 | AL15: =1-AJ15/AK15 -> #DIV/0! | AM15: 0 | AN15: 0 | AO15: 0 | AP15: =1-AN15/AO15 -> #DIV/0! | AQ15: 109 | AR15: 3 | AS15: 3 | AT15: =1-AR15/AS15 -> 0 | AU15: 56 | AV15: 0 | AW15: 1 | AX15: =1-AV15/AW15 -> 1 | AY15: 3662 | AZ15: 34 | BA15: 59 | BB15: =1-AZ15/BA15 -> 0.42372881 | BC15: 23608 | BD15: 155 | BE15: 217 | BF15: =1-BD15/BE15 -> 0.28571429 | BG15: 39099 | BH15: 480 | BI15: 570 | BJ15: =1-BH15/BI15 -> 0.15789474 | BK15: 11219 | BL15: 87 | BM15: 250913 | BN15: =BL15*J15 -> 125220.65 | BO15: 109 | BP15: 313691 | BQ15: =1-BL15/BO15 -> 0.20183486 | BR15: =BM15/$BM$1 -> 0.020435306 | BS15: =B15 -> SS-01 | BT15: 361 | BU15: 9 | BV15: 1000 | BW15: =BT15+BU15+BV15 -> 1370 | BX15: =BW15*J15 -> 1971865.4 | BY15: 1000 | BZ15: =BY15*J15 -> 1439317.8 | CA15: =BW15+BY15 -> 2370 | CB15: =BX15+BZ15 -> 3411183.3 | CC15: =B15 -> SS-01 | CD15: =C15 -> FBA79451 | CE15: =G15 -> B0D9KCKY9F | CF15: =B15 -> SS-01 | CG15: 12243 | CH15: 66 | CI15: 179738.16 | CJ15: =CH15*J15 -> 94994.977 | CK15: 79 | CL15: 214666 | CM15: =1-CH15/CK15 -> 0.16455696 | CN15: =CI15/$CI$1 -> 0.015836024 | CO15: =B15 -> SS-01 | CP15: 440 | CQ15: 555 | CR15: 1000 | CS15: =CP15+CQ15+CR15 -> 1995 | CT15: =CS15*J15 -> 2871439.1 | CU15: 1000 | CV15: =CU15*J15 -> 1439317.8 | CW15: =CS15+CU15 -> 2995 | CX15: =CT15+CV15 -> 4310756.9 | CY15: =B15 -> SS-01 | CZ15: =C15 -> FBA79451 | DA15: =G15 -> B0D9KCKY9F | DB15: =B15 -> SS-01 | DC15: 3521 | DD15: 31 | DE15: 82615.05 | DF15: =DD15*J15 -> 44618.853 | DG15: 41 | DH15: 109261 | DI15: =1-DD15/DG15 -> 0.24390244 | DJ15: =DE15/$DE$1 -> 0.0065506565 | DK15: =B15 -> SS-01 | DL15: 399 | DM15: 419 | DN15: 1000 | DO15: =DL15+DM15+DN15 -> 1818 | DP15: =DO15*J15 -> 2616679.8 | DQ15: 1000 | DR15: =DQ15*J15 -> 1439317.8 | DS15: =DO15+DQ15 -> 2818 | DT15: =DP15+DR15 -> 4055997.7 | DU15: =B15 -> SS-01 | DV15: =C15 -> FBA79451 | DW15: =G15 -> B0D9KCKY9F | DX15: =B15 -> SS-01 | DY15: 3401 | DZ15: 9 | EA15: 23691 | EB15: =DZ15*J15 -> 12953.861 | EC15: 9 | ED15: 23691 | EE15: =1-DZ15/EC15 -> 0 | EF15: =EA15/$EA$1 -> 0.0026962533 | EG15: =B15 -> SS-01 | EH15: 378 | EI15: 1294 | EJ15: 1000 | EK15: =EH15+EI15+EJ15 -> 2672 | EL15: =EK15*J15 -> 3845857.3 | EM15: 1000 | EN15: =EM15*J15 -> 1439317.8 | EO15: =EK15+EM15 -> 3672 | EP15: =EL15+EN15 -> 5285175.1 | EQ15: =B15 -> SS-01 | ER15: =C15 -> FBA79451 | ES15: =G15 -> B0D9KCKY9F | ET15: =B15 -> SS-01 | EU15: 10266 | EV15: 22 | EW15: 55108 | EX15: =EV15*J15 -> 31664.992 | EY15: 24 | EZ15: 60106 | FA15: =1-EV15/EY15 -> 0.083333333 | FB15: =EW15/$EW$1 -> 0.0082697489 | FC15: =B15 -> SS-01 | FD15: 324 | FE15: 771 | FF15: 1000 | FG15: =FD15+FE15+FF15 -> 2095 | FH15: =FG15*J15 -> 3015370.9 | FI15: 1000 | FJ15: =FI15*J15 -> 1439317.8 | FK15: =FG15+FI15 -> 3095 | FL15: =FH15+FJ15 -> 4454688.7 | FM15: =B15 -> SS-01 | FN15: =C15 -> FBA79451 | FO15: =G15 -> B0D9KCKY9F | FP15: =B15 -> SS-01 | FQ15: 84 | FR15: 0 | FS15: 0 | FT15: 0 | FU15: 0 | FV15: =FR15+FT15 -> 0 | FW15: =FS15+FU15 -> 0 | FX15: =FV15*J15 -> 0 | FY15: =FW15/$FW$1 -> 0 | FZ15: =B15 -> SS-01 | GA15: 0 | GB15: 251 | GC15: 1000 | GD15: =GA15+GB15+GC15 -> 1251 | GE15: =GD15*J15 -> 1800586.6 | GF15: 1000 | GG15: =GF15*J15 -> 1439317.8 | GH15: =GD15+GF15 -> 2251 | GI15: =GE15+GG15 -> 3239904.5 | GJ15: =B15 -> SS-01 | GK15: =C15 -> FBA79451 | GL15: =G15 -> B0D9KCKY9F | GM15: =B15 -> SS-01 | GN15: 484 | GO15: 4 | GP15: 10276 | GQ15: 0 | GR15: 0 | GS15: =GO15+GQ15 -> 4 | GT15: =GP15+GR15 -> 10276 | GU15: =GS15*J15 -> 5757.2714 | GV15: =GT15/$GT$1 -> 0.0010857564 | GW15: =B15 -> SS-01 | GX15: 0 | GY15: 237 | GZ15: 1000 | HA15: =GX15+GY15+GZ15 -> 1237 | HB15: =HA15*J15 -> 1780436.2 | HC15: 1000 | HD15: =HC15*J15 -> 1439317.8 | HE15: =HA15+HC15 -> 2237 | HF15: =HB15+HD15 -> 3219754 | HG15: =B15 -> SS-01 | HH15: =C15 -> FBA79451 | HI15: =G15 -> B0D9KCKY9F | HJ15: =B15 -> SS-01 | HK15: NA | HL15: 0 | HM15: 0 | HN15: 0 | HO15: 0 | HP15: =HL15+HN15 -> 0 | HQ15: =HM15+HO15 -> 0 | HR15: =HP15*J15 -> 0 | HS15: =HQ15/$HQ$1 -> 0 | HT15: =B15 -> SS-01 | HU15: 0 | HV15: 60 | HW15: 1000 | HX15: =HU15+HV15+HW15 -> 1060 | HY15: =HX15*J15 -> 1525676.9 | HZ15: 1000 | IA15: =HZ15*J15 -> 1439317.8 | IB15: =HX15+HZ15 -> 2060 | IC15: =HY15+IA15 -> 2964994.7 | ID15: =B15 -> SS-01 | IE15: =C15 -> FBA79451 | IF15: =G15 -> B0D9KCKY9F | IG15: =B15 -> SS-01 | IH15: 5 | II15: 0 | IJ15: 0 | IK15: 0 | IL15: 0 | IM15: =II15+IK15 -> 0 | IN15: =IJ15+IL15 -> 0 | IO15: =IM15*J15 -> 0 | IP15: =IN15/$IN$1 -> 0 | IQ15: =B15 -> SS-01 | IR15: 0 | IS15: 0 | IT15: 1000 | IU15: =IR15+IS15+IT15 -> 1000 | IV15: =IU15*J15 -> 1439317.8 | IW15: 1000 | IX15: =IW15*J15 -> 1439317.8 | IY15: =IU15+IW15 -> 2000 | IZ15: =IV15+IX15 -> 2878635.7 | JA15: =B15 -> SS-01 | JB15: =C15 -> FBA79451 | JC15: =G15 -> B0D9KCKY9F | JD15: =B15 -> SS-01 | JE15: NA | JF15: 0 | JG15: 0 | JH15: 0 | JI15: 0 | JJ15: =JF15+JH15 -> 0 | JK15: =JG15+JI15 -> 0 | JL15: =JJ15*J15 -> 0 | JM15: =JK15/$JK$1 -> 0 | JN15: =B15 -> SS-01 | JO15: 0 | JP15: 0 | JQ15: 1000 | JR15: =JO15+JP15+JQ15 -> 1000 | JS15: =JR15*AG15 -> 0 | JT15: 1000 | JU15: =JT15*AG15 -> 0 | JV15: =JR15+JT15 -> 2000 | JW15: =JS15+JU15 -> 0 | JX15: =B15 -> SS-01 | JY15: =C15 -> FBA79451 | JZ15: =G15 -> B0D9KCKY9F | KA15: =B15 -> SS-01 | KB15: NA | KC15: 0 | KD15: 0 | KE15: 0 | KF15: 0 | KG15: =KC15+KE15 -> 0 | KH15: =KD15+KF15 -> 0 | KI15: =KG15*J15 -> 0 | KJ15: =KH15/$KH$1 -> 0 | KK15: =B15 -> SS-01 | KL15: 0 | KM15: 0 | KN15: 1000 | KO15: =KL15+KM15+KN15 -> 1000 | KP15: =KO15*BD15 -> 155000 | KQ15: 1000 | KR15: =KQ15*BD15 -> 155000 | KS15: =KO15+KQ15 -> 2000 | KT15: =KP15+KR15 -> 310000 | KU15: =B15 -> SS-01 | KV15: =C15 -> FBA79451 | KW15: =G15 -> B0D9KCKY9F | KX15: =B15 -> SS-01 | KY15: NA | KZ15: 0 | LA15: 0 | LB15: 0 | LC15: 0 | LD15: =KZ15+LB15 -> 0 | LE15: =LA15+LC15 -> 0 | LF15: =LD15*J15 -> 0 | LG15: =LE15/$LE$1 -> 0 | LH15: =B15 -> SS-01 | LI15: 0 | LJ15: 0 | LK15: 1000 | LL15: =LI15+LJ15+LK15 -> 1000 | LM15: =LL15*CA15 -> 2370000 | LN15: 1000 | LO15: =LN15*CA15 -> 2370000 | LP15: =LL15+LN15 -> 2000 | LQ15: =LM15+LO15 -> 4740000 | LR15: =B15 -> SS-01 | LS15: =C15 -> FBA79451 | LT15: =G15 -> B0D9KCKY9F | LU15: =B15 -> SS-01 | LV15: 0 | LW15: 0 | LX15: 0 | LY15: 0 | LZ15: 0 | MA15: =LW15+LY15 -> 0 | MB15: =LX15+LZ15 -> 0 | MC15: =MA15*J15 -> 0 | MD15: =MB15/$MB$1 -> 0 | ME15: =B15 -> SS-01 | MF15: 0 | MG15: 0 | MH15: 1000 | MI15: =MF15+MG15+MH15 -> 1000 | MJ15: =MI15*CX15 -> 4.3107569e+09 | MK15: 1000 | ML15: =MK15*CX15 -> 4.3107569e+09 | MM15: =MI15+MK15 -> 2000 | MN15: =MJ15+ML15 -> 8.6215139e+09 | MO15: =B15 -> SS-01 | MP15: =C15 -> FBA79451 | MQ15: =G15 -> B0D9KCKY9F | MR15: =B15 -> SS-01 | MS15: 0 | MT15: 0 | MU15: 0 | MV15: 0 | MW15: 0 | MX15: =MT15+MV15 -> 0 | MY15: =MU15+MW15 -> 0 | MZ15: =MX15*J15 -> 0 | NA15: =MY15/$MY$1 -> 0 | NB15: =B15 -> SS-01 | NC15: 0 | ND15: 0 | NE15: 1000 | NF15: =NC15+ND15+NE15 -> 1000 | NG15: =NF15*DU15 -> #VALUE! | NH15: 1000 | NI15: =NH15*DU15 -> #VALUE! | NJ15: =NF15+NH15 -> 2000 | NK15: =NG15+NI15 -> #VALUE! | NL15: =B15 -> SS-01 | NM15: =C15 -> FBA79451 | NN15: =G15 -> B0D9KCKY9F | NO15: =Y15 -> 0 | NP15: 0 | NQ15: 0 | NR15: 0 | NS15: 0 | NT15: 0 | NU15: =NQ15+NS15 -> 0 | NV15: =NR15+NT15 -> 0 | NW15: =NU15*J15 -> 0 | NX15: =NV15/$NV$1 -> 0 | NY15: =B15 -> SS-01 | NZ15: 0 | OA15: 0 | OB15: 1000 | OC15: =NZ15+OA15+OB15 -> 1000 | OD15: =OC15*ER15 -> #VALUE! | OE15: 1000 | OF15: =OE15*ER15 -> #VALUE! | OG15: =OC15+OE15 -> 2000 | OH15: =OD15+OF15 -> #VALUE! | OI15: =B15 -> SS-01 | OJ15: =C15 -> FBA79451 | OK15: =G15 -> B0D9KCKY9F | OL15: =B15 -> SS-01
A16: FBA79406 | B16: HSB-04 | C16: FBA79406 | D16: HPC | E16: Hair Care | F16: Nexlev | G16: B0DCK3N2JJ | H16: Nexlev Hair Straightener Brush - Portable | I16: 859.09021 | J16: 1013.7264 | K16: 0 | L16: 0 | M16: 0 | N16: =1-L16/M16 -> #DIV/0! | O16: 0 | P16: 0 | Q16: 0 | R16: =1-P16/Q16 -> #DIV/0! | S16: 0 | T16: 0 | U16: 0 | V16: =1-T16/U16 -> #DIV/0! | W16: 0 | X16: 0 | Y16: 0 | Z16: =1-X16/Y16 -> #DIV/0! | AA16: 0 | AB16: 0 | AC16: 0 | AD16: =1-AB16/AC16 -> #DIV/0! | AE16: 0 | AF16: 0 | AG16: 0 | AH16: =1-AF16/AG16 -> #DIV/0! | AI16: 0 | AJ16: 0 | AK16: 0 | AL16: =1-AJ16/AK16 -> #DIV/0! | AM16: 0 | AN16: 0 | AO16: 0 | AP16: =1-AN16/AO16 -> #DIV/0! | AQ16: 0 | AR16: 0 | AS16: 0 | AT16: =1-AR16/AS16 -> #DIV/0! | AU16: 0 | AV16: 0 | AW16: 0 | AX16: =1-AV16/AW16 -> #DIV/0! | AY16: 0 | AZ16: 0 | BA16: 0 | BB16: =1-AZ16/BA16 -> #DIV/0! | BC16: 2707 | BD16: 54 | BE16: 66 | BF16: =1-BD16/BE16 -> 0.18181818 | BG16: 37042 | BH16: 155 | BI16: 175 | BJ16: =1-BH16/BI16 -> 0.11428571 | BK16: 30479 | BL16: 89 | BM16: 215101 | BN16: =BL16*J16 -> 90221.653 | BO16: 107 | BP16: 256649 | BQ16: =1-BL16/BO16 -> 0.1682243 | BR16: =BM16/$BM$1 -> 0.017518641 | BS16: =B16 -> HSB-04 | BT16: 177 | BU16: 491 | BV16: 0 | BW16: =BT16+BU16+BV16 -> 668 | BX16: =BW16*J16 -> 677169.26 | BY16: 0 | BZ16: =BY16*J16 -> 0 | CA16: =BW16+BY16 -> 668 | CB16: =BX16+BZ16 -> 677169.26 | CC16: =B16 -> HSB-04 | CD16: =C16 -> FBA79406 | CE16: =G16 -> B0DCK3N2JJ | CF16: =B16 -> HSB-04 | CG16: 17763 | CH16: 50 | CI16: 119696.04 | CJ16: =CH16*J16 -> 50686.322 | CK16: 55 | CL16: 126650 | CM16: =1-CH16/CK16 -> 0.090909091 | CN16: =CI16/$CI$1 -> 0.010545948 | CO16: =B16 -> HSB-04 | CP16: 256 | CQ16: 367 | CR16: 0 | CS16: =CP16+CQ16+CR16 -> 623 | CT16: =CS16*J16 -> 631551.57 | CU16: 0 | CV16: =CU16*J16 -> 0 | CW16: =CS16+CU16 -> 623 | CX16: =CT16+CV16 -> 631551.57 | CY16: =B16 -> HSB-04 | CZ16: =C16 -> FBA79406 | DA16: =G16 -> B0DCK3N2JJ | DB16: =B16 -> HSB-04 | DC16: 18088 | DD16: 81 | DE16: 191207.74 | DF16: =DD16*J16 -> 82111.842 | DG16: 100 | DH16: 220167.78 | DI16: =1-DD16/DG16 -> 0.19 | DJ16: =DE16/$DE$1 -> 0.015161114 | DK16: =B16 -> HSB-04 | DL16: 231 | DM16: 303 | DN16: 0 | DO16: =DL16+DM16+DN16 -> 534 | DP16: =DO16*J16 -> 541329.92 | DQ16: 0 | DR16: =DQ16*J16 -> 0 | DS16: =DO16+DQ16 -> 534 | DT16: =DP16+DR16 -> 541329.92 | DU16: =B16 -> HSB-04 | DV16: =C16 -> FBA79406 | DW16: =G16 -> B0DCK3N2JJ | DX16: =B16 -> HSB-04 | DY16: 9501 | DZ16: 53 | EA16: 127879 | EB16: =DZ16*J16 -> 53727.501 | EC16: 65 | ED16: 1,54,138.00 | EE16: =1-DZ16/EC16 -> 0.18461538 | EF16: =EA16/$EA$1 -> 0.014553804 | EG16: =B16 -> HSB-04 | EH16: 186 | EI16: 2154 | EJ16: 0 | EK16: =EH16+EI16+EJ16 -> 2340 | EL16: =EK16*J16 -> 2372119.9 | EM16: 0 | EN16: =EM16*J16 -> 0 | EO16: =EK16+EM16 -> 2340 | EP16: =EL16+EN16 -> 2372119.9 | EQ16: =B16 -> HSB-04 | ER16: =C16 -> FBA79406 | ES16: =G16 -> B0DCK3N2JJ | ET16: =B16 -> HSB-04 | EU16: 1205 | EV16: 1 | EW16: 2928 | EX16: =EV16*J16 -> 1013.7264 | EY16: 2 | EZ16: 2928 | FA16: =1-EV16/EY16 -> 0.5 | FB16: =EW16/$EW$1 -> 0.00043938856 | FC16: =B16 -> HSB-04 | FD16: 182 | FE16: 2036 | FF16: 0 | FG16: =FD16+FE16+FF16 -> 2218 | FH16: =FG16*J16 -> 2248445.3 | FI16: 0 | FJ16: =FI16*J16 -> 0 | FK16: =FG16+FI16 -> 2218 | FL16: =FH16+FJ16 -> 2248445.3 | FM16: =B16 -> HSB-04 | FN16: =C16 -> FBA79406 | FO16: =G16 -> B0DCK3N2JJ | FP16: =B16 -> HSB-04 | FQ16: NA | FR16: 0 | FS16: 0 | FT16: 96 | FU16: 240031.41 | FV16: =FR16+FT16 -> 96 | FW16: =FS16+FU16 -> 240031.41 | FX16: =FV16*J16 -> 97317.739 | FY16: =FW16/$FW$1 -> 0.025624955 | FZ16: =B16 -> HSB-04 | GA16: 361 | GB16: 1647 | GC16: 0 | GD16: =GA16+GB16+GC16 -> 2008 | GE16: =GD16*J16 -> 2035562.7 | GF16: 0 | GG16: =GF16*J16 -> 0 | GH16: =GD16+GF16 -> 2008 | GI16: =GE16+GG16 -> 2035562.7 | GJ16: =B16 -> HSB-04 | GK16: =C16 -> FBA79406 | GL16: =G16 -> B0DCK3N2JJ | GM16: =B16 -> HSB-04 | GN16: NA | GO16: 0 | GP16: 0 | GQ16: 105 | GR16: 257677.59 | GS16: =GO16+GQ16 -> 105 | GT16: =GP16+GR16 -> 257677.59 | GU16: =GS16*J16 -> 106441.28 | GV16: =GT16/$GT$1 -> 0.027226069 | GW16: =B16 -> HSB-04 | GX16: 61 | GY16: 1536 | GZ16: 0 | HA16: =GX16+GY16+GZ16 -> 1597 | HB16: =HA16*J16 -> 1618921.1 | HC16: 0 | HD16: =HC16*J16 -> 0 | HE16: =HA16+HC16 -> 1597 | HF16: =HB16+HD16 -> 1618921.1 | HG16: =B16 -> HSB-04 | HH16: =C16 -> FBA79406 | HI16: =G16 -> B0DCK3N2JJ | HJ16: =B16 -> HSB-04 | HK16: 20889 | HL16: 4 | HM16: 10016 | HN16: 142 | HO16: 353708.48 | HP16: =HL16+HN16 -> 146 | HQ16: =HM16+HO16 -> 363724.48 | HR16: =HP16*J16 -> 148004.06 | HS16: =HQ16/$HQ$1 -> 0.033212311 | HT16: =B16 -> HSB-04 | HU16: 183 | HV16: 1235 | HW16: 0 | HX16: =HU16+HV16+HW16 -> 1418 | HY16: =HX16*J16 -> 1437464.1 | HZ16: 0 | IA16: =HZ16*J16 -> 0 | IB16: =HX16+HZ16 -> 1418 | IC16: =HY16+IA16 -> 1437464.1 | ID16: =B16 -> HSB-04 | IE16: =C16 -> FBA79406 | IF16: =G16 -> B0DCK3N2JJ | IG16: =B16 -> HSB-04 | IH16: 20658 | II16: 42 | IJ16: 105825 | IK16: 146 | IL16: 340475.64 | IM16: =II16+IK16 -> 188 | IN16: =IJ16+IL16 -> 446300.64 | IO16: =IM16*J16 -> 190580.57 | IP16: =IN16/$IN$1 -> 0.039362273 | IQ16: =B16 -> HSB-04 | IR16: 355 | IS16: 1012 | IT16: 0 | IU16: =IR16+IS16+IT16 -> 1367 | IV16: =IU16*J16 -> 1385764 | IW16: 0 | IX16: =IW16*J16 -> 0 | IY16: =IU16+IW16 -> 1367 | IZ16: =IV16+IX16 -> 1385764 | JA16: =B16 -> HSB-04 | JB16: =C16 -> FBA79406 | JC16: =G16 -> B0DCK3N2JJ | JD16: =B16 -> HSB-04 | JE16: 31910 | JF16: 38 | JG16: 96077 | JH16: 121 | JI16: 296882.75 | JJ16: =JF16+JH16 -> 159 | JK16: =JG16+JI16 -> 392959.75 | JL16: =JJ16*J16 -> 161182.5 | JM16: =JK16/$JK$1 -> 0.043460439 | JN16: =B16 -> HSB-04 | JO16: 355 | JP16: 1012 | JQ16: 0 | JR16: =JO16+JP16+JQ16 -> 1367 | JS16: =JR16*AG16 -> 0 | JT16: 0 | JU16: =JT16*AG16 -> 0 | JV16: =JR16+JT16 -> 1367 | JW16: =JS16+JU16 -> 0 | JX16: =B16 -> HSB-04 | JY16: =C16 -> FBA79406 | JZ16: =G16 -> B0DCK3N2JJ | KA16: =B16 -> HSB-04 | KB16: 32717 | KC16: 73 | KD16: 170416.32 | KE16: 101 | KF16: 224166.82 | KG16: =KC16+KE16 -> 174 | KH16: =KD16+KF16 -> 394583.14 | KI16: =KG16*J16 -> 176388.4 | KJ16: =KH16/$KH$1 -> 0.033438405 | KK16: =B16 -> HSB-04 | KL16: 355 | KM16: 1012 | KN16: 0 | KO16: =KL16+KM16+KN16 -> 1367 | KP16: =KO16*BD16 -> 73818 | KQ16: 0 | KR16: =KQ16*BD16 -> 0 | KS16: =KO16+KQ16 -> 1367 | KT16: =KP16+KR16 -> 73818 | KU16: =B16 -> HSB-04 | KV16: =C16 -> FBA79406 | KW16: =G16 -> B0DCK3N2JJ | KX16: =B16 -> HSB-04 | KY16: 26944 | KZ16: 99 | LA16: 221874.56 | LB16: 20 | LC16: 44261.021 | LD16: =KZ16+LB16 -> 119 | LE16: =LA16+LC16 -> 266135.58 | LF16: =LD16*J16 -> 120633.45 | LG16: =LE16/$LE$1 -> 0.019791335 | LH16: =B16 -> HSB-04 | LI16: 355 | LJ16: 1012 | LK16: 0 | LL16: =LI16+LJ16+LK16 -> 1367 | LM16: =LL16*CA16 -> 913156 | LN16: 0 | LO16: =LN16*CA16 -> 0 | LP16: =LL16+LN16 -> 1367 | LQ16: =LM16+LO16 -> 913156 | LR16: =B16 -> HSB-04 | LS16: =C16 -> FBA79406 | LT16: =G16 -> B0DCK3N2JJ | LU16: =B16 -> HSB-04 | LV16: 68269 | LW16: 64 | LX16: 155506.74 | LY16: 4 | LZ16: 8183.04 | MA16: =LW16+LY16 -> 68 | MB16: =LX16+LZ16 -> 163689.78 | MC16: =MA16*J16 -> 68933.398 | MD16: =MB16/$MB$1 -> 0.017255181 | ME16: =B16 -> HSB-04 | MF16: 355 | MG16: 1012 | MH16: 0 | MI16: =MF16+MG16+MH16 -> 1367 | MJ16: =MI16*CX16 -> 8.63331e+08 | MK16: 0 | ML16: =MK16*CX16 -> 0 | MM16: =MI16+MK16 -> 1367 | MN16: =MJ16+ML16 -> 8.63331e+08 | MO16: =B16 -> HSB-04 | MP16: =C16 -> FBA79406 | MQ16: =G16 -> B0DCK3N2JJ | MR16: =B16 -> HSB-04 | MS16: 125730 | MT16: 131 | MU16: 287005 | MV16: 0 | MW16: 0 | MX16: =MT16+MV16 -> 131 | MY16: =MU16+MW16 -> 287005 | MZ16: =MX16*J16 -> 132798.16 | NA16: =MY16/$MY$1 -> 0.022860984 | NB16: =B16 -> HSB-04 | NC16: 355 | ND16: 1012 | NE16: 0 | NF16: =NC16+ND16+NE16 -> 1367 | NG16: =NF16*DU16 -> #VALUE! | NH16: 0 | NI16: =NH16*DU16 -> #VALUE! | NJ16: =NF16+NH16 -> 1367 | NK16: =NG16+NI16 -> #VALUE! | NL16: =B16 -> HSB-04 | NM16: =C16 -> FBA79406 | NN16: =G16 -> B0DCK3N2JJ | NO16: =Y16 -> 0 | NP16: 57825 | NQ16: 162 | NR16: 329092 | NS16: 0 | NT16: 0 | NU16: =NQ16+NS16 -> 162 | NV16: =NR16+NT16 -> 329092 | NW16: =NU16*J16 -> 164223.68 | NX16: =NV16/$NV$1 -> 0.034186228 | NY16: =B16 -> HSB-04 | NZ16: 355 | OA16: 1012 | OB16: 0 | OC16: =NZ16+OA16+OB16 -> 1367 | OD16: =OC16*ER16 -> #VALUE! | OE16: 0 | OF16: =OE16*ER16 -> #VALUE! | OG16: =OC16+OE16 -> 1367 | OH16: =OD16+OF16 -> #VALUE! | OI16: =B16 -> HSB-04 | OJ16: =C16 -> FBA79406 | OK16: =G16 -> B0DCK3N2JJ | OL16: =B16 -> HSB-04
A17: FBA79267 | B17: T-02 | C17: FBA79267 | D17: HPC | E17: Trimmers & Body Groomers | F17: Nexlev | G17: B0D2LD6BYJ | H17: Velvet Vibe Plus Multi-Trimmer | I17: 488.95587 | J17: 576.96793 | K17: 0 | L17: 0 | M17: 0 | N17: =1-L17/M17 -> #DIV/0! | O17: 0 | P17: 0 | Q17: 0 | R17: =1-P17/Q17 -> #DIV/0! | S17: 0 | T17: 0 | U17: 0 | V17: =1-T17/U17 -> #DIV/0! | W17: 0 | X17: 0 | Y17: 0 | Z17: =1-X17/Y17 -> #DIV/0! | AA17: 0 | AB17: 0 | AC17: 0 | AD17: =1-AB17/AC17 -> #DIV/0! | AE17: 0 | AF17: 0 | AG17: 0 | AH17: =1-AF17/AG17 -> #DIV/0! | AI17: 0 | AJ17: 0 | AK17: 0 | AL17: =1-AJ17/AK17 -> #DIV/0! | AM17: 43 | AN17: 0 | AO17: 2 | AP17: =1-AN17/AO17 -> 1 | AQ17: 1739 | AR17: 104 | AS17: 123 | AT17: =1-AR17/AS17 -> 0.15447154 | AU17: 4779 | AV17: 225 | AW17: 248 | AX17: =1-AV17/AW17 -> 0.092741935 | AY17: 10845 | AZ17: 246 | BA17: 267 | BB17: =1-AZ17/BA17 -> 0.078651685 | BC17: 5635 | BD17: 227 | BE17: 306 | BF17: =1-BD17/BE17 -> 0.25816993 | BG17: 10749 | BH17: 425 | BI17: 415 | BJ17: =1-BH17/BI17 -> -0.024096386 | BK17: 5793 | BL17: 196 | BM17: 196133 | BN17: =BL17*J17 -> 113085.71 | BO17: 211 | BP17: 209860 | BQ17: =1-BL17/BO17 -> 0.071090047 | BR17: =BM17/$BM$1 -> 0.015973815 | BS17: =B17 -> T-02 | BT17: 850 | BU17: 1610 | BV17: 0 | BW17: =BT17+BU17+BV17 -> 2460 | BX17: =BW17*J17 -> 1419341.1 | BY17: 0 | BZ17: =BY17*J17 -> 0 | CA17: =BW17+BY17 -> 2460 | CB17: =BX17+BZ17 -> 1419341.1 | CC17: =B17 -> T-02 | CD17: =C17 -> FBA79267 | CE17: =G17 -> B0D2LD6BYJ | CF17: =B17 -> T-02 | CG17: 3653 | CH17: 114 | CI17: 123949.59 | CJ17: =CH17*J17 -> 65774.344 | CK17: 122 | CL17: 133348 | CM17: =1-CH17/CK17 -> 0.06557377 | CN17: =CI17/$CI$1 -> 0.010920712 | CO17: =B17 -> T-02 | CP17: 790 | CQ17: 1533 | CR17: 0 | CS17: =CP17+CQ17+CR17 -> 2323 | CT17: =CS17*J17 -> 1340296.5 | CU17: 0 | CV17: =CU17*J17 -> 0 | CW17: =CS17+CU17 -> 2323 | CX17: =CT17+CV17 -> 1340296.5 | CY17: =B17 -> T-02 | CZ17: =C17 -> FBA79267 | DA17: =G17 -> B0D2LD6BYJ | DB17: =B17 -> T-02 | DC17: 3267 | DD17: 50 | DE17: 53259.09 | DF17: =DD17*J17 -> 28848.396 | DG17: 52 | DH17: 55568 | DI17: =1-DD17/DG17 -> 0.038461538 | DJ17: =DE17/$DE$1 -> 0.0042229836 | DK17: =B17 -> T-02 | DL17: 617 | DM17: 1525 | DN17: 0 | DO17: =DL17+DM17+DN17 -> 2142 | DP17: =DO17*J17 -> 1235865.3 | DQ17: 0 | DR17: =DQ17*J17 -> 0 | DS17: =DO17+DQ17 -> 2142 | DT17: =DP17+DR17 -> 1235865.3 | DU17: =B17 -> T-02 | DV17: =C17 -> FBA79267 | DW17: =G17 -> B0D2LD6BYJ | DX17: =B17 -> T-02 | DY17: 3563 | DZ17: 64 | EA17: 71311 | EB17: =DZ17*J17 -> 36925.947 | EC17: 69 | ED17: 74529 | EE17: =1-DZ17/EC17 -> 0.072463768 | EF17: =EA17/$EA$1 -> 0.0081158466 | EG17: =B17 -> T-02 | EH17: 526 | EI17: 1327 | EJ17: 0 | EK17: =EH17+EI17+EJ17 -> 1853 | EL17: =EK17*J17 -> 1069121.6 | EM17: 0 | EN17: =EM17*J17 -> 0 | EO17: =EK17+EM17 -> 1853 | EP17: =EL17+EN17 -> 1069121.6 | EQ17: =B17 -> T-02 | ER17: =C17 -> FBA79267 | ES17: =G17 -> B0D2LD6BYJ | ET17: =B17 -> T-02 | EU17: 4331 | EV17: 4 | EW17: 4720 | EX17: =EV17*J17 -> 2307.8717 | EY17: 5 | EZ17: 4720 | FA17: =1-EV17/EY17 -> 0.2 | FB17: =EW17/$EW$1 -> 0.00070830397 | FC17: =B17 -> T-02 | FD17: 255 | FE17: 1356 | FF17: 0 | FG17: =FD17+FE17+FF17 -> 1611 | FH17: =FG17*J17 -> 929495.33 | FI17: 0 | FJ17: =FI17*J17 -> 0 | FK17: =FG17+FI17 -> 1611 | FL17: =FH17+FJ17 -> 929495.33 | FM17: =B17 -> T-02 | FN17: =C17 -> FBA79267 | FO17: =G17 -> B0D2LD6BYJ | FP17: =B17 -> T-02 | FQ17: 2348 | FR17: 3 | FS17: 3312 | FT17: 64 | FU17: 69756.266 | FV17: =FR17+FT17 -> 67 | FW17: =FS17+FU17 -> 73068.266 | FX17: =FV17*J17 -> 38656.851 | FY17: =FW17/$FW$1 -> 0.007800525 | FZ17: =B17 -> T-02 | GA17: 103 | GB17: 1333 | GC17: 0 | GD17: =GA17+GB17+GC17 -> 1436 | GE17: =GD17*J17 -> 828525.94 | GF17: 0 | GG17: =GF17*J17 -> 0 | GH17: =GD17+GF17 -> 1436 | GI17: =GE17+GG17 -> 828525.94 | GJ17: =B17 -> T-02 | GK17: =C17 -> FBA79267 | GL17: =G17 -> B0D2LD6BYJ | GM17: =B17 -> T-02 | GN17: 3543 | GO17: 1 | GP17: 1122 | GQ17: 101 | GR17: 107499.35 | GS17: =GO17+GQ17 -> 102 | GT17: =GP17+GR17 -> 108621.35 | GU17: =GS17*J17 -> 58850.729 | GV17: =GT17/$GT$1 -> 0.01147687 | GW17: =B17 -> T-02 | GX17: 61 | GY17: 1535 | GZ17: 0 | HA17: =GX17+GY17+GZ17 -> 1596 | HB17: =HA17*J17 -> 920840.81 | HC17: 0 | HD17: =HC17*J17 -> 0 | HE17: =HA17+HC17 -> 1596 | HF17: =HB17+HD17 -> 920840.81 | HG17: =B17 -> T-02 | HH17: =C17 -> FBA79267 | HI17: =G17 -> B0D2LD6BYJ | HJ17: =B17 -> T-02 | HK17: 2098 | HL17: 0 | HM17: 0 | HN17: 41 | HO17: 45759.055 | HP17: =HL17+HN17 -> 41 | HQ17: =HM17+HO17 -> 45759.055 | HR17: =HP17*J17 -> 23655.685 | HS17: =HQ17/$HQ$1 -> 0.0041783383 | HT17: =B17 -> T-02 | HU17: 99 | HV17: 1402 | HW17: 0 | HX17: =HU17+HV17+HW17 -> 1501 | HY17: =HX17*J17 -> 866028.86 | HZ17: 0 | IA17: =HZ17*J17 -> 0 | IB17: =HX17+HZ17 -> 1501 | IC17: =HY17+IA17 -> 866028.86 | ID17: =B17 -> T-02 | IE17: =C17 -> FBA79267 | IF17: =G17 -> B0D2LD6BYJ | IG17: =B17 -> T-02 | IH17: 1546 | II17: 3 | IJ17: 3180 | IK17: 55 | IL17: 59924.046 | IM17: =II17+IK17 -> 58 | IN17: =IJ17+IL17 -> 63104.046 | IO17: =IM17*J17 -> 33464.14 | IP17: =IN17/$IN$1 -> 0.0055655728 | IQ17: =B17 -> T-02 | IR17: 211 | IS17: 1400 | IT17: 0 | IU17: =IR17+IS17+IT17 -> 1611 | IV17: =IU17*J17 -> 929495.33 | IW17: 0 | IX17: =IW17*J17 -> 0 | IY17: =IU17+IW17 -> 1611 | IZ17: =IV17+IX17 -> 929495.33 | JA17: =B17 -> T-02 | JB17: =C17 -> FBA79267 | JC17: =G17 -> B0D2LD6BYJ | JD17: =B17 -> T-02 | JE17: 1388 | JF17: 2 | JG17: 2313 | JH17: 37 | JI17: 40731.028 | JJ17: =JF17+JH17 -> 39 | JK17: =JG17+JI17 -> 43044.028 | JL17: =JJ17*J17 -> 22501.749 | JM17: =JK17/$JK$1 -> 0.0047605698 | JN17: =B17 -> T-02 | JO17: 211 | JP17: 1400 | JQ17: 0 | JR17: =JO17+JP17+JQ17 -> 1611 | JS17: =JR17*AG17 -> 0 | JT17: 0 | JU17: =JT17*AG17 -> 0 | JV17: =JR17+JT17 -> 1611 | JW17: =JS17+JU17 -> 0 | JX17: =B17 -> T-02 | JY17: =C17 -> FBA79267 | JZ17: =G17 -> B0D2LD6BYJ | KA17: =B17 -> T-02 | KB17: 960 | KC17: 1 | KD17: 1186 | KE17: 17 | KF17: 18358.039 | KG17: =KC17+KE17 -> 18 | KH17: =KD17+KF17 -> 19544.039 | KI17: =KG17*J17 -> 10385.423 | KJ17: =KH17/$KH$1 -> 0.0016562327 | KK17: =B17 -> T-02 | KL17: 211 | KM17: 1400 | KN17: 0 | KO17: =KL17+KM17+KN17 -> 1611 | KP17: =KO17*BD17 -> 365697 | KQ17: 0 | KR17: =KQ17*BD17 -> 0 | KS17: =KO17+KQ17 -> 1611 | KT17: =KP17+KR17 -> 365697 | KU17: =B17 -> T-02 | KV17: =C17 -> FBA79267 | KW17: =G17 -> B0D2LD6BYJ | KX17: =B17 -> T-02 | KY17: 959 | KZ17: 1 | LA17: 1140.72 | LB17: 12 | LC17: 13188.058 | LD17: =KZ17+LB17 -> 13 | LE17: =LA17+LC17 -> 14328.778 | LF17: =LD17*J17 -> 7500.583 | LG17: =LE17/$LE$1 -> 0.0010655683 | LH17: =B17 -> T-02 | LI17: 211 | LJ17: 1400 | LK17: 0 | LL17: =LI17+LJ17+LK17 -> 1611 | LM17: =LL17*CA17 -> 3963060 | LN17: 0 | LO17: =LN17*CA17 -> 0 | LP17: =LL17+LN17 -> 1611 | LQ17: =LM17+LO17 -> 3963060 | LR17: =B17 -> T-02 | LS17: =C17 -> FBA79267 | LT17: =G17 -> B0D2LD6BYJ | LU17: =B17 -> T-02 | LV17: 3528 | LW17: 0 | LX17: 0 | LY17: 17 | LZ17: 15833.12 | MA17: =LW17+LY17 -> 17 | MB17: =LX17+LZ17 -> 15833.12 | MC17: =MA17*J17 -> 9808.4548 | MD17: =MB17/$MB$1 -> 0.0016690312 | ME17: =B17 -> T-02 | MF17: 211 | MG17: 1400 | MH17: 0 | MI17: =MF17+MG17+MH17 -> 1611 | MJ17: =MI17*CX17 -> 2.1592177e+09 | MK17: 0 | ML17: =MK17*CX17 -> 0 | MM17: =MI17+MK17 -> 1611 | MN17: =MJ17+ML17 -> 2.1592177e+09 | MO17: =B17 -> T-02 | MP17: =C17 -> FBA79267 | MQ17: =G17 -> B0D2LD6BYJ | MR17: =B17 -> T-02 | MS17: 1685 | MT17: 1 | MU17: 1209 | MV17: 21 | MW17: 23079.101 | MX17: =MT17+MV17 -> 22 | MY17: =MU17+MW17 -> 24288.101 | MZ17: =MX17*J17 -> 12693.294 | NA17: =MY17/$MY$1 -> 0.0019346349 | NB17: =B17 -> T-02 | NC17: 211 | ND17: 1400 | NE17: 0 | NF17: =NC17+ND17+NE17 -> 1611 | NG17: =NF17*DU17 -> #VALUE! | NH17: 0 | NI17: =NH17*DU17 -> #VALUE! | NJ17: =NF17+NH17 -> 1611 | NK17: =NG17+NI17 -> #VALUE! | NL17: =B17 -> T-02 | NM17: =C17 -> FBA79267 | NN17: =G17 -> B0D2LD6BYJ | NO17: =Y17 -> 0 | NP17: 703 | NQ17: 3 | NR17: 3306 | NS17: 0 | NT17: 0 | NU17: =NQ17+NS17 -> 3 | NV17: =NR17+NT17 -> 3306 | NW17: =NU17*J17 -> 1730.9038 | NX17: =NV17/$NV$1 -> 0.00034342879 | NY17: =B17 -> T-02 | NZ17: 211 | OA17: 1400 | OB17: 0 | OC17: =NZ17+OA17+OB17 -> 1611 | OD17: =OC17*ER17 -> #VALUE! | OE17: 0 | OF17: =OE17*ER17 -> #VALUE! | OG17: =OC17+OE17 -> 1611 | OH17: =OD17+OF17 -> #VALUE! | OI17: =B17 -> T-02 | OJ17: =C17 -> FBA79267 | OK17: =G17 -> B0D2LD6BYJ | OL17: =B17 -> T-02
A18: FBA79489 | B18: KE-02 | C18: FBA79489 | D18: Home & Kitchen | E18: Kitchen Appliances | F18: Nexlev | G18: B0DFD123P5 | H18: Nexlev Multi-Purpose Food Kettle 1.5L | I18: 762.35055 | J18: 899.57365 | K18: 0 | L18: 0 | M18: 0 | N18: =1-L18/M18 -> #DIV/0! | O18: 0 | P18: 0 | Q18: 0 | R18: =1-P18/Q18 -> #DIV/0! | S18: 0 | T18: 0 | U18: 0 | V18: =1-T18/U18 -> #DIV/0! | W18: 0 | X18: 0 | Y18: 0 | Z18: =1-X18/Y18 -> #DIV/0! | AA18: 0 | AB18: 0 | AC18: 0 | AD18: =1-AB18/AC18 -> #DIV/0! | AE18: 0 | AF18: 0 | AG18: 0 | AH18: =1-AF18/AG18 -> #DIV/0! | AI18: 0 | AJ18: 0 | AK18: 0 | AL18: =1-AJ18/AK18 -> #DIV/0! | AM18: 0 | AN18: 0 | AO18: 0 | AP18: =1-AN18/AO18 -> #DIV/0! | AQ18: 0 | AR18: 0 | AS18: 0 | AT18: =1-AR18/AS18 -> #DIV/0! | AU18: 0 | AV18: 0 | AW18: 0 | AX18: =1-AV18/AW18 -> #DIV/0! | AY18: 0 | AZ18: 0 | BA18: 0 | BB18: =1-AZ18/BA18 -> #DIV/0! | BC18: 78 | BD18: 0 | BE18: 1 | BF18: =1-BD18/BE18 -> 1 | BG18: 2599 | BH18: 22 | BI18: 29 | BJ18: =1-BH18/BI18 -> 0.24137931 | BK18: 13131 | BL18: 126 | BM18: 189276 | BN18: =BL18*J18 -> 113346.28 | BO18: 159 | BP18: 230967 | BQ18: =1-BL18/BO18 -> 0.20754717 | BR18: =BM18/$BM$1 -> 0.015415355 | BS18: =B18 -> KE-02 | BT18: 275 | BU18: 556 | BV18: 0 | BW18: =BT18+BU18+BV18 -> 831 | BX18: =BW18*J18 -> 747545.7 | BY18: 0 | BZ18: =BY18*J18 -> 0 | CA18: =BW18+BY18 -> 831 | CB18: =BX18+BZ18 -> 747545.7 | CC18: =B18 -> KE-02 | CD18: =C18 -> FBA79489 | CE18: =G18 -> B0DFD123P5 | CF18: =B18 -> KE-02 | CG18: 13522 | CH18: 89 | CI18: 133480.01 | CJ18: =CH18*J18 -> 80062.055 | CK18: 130 | CL18: 194710 | CM18: =1-CH18/CK18 -> 0.31538462 | CN18: =CI18/$CI$1 -> 0.0117604 | CO18: =B18 -> KE-02 | CP18: 385 | CQ18: 365 | CR18: 0 | CS18: =CP18+CQ18+CR18 -> 750 | CT18: =CS18*J18 -> 674680.24 | CU18: 0 | CV18: =CU18*J18 -> 0 | CW18: =CS18+CU18 -> 750 | CX18: =CT18+CV18 -> 674680.24 | CY18: =B18 -> KE-02 | CZ18: =C18 -> FBA79489 | DA18: =G18 -> B0DFD123P5 | DB18: =B18 -> KE-02 | DC18: 9984 | DD18: 96 | DE18: 142571.77 | DF18: =DD18*J18 -> 86359.07 | DG18: 127 | DH18: 184154 | DI18: =1-DD18/DG18 -> 0.24409449 | DJ18: =DE18/$DE$1 -> 0.011304704 | DK18: =B18 -> KE-02 | DL18: 322 | DM18: 276 | DN18: 0 | DO18: =DL18+DM18+DN18 -> 598 | DP18: =DO18*J18 -> 537945.04 | DQ18: 0 | DR18: =DQ18*J18 -> 0 | DS18: =DO18+DQ18 -> 598 | DT18: =DP18+DR18 -> 537945.04 | DU18: =B18 -> KE-02 | DV18: =C18 -> FBA79489 | DW18: =G18 -> B0DFD123P5 | DX18: =B18 -> KE-02 | DY18: 7912 | DZ18: 71 | EA18: 106517.16 | EB18: =DZ18*J18 -> 63869.729 | EC18: 89 | ED18: 1,30,413.00 | EE18: =1-DZ18/EC18 -> 0.20224719 | EF18: =EA18/$EA$1 -> 0.012122631 | EG18: =B18 -> KE-02 | EH18: 397 | EI18: 132 | EJ18: 0 | EK18: =EH18+EI18+EJ18 -> 529 | EL18: =EK18*J18 -> 475874.46 | EM18: 0 | EN18: =EM18*J18 -> 0 | EO18: =EK18+EM18 -> 529 | EP18: =EL18+EN18 -> 475874.46 | EQ18: =B18 -> KE-02 | ER18: =C18 -> FBA79489 | ES18: =G18 -> B0DFD123P5 | ET18: =B18 -> KE-02 | EU18: 6533 | EV18: 38 | EW18: 57001.58 | EX18: =EV18*J18 -> 34183.799 | EY18: 49 | EZ18: 71924 | FA18: =1-EV18/EY18 -> 0.2244898 | FB18: =EW18/$EW$1 -> 0.0085539079 | FC18: =B18 -> KE-02 | FD18: 384 | FE18: 47 | FF18: 0 | FG18: =FD18+FE18+FF18 -> 431 | FH18: =FG18*J18 -> 387716.24 | FI18: 0 | FJ18: =FI18*J18 -> 0 | FK18: =FG18+FI18 -> 431 | FL18: =FH18+FJ18 -> 387716.24 | FM18: =B18 -> KE-02 | FN18: =C18 -> FBA79489 | FO18: =G18 -> B0DFD123P5 | FP18: =B18 -> KE-02 | FQ18: 3815 | FR18: 26 | FS18: 38791 | FT18: 0 | FU18: 0 | FV18: =FR18+FT18 -> 26 | FW18: =FS18+FU18 -> 38791 | FX18: =FV18*J18 -> 23388.915 | FY18: =FW18/$FW$1 -> 0.0041411981 | FZ18: =B18 -> KE-02 | GA18: 0 | GB18: 1037 | GC18: 0 | GD18: =GA18+GB18+GC18 -> 1037 | GE18: =GD18*J18 -> 932857.87 | GF18: 0 | GG18: =GF18*J18 -> 0 | GH18: =GD18+GF18 -> 1037 | GI18: =GE18+GG18 -> 932857.87 | GJ18: =B18 -> KE-02 | GK18: =C18 -> FBA79489 | GL18: =G18 -> B0DFD123P5 | GM18: =B18 -> KE-02 | GN18: 4450 | GO18: 35 | GP18: 52383 | GQ18: 0 | GR18: 0 | GS18: =GO18+GQ18 -> 35 | GT18: =GP18+GR18 -> 52383 | GU18: =GS18*J18 -> 31485.078 | GV18: =GT18/$GT$1 -> 0.0055347582 | GW18: =B18 -> KE-02 | GX18: 304 | GY18: 1000 | GZ18: 0 | HA18: =GX18+GY18+GZ18 -> 1304 | HB18: =HA18*J18 -> 1173044 | HC18: 0 | HD18: =HC18*J18 -> 0 | HE18: =HA18+HC18 -> 1304 | HF18: =HB18+HD18 -> 1173044 | HG18: =B18 -> KE-02 | HH18: =C18 -> FBA79489 | HI18: =G18 -> B0DFD123P5 | HJ18: =B18 -> KE-02 | HK18: 3810 | HL18: 26 | HM18: 38879 | HN18: 0 | HO18: 0 | HP18: =HL18+HN18 -> 26 | HQ18: =HM18+HO18 -> 38879 | HR18: =HP18*J18 -> 23388.915 | HS18: =HQ18/$HQ$1 -> 0.0035501087 | HT18: =B18 -> KE-02 | HU18: 0 | HV18: 995 | HW18: 0 | HX18: =HU18+HV18+HW18 -> 995 | HY18: =HX18*J18 -> 895075.78 | HZ18: 0 | IA18: =HZ18*J18 -> 0 | IB18: =HX18+HZ18 -> 995 | IC18: =HY18+IA18 -> 895075.78 | ID18: =B18 -> KE-02 | IE18: =C18 -> FBA79489 | IF18: =G18 -> B0DFD123P5 | IG18: =B18 -> KE-02 | IH18: 3577 | II18: 33 | IJ18: 49482.5 | IK18: 0 | IL18: 0 | IM18: =II18+IK18 -> 33 | IN18: =IJ18+IL18 -> 49482.5 | IO18: =IM18*J18 -> 29685.93 | IP18: =IN18/$IN$1 -> 0.0043641965 | IQ18: =B18 -> KE-02 | IR18: 231 | IS18: 1018 | IT18: 0 | IU18: =IR18+IS18+IT18 -> 1249 | IV18: =IU18*J18 -> 1123567.5 | IW18: 0 | IX18: =IW18*J18 -> 0 | IY18: =IU18+IW18 -> 1249 | IZ18: =IV18+IX18 -> 1123567.5 | JA18: =B18 -> KE-02 | JB18: =C18 -> FBA79489 | JC18: =G18 -> B0DFD123P5 | JD18: =B18 -> KE-02 | JE18: 6206 | JF18: 99 | JG18: 146536.78 | JH18: 0 | JI18: 0 | JJ18: =JF18+JH18 -> 99 | JK18: =JG18+JI18 -> 146536.78 | JL18: =JJ18*J18 -> 89057.791 | JM18: =JK18/$JK$1 -> 0.016206629 | JN18: =B18 -> KE-02 | JO18: 231 | JP18: 1018 | JQ18: 0 | JR18: =JO18+JP18+JQ18 -> 1249 | JS18: =JR18*AG18 -> 0 | JT18: 0 | JU18: =JT18*AG18 -> 0 | JV18: =JR18+JT18 -> 1249 | JW18: =JS18+JU18 -> 0 | JX18: =B18 -> KE-02 | JY18: =C18 -> FBA79489 | JZ18: =G18 -> B0DFD123P5 | KA18: =B18 -> KE-02 | KB18: 8125 | KC18: 77 | KD18: 114417.62 | KE18: 0 | KF18: 0 | KG18: =KC18+KE18 -> 77 | KH18: =KD18+KF18 -> 114417.62 | KI18: =KG18*J18 -> 69267.171 | KJ18: =KH18/$KH$1 -> 0.0096961638 | KK18: =B18 -> KE-02 | KL18: 231 | KM18: 1018 | KN18: 0 | KO18: =KL18+KM18+KN18 -> 1249 | KP18: =KO18*BD18 -> 0 | KQ18: 0 | KR18: =KQ18*BD18 -> 0 | KS18: =KO18+KQ18 -> 1249 | KT18: =KP18+KR18 -> 0 | KU18: =B18 -> KE-02 | KV18: =C18 -> FBA79489 | KW18: =G18 -> B0DFD123P5 | KX18: =B18 -> KE-02 | KY18: 7897 | KZ18: 45 | LA18: 64013.05 | LB18: 0 | LC18: 0 | LD18: =KZ18+LB18 -> 45 | LE18: =LA18+LC18 -> 64013.05 | LF18: =LD18*J18 -> 40480.814 | LG18: =LE18/$LE$1 -> 0.0047603696 | LH18: =B18 -> KE-02 | LI18: 231 | LJ18: 1018 | LK18: 0 | LL18: =LI18+LJ18+LK18 -> 1249 | LM18: =LL18*CA18 -> 1037919 | LN18: 0 | LO18: =LN18*CA18 -> 0 | LP18: =LL18+LN18 -> 1249 | LQ18: =LM18+LO18 -> 1037919 | LR18: =B18 -> KE-02 | LS18: =C18 -> FBA79489 | LT18: =G18 -> B0DFD123P5 | LU18: =B18 -> KE-02 | LV18: 38196 | LW18: 138 | LX18: 206157.12 | LY18: 0 | LZ18: 0 | MA18: =LW18+LY18 -> 138 | MB18: =LX18+LZ18 -> 206157.12 | MC18: =MA18*J18 -> 124141.16 | MD18: =MB18/$MB$1 -> 0.02173183 | ME18: =B18 -> KE-02 | MF18: 231 | MG18: 1018 | MH18: 0 | MI18: =MF18+MG18+MH18 -> 1249 | MJ18: =MI18*CX18 -> 8.4267562e+08 | MK18: 0 | ML18: =MK18*CX18 -> 0 | MM18: =MI18+MK18 -> 1249 | MN18: =MJ18+ML18 -> 8.4267562e+08 | MO18: =B18 -> KE-02 | MP18: =C18 -> FBA79489 | MQ18: =G18 -> B0DFD123P5 | MR18: =B18 -> KE-02 | MS18: 21341 | MT18: 106 | MU18: 157825 | MV18: 0 | MW18: 0 | MX18: =MT18+MV18 -> 106 | MY18: =MU18+MW18 -> 157825 | MZ18: =MX18*J18 -> 95354.807 | NA18: =MY18/$MY$1 -> 0.012571331 | NB18: =B18 -> KE-02 | NC18: 231 | ND18: 1018 | NE18: 0 | NF18: =NC18+ND18+NE18 -> 1249 | NG18: =NF18*DU18 -> #VALUE! | NH18: 0 | NI18: =NH18*DU18 -> #VALUE! | NJ18: =NF18+NH18 -> 1249 | NK18: =NG18+NI18 -> #VALUE! | NL18: =B18 -> KE-02 | NM18: =C18 -> FBA79489 | NN18: =G18 -> B0DFD123P5 | NO18: =Y18 -> 0 | NP18: 14938 | NQ18: 95 | NR18: 142692 | NS18: 0 | NT18: 0 | NU18: =NQ18+NS18 -> 95 | NV18: =NR18+NT18 -> 142692 | NW18: =NU18*J18 -> 85459.497 | NX18: =NV18/$NV$1 -> 0.01482291 | NY18: =B18 -> KE-02 | NZ18: 231 | OA18: 1018 | OB18: 0 | OC18: =NZ18+OA18+OB18 -> 1249 | OD18: =OC18*ER18 -> #VALUE! | OE18: 0 | OF18: =OE18*ER18 -> #VALUE! | OG18: =OC18+OE18 -> 1249 | OH18: =OD18+OF18 -> #VALUE! | OI18: =B18 -> KE-02 | OJ18: =C18 -> FBA79489 | OK18: =G18 -> B0DFD123P5 | OL18: =B18 -> KE-02
A19: FBA79276 | B19: SM-01 | C19: FBA79276 | D19: Home & Kitchen | E19: Cleaning & Vacumming | F19: Nexlev | G19: B0D2LJSQXZ | H19: Steam Mop | I19: 2103.036 | J19: 2481.5825 | K19: 0 | L19: 0 | M19: 0 | N19: =1-L19/M19 -> #DIV/0! | O19: 0 | P19: 0 | Q19: 0 | R19: =1-P19/Q19 -> #DIV/0! | S19: 0 | T19: 0 | U19: 0 | V19: =1-T19/U19 -> #DIV/0! | W19: 0 | X19: 0 | Y19: 0 | Z19: =1-X19/Y19 -> #DIV/0! | AA19: 0 | AB19: 0 | AC19: 0 | AD19: =1-AB19/AC19 -> #DIV/0! | AE19: 0 | AF19: 0 | AG19: 0 | AH19: =1-AF19/AG19 -> #DIV/0! | AI19: 0 | AJ19: 0 | AK19: 0 | AL19: =1-AJ19/AK19 -> #DIV/0! | AM19: 105 | AN19: 0 | AO19: 6 | AP19: =1-AN19/AO19 -> 1 | AQ19: 5947 | AR19: 52 | AS19: 60 | AT19: =1-AR19/AS19 -> 0.13333333 | AU19: 32767 | AV19: 187 | AW19: 220 | AX19: =1-AV19/AW19 -> 0.15 | AY19: 38315 | AZ19: 132 | BA19: 171 | BB19: =1-AZ19/BA19 -> 0.22807018 | BC19: 34178 | BD19: 55 | BE19: 78 | BF19: =1-BD19/BE19 -> 0.29487179 | BG19: 18557 | BH19: 66 | BI19: 70 | BJ19: =1-BH19/BI19 -> 0.057142857 | BK19: 9341 | BL19: 43 | BM19: 179020 | BN19: =BL19*J19 -> 106708.05 | BO19: 51 | BP19: 194818 | BQ19: =1-BL19/BO19 -> 0.15686275 | BR19: =BM19/$BM$1 -> 0.014580067 | BS19: =B19 -> SM-01 | BT19: 555 | BU19: 32 | BV19: 1000 | BW19: =BT19+BU19+BV19 -> 1587 | BX19: =BW19*J19 -> 3938271.4 | BY19: 0 | BZ19: =BY19*J19 -> 0 | CA19: =BW19+BY19 -> 1587 | CB19: =BX19+BZ19 -> 3938271.4 | CC19: =B19 -> SM-01 | CD19: =C19 -> FBA79276 | CE19: =G19 -> B0D2LJSQXZ | CF19: =B19 -> SM-01 | CG19: 17792 | CH19: 95 | CI19: 380042.04 | CJ19: =CH19*J19 -> 235750.34 | CK19: 107 | CL19: 403899 | CM19: =1-CH19/CK19 -> 0.11214953 | CN19: =CI19/$CI$1 -> 0.033484012 | CO19: =B19 -> SM-01 | CP19: 551 | CQ19: 928 | CR19: 1000 | CS19: =CP19+CQ19+CR19 -> 2479 | CT19: =CS19*J19 -> 6151843 | CU19: 0 | CV19: =CU19*J19 -> 0 | CW19: =CS19+CU19 -> 2479 | CX19: =CT19+CV19 -> 6151843 | CY19: =B19 -> SM-01 | CZ19: =C19 -> FBA79276 | DA19: =G19 -> B0D2LJSQXZ | DB19: =B19 -> SM-01 | DC19: 35355 | DD19: 66 | DE19: 261330.14 | DF19: =DD19*J19 -> 163784.44 | DG19: 71 | DH19: 269482 | DI19: =1-DD19/DG19 -> 0.070422535 | DJ19: =DE19/$DE$1 -> 0.020721212 | DK19: =B19 -> SM-01 | DL19: 474 | DM19: 879 | DN19: 1000 | DO19: =DL19+DM19+DN19 -> 2353 | DP19: =DO19*J19 -> 5839163.6 | DQ19: 0 | DR19: =DQ19*J19 -> 0 | DS19: =DO19+DQ19 -> 2353 | DT19: =DP19+DR19 -> 5839163.6 | DU19: =B19 -> SM-01 | DV19: =C19 -> FBA79276 | DW19: =G19 -> B0D2LJSQXZ | DX19: =B19 -> SM-01 | DY19: 18945 | DZ19: 71 | EA19: 262708 | EB19: =DZ19*J19 -> 176192.36 | EC19: 86 | ED19: 3,14,415.00 | EE19: =1-DZ19/EC19 -> 0.1744186 | EF19: =EA19/$EA$1 -> 0.029898583 | EG19: =B19 -> SM-01 | EH19: 306 | EI19: 789 | EJ19: 1000 | EK19: =EH19+EI19+EJ19 -> 2095 | EL19: =EK19*J19 -> 5198915.3 | EM19: 0 | EN19: =EM19*J19 -> 0 | EO19: =EK19+EM19 -> 2095 | EP19: =EL19+EN19 -> 5198915.3 | EQ19: =B19 -> SM-01 | ER19: =C19 -> FBA79276 | ES19: =G19 -> B0D2LJSQXZ | ET19: =B19 -> SM-01 | EU19: 31699 | EV19: 65 | EW19: 240620 | EX19: =EV19*J19 -> 161302.86 | EY19: 80 | EZ19: 2,69,927 | FA19: =1-EV19/EY19 -> 0.1875 | FB19: =EW19/$EW$1 -> 0.036108496 | FC19: =B19 -> SM-01 | FD19: 145 | FE19: 703 | FF19: 1000 | FG19: =FD19+FE19+FF19 -> 1848 | FH19: =FG19*J19 -> 4585964.4 | FI19: 0 | FJ19: =FI19*J19 -> 0 | FK19: =FG19+FI19 -> 1848 | FL19: =FH19+FJ19 -> 4585964.4 | FM19: =B19 -> SM-01 | FN19: =C19 -> FBA79276 | FO19: =G19 -> B0D2LJSQXZ | FP19: =B19 -> SM-01 | FQ19: 28242 | FR19: 73 | FS19: 270188.58 | FT19: 0 | FU19: 0 | FV19: =FR19+FT19 -> 73 | FW19: =FS19+FU19 -> 270188.58 | FX19: =FV19*J19 -> 181155.52 | FY19: =FW19/$FW$1 -> 0.028844434 | FZ19: =B19 -> SM-01 | GA19: 0 | GB19: 492 | GC19: 1000 | GD19: =GA19+GB19+GC19 -> 1492 | GE19: =GD19*J19 -> 3702521.1 | GF19: 0 | GG19: =GF19*J19 -> 0 | GH19: =GD19+GF19 -> 1492 | GI19: =GE19+GG19 -> 3702521.1 | GJ19: =B19 -> SM-01 | GK19: =C19 -> FBA79276 | GL19: =G19 -> B0D2LJSQXZ | GM19: =B19 -> SM-01 | GN19: 14984 | GO19: 56 | GP19: 206384 | GQ19: 0 | GR19: 0 | GS19: =GO19+GQ19 -> 56 | GT19: =GP19+GR19 -> 206384 | GU19: =GS19*J19 -> 138968.62 | GV19: =GT19/$GT$1 -> 0.021806417 | GW19: =B19 -> SM-01 | GX19: 153 | GY19: 618 | GZ19: 1000 | HA19: =GX19+GY19+GZ19 -> 1771 | HB19: =HA19*J19 -> 4394882.6 | HC19: 0 | HD19: =HC19*J19 -> 0 | HE19: =HA19+HC19 -> 1771 | HF19: =HB19+HD19 -> 4394882.6 | HG19: =B19 -> SM-01 | HH19: =C19 -> FBA79276 | HI19: =G19 -> B0D2LJSQXZ | HJ19: =B19 -> SM-01 | HK19: 17574 | HL19: 53 | HM19: 196070 | HN19: 0 | HO19: 0 | HP19: =HL19+HN19 -> 53 | HQ19: =HM19+HO19 -> 196070 | HR19: =HP19*J19 -> 131523.87 | HS19: =HQ19/$HQ$1 -> 0.01790349 | HT19: =B19 -> SM-01 | HU19: 213 | HV19: 507 | HW19: 1000 | HX19: =HU19+HV19+HW19 -> 1720 | HY19: =HX19*J19 -> 4268321.9 | HZ19: 0 | IA19: =HZ19*J19 -> 0 | IB19: =HX19+HZ19 -> 1720 | IC19: =HY19+IA19 -> 4268321.9 | ID19: =B19 -> SM-01 | IE19: =C19 -> FBA79276 | IF19: =G19 -> B0D2LJSQXZ | IG19: =B19 -> SM-01 | IH19: 19396 | II19: 68 | IJ19: 250448.5 | IK19: 0 | IL19: 0 | IM19: =II19+IK19 -> 68 | IN19: =IJ19+IL19 -> 250448.5 | IO19: =IM19*J19 -> 168747.61 | IP19: =IN19/$IN$1 -> 0.022088748 | IQ19: =B19 -> SM-01 | IR19: 436 | IS19: 485 | IT19: 1000 | IU19: =IR19+IS19+IT19 -> 1921 | IV19: =IU19*J19 -> 4767119.9 | IW19: 0 | IX19: =IW19*J19 -> 0 | IY19: =IU19+IW19 -> 1921 | IZ19: =IV19+IX19 -> 4767119.9 | JA19: =B19 -> SM-01 | JB19: =C19 -> FBA79276 | JC19: =G19 -> B0D2LJSQXZ | JD19: =B19 -> SM-01 | JE19: 20568 | JF19: 59 | JG19: 215221.44 | JH19: 0 | JI19: 0 | JJ19: =JF19+JH19 -> 59 | JK19: =JG19+JI19 -> 215221.44 | JL19: =JJ19*J19 -> 146413.37 | JM19: =JK19/$JK$1 -> 0.023802993 | JN19: =B19 -> SM-01 | JO19: 436 | JP19: 485 | JQ19: 1000 | JR19: =JO19+JP19+JQ19 -> 1921 | JS19: =JR19*AG19 -> 0 | JT19: 0 | JU19: =JT19*AG19 -> 0 | JV19: =JR19+JT19 -> 1921 | JW19: =JS19+JU19 -> 0 | JX19: =B19 -> SM-01 | JY19: =C19 -> FBA79276 | JZ19: =G19 -> B0D2LJSQXZ | KA19: =B19 -> SM-01 | KB19: 11307 | KC19: 43 | KD19: 161620.94 | KE19: 0 | KF19: 0 | KG19: =KC19+KE19 -> 43 | KH19: =KD19+KF19 -> 161620.94 | KI19: =KG19*J19 -> 106708.05 | KJ19: =KH19/$KH$1 -> 0.013696344 | KK19: =B19 -> SM-01 | KL19: 436 | KM19: 485 | KN19: 1000 | KO19: =KL19+KM19+KN19 -> 1921 | KP19: =KO19*BD19 -> 105655 | KQ19: 0 | KR19: =KQ19*BD19 -> 0 | KS19: =KO19+KQ19 -> 1921 | KT19: =KP19+KR19 -> 105655 | KU19: =B19 -> SM-01 | KV19: =C19 -> FBA79276 | KW19: =G19 -> B0D2LJSQXZ | KX19: =B19 -> SM-01 | KY19: 9095 | KZ19: 41 | LA19: 149076.28 | LB19: 0 | LC19: 0 | LD19: =KZ19+LB19 -> 41 | LE19: =LA19+LC19 -> 149076.28 | LF19: =LD19*J19 -> 101744.88 | LG19: =LE19/$LE$1 -> 0.011086149 | LH19: =B19 -> SM-01 | LI19: 436 | LJ19: 485 | LK19: 1000 | LL19: =LI19+LJ19+LK19 -> 1921 | LM19: =LL19*CA19 -> 3048627 | LN19: 0 | LO19: =LN19*CA19 -> 0 | LP19: =LL19+LN19 -> 1921 | LQ19: =LM19+LO19 -> 3048627 | LR19: =B19 -> SM-01 | LS19: =C19 -> FBA79276 | LT19: =G19 -> B0D2LJSQXZ | LU19: =B19 -> SM-01 | LV19: 10698 | LW19: 16 | LX19: 60252.14 | LY19: 0 | LZ19: 0 | MA19: =LW19+LY19 -> 16 | MB19: =LX19+LZ19 -> 60252.14 | MC19: =MA19*J19 -> 39705.32 | MD19: =MB19/$MB$1 -> 0.0063514141 | ME19: =B19 -> SM-01 | MF19: 436 | MG19: 485 | MH19: 1000 | MI19: =MF19+MG19+MH19 -> 1921 | MJ19: =MI19*CX19 -> 1.181769e+10 | MK19: 0 | ML19: =MK19*CX19 -> 0 | MM19: =MI19+MK19 -> 1921 | MN19: =MJ19+ML19 -> 1.181769e+10 | MO19: =B19 -> SM-01 | MP19: =C19 -> FBA79276 | MQ19: =G19 -> B0D2LJSQXZ | MR19: =B19 -> SM-01 | MS19: 9350 | MT19: 39 | MU19: 144062 | MV19: 0 | MW19: 0 | MX19: =MT19+MV19 -> 39 | MY19: =MU19+MW19 -> 144062 | MZ19: =MX19*J19 -> 96781.717 | NA19: =MY19/$MY$1 -> 0.011475058 | NB19: =B19 -> SM-01 | NC19: 436 | ND19: 485 | NE19: 1000 | NF19: =NC19+ND19+NE19 -> 1921 | NG19: =NF19*DU19 -> #VALUE! | NH19: 0 | NI19: =NH19*DU19 -> #VALUE! | NJ19: =NF19+NH19 -> 1921 | NK19: =NG19+NI19 -> #VALUE! | NL19: =B19 -> SM-01 | NM19: =C19 -> FBA79276 | NN19: =G19 -> B0D2LJSQXZ | NO19: =Y19 -> 0 | NP19: 10916 | NQ19: 45 | NR19: 157461 | NS19: 0 | NT19: 0 | NU19: =NQ19+NS19 -> 45 | NV19: =NR19+NT19 -> 157461 | NW19: =NU19*J19 -> 111671.21 | NX19: =NV19/$NV$1 -> 0.016357121 | NY19: =B19 -> SM-01 | NZ19: 436 | OA19: 485 | OB19: 1000 | OC19: =NZ19+OA19+OB19 -> 1921 | OD19: =OC19*ER19 -> #VALUE! | OE19: 0 | OF19: =OE19*ER19 -> #VALUE! | OG19: =OC19+OE19 -> 1921 | OH19: =OD19+OF19 -> #VALUE! | OI19: =B19 -> SM-01 | OJ19: =C19 -> FBA79276 | OK19: =G19 -> B0D2LJSQXZ | OL19: =B19 -> SM-01
A20: FBA79349 | B20: SW-01 | C20: FBA79349 | D20: Home & Kitchen | E20: Fabric Care | F20: Nexlev | G20: B0D9KDQCCM | H20: Portable Sewing Machine | I20: 308.74135 | J20: 364.31479 | K20: 0 | L20: 0 | M20: 0 | N20: =1-L20/M20 -> #DIV/0! | O20: 0 | P20: 0 | Q20: 0 | R20: =1-P20/Q20 -> #DIV/0! | S20: 0 | T20: 0 | U20: 0 | V20: =1-T20/U20 -> #DIV/0! | W20: 0 | X20: 0 | Y20: 0 | Z20: =1-X20/Y20 -> #DIV/0! | AA20: 0 | AB20: 0 | AC20: 0 | AD20: =1-AB20/AC20 -> #DIV/0! | AE20: 0 | AF20: 0 | AG20: 0 | AH20: =1-AF20/AG20 -> #DIV/0! | AI20: 0 | AJ20: 0 | AK20: 0 | AL20: =1-AJ20/AK20 -> #DIV/0! | AM20: 0 | AN20: 0 | AO20: 0 | AP20: =1-AN20/AO20 -> #DIV/0! | AQ20: 0 | AR20: 0 | AS20: 0 | AT20: =1-AR20/AS20 -> #DIV/0! | AU20: 0 | AV20: 0 | AW20: 0 | AX20: =1-AV20/AW20 -> #DIV/0! | AY20: 17055 | AZ20: 306 | BA20: 538 | BB20: =1-AZ20/BA20 -> 0.43122677 | BC20: 10697 | BD20: 84 | BE20: 141 | BF20: =1-BD20/BE20 -> 0.40425532 | BG20: 14856 | BH20: 214 | BI20: 336 | BJ20: =1-BH20/BI20 -> 0.36309524 | BK20: 12710 | BL20: 173 | BM20: 172562 | BN20: =BL20*J20 -> 63026.458 | BO20: 298 | BP20: 290371 | BQ20: =1-BL20/BO20 -> 0.41946309 | BR20: =BM20/$BM$1 -> 0.014054103 | BS20: =B20 -> SW-01 | BT20: 371 | BU20: 1559 | BV20: 0 | BW20: =BT20+BU20+BV20 -> 1930 | BX20: =BW20*J20 -> 703127.54 | BY20: 0 | BZ20: =BY20*J20 -> 0 | CA20: =BW20+BY20 -> 1930 | CB20: =BX20+BZ20 -> 703127.54 | CC20: =B20 -> SW-01 | CD20: =C20 -> FBA79349 | CE20: =G20 -> B0D9KDQCCM | CF20: =B20 -> SW-01 | CG20: 20510 | CH20: 200 | CI20: 204327 | CJ20: =CH20*J20 -> 72862.957 | CK20: 346 | CL20: 344237 | CM20: =1-CH20/CK20 -> 0.42196532 | CN20: =CI20/$CI$1 -> 0.01800245 | CO20: =B20 -> SW-01 | CP20: 867 | CQ20: 813 | CR20: 0 | CS20: =CP20+CQ20+CR20 -> 1680 | CT20: =CS20*J20 -> 612048.84 | CU20: 0 | CV20: =CU20*J20 -> 0 | CW20: =CS20+CU20 -> 1680 | CX20: =CT20+CV20 -> 612048.84 | CY20: =B20 -> SW-01 | CZ20: =C20 -> FBA79349 | DA20: =G20 -> B0D9KDQCCM | DB20: =B20 -> SW-01 | DC20: 13496 | DD20: 230 | DE20: 227949.21 | DF20: =DD20*J20 -> 83792.401 | DG20: 343 | DH20: 330423 | DI20: =1-DD20/DG20 -> 0.32944606 | DJ20: =DE20/$DE$1 -> 0.018074394 | DK20: =B20 -> SW-01 | DL20: 770 | DM20: 760 | DN20: 0 | DO20: =DL20+DM20+DN20 -> 1530 | DP20: =DO20*J20 -> 557401.62 | DQ20: 0 | DR20: =DQ20*J20 -> 0 | DS20: =DO20+DQ20 -> 1530 | DT20: =DP20+DR20 -> 557401.62 | DU20: =B20 -> SW-01 | DV20: =C20 -> FBA79349 | DW20: =G20 -> B0D9KDQCCM | DX20: =B20 -> SW-01 | DY20: 9950 | DZ20: 136 | EA20: 144767 | EB20: =DZ20*J20 -> 49546.811 | EC20: 197 | ED20: 2,03,374.00 | EE20: =1-DZ20/EC20 -> 0.30964467 | EF20: =EA20/$EA$1 -> 0.016475814 | EG20: =B20 -> SW-01 | EH20: 697 | EI20: 753 | EJ20: 0 | EK20: =EH20+EI20+EJ20 -> 1450 | EL20: =EK20*J20 -> 528256.44 | EM20: 0 | EN20: =EM20*J20 -> 0 | EO20: =EK20+EM20 -> 1450 | EP20: =EL20+EN20 -> 528256.44 | EQ20: =B20 -> SW-01 | ER20: =C20 -> FBA79349 | ES20: =G20 -> B0D9KDQCCM | ET20: =B20 -> SW-01 | EU20: 19165 | EV20: 124 | EW20: 135250 | EX20: =EV20*J20 -> 45175.034 | EY20: 204 | EZ20: 2,12,784 | FA20: =1-EV20/EY20 -> 0.39215686 | FB20: =EW20/$EW$1 -> 0.02029621 | FC20: =B20 -> SW-01 | FD20: 642 | FE20: 691 | FF20: 0 | FG20: =FD20+FE20+FF20 -> 1333 | FH20: =FG20*J20 -> 485631.61 | FI20: 0 | FJ20: =FI20*J20 -> 0 | FK20: =FG20+FI20 -> 1333 | FL20: =FH20+FJ20 -> 485631.61 | FM20: =B20 -> SW-01 | FN20: =C20 -> FBA79349 | FO20: =G20 -> B0D9KDQCCM | FP20: =B20 -> SW-01 | FQ20: 12331 | FR20: 116 | FS20: 116071.16 | FT20: 0 | FU20: 0 | FV20: =FR20+FT20 -> 116 | FW20: =FS20+FU20 -> 116071.16 | FX20: =FV20*J20 -> 42260.515 | FY20: =FW20/$FW$1 -> 0.012391371 | FZ20: =B20 -> SW-01 | GA20: 0 | GB20: 647 | GC20: 0 | GD20: =GA20+GB20+GC20 -> 647 | GE20: =GD20*J20 -> 235711.67 | GF20: 0 | GG20: =GF20*J20 -> 0 | GH20: =GD20+GF20 -> 647 | GI20: =GE20+GG20 -> 235711.67 | GJ20: =B20 -> SW-01 | GK20: =C20 -> FBA79349 | GL20: =G20 -> B0D9KDQCCM | GM20: =B20 -> SW-01 | GN20: 8941 | GO20: 131 | GP20: 129656 | GQ20: 0 | GR20: 0 | GS20: =GO20+GQ20 -> 131 | GT20: =GP20+GR20 -> 129656 | GU20: =GS20*J20 -> 47725.237 | GV20: =GT20/$GT$1 -> 0.01369938 | GW20: =B20 -> SW-01 | GX20: 244 | GY20: 503 | GZ20: 0 | HA20: =GX20+GY20+GZ20 -> 747 | HB20: =HA20*J20 -> 272143.15 | HC20: 0 | HD20: =HC20*J20 -> 0 | HE20: =HA20+HC20 -> 747 | HF20: =HB20+HD20 -> 272143.15 | HG20: =B20 -> SW-01 | HH20: =C20 -> FBA79349 | HI20: =G20 -> B0D9KDQCCM | HJ20: =B20 -> SW-01 | HK20: 9022 | HL20: 151 | HM20: 151317 | HN20: 0 | HO20: 0 | HP20: =HL20+HN20 -> 151 | HQ20: =HM20+HO20 -> 151317 | HR20: =HP20*J20 -> 55011.533 | HS20: =HQ20/$HQ$1 -> 0.013817017 | HT20: =B20 -> SW-01 | HU20: 446 | HV20: 67 | HW20: 0 | HX20: =HU20+HV20+HW20 -> 513 | HY20: =HX20*J20 -> 186893.49 | HZ20: 0 | IA20: =HZ20*J20 -> 0 | IB20: =HX20+HZ20 -> 513 | IC20: =HY20+IA20 -> 186893.49 | ID20: =B20 -> SW-01 | IE20: =C20 -> FBA79349 | IF20: =G20 -> B0D9KDQCCM | IG20: =B20 -> SW-01 | IH20: 3917 | II20: 186 | IJ20: 193128 | IK20: 0 | IL20: 0 | IM20: =II20+IK20 -> 186 | IN20: =IJ20+IL20 -> 193128 | IO20: =IM20*J20 -> 67762.55 | IP20: =IN20/$IN$1 -> 0.017033265 | IQ20: =B20 -> SW-01 | IR20: 297 | IS20: 58 | IT20: 0 | IU20: =IR20+IS20+IT20 -> 355 | IV20: =IU20*J20 -> 129331.75 | IW20: 0 | IX20: =IW20*J20 -> 0 | IY20: =IU20+IW20 -> 355 | IZ20: =IV20+IX20 -> 129331.75 | JA20: =B20 -> SW-01 | JB20: =C20 -> FBA79349 | JC20: =G20 -> B0D9KDQCCM | JD20: =B20 -> SW-01 | JE20: 8449 | JF20: 142 | JG20: 157794.12 | JH20: 0 | JI20: 0 | JJ20: =JF20+JH20 -> 142 | JK20: =JG20+JI20 -> 157794.12 | JL20: =JJ20*J20 -> 51732.7 | JM20: =JK20/$JK$1 -> 0.017451664 | JN20: =B20 -> SW-01 | JO20: 297 | JP20: 58 | JQ20: 0 | JR20: =JO20+JP20+JQ20 -> 355 | JS20: =JR20*AG20 -> 0 | JT20: 0 | JU20: =JT20*AG20 -> 0 | JV20: =JR20+JT20 -> 355 | JW20: =JS20+JU20 -> 0 | JX20: =B20 -> SW-01 | JY20: =C20 -> FBA79349 | JZ20: =G20 -> B0D9KDQCCM | KA20: =B20 -> SW-01 | KB20: 188 | KC20: 53 | KD20: 63239 | KE20: 0 | KF20: 0 | KG20: =KC20+KE20 -> 53 | KH20: =KD20+KF20 -> 63239 | KI20: =KG20*J20 -> 19308.684 | KJ20: =KH20/$KH$1 -> 0.005359102 | KK20: =B20 -> SW-01 | KL20: 297 | KM20: 58 | KN20: 0 | KO20: =KL20+KM20+KN20 -> 355 | KP20: =KO20*BD20 -> 29820 | KQ20: 0 | KR20: =KQ20*BD20 -> 0 | KS20: =KO20+KQ20 -> 355 | KT20: =KP20+KR20 -> 29820 | KU20: =B20 -> SW-01 | KV20: =C20 -> FBA79349 | KW20: =G20 -> B0D9KDQCCM | KX20: =B20 -> SW-01 | KY20: 1402 | KZ20: 36 | LA20: 38907 | LB20: 0 | LC20: 0 | LD20: =KZ20+LB20 -> 36 | LE20: =LA20+LC20 -> 38907 | LF20: =LD20*J20 -> 13115.332 | LG20: =LE20/$LE$1 -> 0.0028933428 | LH20: =B20 -> SW-01 | LI20: 297 | LJ20: 58 | LK20: 0 | LL20: =LI20+LJ20+LK20 -> 355 | LM20: =LL20*CA20 -> 685150 | LN20: 0 | LO20: =LN20*CA20 -> 0 | LP20: =LL20+LN20 -> 355 | LQ20: =LM20+LO20 -> 685150 | LR20: =B20 -> SW-01 | LS20: =C20 -> FBA79349 | LT20: =G20 -> B0D9KDQCCM | LU20: =B20 -> SW-01 | LV20: 5902 | LW20: 50 | LX20: 54960 | LY20: 0 | LZ20: 0 | MA20: =LW20+LY20 -> 50 | MB20: =LX20+LZ20 -> 54960 | MC20: =MA20*J20 -> 18215.739 | MD20: =MB20/$MB$1 -> 0.0057935489 | ME20: =B20 -> SW-01 | MF20: 297 | MG20: 58 | MH20: 0 | MI20: =MF20+MG20+MH20 -> 355 | MJ20: =MI20*CX20 -> 2.1727734e+08 | MK20: 0 | ML20: =MK20*CX20 -> 0 | MM20: =MI20+MK20 -> 355 | MN20: =MJ20+ML20 -> 2.1727734e+08 | MO20: =B20 -> SW-01 | MP20: =C20 -> FBA79349 | MQ20: =G20 -> B0D9KDQCCM | MR20: =B20 -> SW-01 | MS20: 7502 | MT20: 125 | MU20: 119781 | MV20: 0 | MW20: 0 | MX20: =MT20+MV20 -> 125 | MY20: =MU20+MW20 -> 119781 | MZ20: =MX20*J20 -> 45539.348 | NA20: =MY20/$MY$1 -> 0.0095409888 | NB20: =B20 -> SW-01 | NC20: 297 | ND20: 58 | NE20: 0 | NF20: =NC20+ND20+NE20 -> 355 | NG20: =NF20*DU20 -> #VALUE! | NH20: 0 | NI20: =NH20*DU20 -> #VALUE! | NJ20: =NF20+NH20 -> 355 | NK20: =NG20+NI20 -> #VALUE! | NL20: =B20 -> SW-01 | NM20: =C20 -> FBA79349 | NN20: =G20 -> B0D9KDQCCM | NO20: =Y20 -> 0 | NP20: 10629 | NQ20: 183 | NR20: 179608 | NS20: 0 | NT20: 0 | NU20: =NQ20+NS20 -> 183 | NV20: =NR20+NT20 -> 179608 | NW20: =NU20*J20 -> 66669.606 | NX20: =NV20/$NV$1 -> 0.018657761 | NY20: =B20 -> SW-01 | NZ20: 297 | OA20: 58 | OB20: 0 | OC20: =NZ20+OA20+OB20 -> 355 | OD20: =OC20*ER20 -> #VALUE! | OE20: 0 | OF20: =OE20*ER20 -> #VALUE! | OG20: =OC20+OE20 -> 355 | OH20: =OD20+OF20 -> #VALUE! | OI20: =B20 -> SW-01 | OJ20: =C20 -> FBA79349 | OK20: =G20 -> B0D9KDQCCM | OL20: =B20 -> SW-01
A21: FBA79279 | B21: LR-01 | C21: FBA79279 | D21: Home & Kitchen | E21: Fabric Care | F21: Nexlev | G21: B0D8445KJN | H21: Nexlev Lint Remover - Mini | I21: 362.77371 | J21: 428.07298 | K21: 0 | L21: 0 | M21: 0 | N21: =1-L21/M21 -> #DIV/0! | O21: 0 | P21: 0 | Q21: 0 | R21: =1-P21/Q21 -> #DIV/0! | S21: 0 | T21: 0 | U21: 0 | V21: =1-T21/U21 -> #DIV/0! | W21: 0 | X21: 0 | Y21: 0 | Z21: =1-X21/Y21 -> #DIV/0! | AA21: 0 | AB21: 0 | AC21: 0 | AD21: =1-AB21/AC21 -> #DIV/0! | AE21: 0 | AF21: 0 | AG21: 0 | AH21: =1-AF21/AG21 -> #DIV/0! | AI21: 0 | AJ21: 0 | AK21: 0 | AL21: =1-AJ21/AK21 -> #DIV/0! | AM21: 0 | AN21: 0 | AO21: 0 | AP21: =1-AN21/AO21 -> #DIV/0! | AQ21: 0 | AR21: 0 | AS21: 0 | AT21: =1-AR21/AS21 -> #DIV/0! | AU21: 1984 | AV21: 19 | AW21: 25 | AX21: =1-AV21/AW21 -> 0.24 | AY21: 8422 | AZ21: 75 | BA21: 81 | BB21: =1-AZ21/BA21 -> 0.074074074 | BC21: 10490 | BD21: 101 | BE21: 121 | BF21: =1-BD21/BE21 -> 0.16528926 | BG21: 5713 | BH21: 246 | BI21: 294 | BJ21: =1-BH21/BI21 -> 0.16326531 | BK21: 4543 | BL21: 228 | BM21: 170491 | BN21: =BL21*J21 -> 97600.639 | BO21: 239 | BP21: 178793 | BQ21: =1-BL21/BO21 -> 0.046025105 | BR21: =BM21/$BM$1 -> 0.013885433 | BS21: =B21 -> LR-01 | BT21: 267 | BU21: 60 | BV21: 0 | BW21: =BT21+BU21+BV21 -> 327 | BX21: =BW21*J21 -> 139979.86 | BY21: 3000 | BZ21: =BY21*J21 -> 1284218.9 | CA21: =BW21+BY21 -> 3327 | CB21: =BX21+BZ21 -> 1424198.8 | CC21: =B21 -> LR-01 | CD21: =C21 -> FBA79279 | CE21: =G21 -> B0D8445KJN | CF21: =B21 -> LR-01 | CG21: 4982 | CH21: 186 | CI21: 151266.62 | CJ21: =CH21*J21 -> 79621.574 | CK21: 199 | CL21: 159591 | CM21: =1-CH21/CK21 -> 0.065326633 | CN21: =CI21/$CI$1 -> 0.013327508 | CO21: =B21 -> LR-01 | CP21: 116 | CQ21: 13 | CR21: 0 | CS21: =CP21+CQ21+CR21 -> 129 | CT21: =CS21*J21 -> 55221.414 | CU21: 3000 | CV21: =CU21*J21 -> 1284218.9 | CW21: =CS21+CU21 -> 3129 | CX21: =CT21+CV21 -> 1339440.3 | CY21: =B21 -> LR-01 | CZ21: =C21 -> FBA79279 | DA21: =G21 -> B0D8445KJN | DB21: =B21 -> LR-01 | DC21: 9357 | DD21: 150 | DE21: 109935.21 | DF21: =DD21*J21 -> 64210.947 | DG21: 159 | DH21: 114893 | DI21: =1-DD21/DG21 -> 0.056603774 | DJ21: =DE21/$DE$1 -> 0.0087169081 | DK21: =B21 -> LR-01 | DL21: 440 | DM21: 2506 | DN21: 0 | DO21: =DL21+DM21+DN21 -> 2946 | DP21: =DO21*J21 -> 1261103 | DQ21: 3000 | DR21: =DQ21*J21 -> 1284218.9 | DS21: =DO21+DQ21 -> 5946 | DT21: =DP21+DR21 -> 2545321.9 | DU21: =B21 -> LR-01 | DV21: =C21 -> FBA79279 | DW21: =G21 -> B0D8445KJN | DX21: =B21 -> LR-01 | DY21: 5575 | DZ21: 45 | EA21: 32614 | EB21: =DZ21*J21 -> 19263.284 | EC21: 53 | ED21: 36250 | EE21: =1-DZ21/EC21 -> 0.1509434 | EF21: =EA21/$EA$1 -> 0.0037117727 | EG21: =B21 -> LR-01 | EH21: 391 | EI21: 2519 | EJ21: 0 | EK21: =EH21+EI21+EJ21 -> 2910 | EL21: =EK21*J21 -> 1245692.4 | EM21: 3000 | EN21: =EM21*J21 -> 1284218.9 | EO21: =EK21+EM21 -> 5910 | EP21: =EL21+EN21 -> 2529911.3 | EQ21: =B21 -> LR-01 | ER21: =C21 -> FBA79279 | ES21: =G21 -> B0D8445KJN | ET21: =B21 -> LR-01 | EU21: 4520 | EV21: 37 | EW21: 26075 | EX21: =EV21*J21 -> 15838.7 | EY21: 37 | EZ21: 25875 | FA21: =1-EV21/EY21 -> 0 | FB21: =EW21/$EW$1 -> 0.0039129292 | FC21: =B21 -> LR-01 | FD21: 350 | FE21: 2454 | FF21: 0 | FG21: =FD21+FE21+FF21 -> 2804 | FH21: =FG21*J21 -> 1200316.6 | FI21: 3000 | FJ21: =FI21*J21 -> 1284218.9 | FK21: =FG21+FI21 -> 5804 | FL21: =FH21+FJ21 -> 2484535.6 | FM21: =B21 -> LR-01 | FN21: =C21 -> FBA79279 | FO21: =G21 -> B0D8445KJN | FP21: =B21 -> LR-01 | FQ21: 7163 | FR21: 58 | FS21: 37690 | FT21: 0 | FU21: 0 | FV21: =FR21+FT21 -> 58 | FW21: =FS21+FU21 -> 37690 | FX21: =FV21*J21 -> 24828.233 | FY21: =FW21/$FW$1 -> 0.004023659 | FZ21: =B21 -> LR-01 | GA21: 0 | GB21: 2447 | GC21: 0 | GD21: =GA21+GB21+GC21 -> 2447 | GE21: =GD21*J21 -> 1047494.6 | GF21: 3000 | GG21: =GF21*J21 -> 1284218.9 | GH21: =GD21+GF21 -> 5447 | GI21: =GE21+GG21 -> 2331713.5 | GJ21: =B21 -> LR-01 | GK21: =C21 -> FBA79279 | GL21: =G21 -> B0D8445KJN | GM21: =B21 -> LR-01 | GN21: 7096 | GO21: 36 | GP21: 24722 | GQ21: 0 | GR21: 0 | GS21: =GO21+GQ21 -> 36 | GT21: =GP21+GR21 -> 24722 | GU21: =GS21*J21 -> 15410.627 | GV21: =GT21/$GT$1 -> 0.0026121126 | GW21: =B21 -> LR-01 | GX21: 249 | GY21: 1879 | GZ21: 0 | HA21: =GX21+GY21+GZ21 -> 2128 | HB21: =HA21*J21 -> 910939.3 | HC21: 3000 | HD21: =HC21*J21 -> 1284218.9 | HE21: =HA21+HC21 -> 5128 | HF21: =HB21+HD21 -> 2195158.2 | HG21: =B21 -> LR-01 | HH21: =C21 -> FBA79279 | HI21: =G21 -> B0D8445KJN | HJ21: =B21 -> LR-01 | HK21: 1008 | HL21: 30 | HM21: 20973 | HN21: 0 | HO21: 0 | HP21: =HL21+HN21 -> 30 | HQ21: =HM21+HO21 -> 20973 | HR21: =HP21*J21 -> 12842.189 | HS21: =HQ21/$HQ$1 -> 0.0019150809 | HT21: =B21 -> LR-01 | HU21: 574 | HV21: 1377 | HW21: 0 | HX21: =HU21+HV21+HW21 -> 1951 | HY21: =HX21*J21 -> 835170.38 | HZ21: 3000 | IA21: =HZ21*J21 -> 1284218.9 | IB21: =HX21+HZ21 -> 4951 | IC21: =HY21+IA21 -> 2119389.3 | ID21: =B21 -> LR-01 | IE21: =C21 -> FBA79279 | IF21: =G21 -> B0D8445KJN | IG21: =B21 -> LR-01 | IH21: 971 | II21: 35 | IJ21: 32385.84 | IK21: 0 | IL21: 0 | IM21: =II21+IK21 -> 35 | IN21: =IJ21+IL21 -> 32385.84 | IO21: =IM21*J21 -> 14982.554 | IP21: =IN21/$IN$1 -> 0.0028563263 | IQ21: =B21 -> LR-01 | IR21: 283 | IS21: 1261 | IT21: 0 | IU21: =IR21+IS21+IT21 -> 1544 | IV21: =IU21*J21 -> 660944.68 | IW21: 3000 | IX21: =IW21*J21 -> 1284218.9 | IY21: =IU21+IW21 -> 4544 | IZ21: =IV21+IX21 -> 1945163.6 | JA21: =B21 -> LR-01 | JB21: =C21 -> FBA79279 | JC21: =G21 -> B0D8445KJN | JD21: =B21 -> LR-01 | JE21: 326 | JF21: 7 | JG21: 6805.04 | JH21: 0 | JI21: 0 | JJ21: =JF21+JH21 -> 7 | JK21: =JG21+JI21 -> 6805.04 | JL21: =JJ21*J21 -> 2996.5108 | JM21: =JK21/$JK$1 -> 0.00075262167 | JN21: =B21 -> LR-01 | JO21: 283 | JP21: 1261 | JQ21: 0 | JR21: =JO21+JP21+JQ21 -> 1544 | JS21: =JR21*AG21 -> 0 | JT21: 3000 | JU21: =JT21*AG21 -> 0 | JV21: =JR21+JT21 -> 4544 | JW21: =JS21+JU21 -> 0 | JX21: =B21 -> LR-01 | JY21: =C21 -> FBA79279 | JZ21: =G21 -> B0D8445KJN | KA21: =B21 -> LR-01 | KB21: 534 | KC21: 5 | KD21: 4589.26 | KE21: 0 | KF21: 0 | KG21: =KC21+KE21 -> 5 | KH21: =KD21+KF21 -> 4589.26 | KI21: =KG21*J21 -> 2140.3649 | KJ21: =KH21/$KH$1 -> 0.00038891052 | KK21: =B21 -> LR-01 | KL21: 283 | KM21: 1261 | KN21: 0 | KO21: =KL21+KM21+KN21 -> 1544 | KP21: =KO21*BD21 -> 155944 | KQ21: 3000 | KR21: =KQ21*BD21 -> 303000 | KS21: =KO21+KQ21 -> 4544 | KT21: =KP21+KR21 -> 458944 | KU21: =B21 -> LR-01 | KV21: =C21 -> FBA79279 | KW21: =G21 -> B0D8445KJN | KX21: =B21 -> LR-01 | KY21: 383 | KZ21: 8 | LA21: 7459 | LB21: 0 | LC21: 0 | LD21: =KZ21+LB21 -> 8 | LE21: =LA21+LC21 -> 7459 | LF21: =LD21*J21 -> 3424.5838 | LG21: =LE21/$LE$1 -> 0.00055469309 | LH21: =B21 -> LR-01 | LI21: 283 | LJ21: 1261 | LK21: 0 | LL21: =LI21+LJ21+LK21 -> 1544 | LM21: =LL21*CA21 -> 5136888 | LN21: 3000 | LO21: =LN21*CA21 -> 9981000 | LP21: =LL21+LN21 -> 4544 | LQ21: =LM21+LO21 -> 15117888 | LR21: =B21 -> LR-01 | LS21: =C21 -> FBA79279 | LT21: =G21 -> B0D8445KJN | LU21: =B21 -> LR-01 | LV21: 3504 | LW21: 17 | LX21: 15606 | LY21: 0 | LZ21: 0 | MA21: =LW21+LY21 -> 17 | MB21: =LX21+LZ21 -> 15606 | MC21: =MA21*J21 -> 7277.2406 | MD21: =MB21/$MB$1 -> 0.0016450896 | ME21: =B21 -> LR-01 | MF21: 283 | MG21: 1261 | MH21: 0 | MI21: =MF21+MG21+MH21 -> 1544 | MJ21: =MI21*CX21 -> 2.0680959e+09 | MK21: 3000 | ML21: =MK21*CX21 -> 4.018321e+09 | MM21: =MI21+MK21 -> 4544 | MN21: =MJ21+ML21 -> 6.0864169e+09 | MO21: =B21 -> LR-01 | MP21: =C21 -> FBA79279 | MQ21: =G21 -> B0D8445KJN | MR21: =B21 -> LR-01 | MS21: 2367 | MT21: 19 | MU21: 15426 | MV21: 0 | MW21: 0 | MX21: =MT21+MV21 -> 19 | MY21: =MU21+MW21 -> 15426 | MZ21: =MX21*J21 -> 8133.3866 | NA21: =MY21/$MY$1 -> 0.0012287366 | NB21: =B21 -> LR-01 | NC21: 283 | ND21: 1261 | NE21: 0 | NF21: =NC21+ND21+NE21 -> 1544 | NG21: =NF21*DU21 -> #VALUE! | NH21: 3000 | NI21: =NH21*DU21 -> #VALUE! | NJ21: =NF21+NH21 -> 4544 | NK21: =NG21+NI21 -> #VALUE! | NL21: =B21 -> LR-01 | NM21: =C21 -> FBA79279 | NN21: =G21 -> B0D8445KJN | NO21: =Y21 -> 0 | NP21: 1667 | NQ21: 33 | NR21: 27029 | NS21: 0 | NT21: 0 | NU21: =NQ21+NS21 -> 33 | NV21: =NR21+NT21 -> 27029 | NW21: =NU21*J21 -> 14126.408 | NX21: =NV21/$NV$1 -> 0.0028077849 | NY21: =B21 -> LR-01 | NZ21: 283 | OA21: 1261 | OB21: 0 | OC21: =NZ21+OA21+OB21 -> 1544 | OD21: =OC21*ER21 -> #VALUE! | OE21: 3000 | OF21: =OE21*ER21 -> #VALUE! | OG21: =OC21+OE21 -> 4544 | OH21: =OD21+OF21 -> #VALUE! | OI21: =B21 -> LR-01 | OJ21: =C21 -> FBA79279 | OK21: =G21 -> B0D8445KJN | OL21: =B21 -> LR-01
A22: FBA79352 | B22: WF-02-BL | C22: FBA79352 | D22: Pet Supplies | E22: Pet Supplies | F22: Nexlev | G22: B0D637B562 | H22: Nexlev Pet Water Fountain 2L | I22: 438.51317 | J22: 517.44554 | K22: 0 | L22: 0 | M22: 0 | N22: =1-L22/M22 -> #DIV/0! | O22: 0 | P22: 0 | Q22: 0 | R22: =1-P22/Q22 -> #DIV/0! | S22: 0 | T22: 0 | U22: 0 | V22: =1-T22/U22 -> #DIV/0! | W22: 0 | X22: 0 | Y22: 0 | Z22: =1-X22/Y22 -> #DIV/0! | AA22: 0 | AB22: 0 | AC22: 0 | AD22: =1-AB22/AC22 -> #DIV/0! | AE22: 0 | AF22: 0 | AG22: 0 | AH22: =1-AF22/AG22 -> #DIV/0! | AI22: 0 | AJ22: 0 | AK22: 0 | AL22: =1-AJ22/AK22 -> #DIV/0! | AM22: 0 | AN22: 0 | AO22: 0 | AP22: =1-AN22/AO22 -> #DIV/0! | AQ22: 351 | AR22: 17 | AS22: 25 | AT22: =1-AR22/AS22 -> 0.32 | AU22: 2653 | AV22: 159 | AW22: 191 | AX22: =1-AV22/AW22 -> 0.16753927 | AY22: 4111 | AZ22: 188 | BA22: 224 | BB22: =1-AZ22/BA22 -> 0.16071429 | BC22: 2785 | BD22: 157 | BE22: 210 | BF22: =1-BD22/BE22 -> 0.25238095 | BG22: 2420 | BH22: 189 | BI22: 220 | BJ22: =1-BH22/BI22 -> 0.14090909 | BK22: 1824 | BL22: 130 | BM22: 162717 | BN22: =BL22*J22 -> 67267.921 | BO22: 157 | BP22: 189659 | BQ22: =1-BL22/BO22 -> 0.17197452 | BR22: =BM22/$BM$1 -> 0.013252289 | BS22: =B22 -> WF-02-BL | BT22: 411 | BU22: 657 | BV22: 0 | BW22: =BT22+BU22+BV22 -> 1068 | BX22: =BW22*J22 -> 552631.84 | BY22: 0 | BZ22: =BY22*J22 -> 0 | CA22: =BW22+BY22 -> 1068 | CB22: =BX22+BZ22 -> 552631.84 | CC22: =B22 -> WF-02-BL | CD22: =C22 -> FBA79352 | CE22: =G22 -> B0D637B562 | CF22: =B22 -> WF-02-BL | CG22: 810 | CH22: 60 | CI22: 74408.62 | CJ22: =CH22*J22 -> 31046.733 | CK22: 65 | CL22: 76812 | CM22: =1-CH22/CK22 -> 0.076923077 | CN22: =CI22/$CI$1 -> 0.0065558514 | CO22: =B22 -> WF-02-BL | CP22: 427 | CQ22: 586 | CR22: 0 | CS22: =CP22+CQ22+CR22 -> 1013 | CT22: =CS22*J22 -> 524172.34 | CU22: 0 | CV22: =CU22*J22 -> 0 | CW22: =CS22+CU22 -> 1013 | CX22: =CT22+CV22 -> 524172.34 | CY22: =B22 -> WF-02-BL | CZ22: =C22 -> FBA79352 | DA22: =G22 -> B0D637B562 | DB22: =B22 -> WF-02-BL | DC22: 5239 | DD22: 128 | DE22: 141097.68 | DF22: =DD22*J22 -> 66233.03 | DG22: 150 | DH22: 163380 | DI22: =1-DD22/DG22 -> 0.14666667 | DJ22: =DE22/$DE$1 -> 0.011187821 | DK22: =B22 -> WF-02-BL | DL22: 353 | DM22: 513 | DN22: 0 | DO22: =DL22+DM22+DN22 -> 866 | DP22: =DO22*J22 -> 448107.84 | DQ22: 0 | DR22: =DQ22*J22 -> 0 | DS22: =DO22+DQ22 -> 866 | DT22: =DP22+DR22 -> 448107.84 | DU22: =B22 -> WF-02-BL | DV22: =C22 -> FBA79352 | DW22: =G22 -> B0D637B562 | DX22: =B22 -> WF-02-BL | DY22: 6454 | DZ22: 66 | EA22: 82592 | EB22: =DZ22*J22 -> 34151.406 | EC22: 71 | ED22: 86181 | EE22: =1-DZ22/EC22 -> 0.070422535 | EF22: =EA22/$EA$1 -> 0.009399728 | EG22: =B22 -> WF-02-BL | EH22: 161 | EI22: 511 | EJ22: 0 | EK22: =EH22+EI22+EJ22 -> 672 | EL22: =EK22*J22 -> 347723.41 | EM22: 0 | EN22: =EM22*J22 -> 0 | EO22: =EK22+EM22 -> 672 | EP22: =EL22+EN22 -> 347723.41 | EQ22: =B22 -> WF-02-BL | ER22: =C22 -> FBA79352 | ES22: =G22 -> B0D637B562 | ET22: =B22 -> WF-02-BL | EU22: 4516 | EV22: 48 | EW22: 60280 | EX22: =EV22*J22 -> 24837.386 | EY22: 51 | EZ22: 63691 | FA22: =1-EV22/EY22 -> 0.058823529 | FB22: =EW22/$EW$1 -> 0.009045882 | FC22: =B22 -> WF-02-BL | FD22: 123 | FE22: 482 | FF22: 0 | FG22: =FD22+FE22+FF22 -> 605 | FH22: =FG22*J22 -> 313054.55 | FI22: 0 | FJ22: =FI22*J22 -> 0 | FK22: =FG22+FI22 -> 605 | FL22: =FH22+FJ22 -> 313054.55 | FM22: =B22 -> WF-02-BL | FN22: =C22 -> FBA79352 | FO22: =G22 -> B0D637B562 | FP22: =B22 -> WF-02-BL | FQ22: 946 | FR22: 54 | FS22: 67663 | FT22: 0 | FU22: 0 | FV22: =FR22+FT22 -> 54 | FW22: =FS22+FU22 -> 67663 | FX22: =FV22*J22 -> 27942.059 | FY22: =FW22/$FW$1 -> 0.0072234767 | FZ22: =B22 -> WF-02-BL | GA22: 0 | GB22: 392 | GC22: 0 | GD22: =GA22+GB22+GC22 -> 392 | GE22: =GD22*J22 -> 202838.65 | GF22: 0 | GG22: =GF22*J22 -> 0 | GH22: =GD22+GF22 -> 392 | GI22: =GE22+GG22 -> 202838.65 | GJ22: =B22 -> WF-02-BL | GK22: =C22 -> FBA79352 | GL22: =G22 -> B0D637B562 | GM22: =B22 -> WF-02-BL | GN22: 1456 | GO22: 84 | GP22: 83357.32 | GQ22: 0 | GR22: 0 | GS22: =GO22+GQ22 -> 84 | GT22: =GP22+GR22 -> 83357.32 | GU22: =GS22*J22 -> 43465.426 | GV22: =GT22/$GT$1 -> 0.0088074874 | GW22: =B22 -> WF-02-BL | GX22: 171 | GY22: 288 | GZ22: 0 | HA22: =GX22+GY22+GZ22 -> 459 | HB22: =HA22*J22 -> 237507.5 | HC22: 0 | HD22: =HC22*J22 -> 0 | HE22: =HA22+HC22 -> 459 | HF22: =HB22+HD22 -> 237507.5 | HG22: =B22 -> WF-02-BL | HH22: =C22 -> FBA79352 | HI22: =G22 -> B0D637B562 | HJ22: =B22 -> WF-02-BL | HK22: 1098 | HL22: 58 | HM22: 72882 | HN22: 0 | HO22: 0 | HP22: =HL22+HN22 -> 58 | HQ22: =HM22+HO22 -> 72882 | HR22: =HP22*J22 -> 30011.842 | HS22: =HQ22/$HQ$1 -> 0.0066549813 | HT22: =B22 -> WF-02-BL | HU22: 297 | HV22: 62 | HW22: 0 | HX22: =HU22+HV22+HW22 -> 359 | HY22: =HX22*J22 -> 185762.95 | HZ22: 0 | IA22: =HZ22*J22 -> 0 | IB22: =HX22+HZ22 -> 359 | IC22: =HY22+IA22 -> 185762.95 | ID22: =B22 -> WF-02-BL | IE22: =C22 -> FBA79352 | IF22: =G22 -> B0D637B562 | IG22: =B22 -> WF-02-BL | IH22: 6254 | II22: 66 | IJ22: 79467.7 | IK22: 0 | IL22: 0 | IM22: =II22+IK22 -> 66 | IN22: =IJ22+IL22 -> 79467.7 | IO22: =IM22*J22 -> 34151.406 | IP22: =IN22/$IN$1 -> 0.0070087941 | IQ22: =B22 -> WF-02-BL | IR22: 364 | IS22: 86 | IT22: 0 | IU22: =IR22+IS22+IT22 -> 450 | IV22: =IU22*J22 -> 232850.49 | IW22: 0 | IX22: =IW22*J22 -> 0 | IY22: =IU22+IW22 -> 450 | IZ22: =IV22+IX22 -> 232850.49 | JA22: =B22 -> WF-02-BL | JB22: =C22 -> FBA79352 | JC22: =G22 -> B0D637B562 | JD22: =B22 -> WF-02-BL | JE22: 8218 | JF22: 47 | JG22: 54125.18 | JH22: 0 | JI22: 0 | JJ22: =JF22+JH22 -> 47 | JK22: =JG22+JI22 -> 54125.18 | JL22: =JJ22*J22 -> 24319.941 | JM22: =JK22/$JK$1 -> 0.0059861196 | JN22: =B22 -> WF-02-BL | JO22: 364 | JP22: 86 | JQ22: 0 | JR22: =JO22+JP22+JQ22 -> 450 | JS22: =JR22*AG22 -> 0 | JT22: 0 | JU22: =JT22*AG22 -> 0 | JV22: =JR22+JT22 -> 450 | JW22: =JS22+JU22 -> 0 | JX22: =B22 -> WF-02-BL | JY22: =C22 -> FBA79352 | JZ22: =G22 -> B0D637B562 | KA22: =B22 -> WF-02-BL | KB22: 1725 | KC22: 105 | KD22: 103220.48 | KE22: 0 | KF22: 0 | KG22: =KC22+KE22 -> 105 | KH22: =KD22+KF22 -> 103220.48 | KI22: =KG22*J22 -> 54331.782 | KJ22: =KH22/$KH$1 -> 0.0087472775 | KK22: =B22 -> WF-02-BL | KL22: 364 | KM22: 86 | KN22: 0 | KO22: =KL22+KM22+KN22 -> 450 | KP22: =KO22*BD22 -> 70650 | KQ22: 0 | KR22: =KQ22*BD22 -> 0 | KS22: =KO22+KQ22 -> 450 | KT22: =KP22+KR22 -> 70650 | KU22: =B22 -> WF-02-BL | KV22: =C22 -> FBA79352 | KW22: =G22 -> B0D637B562 | KX22: =B22 -> WF-02-BL | KY22: 1972 | KZ22: 137 | LA22: 134477.88 | LB22: 0 | LC22: 0 | LD22: =KZ22+LB22 -> 137 | LE22: =LA22+LC22 -> 134477.88 | LF22: =LD22*J22 -> 70890.039 | LG22: =LE22/$LE$1 -> 0.01000053 | LH22: =B22 -> WF-02-BL | LI22: 364 | LJ22: 86 | LK22: 0 | LL22: =LI22+LJ22+LK22 -> 450 | LM22: =LL22*CA22 -> 480600 | LN22: 0 | LO22: =LN22*CA22 -> 0 | LP22: =LL22+LN22 -> 450 | LQ22: =LM22+LO22 -> 480600 | LR22: =B22 -> WF-02-BL | LS22: =C22 -> FBA79352 | LT22: =G22 -> B0D637B562 | LU22: =B22 -> WF-02-BL | LV22: 1240 | LW22: 16 | LX22: 20009.08 | LY22: 0 | LZ22: 0 | MA22: =LW22+LY22 -> 16 | MB22: =LX22+LZ22 -> 20009.08 | MC22: =MA22*J22 -> 8279.1287 | MD22: =MB22/$MB$1 -> 0.0021092355 | ME22: =B22 -> WF-02-BL | MF22: 364 | MG22: 86 | MH22: 0 | MI22: =MF22+MG22+MH22 -> 450 | MJ22: =MI22*CX22 -> 2.3587755e+08 | MK22: 0 | ML22: =MK22*CX22 -> 0 | MM22: =MI22+MK22 -> 450 | MN22: =MJ22+ML22 -> 2.3587755e+08 | MO22: =B22 -> WF-02-BL | MP22: =C22 -> FBA79352 | MQ22: =G22 -> B0D637B562 | MR22: =B22 -> WF-02-BL | MS22: 1324 | MT22: 44 | MU22: 52458 | MV22: 0 | MW22: 0 | MX22: =MT22+MV22 -> 44 | MY22: =MU22+MW22 -> 52458 | MZ22: =MX22*J22 -> 22767.604 | NA22: =MY22/$MY$1 -> 0.004178469 | NB22: =B22 -> WF-02-BL | NC22: 364 | ND22: 86 | NE22: 0 | NF22: =NC22+ND22+NE22 -> 450 | NG22: =NF22*DU22 -> #VALUE! | NH22: 0 | NI22: =NH22*DU22 -> #VALUE! | NJ22: =NF22+NH22 -> 450 | NK22: =NG22+NI22 -> #VALUE! | NL22: =B22 -> WF-02-BL | NM22: =C22 -> FBA79352 | NN22: =G22 -> B0D637B562 | NO22: =Y22 -> 0 | NP22: 411 | NQ22: 37 | NR22: 46300 | NS22: 0 | NT22: 0 | NU22: =NQ22+NS22 -> 37 | NV22: =NR22+NT22 -> 46300 | NW22: =NU22*J22 -> 19145.485 | NX22: =NV22/$NV$1 -> 0.0048096652 | NY22: =B22 -> WF-02-BL | NZ22: 364 | OA22: 86 | OB22: 0 | OC22: =NZ22+OA22+OB22 -> 450 | OD22: =OC22*ER22 -> #VALUE! | OE22: 0 | OF22: =OE22*ER22 -> #VALUE! | OG22: =OC22+OE22 -> 450 | OH22: =OD22+OF22 -> #VALUE! | OI22: =B22 -> WF-02-BL | OJ22: =C22 -> FBA79352 | OK22: =G22 -> B0D637B562 | OL22: =B22 -> WF-02-BL
A23: FBA79588 | B23: EA-01 Pro | C23: FBA79588 | D23: HPC | E23: Hair Care | F23: Nexlev | G23: B0DHRQPGGM | H23: Nexlev Oil Applicator Pro | I23: 574.0254 | J23: 677.34997 | K23: 0 | L23: 0 | M23: 0 | N23: =1-L23/M23 -> #DIV/0! | O23: 0 | P23: 0 | Q23: 0 | R23: =1-P23/Q23 -> #DIV/0! | S23: 0 | T23: 0 | U23: 0 | V23: =1-T23/U23 -> #DIV/0! | W23: 0 | X23: 0 | Y23: 0 | Z23: =1-X23/Y23 -> #DIV/0! | AA23: 0 | AB23: 0 | AC23: 0 | AD23: =1-AB23/AC23 -> #DIV/0! | AE23: 0 | AF23: 0 | AG23: 0 | AH23: =1-AF23/AG23 -> #DIV/0! | AI23: 0 | AJ23: 0 | AK23: 0 | AL23: =1-AJ23/AK23 -> #DIV/0! | AM23: 0 | AN23: 0 | AO23: 0 | AP23: =1-AN23/AO23 -> #DIV/0! | AQ23: 0 | AR23: 0 | AS23: 0 | AT23: =1-AR23/AS23 -> #DIV/0! | AU23: 0 | AV23: 0 | AW23: 0 | AX23: =1-AV23/AW23 -> #DIV/0! | AY23: 0 | AZ23: 0 | BA23: 0 | BB23: =1-AZ23/BA23 -> #DIV/0! | BC23: 0 | BD23: 0 | BE23: 0 | BF23: =1-BD23/BE23 -> #DIV/0! | BG23: 3364 | BH23: 164 | BI23: 185 | BJ23: =1-BH23/BI23 -> 0.11351351 | BK23: 3421 | BL23: 113 | BM23: 162090 | BN23: =BL23*J23 -> 76540.547 | BO23: 128 | BP23: 171842 | BQ23: =1-BL23/BO23 -> 0.1171875 | BR23: =BM23/$BM$1 -> 0.013201224 | BS23: =B23 -> EA-01 Pro | BT23: 346 | BU23: 0 | BV23: 0 | BW23: =BT23+BU23+BV23 -> 346 | BX23: =BW23*J23 -> 234363.09 | BY23: 0 | BZ23: =BY23*J23 -> 0 | CA23: =BW23+BY23 -> 346 | CB23: =BX23+BZ23 -> 234363.09 | CC23: =B23 -> EA-01 Pro | CD23: =C23 -> FBA79588 | CE23: =G23 -> B0DHRQPGGM | CF23: =B23 -> EA-01 Pro | CG23: 6814 | CH23: 96 | CI23: 133911.03 | CJ23: =CH23*J23 -> 65025.597 | CK23: 102 | CL23: 136902 | CM23: =1-CH23/CK23 -> 0.058823529 | CN23: =CI23/$CI$1 -> 0.011798375 | CO23: =B23 -> EA-01 Pro | CP23: 493 | CQ23: 0 | CR23: 0 | CS23: =CP23+CQ23+CR23 -> 493 | CT23: =CS23*J23 -> 333933.54 | CU23: 0 | CV23: =CU23*J23 -> 0 | CW23: =CS23+CU23 -> 493 | CX23: =CT23+CV23 -> 333933.54 | CY23: =B23 -> EA-01 Pro | CZ23: =C23 -> FBA79588 | DA23: =G23 -> B0DHRQPGGM | DB23: =B23 -> EA-01 Pro | DC23: 6544 | DD23: 22 | DE23: 31007.24 | DF23: =DD23*J23 -> 14901.699 | DG23: 25 | DH23: 33864 | DI23: =1-DD23/DG23 -> 0.12 | DJ23: =DE23/$DE$1 -> 0.002458605 | DK23: =B23 -> EA-01 Pro | DL23: 2 | DM23: 0 | DN23: 0 | DO23: =DL23+DM23+DN23 -> 2 | DP23: =DO23*J23 -> 1354.6999 | DQ23: 0 | DR23: =DQ23*J23 -> 0 | DS23: =DO23+DQ23 -> 2 | DT23: =DP23+DR23 -> 1354.6999 | DU23: =B23 -> EA-01 Pro | DV23: =C23 -> FBA79588 | DW23: =G23 -> B0DHRQPGGM | DX23: =B23 -> EA-01 Pro | DY23: 116 | DZ23: 1 | EA23: 1539 | EB23: =DZ23*J23 -> 677.34997 | EC23: 1 | ED23: 1539 | EE23: =1-DZ23/EC23 -> 0 | EF23: =EA23/$EA$1 -> 0.00017515233 | EG23: =B23 -> EA-01 Pro | EH23: 0 | EI23: 0 | EJ23: 0 | EK23: =EH23+EI23+EJ23 -> 0 | EL23: =EK23*J23 -> 0 | EM23: 0 | EN23: =EM23*J23 -> 0 | EO23: =EK23+EM23 -> 0 | EP23: =EL23+EN23 -> 0 | EQ23: =B23 -> EA-01 Pro | ER23: =C23 -> FBA79588 | ES23: =G23 -> B0DHRQPGGM | ET23: =B23 -> EA-01 Pro | EU23: NA | EV23: 0 | EW23: 0 | EX23: =EV23*J23 -> 0 | EY23: NA | EZ23: NA | FA23: =1-EV23/EY23 -> #VALUE! | FB23: =EW23/$EW$1 -> 0 | FC23: =B23 -> EA-01 Pro | FD23: 0 | FE23: 0 | FF23: 0 | FG23: =FD23+FE23+FF23 -> 0 | FH23: =FG23*J23 -> 0 | FI23: 0 | FJ23: =FI23*J23 -> 0 | FK23: =FG23+FI23 -> 0 | FL23: =FH23+FJ23 -> 0 | FM23: =B23 -> EA-01 Pro | FN23: =C23 -> FBA79588 | FO23: =G23 -> B0DHRQPGGM | FP23: =B23 -> EA-01 Pro | FQ23: NA | FR23: 0 | FS23: 0 | FT23: 0 | FU23: 0 | FV23: =FR23+FT23 -> 0 | FW23: =FS23+FU23 -> 0 | FX23: =FV23*J23 -> 0 | FY23: =FW23/$FW$1 -> 0 | FZ23: =B23 -> EA-01 Pro | GA23: 0 | GB23: 0 | GC23: 0 | GD23: =GA23+GB23+GC23 -> 0 | GE23: =GD23*J23 -> 0 | GF23: 0 | GG23: =GF23*J23 -> 0 | GH23: =GD23+GF23 -> 0 | GI23: =GE23+GG23 -> 0 | GJ23: =B23 -> EA-01 Pro | GK23: =C23 -> FBA79588 | GL23: =G23 -> B0DHRQPGGM | GM23: =B23 -> EA-01 Pro | GN23: 85 | GO23: 0 | GP23: 0 | GQ23: 0 | GR23: 0 | GS23: =GO23+GQ23 -> 0 | GT23: =GP23+GR23 -> 0 | GU23: =GS23*J23 -> 0 | GV23: =GT23/$GT$1 -> 0 | GW23: =B23 -> EA-01 Pro | GX23: 2 | GY23: 0 | GZ23: 0 | HA23: =GX23+GY23+GZ23 -> 2 | HB23: =HA23*J23 -> 1354.6999 | HC23: 0 | HD23: =HC23*J23 -> 0 | HE23: =HA23+HC23 -> 2 | HF23: =HB23+HD23 -> 1354.6999 | HG23: =B23 -> EA-01 Pro | HH23: =C23 -> FBA79588 | HI23: =G23 -> B0DHRQPGGM | HJ23: =B23 -> EA-01 Pro | HK23: 139 | HL23: 2 | HM23: 2579 | HN23: 0 | HO23: 0 | HP23: =HL23+HN23 -> 2 | HQ23: =HM23+HO23 -> 2579 | HR23: =HP23*J23 -> 1354.6999 | HS23: =HQ23/$HQ$1 -> 0.00023549295 | HT23: =B23 -> EA-01 Pro | HU23: 0 | HV23: 0 | HW23: 0 | HX23: =HU23+HV23+HW23 -> 0 | HY23: =HX23*J23 -> 0 | HZ23: 0 | IA23: =HZ23*J23 -> 0 | IB23: =HX23+HZ23 -> 0 | IC23: =HY23+IA23 -> 0 | ID23: =B23 -> EA-01 Pro | IE23: =C23 -> FBA79588 | IF23: =G23 -> B0DHRQPGGM | IG23: =B23 -> EA-01 Pro | IH23: 82 | II23: 1 | IJ23: 1539 | IK23: 0 | IL23: 0 | IM23: =II23+IK23 -> 1 | IN23: =IJ23+IL23 -> 1539 | IO23: =IM23*J23 -> 677.34997 | IP23: =IN23/$IN$1 -> 0.00013573482 | IQ23: =B23 -> EA-01 Pro | IR23: 0 | IS23: 0 | IT23: 0 | IU23: =IR23+IS23+IT23 -> 0 | IV23: =IU23*J23 -> 0 | IW23: 0 | IX23: =IW23*J23 -> 0 | IY23: =IU23+IW23 -> 0 | IZ23: =IV23+IX23 -> 0 | JA23: =B23 -> EA-01 Pro | JB23: =C23 -> FBA79588 | JC23: =G23 -> B0DHRQPGGM | JD23: =B23 -> EA-01 Pro | JE23: NA | JF23: 0 | JG23: 0 | JH23: 0 | JI23: 0 | JJ23: =JF23+JH23 -> 0 | JK23: =JG23+JI23 -> 0 | JL23: =JJ23*J23 -> 0 | JM23: =JK23/$JK$1 -> 0 | JN23: =B23 -> EA-01 Pro | JO23: 0 | JP23: 0 | JQ23: 0 | JR23: =JO23+JP23+JQ23 -> 0 | JS23: =JR23*AG23 -> 0 | JT23: 0 | JU23: =JT23*AG23 -> 0 | JV23: =JR23+JT23 -> 0 | JW23: =JS23+JU23 -> 0 | JX23: =B23 -> EA-01 Pro | JY23: =C23 -> FBA79588 | JZ23: =G23 -> B0DHRQPGGM | KA23: =B23 -> EA-01 Pro | KB23: NA | KC23: 0 | KD23: 0 | KE23: 0 | KF23: 0 | KG23: =KC23+KE23 -> 0 | KH23: =KD23+KF23 -> 0 | KI23: =KG23*J23 -> 0 | KJ23: =KH23/$KH$1 -> 0 | KK23: =B23 -> EA-01 Pro | KL23: 0 | KM23: 0 | KN23: 0 | KO23: =KL23+KM23+KN23 -> 0 | KP23: =KO23*BD23 -> 0 | KQ23: 0 | KR23: =KQ23*BD23 -> 0 | KS23: =KO23+KQ23 -> 0 | KT23: =KP23+KR23 -> 0 | KU23: =B23 -> EA-01 Pro | KV23: =C23 -> FBA79588 | KW23: =G23 -> B0DHRQPGGM | KX23: =B23 -> EA-01 Pro | KY23: NA | KZ23: 0 | LA23: 0 | LB23: 0 | LC23: 0 | LD23: =KZ23+LB23 -> 0 | LE23: =LA23+LC23 -> 0 | LF23: =LD23*J23 -> 0 | LG23: =LE23/$LE$1 -> 0 | LH23: =B23 -> EA-01 Pro | LI23: 0 | LJ23: 0 | LK23: 0 | LL23: =LI23+LJ23+LK23 -> 0 | LM23: =LL23*CA23 -> 0 | LN23: 0 | LO23: =LN23*CA23 -> 0 | LP23: =LL23+LN23 -> 0 | LQ23: =LM23+LO23 -> 0 | LR23: =B23 -> EA-01 Pro | LS23: =C23 -> FBA79588 | LT23: =G23 -> B0DHRQPGGM | LU23: =B23 -> EA-01 Pro | LV23: 0 | LW23: 0 | LX23: 0 | LY23: 0 | LZ23: 0 | MA23: =LW23+LY23 -> 0 | MB23: =LX23+LZ23 -> 0 | MC23: =MA23*J23 -> 0 | MD23: =MB23/$MB$1 -> 0 | ME23: =B23 -> EA-01 Pro | MF23: 0 | MG23: 0 | MH23: 0 | MI23: =MF23+MG23+MH23 -> 0 | MJ23: =MI23*CX23 -> 0 | MK23: 0 | ML23: =MK23*CX23 -> 0 | MM23: =MI23+MK23 -> 0 | MN23: =MJ23+ML23 -> 0 | MO23: =B23 -> EA-01 Pro | MP23: =C23 -> FBA79588 | MQ23: =G23 -> B0DHRQPGGM | MR23: =B23 -> EA-01 Pro | MS23: 0 | MT23: 0 | MU23: 0 | MV23: 0 | MW23: 0 | MX23: =MT23+MV23 -> 0 | MY23: =MU23+MW23 -> 0 | MZ23: =MX23*J23 -> 0 | NA23: =MY23/$MY$1 -> 0 | NB23: =B23 -> EA-01 Pro | NC23: 0 | ND23: 0 | NE23: 0 | NF23: =NC23+ND23+NE23 -> 0 | NG23: =NF23*DU23 -> #VALUE! | NH23: 0 | NI23: =NH23*DU23 -> #VALUE! | NJ23: =NF23+NH23 -> 0 | NK23: =NG23+NI23 -> #VALUE! | NL23: =B23 -> EA-01 Pro | NM23: =C23 -> FBA79588 | NN23: =G23 -> B0DHRQPGGM | NO23: =Y23 -> 0 | NP23: 0 | NQ23: 0 | NR23: 0 | NS23: 0 | NT23: 0 | NU23: =NQ23+NS23 -> 0 | NV23: =NR23+NT23 -> 0 | NW23: =NU23*J23 -> 0 | NX23: =NV23/$NV$1 -> 0 | NY23: =B23 -> EA-01 Pro | NZ23: 0 | OA23: 0 | OB23: 0 | OC23: =NZ23+OA23+OB23 -> 0 | OD23: =OC23*ER23 -> #VALUE! | OE23: 0 | OF23: =OE23*ER23 -> #VALUE! | OG23: =OC23+OE23 -> 0 | OH23: =OD23+OF23 -> #VALUE! | OI23: =B23 -> EA-01 Pro | OJ23: =C23 -> FBA79588 | OK23: =G23 -> B0DHRQPGGM | OL23: =B23 -> EA-01 Pro
A24: FBA79488 | B24: KE-01 | C24: FBA79488 | D24: Home & Kitchen | E24: Kitchen Appliances | F24: Nexlev | G24: B0DFCG2VGS | H24: Nexlev Multi-Purpose Food Kettle 1.8L | I24: 762.35055 | J24: 899.57365 | K24: 0 | L24: 0 | M24: 0 | N24: =1-L24/M24 -> #DIV/0! | O24: 0 | P24: 0 | Q24: 0 | R24: =1-P24/Q24 -> #DIV/0! | S24: 0 | T24: 0 | U24: 0 | V24: =1-T24/U24 -> #DIV/0! | W24: 0 | X24: 0 | Y24: 0 | Z24: =1-X24/Y24 -> #DIV/0! | AA24: 0 | AB24: 0 | AC24: 0 | AD24: =1-AB24/AC24 -> #DIV/0! | AE24: 0 | AF24: 0 | AG24: 0 | AH24: =1-AF24/AG24 -> #DIV/0! | AI24: 0 | AJ24: 0 | AK24: 0 | AL24: =1-AJ24/AK24 -> #DIV/0! | AM24: 0 | AN24: 0 | AO24: 0 | AP24: =1-AN24/AO24 -> #DIV/0! | AQ24: 0 | AR24: 0 | AS24: 0 | AT24: =1-AR24/AS24 -> #DIV/0! | AU24: 0 | AV24: 0 | AW24: 0 | AX24: =1-AV24/AW24 -> #DIV/0! | AY24: 0 | AZ24: 0 | BA24: 0 | BB24: =1-AZ24/BA24 -> #DIV/0! | BC24: 76 | BD24: 0 | BE24: 0 | BF24: =1-BD24/BE24 -> #DIV/0! | BG24: 1879 | BH24: 30 | BI24: 41 | BJ24: =1-BH24/BI24 -> 0.26829268 | BK24: 5679 | BL24: 86 | BM24: 146299 | BN24: =BL24*J24 -> 77363.334 | BO24: 111 | BP24: 188201 | BQ24: =1-BL24/BO24 -> 0.22522523 | BR24: =BM24/$BM$1 -> 0.011915145 | BS24: =B24 -> KE-01 | BT24: 333 | BU24: 522 | BV24: 0 | BW24: =BT24+BU24+BV24 -> 855 | BX24: =BW24*J24 -> 769135.47 | BY24: 0 | BZ24: =BY24*J24 -> 0 | CA24: =BW24+BY24 -> 855 | CB24: =BX24+BZ24 -> 769135.47 | CC24: =B24 -> KE-01 | CD24: =C24 -> FBA79488 | CE24: =G24 -> B0DFCG2VGS | CF24: =B24 -> KE-01 | CG24: 6455 | CH24: 91 | CI24: 153785.61 | CJ24: =CH24*J24 -> 81861.202 | CK24: 109 | CL24: 179066 | CM24: =1-CH24/CK24 -> 0.16513761 | CN24: =CI24/$CI$1 -> 0.013549446 | CO24: =B24 -> KE-01 | CP24: 401 | CQ24: 332 | CR24: 0 | CS24: =CP24+CQ24+CR24 -> 733 | CT24: =CS24*J24 -> 659387.48 | CU24: 0 | CV24: =CU24*J24 -> 0 | CW24: =CS24+CU24 -> 733 | CX24: =CT24+CV24 -> 659387.48 | CY24: =B24 -> KE-01 | CZ24: =C24 -> FBA79488 | DA24: =G24 -> B0DFCG2VGS | DB24: =B24 -> KE-01 | DC24: 14172 | DD24: 56 | DE24: 94274.85 | DF24: =DD24*J24 -> 50376.124 | DG24: 68 | DH24: 112915 | DI24: =1-DD24/DG24 -> 0.17647059 | DJ24: =DE24/$DE$1 -> 0.0074751774 | DK24: =B24 -> KE-01 | DL24: 391 | DM24: 240 | DN24: 0 | DO24: =DL24+DM24+DN24 -> 631 | DP24: =DO24*J24 -> 567630.97 | DQ24: 0 | DR24: =DQ24*J24 -> 0 | DS24: =DO24+DQ24 -> 631 | DT24: =DP24+DR24 -> 567630.97 | DU24: =B24 -> KE-01 | DV24: =C24 -> FBA79488 | DW24: =G24 -> B0DFCG2VGS | DX24: =B24 -> KE-01 | DY24: 14646 | DZ24: 74 | EA24: 126078.58 | EB24: =DZ24*J24 -> 66568.45 | EC24: 98 | ED24: 1,61,745.00 | EE24: =1-DZ24/EC24 -> 0.24489796 | EF24: =EA24/$EA$1 -> 0.0143489 | EG24: =B24 -> KE-01 | EH24: 402 | EI24: 163 | EJ24: 0 | EK24: =EH24+EI24+EJ24 -> 565 | EL24: =EK24*J24 -> 508259.11 | EM24: 0 | EN24: =EM24*J24 -> 0 | EO24: =EK24+EM24 -> 565 | EP24: =EL24+EN24 -> 508259.11 | EQ24: =B24 -> KE-01 | ER24: =C24 -> FBA79488 | ES24: =G24 -> B0DFCG2VGS | ET24: =B24 -> KE-01 | EU24: 8550 | EV24: 32 | EW24: 54417 | EX24: =EV24*J24 -> 28786.357 | EY24: 39 | EZ24: 66251 | FA24: =1-EV24/EY24 -> 0.17948718 | FB24: =EW24/$EW$1 -> 0.0081660544 | FC24: =B24 -> KE-01 | FD24: 364 | FE24: 93 | FF24: 0 | FG24: =FD24+FE24+FF24 -> 457 | FH24: =FG24*J24 -> 411105.16 | FI24: 0 | FJ24: =FI24*J24 -> 0 | FK24: =FG24+FI24 -> 457 | FL24: =FH24+FJ24 -> 411105.16 | FM24: =B24 -> KE-01 | FN24: =C24 -> FBA79488 | FO24: =G24 -> B0DFCG2VGS | FP24: =B24 -> KE-01 | FQ24: 6893 | FR24: 37 | FS24: 62691 | FT24: 0 | FU24: 0 | FV24: =FR24+FT24 -> 37 | FW24: =FS24+FU24 -> 62691 | FX24: =FV24*J24 -> 33284.225 | FY24: =FW24/$FW$1 -> 0.0066926825 | FZ24: =B24 -> KE-01 | GA24: 0 | GB24: 1093 | GC24: 0 | GD24: =GA24+GB24+GC24 -> 1093 | GE24: =GD24*J24 -> 983234 | GF24: 0 | GG24: =GF24*J24 -> 0 | GH24: =GD24+GF24 -> 1093 | GI24: =GE24+GG24 -> 983234 | GJ24: =B24 -> KE-01 | GK24: =C24 -> FBA79488 | GL24: =G24 -> B0DFCG2VGS | GM24: =B24 -> KE-01 | GN24: 12067 | GO24: 50 | GP24: 84127.58 | GQ24: 0 | GR24: 0 | GS24: =GO24+GQ24 -> 50 | GT24: =GP24+GR24 -> 84127.58 | GU24: =GS24*J24 -> 44978.682 | GV24: =GT24/$GT$1 -> 0.0088888726 | GW24: =B24 -> KE-01 | GX24: 189 | GY24: 1048 | GZ24: 0 | HA24: =GX24+GY24+GZ24 -> 1237 | HB24: =HA24*J24 -> 1112772.6 | HC24: 0 | HD24: =HC24*J24 -> 0 | HE24: =HA24+HC24 -> 1237 | HF24: =HB24+HD24 -> 1112772.6 | HG24: =B24 -> KE-01 | HH24: =C24 -> FBA79488 | HI24: =G24 -> B0DFCG2VGS | HJ24: =B24 -> KE-01 | HK24: 7785 | HL24: 30 | HM24: 51056 | HN24: 0 | HO24: 0 | HP24: =HL24+HN24 -> 30 | HQ24: =HM24+HO24 -> 51056 | HR24: =HP24*J24 -> 26987.209 | HS24: =HQ24/$HQ$1 -> 0.0046620116 | HT24: =B24 -> KE-01 | HU24: 3 | HV24: 1026 | HW24: 0 | HX24: =HU24+HV24+HW24 -> 1029 | HY24: =HX24*J24 -> 925661.28 | HZ24: 0 | IA24: =HZ24*J24 -> 0 | IB24: =HX24+HZ24 -> 1029 | IC24: =HY24+IA24 -> 925661.28 | ID24: =B24 -> KE-01 | IE24: =C24 -> FBA79488 | IF24: =G24 -> B0DFCG2VGS | IG24: =B24 -> KE-01 | IH24: 2805 | II24: 19 | IJ24: 32051.01 | IK24: 0 | IL24: 0 | IM24: =II24+IK24 -> 19 | IN24: =IJ24+IL24 -> 32051.01 | IO24: =IM24*J24 -> 17091.899 | IP24: =IN24/$IN$1 -> 0.0028267954 | IQ24: =B24 -> KE-01 | IR24: 221 | IS24: 1004 | IT24: 0 | IU24: =IR24+IS24+IT24 -> 1225 | IV24: =IU24*J24 -> 1101977.7 | IW24: 0 | IX24: =IW24*J24 -> 0 | IY24: =IU24+IW24 -> 1225 | IZ24: =IV24+IX24 -> 1101977.7 | JA24: =B24 -> KE-01 | JB24: =C24 -> FBA79488 | JC24: =G24 -> B0DFCG2VGS | JD24: =B24 -> KE-01 | JE24: 9110 | JF24: 63 | JG24: 105290.2 | JH24: 0 | JI24: 0 | JJ24: =JF24+JH24 -> 63 | JK24: =JG24+JI24 -> 105290.2 | JL24: =JJ24*J24 -> 56673.14 | JM24: =JK24/$JK$1 -> 0.011644852 | JN24: =B24 -> KE-01 | JO24: 221 | JP24: 1004 | JQ24: 0 | JR24: =JO24+JP24+JQ24 -> 1225 | JS24: =JR24*AG24 -> 0 | JT24: 0 | JU24: =JT24*AG24 -> 0 | JV24: =JR24+JT24 -> 1225 | JW24: =JS24+JU24 -> 0 | JX24: =B24 -> KE-01 | JY24: =C24 -> FBA79488 | JZ24: =G24 -> B0DFCG2VGS | KA24: =B24 -> KE-01 | KB24: 5676 | KC24: 65 | KD24: 108861.7 | KE24: 0 | KF24: 0 | KG24: =KC24+KE24 -> 65 | KH24: =KD24+KF24 -> 108861.7 | KI24: =KG24*J24 -> 58472.287 | KJ24: =KH24/$KH$1 -> 0.009225335 | KK24: =B24 -> KE-01 | KL24: 221 | KM24: 1004 | KN24: 0 | KO24: =KL24+KM24+KN24 -> 1225 | KP24: =KO24*BD24 -> 0 | KQ24: 0 | KR24: =KQ24*BD24 -> 0 | KS24: =KO24+KQ24 -> 1225 | KT24: =KP24+KR24 -> 0 | KU24: =B24 -> KE-01 | KV24: =C24 -> FBA79488 | KW24: =G24 -> B0DFCG2VGS | KX24: =B24 -> KE-01 | KY24: 4669 | KZ24: 57 | LA24: 91850.02 | LB24: 0 | LC24: 0 | LD24: =KZ24+LB24 -> 57 | LE24: =LA24+LC24 -> 91850.02 | LF24: =LD24*J24 -> 51275.698 | LG24: =LE24/$LE$1 -> 0.0068304829 | LH24: =B24 -> KE-01 | LI24: 221 | LJ24: 1004 | LK24: 0 | LL24: =LI24+LJ24+LK24 -> 1225 | LM24: =LL24*CA24 -> 1047375 | LN24: 0 | LO24: =LN24*CA24 -> 0 | LP24: =LL24+LN24 -> 1225 | LQ24: =LM24+LO24 -> 1047375 | LR24: =B24 -> KE-01 | LS24: =C24 -> FBA79488 | LT24: =G24 -> B0DFCG2VGS | LU24: =B24 -> KE-01 | LV24: 15659 | LW24: 82 | LX24: 138836.18 | LY24: 0 | LZ24: 0 | MA24: =LW24+LY24 -> 82 | MB24: =LX24+LZ24 -> 138836.18 | MC24: =MA24*J24 -> 73765.039 | MD24: =MB24/$MB$1 -> 0.014635266 | ME24: =B24 -> KE-01 | MF24: 221 | MG24: 1004 | MH24: 0 | MI24: =MF24+MG24+MH24 -> 1225 | MJ24: =MI24*CX24 -> 8.0774967e+08 | MK24: 0 | ML24: =MK24*CX24 -> 0 | MM24: =MI24+MK24 -> 1225 | MN24: =MJ24+ML24 -> 8.0774967e+08 | MO24: =B24 -> KE-01 | MP24: =C24 -> FBA79488 | MQ24: =G24 -> B0DFCG2VGS | MR24: =B24 -> KE-01 | MS24: 14942 | MT24: 71 | MU24: 106178 | MV24: 0 | MW24: 0 | MX24: =MT24+MV24 -> 71 | MY24: =MU24+MW24 -> 106178 | MZ24: =MX24*J24 -> 63869.729 | NA24: =MY24/$MY$1 -> 0.0084574608 | NB24: =B24 -> KE-01 | NC24: 221 | ND24: 1004 | NE24: 0 | NF24: =NC24+ND24+NE24 -> 1225 | NG24: =NF24*DU24 -> #VALUE! | NH24: 0 | NI24: =NH24*DU24 -> #VALUE! | NJ24: =NF24+NH24 -> 1225 | NK24: =NG24+NI24 -> #VALUE! | NL24: =B24 -> KE-01 | NM24: =C24 -> FBA79488 | NN24: =G24 -> B0DFCG2VGS | NO24: =Y24 -> 0 | NP24: 10259 | NQ24: 74 | NR24: 118691 | NS24: 0 | NT24: 0 | NU24: =NQ24+NS24 -> 74 | NV24: =NR24+NT24 -> 118691 | NW24: =NU24*J24 -> 66568.45 | NX24: =NV24/$NV$1 -> 0.012329675 | NY24: =B24 -> KE-01 | NZ24: 221 | OA24: 1004 | OB24: 0 | OC24: =NZ24+OA24+OB24 -> 1225 | OD24: =OC24*ER24 -> #VALUE! | OE24: 0 | OF24: =OE24*ER24 -> #VALUE! | OG24: =OC24+OE24 -> 1225 | OH24: =OD24+OF24 -> #VALUE! | OI24: =B24 -> KE-01 | OJ24: =C24 -> FBA79488 | OK24: =G24 -> B0DFCG2VGS | OL24: =B24 -> KE-01
A25: FBA79463 | B25: VC-02 | C25: FBA79463 | D25: Home & Kitchen | E25: Cleaning & Vacumming | F25: Nexlev | G25: B0DCK56Q85 | H25: Nexlev Portable vacuum cleaner - Duster Pro | I25: 1131.4334 | J25: 1335.0914 | K25: 0 | L25: 0 | M25: 0 | N25: =1-L25/M25 -> #DIV/0! | O25: 0 | P25: 0 | Q25: 0 | R25: =1-P25/Q25 -> #DIV/0! | S25: 0 | T25: 0 | U25: 0 | V25: =1-T25/U25 -> #DIV/0! | W25: 0 | X25: 0 | Y25: 0 | Z25: =1-X25/Y25 -> #DIV/0! | AA25: 0 | AB25: 0 | AC25: 0 | AD25: =1-AB25/AC25 -> #DIV/0! | AE25: 0 | AF25: 0 | AG25: 0 | AH25: =1-AF25/AG25 -> #DIV/0! | AI25: 0 | AJ25: 0 | AK25: 0 | AL25: =1-AJ25/AK25 -> #DIV/0! | AM25: 0 | AN25: 0 | AO25: 0 | AP25: =1-AN25/AO25 -> #DIV/0! | AQ25: 0 | AR25: 0 | AS25: 0 | AT25: =1-AR25/AS25 -> #DIV/0! | AU25: 0 | AV25: 0 | AW25: 0 | AX25: =1-AV25/AW25 -> #DIV/0! | AY25: 0 | AZ25: 0 | BA25: 0 | BB25: =1-AZ25/BA25 -> #DIV/0! | BC25: 1149 | BD25: 0 | BE25: 3 | BF25: =1-BD25/BE25 -> 1 | BG25: 12123 | BH25: 52 | BI25: 63 | BJ25: =1-BH25/BI25 -> 0.17460317 | BK25: 8133 | BL25: 57 | BM25: 130073 | BN25: =BL25*J25 -> 76100.208 | BO25: 65 | BP25: 148435 | BQ25: =1-BL25/BO25 -> 0.12307692 | BR25: =BM25/$BM$1 -> 0.010593638 | BS25: =B25 -> VC-02 | BT25: 276 | BU25: 583 | BV25: 0 | BW25: =BT25+BU25+BV25 -> 859 | BX25: =BW25*J25 -> 1146843.5 | BY25: 0 | BZ25: =BY25*J25 -> 0 | CA25: =BW25+BY25 -> 859 | CB25: =BX25+BZ25 -> 1146843.5 | CC25: =B25 -> VC-02 | CD25: =C25 -> FBA79463 | CE25: =G25 -> B0DCK56Q85 | CF25: =B25 -> VC-02 | CG25: 15206 | CH25: 83 | CI25: 190002.11 | CJ25: =CH25*J25 -> 110812.58 | CK25: 97 | CL25: 220242 | CM25: =1-CH25/CK25 -> 0.1443299 | CN25: =CI25/$CI$1 -> 0.01674034 | CO25: =B25 -> VC-02 | CP25: 390 | CQ25: 379 | CR25: 0 | CS25: =CP25+CQ25+CR25 -> 769 | CT25: =CS25*J25 -> 1026685.3 | CU25: 0 | CV25: =CU25*J25 -> 0 | CW25: =CS25+CU25 -> 769 | CX25: =CT25+CV25 -> 1026685.3 | CY25: =B25 -> VC-02 | CZ25: =C25 -> FBA79463 | DA25: =G25 -> B0DCK56Q85 | DB25: =B25 -> VC-02 | DC25: 14622 | DD25: 85 | DE25: 193842.22 | DF25: =DD25*J25 -> 113482.77 | DG25: 93 | DH25: 207813 | DI25: =1-DD25/DG25 -> 0.086021505 | DJ25: =DE25/$DE$1 -> 0.015370006 | DK25: =B25 -> VC-02 | DL25: 473 | DM25: 184 | DN25: 0 | DO25: =DL25+DM25+DN25 -> 657 | DP25: =DO25*J25 -> 877155.03 | DQ25: 0 | DR25: =DQ25*J25 -> 0 | DS25: =DO25+DQ25 -> 657 | DT25: =DP25+DR25 -> 877155.03 | DU25: =B25 -> VC-02 | DV25: =C25 -> FBA79463 | DW25: =G25 -> B0DCK56Q85 | DX25: =B25 -> VC-02 | DY25: 8193 | DZ25: 31 | EA25: 71269 | EB25: =DZ25*J25 -> 41387.833 | EC25: 31 | ED25: 71269 | EE25: =1-DZ25/EC25 -> 0 | EF25: =EA25/$EA$1 -> 0.0081110666 | EG25: =B25 -> VC-02 | EH25: 445 | EI25: 176 | EJ25: 0 | EK25: =EH25+EI25+EJ25 -> 621 | EL25: =EK25*J25 -> 829091.74 | EM25: 0 | EN25: =EM25*J25 -> 0 | EO25: =EK25+EM25 -> 621 | EP25: =EL25+EN25 -> 829091.74 | EQ25: =B25 -> VC-02 | ER25: =C25 -> FBA79463 | ES25: =G25 -> B0DCK56Q85 | ET25: =B25 -> VC-02 | EU25: 11824 | EV25: 37 | EW25: 85338 | EX25: =EV25*J25 -> 49398.381 | EY25: 40 | EZ25: 92198 | FA25: =1-EV25/EY25 -> 0.075 | FB25: =EW25/$EW$1 -> 0.012806196 | FC25: =B25 -> VC-02 | FD25: 361 | FE25: 117 | FF25: 0 | FG25: =FD25+FE25+FF25 -> 478 | FH25: =FG25*J25 -> 638173.68 | FI25: 0 | FJ25: =FI25*J25 -> 0 | FK25: =FG25+FI25 -> 478 | FL25: =FH25+FJ25 -> 638173.68 | FM25: =B25 -> VC-02 | FN25: =C25 -> FBA79463 | FO25: =G25 -> B0DCK56Q85 | FP25: =B25 -> VC-02 | FQ25: 8761 | FR25: 39 | FS25: 89481 | FT25: 0 | FU25: 0 | FV25: =FR25+FT25 -> 39 | FW25: =FS25+FU25 -> 89481 | FX25: =FV25*J25 -> 52068.564 | FY25: =FW25/$FW$1 -> 0.0095526938 | FZ25: =B25 -> VC-02 | GA25: 0 | GB25: 108 | GC25: 0 | GD25: =GA25+GB25+GC25 -> 108 | GE25: =GD25*J25 -> 144189.87 | GF25: 0 | GG25: =GF25*J25 -> 0 | GH25: =GD25+GF25 -> 108 | GI25: =GE25+GG25 -> 144189.87 | GJ25: =B25 -> VC-02 | GK25: =C25 -> FBA79463 | GL25: =G25 -> B0DCK56Q85 | GM25: =B25 -> VC-02 | GN25: 8854 | GO25: 16 | GP25: 36907 | GQ25: 0 | GR25: 0 | GS25: =GO25+GQ25 -> 16 | GT25: =GP25+GR25 -> 36907 | GU25: =GS25*J25 -> 21361.462 | GV25: =GT25/$GT$1 -> 0.0038995728 | GW25: =B25 -> VC-02 | GX25: 297 | GY25: 113 | GZ25: 0 | HA25: =GX25+GY25+GZ25 -> 410 | HB25: =HA25*J25 -> 547387.46 | HC25: 0 | HD25: =HC25*J25 -> 0 | HE25: =HA25+HC25 -> 410 | HF25: =HB25+HD25 -> 547387.46 | HG25: =B25 -> VC-02 | HH25: =C25 -> FBA79463 | HI25: =G25 -> B0DCK56Q85 | HJ25: =B25 -> VC-02 | HK25: 2441 | HL25: 31 | HM25: 77261 | HN25: 0 | HO25: 0 | HP25: =HL25+HN25 -> 31 | HQ25: =HM25+HO25 -> 77261 | HR25: =HP25*J25 -> 41387.833 | HS25: =HQ25/$HQ$1 -> 0.0070548354 | HT25: =B25 -> VC-02 | HU25: 90 | HV25: 39 | HW25: 0 | HX25: =HU25+HV25+HW25 -> 129 | HY25: =HX25*J25 -> 172226.79 | HZ25: 0 | IA25: =HZ25*J25 -> 0 | IB25: =HX25+HZ25 -> 129 | IC25: =HY25+IA25 -> 172226.79 | ID25: =B25 -> VC-02 | IE25: =C25 -> FBA79463 | IF25: =G25 -> B0DCK56Q85 | IG25: =B25 -> VC-02 | IH25: 3027 | II25: 45 | IJ25: 110233.18 | IK25: 0 | IL25: 0 | IM25: =II25+IK25 -> 45 | IN25: =IJ25+IL25 -> 110233.18 | IO25: =IM25*J25 -> 60079.112 | IP25: =IN25/$IN$1 -> 0.0097222099 | IQ25: =B25 -> VC-02 | IR25: 205 | IS25: 105 | IT25: 0 | IU25: =IR25+IS25+IT25 -> 310 | IV25: =IU25*J25 -> 413878.33 | IW25: 0 | IX25: =IW25*J25 -> 0 | IY25: =IU25+IW25 -> 310 | IZ25: =IV25+IX25 -> 413878.33 | JA25: =B25 -> VC-02 | JB25: =C25 -> FBA79463 | JC25: =G25 -> B0DCK56Q85 | JD25: =B25 -> VC-02 | JE25: 2894 | JF25: 39 | JG25: 95353.88 | JH25: 0 | JI25: 0 | JJ25: =JF25+JH25 -> 39 | JK25: =JG25+JI25 -> 95353.88 | JL25: =JJ25*J25 -> 52068.564 | JM25: =JK25/$JK$1 -> 0.010545918 | JN25: =B25 -> VC-02 | JO25: 205 | JP25: 105 | JQ25: 0 | JR25: =JO25+JP25+JQ25 -> 310 | JS25: =JR25*AG25 -> 0 | JT25: 0 | JU25: =JT25*AG25 -> 0 | JV25: =JR25+JT25 -> 310 | JW25: =JS25+JU25 -> 0 | JX25: =B25 -> VC-02 | JY25: =C25 -> FBA79463 | JZ25: =G25 -> B0DCK56Q85 | KA25: =B25 -> VC-02 | KB25: 2598 | KC25: 29 | KD25: 69869.92 | KE25: 0 | KF25: 0 | KG25: =KC25+KE25 -> 29 | KH25: =KD25+KF25 -> 69869.92 | KI25: =KG25*J25 -> 38717.65 | KJ25: =KH25/$KH$1 -> 0.0059210302 | KK25: =B25 -> VC-02 | KL25: 205 | KM25: 105 | KN25: 0 | KO25: =KL25+KM25+KN25 -> 310 | KP25: =KO25*BD25 -> 0 | KQ25: 0 | KR25: =KQ25*BD25 -> 0 | KS25: =KO25+KQ25 -> 310 | KT25: =KP25+KR25 -> 0 | KU25: =B25 -> VC-02 | KV25: =C25 -> FBA79463 | KW25: =G25 -> B0DCK56Q85 | KX25: =B25 -> VC-02 | KY25: 2957 | KZ25: 48 | LA25: 112081.1 | LB25: 0 | LC25: 0 | LD25: =KZ25+LB25 -> 48 | LE25: =LA25+LC25 -> 112081.1 | LF25: =LD25*J25 -> 64084.386 | LG25: =LE25/$LE$1 -> 0.0083349795 | LH25: =B25 -> VC-02 | LI25: 205 | LJ25: 105 | LK25: 0 | LL25: =LI25+LJ25+LK25 -> 310 | LM25: =LL25*CA25 -> 266290 | LN25: 0 | LO25: =LN25*CA25 -> 0 | LP25: =LL25+LN25 -> 310 | LQ25: =LM25+LO25 -> 266290 | LR25: =B25 -> VC-02 | LS25: =C25 -> FBA79463 | LT25: =G25 -> B0DCK56Q85 | LU25: =B25 -> VC-02 | LV25: 6618 | LW25: 16 | LX25: 41349 | LY25: 0 | LZ25: 0 | MA25: =LW25+LY25 -> 16 | MB25: =LX25+LZ25 -> 41349 | MC25: =MA25*J25 -> 21361.462 | MD25: =MB25/$MB$1 -> 0.0043587601 | ME25: =B25 -> VC-02 | MF25: 205 | MG25: 105 | MH25: 0 | MI25: =MF25+MG25+MH25 -> 310 | MJ25: =MI25*CX25 -> 3.1827243e+08 | MK25: 0 | ML25: =MK25*CX25 -> 0 | MM25: =MI25+MK25 -> 310 | MN25: =MJ25+ML25 -> 3.1827243e+08 | MO25: =B25 -> VC-02 | MP25: =C25 -> FBA79463 | MQ25: =G25 -> B0DCK56Q85 | MR25: =B25 -> VC-02 | MS25: 1666 | MT25: 29 | MU25: 65854 | MV25: 0 | MW25: 0 | MX25: =MT25+MV25 -> 29 | MY25: =MU25+MW25 -> 65854 | MZ25: =MX25*J25 -> 38717.65 | NA25: =MY25/$MY$1 -> 0.0052455087 | NB25: =B25 -> VC-02 | NC25: 205 | ND25: 105 | NE25: 0 | NF25: =NC25+ND25+NE25 -> 310 | NG25: =NF25*DU25 -> #VALUE! | NH25: 0 | NI25: =NH25*DU25 -> #VALUE! | NJ25: =NF25+NH25 -> 310 | NK25: =NG25+NI25 -> #VALUE! | NL25: =B25 -> VC-02 | NM25: =C25 -> FBA79463 | NN25: =G25 -> B0DCK56Q85 | NO25: =Y25 -> 0 | NP25: 61 | NQ25: 2 | NR25: 5198 | NS25: 0 | NT25: 0 | NU25: =NQ25+NS25 -> 2 | NV25: =NR25+NT25 -> 5198 | NW25: =NU25*J25 -> 2670.1827 | NX25: =NV25/$NV$1 -> 0.00053997062 | NY25: =B25 -> VC-02 | NZ25: 205 | OA25: 105 | OB25: 0 | OC25: =NZ25+OA25+OB25 -> 310 | OD25: =OC25*ER25 -> #VALUE! | OE25: 0 | OF25: =OE25*ER25 -> #VALUE! | OG25: =OC25+OE25 -> 310 | OH25: =OD25+OF25 -> #VALUE! | OI25: =B25 -> VC-02 | OJ25: =C25 -> FBA79463 | OK25: =G25 -> B0DCK56Q85 | OL25: =B25 -> VC-02
