Workbook

Sheet Master
A1: SKU | B1: ASIN | C1: Model | D1: Category - L1 | E1: Category - L2 | F1: Fee Category | G1: Product Name | H1: HSN | I1: Latest FOB | J1: Freight+Clearance | K1: L (cm) | L1: B (cm) | M1: H (cm) | N1: CBM per unit | O1: Import Duty % | P1: Duty and Surcharge | Q1: DP | R1: NLC | S1: Referral Fee % | T1: Fixed Closing Fee | U1: Fulfillment Fees | V1: AMS % | W1: Coupon % | X1: Returns Loss % | Y1: SMM | Z1: GST Slab | AA1: GST in SP | AB1: Business overhead expenses | AC1: Cost of finance | AD1: Additional Cost | AE1: BAU Deal SP | AF1: MRP | AG1: Gross Margin | AH1: Gross Margin % | AI1: BAU SP/MOP(MP) | AJ1: Deals | AK1: Art deals | AL1: MOP(B2B) | AM1: MOP(D2C)
A2: FBA75673 | B2: B0B4DPX2J2 | C2: AM-C1 | D2: Microphone | E2: Condenser Mic with Boom Arm | F2: 0.11 | G2: AM-C1 | H2: 85181000 | I2: 11 | J2: ='Edit Parameters'!$B$2/('Edit Parameters'!$B$3/N2) | K2: 42.4 | L2: 20.8 | M2: 8.8 | N2: =(K2*L2*M2)/1000000 | O2: 15 | P2: =(I2+J2)*(O2%+(O2%*10%)) | Q2: =(I2+J2+P2)*'Edit Parameters'!B$1 | R2: =Q2*1.18 | S2: 11 | T2: 51 | U2: 114 | V2: 10 | W2: 2 | X2: 5 | Y2: 0 | Z2: 18 | AA2: =AE2-(AE2/1.18) | AB2: =R2*0.05 | AC2: =R2*0.03 | AD2: 0 | AE2: 2699 | AF2: 4999 | AI2: 2699
A3: FBA76864 | B3: B0BPLZ5CGV | C3: AI-04 Red | D3: Audio Interface | E3: 4 Channel Audio Interface | F3: 0.11 | G3: AI-04 Red | H3: 85437029 | I3: 18 | J3: ='Edit Parameters'!$B$2/('Edit Parameters'!$B$3/N3) | K3: 26.4 | L3: 14 | M3: 7 | N3: =(K3*L3*M3)/1000000 | O3: 7.5 | P3: =(I3+J3)*(O3%+(O3%*10%)) | Q3: =(I3+J3+P3)*'Edit Parameters'!B$1 | R3: =Q3*1.18 | S3: 11 | T3: 51 | U3: 76 | V3: 10 | W3: 2 | X3: 5 | Y3: 0 | Z3: 18 | AA3: =AE3-(AE3/1.18) | AB3: =R3*0.05 | AC3: =R3*0.03 | AD3: 0 | AE3: 4398 | AF3: 9999 | AI3: 4599
A4: FBA79482 | B4: B0DXFPM4N2 | C4: AM-S1 | D4: Speaker | E4: Studio Monitor Speaker | F4: 0.11 | G4: AM-S1 | H4: 85182290 | I4: 32.85 | J4: ='Edit Parameters'!$B$2/('Edit Parameters'!$B$3/N4) | K4: 38.5 | L4: 29.2 | M4: 21.3 | N4: =(K4*L4*M4)/1000000 | O4: 20 | P4: =(I4+J4)*(O4%+(O4%*10%)) | Q4: =(I4+J4+P4)*'Edit Parameters'!B$1 | R4: =Q4*1.18 | S4: 11 | T4: 51 | U4: 213 | V4: 10 | W4: 2 | X4: 5 | Y4: 0 | Z4: 18 | AA4: =AE4-(AE4/1.18) | AB4: =R4*0.05 | AC4: =R4*0.03 | AD4: 0 | AE4: 7999 | AF4: 12999 | AI4: 8799
A5: FBA79103 | B5: B0CM6NTWBP | C5: AI-10 | D5: Audio Interface | E5: Audio Interface | F5: 0.11 | G5: AI-10 | H5: 85437029 | I5: 11.5 | J5: ='Edit Parameters'!$B$2/('Edit Parameters'!$B$3/N5) | K5: 25.3 | L5: 15 | M5: 5.7 | N5: =(K5*L5*M5)/1000000 | O5: 7.5 | P5: =(I5+J5)*(O5%+(O5%*10%)) | Q5: =(I5+J5+P5)*'Edit Parameters'!B$1 | R5: =Q5*1.18 | S5: 11 | T5: 51 | U5: 76 | V5: 10 | W5: 2 | X5: 5 | Y5: 0 | Z5: 18 | AA5: =AE5-(AE5/1.18) | AB5: =R5*0.05 | AC5: =R5*0.03 | AD5: 0 | AE5: 2749 | AF5: 6999 | AI5: 3249
A6: FBA79816 | B6: B0FPR962YS | C6: AM-W22 | D6: Microphone | E6: Wireless Lapel Microphone | F6: 0.11 | G6: AM-W22 | H6: 85181000 | I6: 12.88 | J6: ='Edit Parameters'!$B$2/('Edit Parameters'!$B$3/N6) | K6: 11.7 | L6: 8.2 | M6: 6.8 | N6: =(K6*L6*M6)/1000000 | O6: 15 | P6: =(I6+J6)*(O6%+(O6%*10%)) | Q6: =(I6+J6+P6)*'Edit Parameters'!B$1 | R6: =Q6*1.18 | S6: 11 | T6: 51 | U6: 59 | V6: 10 | W6: 2 | X6: 5 | Y6: 0 | Z6: 18 | AA6: =AE6-(AE6/1.18) | AB6: =R6*0.05 | AC6: =R6*0.03 | AD6: 0 | AE6: 2999 | AF6: 6499 | AI6: 3599
A7: FBA79005 | B7: B0CKHVHVQ1 | C7: AM-W45 | D7: Microphone | E7: Wireless Conference Microphone | F7: 0.11 | G7: AM-W45 | H7: 85181000 | I7: 21.7 | J7: ='Edit Parameters'!$B$2/('Edit Parameters'!$B$3/N7) | K7: 18 | L7: 16.7 | M7: 5.7 | N7: =(K7*L7*M7)/1000000 | O7: 15 | P7: =(I7+J7)*(O7%+(O7%*10%)) | Q7: =(I7+J7+P7)*'Edit Parameters'!B$1 | R7: =Q7*1.18 | S7: 11 | T7: 51 | U7: 143.94915 | V7: 10 | W7: 2 | X7: 5 | Y7: 0 | Z7: 18 | AA7: =AE7-(AE7/1.18) | AB7: =R7*0.05 | AC7: =R7*0.03 | AD7: 0 | AE7: 4990 | AF7: 9999 | AI7: 4999
A8: FBA79380 | B8: B0D3M1B4Z8 | C8: AM-C46 | D8: Microphone | E8: RGB Condenser Mic with Boom Arm | F8: 0.11 | G8: AM-C46 | H8: 85181000 | I8: 15.5 | J8: ='Edit Parameters'!$B$2/('Edit Parameters'!$B$3/N8) | K8: 43.6 | L8: 17 | M8: 10.4 | N8: =(K8*L8*M8)/1000000 | O8: 15 | P8: =(I8+J8)*(O8%+(O8%*10%)) | Q8: =(I8+J8+P8)*'Edit Parameters'!B$1 | R8: =Q8*1.18 | S8: 11 | T8: 51 | U8: 114 | V8: 10 | W8: 2 | X8: 5 | Y8: 0 | Z8: 18 | AA8: =AE8-(AE8/1.18) | AB8: =R8*0.05 | AC8: =R8*0.03 | AD8: 0 | AE8: 3599 | AF8: 7999 | AI8: 3549
A9: FBA78975 | B9: B0CF5TCQKL | C9: AA-21 | D9: Speaker Accessories | E9: Speaker Stand | F9: 0.11 | G9: AA-21 | H9: 85189000 | I9: 12.8 | J9: ='Edit Parameters'!$B$2/('Edit Parameters'!$B$3/N9) | K9: 29.5 | L9: 27.3 | M9: 10.5 | N9: =(K9*L9*M9)/1000000 | O9: 15 | P9: =(I9+J9)*(O9%+(O9%*10%)) | Q9: =(I9+J9+P9)*'Edit Parameters'!B$1 | R9: =Q9*1.18 | S9: 11 | T9: 51 | U9: 214 | V9: 10 | W9: 2 | X9: 5 | Y9: 0 | Z9: 18 | AA9: =AE9-(AE9/1.18) | AB9: =R9*0.05 | AC9: =R9*0.03 | AD9: 0 | AE9: 3799 | AF9: 7399 | AI9: 3699
A10: FBA79815 | B10: B0FPR7VFCH | C10: AM-W19 | D10: Microphone | E10: Wireless Lapel Microphone | F10: 0.11 | G10: AM-W19 | H10: 85181000 | I10: 8.89 | J10: ='Edit Parameters'!$B$2/('Edit Parameters'!$B$3/N10) | K10: 12.1 | L10: 8.2 | M10: 3.4 | N10: =(K10*L10*M10)/1000000 | O10: 15 | P10: =(I10+J10)*(O10%+(O10%*10%)) | Q10: =(I10+J10+P10)*'Edit Parameters'!B$1 | R10: =Q10*1.18 | S10: 11 | T10: 51 | U10: 59 | V10: 10 | W10: 2 | X10: 5 | Y10: 0 | Z10: 18 | AA10: =AE10-(AE10/1.18) | AB10: =R10*0.05 | AC10: =R10*0.03 | AD10: 0 | AE10: 2199 | AF10: 3999 | AI10: 1999
A11: FBA79379 | B11: B0D3LZWTHV | C11: AM-C45 | D11: Microphone | E11: RGB Dynamic Microphone | F11: 0.11 | G11: AM-C45 | H11: 85181000 | I11: 15.5 | J11: ='Edit Parameters'!$B$2/('Edit Parameters'!$B$3/N11) | K11: 24.7 | L11: 17.5 | M11: 7.9 | N11: =(K11*L11*M11)/1000000 | O11: 15 | P11: =(I11+J11)*(O11%+(O11%*10%)) | Q11: =(I11+J11+P11)*'Edit Parameters'!B$1 | R11: =Q11*1.18 | S11: 11 | T11: 51 | U11: 76 | V11: 10 | W11: 2 | X11: 5 | Y11: 0 | Z11: 18 | AA11: =AE11-(AE11/1.18) | AB11: =R11*0.05 | AC11: =R11*0.03 | AD11: 0 | AE11: 3499 | AF11: 7499 | AI11: 3499
A12: FBA79011 | B12: B0CH4RNWJX | C12: AM-C43 | D12: Microphone | E12: XLR Condenser Microphone Kit - Boomarm | F12: 0.11 | G12: AM-C43 | H12: 85181000 | I12: 10 | J12: ='Edit Parameters'!$B$2/('Edit Parameters'!$B$3/N12) | K12: 42.5 | L12: 20.7 | M12: 7.3 | N12: =(K12*L12*M12)/1000000 | O12: 15 | P12: =(I12+J12)*(O12%+(O12%*10%)) | Q12: =(I12+J12+P12)*'Edit Parameters'!B$1 | R12: =Q12*1.18 | S12: 11 | T12: 51 | U12: 114 | V12: 10 | W12: 2 | X12: 5 | Y12: 0 | Z12: 18 | AA12: =AE12-(AE12/1.18) | AB12: =R12*0.05 | AC12: =R12*0.03 | AD12: 0 | AE12: 2499 | AF12: 5999 | AI12: 2499
A13: FBA79446 | B13: B0DFMMTWLY | C13: AM-W33 | D13: Microphone | E13: Wireless UHF Microphone | F13: 0.11 | G13: AM-W33 | H13: 85181000 | I13: 9.16 | J13: ='Edit Parameters'!$B$2/('Edit Parameters'!$B$3/N13) | K13: 30.2 | L13: 12.8 | M13: 6.3 | N13: =(K13*L13*M13)/1000000 | O13: 15 | P13: =(I13+J13)*(O13%+(O13%*10%)) | Q13: =(I13+J13+P13)*'Edit Parameters'!B$1 | R13: =Q13*1.18 | S13: 11 | T13: 51 | U13: 76 | V13: 10 | W13: 2 | X13: 5 | Y13: 0 | Z13: 18 | AA13: =AE13-(AE13/1.18) | AB13: =R13*0.05 | AC13: =R13*0.03 | AD13: 0 | AE13: 1799 | AF13: 3299 | AI13: 1999
... A36: FBA79838 | B36: B0FQBX8J17 | C36: AH-40 SL | D36: Headphone | E36: DJ Headphone | F36: 0.11 | G36: AH-40 SL | H36: 85183020 | I36: 3.5 | J36: ='Edit Parameters'!$B$2/('Edit Parameters'!$B$3/N36) | K36: 18.9 | L36: 16.2 | M36: 8.9 | N36: =(K36*L36*M36)/1000000 | O36: 20 | P36: =(I36+J36)*(O36%+(O36%*10%)) | Q36: =(I36+J36+P36)*'Edit Parameters'!B$1 | R36: =Q36*1.18 | S36: 11 | T36: 51 | U36: 144 | V36: 10 | W36: 2 | X36: 5 | Y36: 0 | Z36: 18 | AA36: =AE36-(AE36/1.18) | AB36: =R36*0.05 | AC36: =R36*0.03 | AD36: 0 | AE36: 1199 | AF36: 1999 | AI36: 1299
A37: FBA79844 | B37: B0FN7DYB2M | C37: PB-08 (AM-C1 + AI-04) | D37: Bundles | E37: PB-08 | F37: 0.11 | G37: PB-08 (AM-C1 + AI-04) | H37: 85181000 | I37: 29 | J37: ='Edit Parameters'!$B$2/('Edit Parameters'!$B$3/N37) | K37: 43.4 | L37: 27.4 | M37: 18.5 | N37: =(K37*L37*M37)/1000000 | O37: 15 | P37: =(I37+J37)*(O37%+(O37%*10%)) | Q37: =(I37+J37+P37)*'Edit Parameters'!B$1 | R37: =Q37*1.18 | S37: 11 | T37: 51 | U37: 214 | V37: 10 | W37: 2 | X37: 5 | Y37: 0 | Z37: 18 | AA37: =AE37-(AE37/1.18) | AB37: =R37*0.05 | AC37: =R37*0.03 | AD37: 0 | AE37: 6999 | AF37: ₹ 11,999.00
A38: FBA79694 | B38: B0DT6T6N6B | C38: AA-26 | D38: Microphone Accessories | E38: Microphone Stand | F38: 0.07 | G38: AA-26 | H38: 85189000 | I38: 2 | J38: ='Edit Parameters'!$B$2/('Edit Parameters'!$B$3/N38) | K38: 12.6 | L38: 12.3 | M38: 3.02 | N38: =(K38*L38*M38)/1000000 | O38: 15 | P38: =(I38+J38)*(O38%+(O38%*10%)) | Q38: =(I38+J38+P38)*'Edit Parameters'!B$1 | R38: =Q38*1.18 | S38: 7 | T38: 26 | U38: 58 | V38: 10 | W38: 2 | X38: 5 | Y38: 0 | Z38: 18 | AA38: =AE38-(AE38/1.18) | AB38: =R38*0.05 | AC38: =R38*0.03 | AD38: 0 | AE38: 499 | AF38: 899 | AI38: 549
A39: FBA78960 | B39: B0CBCB82MT | C39: AM-C39 | D39: Microphone | E39: XLR Condenser Microphone Kit - Tripod | F39: 0.11 | G39: AM-C39 | H39: 85181000 | I39: 5.5 | J39: ='Edit Parameters'!$B$2/('Edit Parameters'!$B$3/N39) | K39: 20.8 | L39: 19.8 | M39: 7.3 | N39: =(K39*L39*M39)/1000000 | O39: 15 | P39: =(I39+J39)*(O39%+(O39%*10%)) | Q39: =(I39+J39+P39)*'Edit Parameters'!B$1 | R39: =Q39*1.18 | S39: 11 | T39: 51 | U39: 101.42373 | V39: 10 | W39: 2 | X39: 5 | Y39: 0 | Z39: 18 | AA39: =AE39-(AE39/1.18) | AB39: =R39*0.05 | AC39: =R39*0.03 | AD39: 0 | AE39: 1599 | AF39: 3999 | AI39: 1699
A40: FBA75679 | B40: B0B4JRQP22 | C40: AA-02 | D40: Microphone Accessories | E40: Sound Isolation Shield | F40: 0.11 | G40: AA-02 | H40: 85189000 | I40: 9.5 | J40: ='Edit Parameters'!$B$2/('Edit Parameters'!$B$3/N40) | K40: 33.4 | L40: 17.4 | M40: 17.4 | N40: =(K40*L40*M40)/1000000 | O40: 15 | P40: =(I40+J40)*(O40%+(O40%*10%)) | Q40: =(I40+J40+P40)*'Edit Parameters'!B$1 | R40: =Q40*1.18 | S40: 11 | T40: 51 | U40: 147 | V40: 10 | W40: 2 | X40: 5 | Y40: 0 | Z40: 18 | AA40: =AE40-(AE40/1.18) | AB40: =R40*0.05 | AC40: =R40*0.03 | AD40: 0 | AE40: 2499 | AF40: 5999 | AI40: 2499
A41: FBA79107 | B41: B0CM9P5CCK | C41: AM-W17 | D41: Microphone | E41: Wireless Lapel Microphone | F41: 0.115 | G41: AM-W17 | H41: 85181000 | I41: 8 | J41: ='Edit Parameters'!$B$2/('Edit Parameters'!$B$3/N41) | K41: 14.3 | L41: 8.2 | M41: 3.4 | N41: =(K41*L41*M41)/1000000 | O41: 15 | P41: =(I41+J41)*(O41%+(O41%*10%)) | Q41: =(I41+J41+P41)*'Edit Parameters'!B$1 | R41: =Q41*1.18 | S41: 11.5 | T41: 51 | U41: 58 | V41: 10 | W41: 2 | X41: 5 | Y41: 0 | Z41: 18 | AA41: =AE41-(AE41/1.18) | AB41: =R41*0.05 | AC41: =R41*0.03 | AD41: 0 | AE41: 1899 | AF41: 4999 | AI41: 1749
A42: FBA79655 | B42: B0DN6PFWNK | C42: AM-C44 Pro | D42: Bundles | E42: Bundles | F42: 0.11 | G42: AM-C44 Pro | H42: 85181000 | I42: 24 | J42: ='Edit Parameters'!$B$2/('Edit Parameters'!$B$3/N42) | K42: 41.4 | L42: 19.4 | M42: 16.1 | N42: =(K42*L42*M42)/1000000 | O42: 15 | P42: =(I42+J42)*(O42%+(O42%*10%)) | Q42: =(I42+J42+P42)*'Edit Parameters'!B$1 | R42: =Q42*1.18 | S42: 11 | T42: 51 | U42: 27 | V42: 10 | W42: 2 | X42: 5 | Y42: 0 | Z42: 18 | AA42: =AE42-(AE42/1.18) | AB42: =R42*0.05 | AC42: =R42*0.03 | AD42: 0 | AE42: 5799 | AF42: 9499 | AI42: 5299
A43: FBA79841 | B43: B0FQBTRM28 | C43: AH-60 BL | D43: Headphone | E43: DJ Headphone | F43: 0.11 | G43: AH-60 BL | H43: 85183020 | I43: 8 | J43: ='Edit Parameters'!$B$2/('Edit Parameters'!$B$3/N43) | K43: 27.1 | L43: 26.5 | M43: 12.4 | N43: =(K43*L43*M43)/1000000 | O43: 20 | P43: =(I43+J43)*(O43%+(O43%*10%)) | Q43: =(I43+J43+P43)*'Edit Parameters'!B$1 | R43: =Q43*1.18 | S43: 11 | T43: 51 | U43: 115 | V43: 10 | W43: 2 | X43: 5 | Y43: 0 | Z43: 18 | AA43: =AE43-(AE43/1.18) | AB43: =R43*0.05 | AC43: =R43*0.03 | AD43: 0 | AE43: 1999 | AF43: 3499 | AI43: 1999
A44: FBA75684 | B44: B0B4G7VWXD | C44: AA-04 | D44: Microphone Accessories | E44: Shock Mount | F44: 0.11 | G44: AA-04 | H44: 85189000 | I44: 6.6 | J44: ='Edit Parameters'!$B$2/('Edit Parameters'!$B$3/N44) | K44: 15.5 | L44: 13.1 | M44: 12.7 | N44: =(K44*L44*M44)/1000000 | O44: 15 | P44: =(I44+J44)*(O44%+(O44%*10%)) | Q44: =(I44+J44+P44)*'Edit Parameters'!B$1 | R44: =Q44*1.18 | S44: 11 | T44: 51 | U44: 76 | V44: 10 | W44: 2 | X44: 5 | Y44: 0 | Z44: 18 | AA44: =AE44-(AE44/1.18) | AB44: =R44*0.05 | AC44: =R44*0.03 | AD44: 0 | AE44: 1599 | AF44: 2999 | AI44: 1699
A45: FBA79008 | B45: B0CH4RT4P8 | C45: AI-06 | D45: Audio Interface | E45: Audio Interface | F45: 0.11 | G45: AI-06 | H45: 85437029 | I45: 22.5 | J45: ='Edit Parameters'!$B$2/('Edit Parameters'!$B$3/N45) | K45: 23 | L45: 15.8 | M45: 7.9 | N45: =(K45*L45*M45)/1000000 | O45: 7.5 | P45: =(I45+J45)*(O45%+(O45%*10%)) | Q45: =(I45+J45+P45)*'Edit Parameters'!B$1 | R45: =Q45*1.18 | S45: 11 | T45: 51 | U45: 77 | V45: 10 | W45: 2 | X45: 5 | Y45: 0 | Z45: 18 | AA45: =AE45-(AE45/1.18) | AB45: =R45*0.05 | AC45: =R45*0.03 | AD45: 0 | AE45: 3999 | AF45: 9999 | AI45: 3499
A46: FBA79445 | B46: B0DFMLS8JG | C46: AM-W32 | D46: Microphone | E46: Wireless UHF Microphone | F46: 0.11 | G46: AM-W32 | H46: 85181000 | I46: 16.62 | J46: ='Edit Parameters'!$B$2/('Edit Parameters'!$B$3/N46) | K46: 30.5 | L46: 19.1 | M46: 6.2 | N46: =(K46*L46*M46)/1000000 | O46: 15 | P46: =(I46+J46)*(O46%+(O46%*10%)) | Q46: =(I46+J46+P46)*'Edit Parameters'!B$1 | R46: =Q46*1.18 | S46: 11 | T46: 51 | U46: 76 | V46: 10 | W46: 2 | X46: 5 | Y46: 0 | Z46: 18 | AA46: =AE46-(AE46/1.18) | AB46: =R46*0.05 | AC46: =R46*0.03 | AD46: 0 | AE46: 3899 | AF46: 6999 | AI46: 3549
A47: FBA76414 | B47: B0BLJVJ2GN | C47: AA-05 | D47: Microphone Accessories | E47: Boom Arm | F47: 0.105 | G47: AA-05 | H47: 85189000 | I47: 2 | J47: ='Edit Parameters'!$B$2/('Edit Parameters'!$B$3/N47) | K47: 39.79 | L47: 11.4 | M47: 4.9 | N47: =(K47*L47*M47)/1000000 | O47: 15 | P47: =(I47+J47)*(O47%+(O47%*10%)) | Q47: =(I47+J47+P47)*'Edit Parameters'!B$1 | R47: =Q47*1.18 | S47: 10.5 | T47: 26 | U47: 76 | V47: 10 | W47: 2 | X47: 5 | Y47: 0 | Z47: 18 | AA47: =AE47-(AE47/1.18) | AB47: =R47*0.05 | AC47: =R47*0.03 | AD47: 0 | AE47: 679 | AF47: 1999 | AI47: 649
A48: FBA75675 | B48: B0B4G8ZB64 | C48: AM-C3 | D48: Microphone | E48: Wired Dynamic Mic | F48: 0.055 | G48: AM-C3 | H48: 85181000 | I48: 5 | J48: ='Edit Parameters'!$B$2/('Edit Parameters'!$B$3/N48) | K48: 24.5 | L48: 13.1 | M48: 5.8 | N48: =(K48*L48*M48)/1000000 | O48: 15 | P48: =(I48+J48)*(O48%+(O48%*10%)) | Q48: =(I48+J48+P48)*'Edit Parameters'!B$1 | R48: =Q48*1.18 | S48: 5.5 | T48: 26 | U48: 17 | V48: 10 | W48: 2 | X48: 5 | Y48: 0 | Z48: 18 | AA48: =AE48-(AE48/1.18) | AB48: =R48*0.05 | AC48: =R48*0.03 | AD48: 0 | AE48: 899 | AF48: 2999 | AI48: 899
A49: FBA79783 | B49: B0FF9R3GKK | C49: AM-C47 | D49: Microphone | E49: RGB Condenser Mic with Boom Arm | F49: 0.11 | G49: AM-C47 | H49: 85181000 | I49: 12.4 | J49: ='Edit Parameters'!$B$2/('Edit Parameters'!$B$3/N49) | K49: 43 | L49: 20.4 | M49: 10.2 | N49: =(K49*L49*M49)/1000000 | O49: 15 | P49: =(I49+J49)*(O49%+(O49%*10%)) | Q49: =(I49+J49+P49)*'Edit Parameters'!B$1 | R49: =Q49*1.18 | S49: 11 | T49: 51 | U49: 114 | V49: 10 | W49: 2 | X49: 5 | Y49: 0 | Z49: 18 | AA49: =AE49-(AE49/1.18) | AB49: =R49*0.05 | AC49: =R49*0.03 | AD49: 0 | AE49: 2999 | AF49: 4999 | AI49: 2999
A50: FBA79827 | B50: B0FJ8S5XJ8 | C50: PB-03 (AI-04 Red + AM-C11 x 2) | D50: Bundles | E50: PB-03 | F50: 0.11 | G50: PB-03 (AI-04 Red + AM-C11 x 2) | H50: 85181000 | I50: 64 | J50: ='Edit Parameters'!$B$2/('Edit Parameters'!$B$3/N50) | K50: 43.6 | L50: 21.5 | M50: 18.8 | N50: =(K50*L50*M50)/1000000 | O50: 15 | P50: =(I50+J50)*(O50%+(O50%*10%)) | Q50: =(I50+J50+P50)*'Edit Parameters'!B$1 | R50: =Q50*1.18 | S50: 11 | T50: 51 | U50: 246.94915 | V50: 10 | W50: 2 | X50: 5 | Y50: 0 | Z50: 18 | AA50: =AE50-(AE50/1.18) | AB50: =R50*0.05 | AC50: =R50*0.03 | AD50: 0 | AE50: 13999 | AF50: ₹ 26,299.00 | AI50: 13899
A51: FBA77171 | B51: B0CH4VCD6R | C51: AC-6XL | D51: Microphone Accessories | E51: 6m XLR to 6.35m Cable | F51: 0.155 | G51: AC-6XL | H51: 85189000 | I51: 1.3 | J51: ='Edit Parameters'!$B$2/('Edit Parameters'!$B$3/N51) | K51: 28.4 | L51: 19.5 | M51: 3.7 | N51: =(K51*L51*M51)/1000000 | O51: 15 | P51: =(I51+J51)*(O51%+(O51%*10%)) | Q51: =(I51+J51+P51)*'Edit Parameters'!B$1 | R51: =Q51*1.18 | S51: 15.5 | T51: 26 | U51: 76 | V51: 10 | W51: 2 | X51: 5 | Y51: 0 | Z51: 18 | AA51: =AE51-(AE51/1.18) | AB51: =R51*0.05 | AC51: =R51*0.03 | AD51: 0 | AE51: 499 | AF51: 999 | AI51: 549
A52: FBA79653 | B52: B0DN6LJZBR | C52: AM-C45 Pro | D52: Bundles | E52: Bundles | F52: 0.11 | G52: AM-C45 Pro | H52: 85181000 | I52: 17.5 | J52: ='Edit Parameters'!$B$2/('Edit Parameters'!$B$3/N52) | K52: 41.5 | L52: 19.3 | M52: 16 | N52: =(K52*L52*M52)/1000000 | O52: 15 | P52: =(I52+J52)*(O52%+(O52%*10%)) | Q52: =(I52+J52+P52)*'Edit Parameters'!B$1 | R52: =Q52*1.18 | S52: 11 | T52: 51 | U52: 27 | V52: 10 | W52: 2 | X52: 5 | Y52: 0 | Z52: 18 | AA52: =AE52-(AE52/1.18) | AB52: =R52*0.05 | AC52: =R52*0.03 | AD52: 0 | AE52: 4499 | AF52: 8999 | AI52: 4099
A53: FBA79825 | B53: B0FJ2DT13L | C53: GB-02 (AM-C43 + AI-11) | D53: Bundles | E53: GB-02 | F53: 0.11 | G53: GB-02 (AM-C43 + AI-11) | H53: 85181000 | I53: 16.5 | J53: ='Edit Parameters'!$B$2/('Edit Parameters'!$B$3/N53) | K53: 43.7 | L53: 21.9 | M53: 18.3 | N53: =(K53*L53*M53)/1000000 | O53: 15 | P53: =(I53+J53)*(O53%+(O53%*10%)) | Q53: =(I53+J53+P53)*'Edit Parameters'!B$1 | R53: =Q53*1.18 | S53: 11 | T53: 51 | U53: 247.94915 | V53: 10 | W53: 2 | X53: 5 | Y53: 0 | Z53: 18 | AA53: =AE53-(AE53/1.18) | AB53: =R53*0.05 | AC53: =R53*0.03 | AD53: 0 | AE53: 3899 | AF53: ₹ 12,499.00 | AI53: 3899
A54: FBA75687 | B54: B0B4G5ZLTB | C54: AM-W11 | D54: Microphone | E54: Wireless UHF Microphone | F54: 0.11 | G54: AM-W11 | H54: 85181000 | I54: 22.3 | J54: ='Edit Parameters'!$B$2/('Edit Parameters'!$B$3/N54) | K54: 12.4 | L54: 10.2 | M54: 5.4 | N54: =(K54*L54*M54)/1000000 | O54: 15 | P54: =(I54+J54)*(O54%+(O54%*10%)) | Q54: =(I54+J54+P54)*'Edit Parameters'!B$1 | R54: =Q54*1.18 | S54: 11 | T54: 51 | U54: 58 | V54: 10 | W54: 2 | X54: 5 | Y54: 0 | Z54: 18 | AA54: =AE54-(AE54/1.18) | AB54: =R54*0.05 | AC54: =R54*0.03 | AD54: 0 | AE54: 2799 | AF54: 9999 | AI54: 2299
A55: FBA78974 | B55: B0CF5RRTDJ | C55: AA-20 | D55: Microphone Accessories | E55: Boom Arm | F55: 0.11 | G55: AA-20 | H55: 85189000 | I55: 8.1 | J55: ='Edit Parameters'!$B$2/('Edit Parameters'!$B$3/N55) | K55: 44.9 | L55: 16 | M55: 10.6 | N55: =(K55*L55*M55)/1000000 | O55: 15 | P55: =(I55+J55)*(O55%+(O55%*10%)) | Q55: =(I55+J55+P55)*'Edit Parameters'!B$1 | R55: =Q55*1.18 | S55: 11 | T55: 51 | U55: 114 | V55: 10 | W55: 2 | X55: 5 | Y55: 0 | Z55: 18 | AA55: =AE55-(AE55/1.18) | AB55: =R55*0.05 | AC55: =R55*0.03 | AD55: 0 | AE55: 2499 | AF55: 4999 | AI55: 2149
A56: FBA75680 | B56: B0B4G1PXWV | C56: AM-C6 | D56: Microphone | E56: USB Microphone Kit - Tripod | F56: 0.11 | G56: AM-C6 | H56: 85181000 | I56: 14 | J56: ='Edit Parameters'!$B$2/('Edit Parameters'!$B$3/N56) | K56: 21.7 | L56: 12.2 | M56: 8.4 | N56: =(K56*L56*M56)/1000000 | O56: 15 | P56: =(I56+J56)*(O56%+(O56%*10%)) | Q56: =(I56+J56+P56)*'Edit Parameters'!B$1 | R56: =Q56*1.18 | S56: 11 | T56: 51 | U56: 76 | V56: 10 | W56: 2 | X56: 5 | Y56: 0 | Z56: 18 | AA56: =AE56-(AE56/1.18) | AB56: =R56*0.05 | AC56: =R56*0.03 | AD56: 0 | AE56: 2599 | AF56: 5999 | AI56: 1999
A57: FBA79009 | B57: B0CH4PMR8K | C57: AM-C41 | D57: Microphone | E57: USB Microphone Kit - Tripod | F57: 0.11 | G57: AM-C41 | H57: 85181000 | I57: 8 | J57: ='Edit Parameters'!$B$2/('Edit Parameters'!$B$3/N57) | K57: 20.8 | L57: 20.2 | M57: 7.5 | N57: =(K57*L57*M57)/1000000 | O57: 15 | P57: =(I57+J57)*(O57%+(O57%*10%)) | Q57: =(I57+J57+P57)*'Edit Parameters'!B$1 | R57: =Q57*1.18 | S57: 11 | T57: 51 | U57: 17 | V57: 10 | W57: 2 | X57: 5 | Y57: 0 | Z57: 18 | AA57: =AE57-(AE57/1.18) | AB57: =R57*0.05 | AC57: =R57*0.03 | AD57: 0 | AE57: 1799 | AF57: 3999 | AI57: 1649
A58: FBA75676 | B58: B0B4DS678Q | C58: AM-C4 | D58: Microphone | E58: USB Microphone Kit - Tripod | F58: 0.11 | G58: AM-C4 | H58: 85181000 | I58: 13 | J58: ='Edit Parameters'!$B$2/('Edit Parameters'!$B$3/N58) | K58: 23.3 | L58: 13.9 | M58: 10.9 | N58: =(K58*L58*M58)/1000000 | O58: 15 | P58: =(I58+J58)*(O58%+(O58%*10%)) | Q58: =(I58+J58+P58)*'Edit Parameters'!B$1 | R58: =Q58*1.18 | S58: 11 | T58: 51 | U58: 77 | V58: 10 | W58: 2 | X58: 5 | Y58: 0 | Z58: 18 | AA58: =AE58-(AE58/1.18) | AB58: =R58*0.05 | AC58: =R58*0.03 | AD58: 0 | AE58: 2499 | AF58: 5999 | AI58: 1999
A59: FBA76597 | B59: B0BQ7H7418 | C59: AA-06 | D59: Microphone Accessories | E59: Boom Arm Kit | F59: 0.11 | G59: AA-06 | H59: 85189000 | I59: 4.3 | J59: ='Edit Parameters'!$B$2/('Edit Parameters'!$B$3/N59) | K59: 40.5 | L59: 16.4 | M59: 7.2 | N59: =(K59*L59*M59)/1000000 | O59: 15 | P59: =(I59+J59)*(O59%+(O59%*10%)) | Q59: =(I59+J59+P59)*'Edit Parameters'!B$1 | R59: =Q59*1.18 | S59: 11 | T59: 51 | U59: 109 | V59: 10 | W59: 2 | X59: 5 | Y59: 0 | Z59: 18 | AA59: =AE59-(AE59/1.18) | AB59: =R59*0.05 | AC59: =R59*0.03 | AD59: 0 | AE59: 1349 | AF59: 2999 | AI59: 1299
A60: FBA79016 | B60: B0CH4R1V6S | C60: AM-C3a | D60: Microphone | E60: Wired Dynamic Mic | F60: 0.055 | G60: AM-C3a | H60: 85181000 | I60: 4 | J60: ='Edit Parameters'!$B$2/('Edit Parameters'!$B$3/N60) | K60: 25.3 | L60: 13.4 | M60: 5.7 | N60: =(K60*L60*M60)/1000000 | O60: 15 | P60: =(I60+J60)*(O60%+(O60%*10%)) | Q60: =(I60+J60+P60)*'Edit Parameters'!B$1 | R60: =Q60*1.18 | S60: 5.5 | T60: 26 | U60: 58 | V60: 10 | W60: 2 | X60: 5 | Y60: 0 | Z60: 18 | AA60: =AE60-(AE60/1.18) | AB60: =R60*0.05 | AC60: =R60*0.03 | AD60: 0 | AE60: 899 | AF60: 1999 | AI60: 749
A61: FBA79230 | B61: B0CX1XK5R6 | C61: AM-W46 | D61: Speaker | E61: Microphone with Speaker | F61: 0.11 | G61: AM-W46 | H61: 85182290 | I61: 32.8 | J61: ='Edit Parameters'!$B$2/('Edit Parameters'!$B$3/N61) | K61: 27.9 | L61: 23 | M61: 12.1 | N61: =(K61*L61*M61)/1000000 | O61: 20 | P61: =(I61+J61)*(O61%+(O61%*10%)) | Q61: =(I61+J61+P61)*'Edit Parameters'!B$1 | R61: =Q61*1.18 | S61: 11 | T61: 51 | U61: 142 | V61: 10 | W61: 2 | X61: 5 | Y61: 0 | Z61: 18 | AA61: =AE61-(AE61/1.18) | AB61: =R61*0.05 | AC61: =R61*0.03 | AD61: 0 | AE61: 5999 | AF61: 12999 | AI61: 4799
A62: FBA79448 | B62: B0DFMKY4TT | C62: AM-W35 | D62: Microphone | E62: Wireless UHF Microphone | F62: 0.11 | G62: AM-W35 | H62: 85181000 | I62: 15.22 | J62: ='Edit Parameters'!$B$2/('Edit Parameters'!$B$3/N62) | K62: 26.2 | L62: 15.3 | M62: 6.2 | N62: =(K62*L62*M62)/1000000 | O62: 15 | P62: =(I62+J62)*(O62%+(O62%*10%)) | Q62: =(I62+J62+P62)*'Edit Parameters'!B$1 | R62: =Q62*1.18 | S62: 11 | T62: 51 | U62: 76 | V62: 10 | W62: 2 | X62: 5 | Y62: 0 | Z62: 18 | AA62: =AE62-(AE62/1.18) | AB62: =R62*0.05 | AC62: =R62*0.03 | AD62: 0 | AE62: 3359 | AF62: 6499 | AI62: 3199
A63: FBA79108 | B63: B0CM9L1QZG | C63: AM-W16 | D63: Microphone | E63: Wireless Lapel Microphone | F63: 0.11 | G63: AM-W16 | H63: 85181000 | I63: 5.8 | J63: ='Edit Parameters'!$B$2/('Edit Parameters'!$B$3/N63) | K63: 14.5 | L63: 8.1 | M63: 3.4 | N63: =(K63*L63*M63)/1000000 | O63: 15 | P63: =(I63+J63)*(O63%+(O63%*10%)) | Q63: =(I63+J63+P63)*'Edit Parameters'!B$1 | R63: =Q63*1.18 | S63: 11 | T63: 51 | U63: 59 | V63: 10 | W63: 2 | X63: 5 | Y63: 0 | Z63: 18 | AA63: =AE63-(AE63/1.18) | AB63: =R63*0.05 | AC63: =R63*0.03 | AD63: 0 | AE63: 1399 | AF63: 7999 | AI63: 1399
A64: FBA78961 | B64: B0CBCB9S14 | C64: AM-C40 | D64: Microphone | E64: Condenser Mic with Boom Arm | F64: 0.11 | G64: AM-C40 | H64: 85181000 | I64: 24 | J64: ='Edit Parameters'!$B$2/('Edit Parameters'!$B$3/N64) | K64: 42.6 | L64: 20.7 | M64: 11.4 | N64: =(K64*L64*M64)/1000000 | O64: 15 | P64: =(I64+J64)*(O64%+(O64%*10%)) | Q64: =(I64+J64+P64)*'Edit Parameters'!B$1 | R64: =Q64*1.18 | S64: 11 | T64: 51 | U64: 147 | V64: 10 | W64: 2 | X64: 5 | Y64: 0 | Z64: 18 | AA64: =AE64-(AE64/1.18) | AB64: =R64*0.05 | AC64: =R64*0.03 | AD64: 0 | AE64: 3499 | AF64: 8999 | AI64: 2499
A65: FBA79010 | B65: B0CH4T2BJD | C65: AM-C42 | D65: Microphone | E65: USB Microphone Kit - Boomarm | F65: 0.11 | G65: AM-C42 | H65: 85181000 | I65: 11.5 | J65: ='Edit Parameters'!$B$2/('Edit Parameters'!$B$3/N65) | K65: 42.2 | L65: 20.5 | M65: 7.4 | N65: =(K65*L65*M65)/1000000 | O65: 15 | P65: =(I65+J65)*(O65%+(O65%*10%)) | Q65: =(I65+J65+P65)*'Edit Parameters'!B$1 | R65: =Q65*1.18 | S65: 11 | T65: 51 | U65: 114 | V65: 10 | W65: 2 | X65: 5 | Y65: 0 | Z65: 18 | AA65: =AE65-(AE65/1.18) | AB65: =R65*0.05 | AC65: =R65*0.03 | AD65: 0 | AE65: 2699 | AF65: 5999 | AI65: 2399
... A67: FBA75678 | B67: B0B4G8PH2P | C67: AA-01 | D67: Microphone Accessories | E67: Boom Arm Kit | F67: 0.11 | G67: AA-01 | H67: 85189000 | I67: 9 | J67: ='Edit Parameters'!$B$2/('Edit Parameters'!$B$3/N67) | K67: 41.1 | L67: 18.5 | M67: 9.5 | N67: =(K67*L67*M67)/1000000 | O67: 15 | P67: =(I67+J67)*(O67%+(O67%*10%)) | Q67: =(I67+J67+P67)*'Edit Parameters'!B$1 | R67: =Q67*1.18 | S67: 11 | T67: 51 | U67: 114 | V67: 10 | W67: 2 | X67: 5 | Y67: 0 | Z67: 18 | AA67: =AE67-(AE67/1.18) | AB67: =R67*0.05 | AC67: =R67*0.03 | AD67: 0 | AE67: 2099 | AF67: 4999 | AI67: 2199
A68: FBA79708 | B68: B0FFB6YJM1 | C68: SB-01 | D68: Speaker | E68: Sound Bar | F68: 0.11 | G68: SB-01 | H68: 85182290 | I68: 0 | J68: ='Edit Parameters'!$B$2/('Edit Parameters'!$B$3/N68) | K68: 41.1 | L68: 12.1 | M68: 11.7 | N68: =(K68*L68*M68)/1000000 | O68: 0 | P68: =(I68+J68)*(O68%+(O68%*10%)) | Q68: =(I68+J68+P68)*'Edit Parameters'!B$1 | R68: =Q68*1.18 | S68: 11 | T68: 51 | U68: 115 | V68: 10 | W68: 2 | X68: 5 | Y68: 0 | Z68: 18 | AA68: =AE68-(AE68/1.18) | AB68: =R68*0.05 | AC68: =R68*0.03 | AD68: 0 | AE68: #N/A | AF68: #N/A | AI68: 1299
A69: FBA79840 | B69: B0FQBWV1ST | C69: AH-60 RD | D69: Headphone | E69: DJ Headphone | F69: 0.11 | G69: AH-60 RD | H69: 85183020 | I69: 8 | J69: ='Edit Parameters'!$B$2/('Edit Parameters'!$B$3/N69) | K69: 28.7 | L69: 26.3 | M69: 11.9 | N69: =(K69*L69*M69)/1000000 | O69: 20 | P69: =(I69+J69)*(O69%+(O69%*10%)) | Q69: =(I69+J69+P69)*'Edit Parameters'!B$1 | R69: =Q69*1.18 | S69: 11 | T69: 51 | U69: 115 | V69: 10 | W69: 2 | X69: 5 | Y69: 0 | Z69: 18 | AA69: =AE69-(AE69/1.18) | AB69: =R69*0.05 | AC69: =R69*0.03 | AD69: 0 | AE69: 1999 | AF69: 3499 | AI69: 1999
A70: FBA78925 | B70: B0CBC7QMNV | C70: AM-C11X | D70: Microphone | E70: XLR Dynamic Mic | F70: 0.11 | G70: AM-C11X | H70: 85181000 | I70: 17 | J70: ='Edit Parameters'!$B$2/('Edit Parameters'!$B$3/N70) | K70: 22.6 | L70: 17.3 | M70: 8.5 | N70: =(K70*L70*M70)/1000000 | O70: 15 | P70: =(I70+J70)*(O70%+(O70%*10%)) | Q70: =(I70+J70+P70)*'Edit Parameters'!B$1 | R70: =Q70*1.18 | S70: 11 | T70: 51 | U70: 110 | V70: 10 | W70: 2 | X70: 5 | Y70: 0 | Z70: 18 | AA70: =AE70-(AE70/1.18) | AB70: =R70*0.05 | AC70: =R70*0.03 | AD70: 0 | AE70: 3699 | AF70: 7599 | AI70: 3649
A71: FBA79903 | B71: B0FR5DLXH9 | C71: AA-25M | D71: Microphone Accessories | E71: Lapel Mic Holder | F71: 0.055 | G71: AA-25M | H71: 85189000 | I71: 2.3 | J71: ='Edit Parameters'!$B$2/('Edit Parameters'!$B$3/N71) | K71: 26.6 | L71: 7.8 | M71: 7.7 | N71: =(K71*L71*M71)/1000000 | O71: 15 | P71: =(I71+J71)*(O71%+(O71%*10%)) | Q71: =(I71+J71+P71)*'Edit Parameters'!B$1 | R71: =Q71*1.18 | S71: 5.5 | T71: 26 | U71: 59 | V71: 10 | W71: 2 | X71: 5 | Y71: 0 | Z71: 18 | AA71: =AE71-(AE71/1.18) | AB71: =R71*0.05 | AC71: =R71*0.03 | AD71: 0 | AE71: 799 | AF71: 1799 | AI71: 849
A72: FBA76730 | B72: B0BLKB6FRR | C72: AM-C27 | D72: Microphone | E72: Wired Dynamic Mic | F72: 0.11 | G72: AM-C27 | H72: 85181000 | I72: 6.27 | J72: ='Edit Parameters'!$B$2/('Edit Parameters'!$B$3/N72) | K72: 25.5 | L72: 13.2 | M72: 7.5 | N72: =(K72*L72*M72)/1000000 | O72: 15 | P72: =(I72+J72)*(O72%+(O72%*10%)) | Q72: =(I72+J72+P72)*'Edit Parameters'!B$1 | R72: =Q72*1.18 | S72: 11 | T72: 51 | U72: 17 | V72: 10 | W72: 2 | X72: 5 | Y72: 0 | Z72: 18 | AA72: =AE72-(AE72/1.18) | AB72: =R72*0.05 | AC72: =R72*0.03 | AD72: 0 | AE72: 1499 | AF72: 3299 | AI72: 1399
A73: FBA79064 | B73: B0CJR76Y7G | C73: AA-25 | D73: Microphone Accessories | E73: Lapel Mic Holder | F73: 0.055 | G73: AA-25 | H73: 85189000 | I73: 2.5 | J73: ='Edit Parameters'!$B$2/('Edit Parameters'!$B$3/N73) | K73: 26.6 | L73: 7.6 | M73: 7.3 | N73: =(K73*L73*M73)/1000000 | O73: 15 | P73: =(I73+J73)*(O73%+(O73%*10%)) | Q73: =(I73+J73+P73)*'Edit Parameters'!B$1 | R73: =Q73*1.18 | S73: 5.5 | T73: 26 | U73: 58 | V73: 10 | W73: 2 | X73: 5 | Y73: 0 | Z73: 18 | AA73: =AE73-(AE73/1.18) | AB73: =R73*0.05 | AC73: =R73*0.03 | AD73: 0 | AE73: 799 | AF73: 1799 | AI73: 799
A74: FBA75683 | B74: B0B4G94VP3 | C74: AA-03 | D74: Microphone Accessories | E74: Pop Filter | F74: 0.07 | G74: AA-03 | H74: 85189000 | I74: 1.3 | J74: ='Edit Parameters'!$B$2/('Edit Parameters'!$B$3/N74) | K74: 29.6 | L74: 16.6 | M74: 2.7 | N74: =(K74*L74*M74)/1000000 | O74: 15 | P74: =(I74+J74)*(O74%+(O74%*10%)) | Q74: =(I74+J74+P74)*'Edit Parameters'!B$1 | R74: =Q74*1.18 | S74: 7 | T74: 26 | U74: 58 | V74: 10 | W74: 2 | X74: 5 | Y74: 0 | Z74: 18 | AA74: =AE74-(AE74/1.18) | AB74: =R74*0.05 | AC74: =R74*0.03 | AD74: 0 | AE74: 479 | AF74: 1499 | AI74: 499
A75: FBA79820 | B75: B0FQJWWDVK | C75: AC-3XL | D75: Microphone Accessories | E75: 3m XLR to 6.35m Cable | F75: 0.07 | G75: AC-3XL | H75: 85189000 | I75: 1 | J75: ='Edit Parameters'!$B$2/('Edit Parameters'!$B$3/N75) | K75: 29.6 | L75: 18.5 | M75: 2.9 | N75: =(K75*L75*M75)/1000000 | O75: 15 | P75: =(I75+J75)*(O75%+(O75%*10%)) | Q75: =(I75+J75+P75)*'Edit Parameters'!B$1 | R75: =Q75*1.18 | S75: 7 | T75: 21 | U75: 59 | V75: 10 | W75: 2 | X75: 5 | Y75: 0 | Z75: 18 | AA75: =AE75-(AE75/1.18) | AB75: =R75*0.05 | AC75: =R75*0.03 | AD75: 0 | AE75: 399 | AF75: 749 | AI75: 449
A76: FBA78206 | B76: B0C4YSV3XL | C76: AM-W15 | D76: Microphone | E76: Wireless Mic with Charging Case | F76: 0.11 | G76: AM-W15 | H76: 85181000 | I76: 92 | J76: ='Edit Parameters'!$B$2/('Edit Parameters'!$B$3/N76) | K76: 16.7 | L76: 10.7 | M76: 7.2 | N76: =(K76*L76*M76)/1000000 | O76: 15 | P76: =(I76+J76)*(O76%+(O76%*10%)) | Q76: =(I76+J76+P76)*'Edit Parameters'!B$1 | R76: =Q76*1.18 | S76: 11 | T76: 51 | U76: 77 | V76: 10 | W76: 2 | X76: 5 | Y76: 0 | Z76: 18 | AA76: =AE76-(AE76/1.18) | AB76: =R76*0.05 | AC76: =R76*0.03 | AD76: 0 | AE76: 14990 | AF76: 34999 | AI76: 5990
A77: FBA75686 | B77: B0B4G89VQJ | C77: AM-W10 | D77: Microphone | E77: Wireless Lavalier Microphone | F77: 0.11 | G77: AM-W10 | H77: 85181000 | I77: 38.5 | J77: ='Edit Parameters'!$B$2/('Edit Parameters'!$B$3/N77) | K77: 18.6 | L77: 13.3 | M77: 5.5 | N77: =(K77*L77*M77)/1000000 | O77: 15 | P77: =(I77+J77)*(O77%+(O77%*10%)) | Q77: =(I77+J77+P77)*'Edit Parameters'!B$1 | R77: =Q77*1.18 | S77: 11 | T77: 51 | U77: 17 | V77: 10 | W77: 2 | X77: 5 | Y77: 0 | Z77: 18 | AA77: =AE77-(AE77/1.18) | AB77: =R77*0.05 | AC77: =R77*0.03 | AD77: 0 | AE77: 5999 | AF77: 20999 | AI77: 3899
A78: FBA79833 | B78: B0FJ8PZ9H7 | C78: PB-04 (AI-04 Red + AM-C44 x 2) | D78: Bundles | E78: PB-04 | F78: 0.11 | G78: PB-04 (AI-04 Red + AM-C44 x 2) | H78: 85181000 | I78: 60 | J78: ='Edit Parameters'!$B$2/('Edit Parameters'!$B$3/N78) | K78: 45 | L78: 23.9 | M78: 18.6 | N78: =(K78*L78*M78)/1000000 | O78: 15 | P78: =(I78+J78)*(O78%+(O78%*10%)) | Q78: =(I78+J78+P78)*'Edit Parameters'!B$1 | R78: =Q78*1.18 | S78: 11 | T78: 51 | U78: 213 | V78: 10 | W78: 2 | X78: 5 | Y78: 0 | Z78: 18 | AA78: =AE78-(AE78/1.18) | AB78: =R78*0.05 | AC78: =R78*0.03 | AD78: 0 | AE78: 13499 | AF78: ₹ 24,499.00 | AI78: 13399
A79: FBA79447 | B79: B0DFMLXD9S | C79: AM-W34 | D79: Microphone | E79: Wireless UHF Microphone | F79: 0.11 | G79: AM-W34 | H79: 85181000 | I79: 18.1 | J79: ='Edit Parameters'!$B$2/('Edit Parameters'!$B$3/N79) | K79: 36.79 | L79: 26.2 | M79: 6.2 | N79: =(K79*L79*M79)/1000000 | O79: 15 | P79: =(I79+J79)*(O79%+(O79%*10%)) | Q79: =(I79+J79+P79)*'Edit Parameters'!B$1 | R79: =Q79*1.18 | S79: 11 | T79: 51 | U79: 114 | V79: 10 | W79: 2 | X79: 5 | Y79: 0 | Z79: 18 | AA79: =AE79-(AE79/1.18) | AB79: =R79*0.05 | AC79: =R79*0.03 | AD79: 0 | AE79: 3799 | AF79: 7499 | AI79: 3549
A80: FBA79909 | B80: B0FVM17Q4W | C80: AM-W20 | D80: Microphone | E80: Wireless Lapel Microphone | F80: 0.11 | G80: AM-W20 | H80: 85181000 | I80: 16.6 | J80: ='Edit Parameters'!$B$2/('Edit Parameters'!$B$3/N80) | K80: 11.2 | L80: 10 | M80: 4.9 | N80: =(K80*L80*M80)/1000000 | O80: 15 | P80: =(I80+J80)*(O80%+(O80%*10%)) | Q80: =(I80+J80+P80)*'Edit Parameters'!B$1 | R80: =Q80*1.18 | S80: 11 | T80: 51 | U80: 59 | V80: 10 | W80: 2 | X80: 5 | Y80: 0 | Z80: 18 | AA80: =AE80-(AE80/1.18) | AB80: =R80*0.05 | AC80: =R80*0.03 | AD80: 0 | AE80: #N/A | AF80: #N/A | AI80: 2199
A81: FBA75691 | B81: B0B4G5JG4P | C81: AM-W14 | D81: Microphone | E81: Wireless UHF Microphone | F81: 0.11 | G81: AM-W14 | H81: 85181000 | I81: 25 | J81: ='Edit Parameters'!$B$2/('Edit Parameters'!$B$3/N81) | K81: 29.4 | L81: 20.4 | M81: 11.7 | N81: =(K81*L81*M81)/1000000 | O81: 15 | P81: =(I81+J81)*(O81%+(O81%*10%)) | Q81: =(I81+J81+P81)*'Edit Parameters'!B$1 | R81: =Q81*1.18 | S81: 11 | T81: 51 | U81: 22 | V81: 10 | W81: 2 | X81: 5 | Y81: 0 | Z81: 18 | AA81: =AE81-(AE81/1.18) | AB81: =R81*0.05 | AC81: =R81*0.03 | AD81: 0 | AE81: 6999 | AF81: 12999 | AI81: 6499
A82: FBA76742 | B82: B0BLKBJ5HN | C82: AM-K1 | D82: Microphone | E82: Instrument Microphone - Drum Kit | F82: 0.11 | G82: AM-K1 | H82: 85181000 | I82: 55.11 | J82: ='Edit Parameters'!$B$2/('Edit Parameters'!$B$3/N82) | K82: 28.8 | L82: 25.8 | M82: 10 | N82: =(K82*L82*M82)/1000000 | O82: 15 | P82: =(I82+J82)*(O82%+(O82%*10%)) | Q82: =(I82+J82+P82)*'Edit Parameters'!B$1 | R82: =Q82*1.18 | S82: 11 | T82: 51 | U82: 114 | V82: 10 | W82: 2 | X82: 5 | Y82: 0 | Z82: 18 | AA82: =AE82-(AE82/1.18) | AB82: =R82*0.05 | AC82: =R82*0.03 | AD82: 0 | AE82: 9499 | AF82: 19999
A83: FBA79832 | B83: B0FJ8S53GW | C83: GB-05 (AM-C43 + AI-06) | D83: Bundles | E83: GB-05 | F83: 0.11 | G83: GB-05 (AM-C43 + AI-06) | H83: 85181000 | I83: 32.5 | J83: ='Edit Parameters'!$B$2/('Edit Parameters'!$B$3/N83) | K83: 43.4 | L83: 22.1 | M83: 18.2 | N83: =(K83*L83*M83)/1000000 | O83: 15 | P83: =(I83+J83)*(O83%+(O83%*10%)) | Q83: =(I83+J83+P83)*'Edit Parameters'!B$1 | R83: =Q83*1.18 | S83: 11 | T83: 51 | U83: 32 | V83: 10 | W83: 2 | X83: 5 | Y83: 0 | Z83: 18 | AA83: =AE83-(AE83/1.18) | AB83: =R83*0.05 | AC83: =R83*0.03 | AD83: 0 | AE83: 5999 | AF83: ₹ 13,299.00 | AI83: 5899
A84: FBA76721 | B84: B0BLKB55BM | C84: AM-C18 | D84: Microphone | E84: Vlogging Kit | F84: 0.11 | G84: AM-C18 | H84: 85181000 | I84: 20.5 | J84: ='Edit Parameters'!$B$2/('Edit Parameters'!$B$3/N84) | K84: 23.4 | L84: 23 | M84: 8.1 | N84: =(K84*L84*M84)/1000000 | O84: 15 | P84: =(I84+J84)*(O84%+(O84%*10%)) | Q84: =(I84+J84+P84)*'Edit Parameters'!B$1 | R84: =Q84*1.18 | S84: 11 | T84: 51 | U84: 17 | V84: 10 | W84: 2 | X84: 5 | Y84: 0 | Z84: 18 | AA84: =AE84-(AE84/1.18) | AB84: =R84*0.05 | AC84: =R84*0.03 | AD84: 0 | AE84: 2699 | AF84: 7799 | AI84: 2399
A85: FBA79846 | B85: B0FN7C25VS | C85: AM-C11X Pro | D85: Bundles | E85: AM-C11X Pro | F85: 0.11 | G85: AM-C11X Pro | H85: 85181000 | I85: 19 | J85: ='Edit Parameters'!$B$2/('Edit Parameters'!$B$3/N85) | K85: 45.29 | L85: 21.9 | M85: 19.3 | N85: =(K85*L85*M85)/1000000 | O85: 15 | P85: =(I85+J85)*(O85%+(O85%*10%)) | Q85: =(I85+J85+P85)*'Edit Parameters'!B$1 | R85: =Q85*1.18 | S85: 11 | T85: 51 | U85: 32 | V85: 10 | W85: 2 | X85: 5 | Y85: 0 | Z85: 18 | AA85: =AE85-(AE85/1.18) | AB85: =R85*0.05 | AC85: =R85*0.03 | AD85: 0 | AE85: 4499 | AF85: ₹ 7,999.00 | AI85: 4199
A86: FBA79444 | B86: B0DFMLQBMC | C86: AM-W20 | D86: Microphone | E86: Wireless Lapel Microphone | F86: 0.11 | G86: AM-W20 | H86: 85181000 | I86: 16.6 | J86: ='Edit Parameters'!$B$2/('Edit Parameters'!$B$3/N86) | K86: 32.2 | L86: 10.2 | M86: 4.9 | N86: =(K86*L86*M86)/1000000 | O86: 15 | P86: =(I86+J86)*(O86%+(O86%*10%)) | Q86: =(I86+J86+P86)*'Edit Parameters'!B$1 | R86: =Q86*1.18 | S86: 11 | T86: 51 | U86: 17 | V86: 10 | W86: 2 | X86: 5 | Y86: 0 | Z86: 18 | AA86: =AE86-(AE86/1.18) | AB86: =R86*0.05 | AC86: =R86*0.03 | AD86: 0 | AE86: 3099 | AF86: 7499 | AI86: 2199
A87: FBA76716 | B87: B0BLK8DNPD | C87: AM-C13 | D87: Microphone | E87: WiredLavalier Microphone | F87: 0.055 | G87: AM-C13 | H87: 85181000 | I87: 0 | J87: ='Edit Parameters'!$B$2/('Edit Parameters'!$B$3/N87) | K87: 13.1 | L87: 9.1 | M87: 3.4 | N87: =(K87*L87*M87)/1000000 | O87: 15 | P87: =(I87+J87)*(O87%+(O87%*10%)) | Q87: =(I87+J87+P87)*'Edit Parameters'!B$1 | R87: =Q87*1.18 | S87: 5.5 | T87: 26 | U87: 76 | V87: 10 | W87: 2 | X87: 5 | Y87: 0 | Z87: 18 | AA87: =AE87-(AE87/1.18) | AB87: =R87*0.05 | AC87: =R87*0.03 | AD87: 0 | AE87: 749 | AF87: 2299
A88: FBA79848 | B88: - | C88: AM-S2 | D88: Speaker | E88: Studio Monitor Speaker | F88: 0.11 | G88: AM-S2 | H88: 85182290 | I88: 27.45 | J88: ='Edit Parameters'!$B$2/('Edit Parameters'!$B$3/N88) | N88: =(K88*L88*M88)/1000000 | O88: 20 | P88: =(I88+J88)*(O88%+(O88%*10%)) | Q88: =(I88+J88+P88)*'Edit Parameters'!B$1 | R88: =Q88*1.18 | S88: 11 | U88: 0 | V88: 10 | W88: 2 | X88: 5 | Y88: 0 | Z88: 18 | AA88: =AE88-(AE88/1.18) | AB88: =R88*0.05 | AC88: =R88*0.03 | AD88: 0 | AE88: 6999 | AF88: 0
A89: FBK79009 | B89: B0FLYHJ6DK | C89: AM-C41 | D89: Microphone | E89: USB Microphone Kit - Tripod | F89: 0.11 | G89: AM-C41 | H89: 85181000 | I89: 8 | J89: ='Edit Parameters'!$B$2/('Edit Parameters'!$B$3/N89) | K89: 20.7 | L89: 19.8 | M89: 7.2 | N89: =(K89*L89*M89)/1000000 | O89: 15 | P89: =(I89+J89)*(O89%+(O89%*10%)) | Q89: =(I89+J89+P89)*'Edit Parameters'!B$1 | R89: =Q89*1.18 | S89: 11 | T89: 51 | U89: 76 | V89: 10 | W89: 2 | X89: 5 | Y89: 0 | Z89: 18 | AA89: =AE89-(AE89/1.18) | AB89: =R89*0.05 | AC89: =R89*0.03 | AD89: 0 | AE89: #N/A | AF89: #N/A | AI89: 1649
A90: FBA76728 | B90: B0BLNCP74M | C90: AM-C25 | D90: Microphone | E90: USB Microphone Kit - Boomarm | F90: 0.11 | G90: AM-C25 | H90: 85181000 | I90: 16.3 | J90: ='Edit Parameters'!$B$2/('Edit Parameters'!$B$3/N90) | K90: 44.4 | L90: 20.2 | M90: 6.9 | N90: =(K90*L90*M90)/1000000 | O90: 15 | P90: =(I90+J90)*(O90%+(O90%*10%)) | Q90: =(I90+J90+P90)*'Edit Parameters'!B$1 | R90: =Q90*1.18 | S90: 11 | T90: 51 | U90: 115 | V90: 10 | W90: 2 | X90: 5 | Y90: 0 | Z90: 18 | AA90: =AE90-(AE90/1.18) | AB90: =R90*0.05 | AC90: =R90*0.03 | AD90: 0 | AE90: 2799 | AF90: 6699 | AI90: 2199
A91: FBA78424 | B91: B0C55MY66L | C91: AM-C37 | D91: Microphone | E91: USB/XLR Dynamic Mic | F91: 0.11 | G91: AM-C37 | H91: 85181000 | I91: 24 | J91: ='Edit Parameters'!$B$2/('Edit Parameters'!$B$3/N91) | K91: 25.4 | L91: 14.4 | M91: 7.4 | N91: =(K91*L91*M91)/1000000 | O91: 15 | P91: =(I91+J91)*(O91%+(O91%*10%)) | Q91: =(I91+J91+P91)*'Edit Parameters'!B$1 | R91: =Q91*1.18 | S91: 11 | T91: 51 | U91: 77 | V91: 10 | W91: 2 | X91: 5 | Y91: 0 | Z91: 18 | AA91: =AE91-(AE91/1.18) | AB91: =R91*0.05 | AC91: =R91*0.03 | AD91: 0 | AE91: 4199 | AF91: 9399 | AI91: 3799
A92: FBK79010 | B92: B0FLYJFC22 | C92: AM-C42 | D92: Microphone | E92: USB Microphone Kit - Boomarm | F92: 0.11 | G92: AM-C42 | H92: 85181000 | I92: 11.5 | J92: ='Edit Parameters'!$B$2/('Edit Parameters'!$B$3/N92) | K92: 42.6 | L92: 20.6 | M92: 7.1 | N92: =(K92*L92*M92)/1000000 | O92: 15 | P92: =(I92+J92)*(O92%+(O92%*10%)) | Q92: =(I92+J92+P92)*'Edit Parameters'!B$1 | R92: =Q92*1.18 | S92: 11 | T92: 51 | U92: 114 | V92: 10 | W92: 2 | X92: 5 | Y92: 0 | Z92: 18 | AA92: =AE92-(AE92/1.18) | AB92: =R92*0.05 | AC92: =R92*0.03 | AD92: 0 | AE92: #N/A | AF92: #N/A | AI92: 2399
A93: FBA78204 | B93: B0C4YT43Z3 | C93: AM-C31 | D93: Microphone | E93: USB Microphone Kit - Tripod | F93: 0.11 | G93: AM-C31 | H93: 85181000 | I93: 30 | J93: ='Edit Parameters'!$B$2/('Edit Parameters'!$B$3/N93) | K93: 26.2 | L93: 15 | M93: 11 | N93: =(K93*L93*M93)/1000000 | O93: 15 | P93: =(I93+J93)*(O93%+(O93%*10%)) | Q93: =(I93+J93+P93)*'Edit Parameters'!B$1 | R93: =Q93*1.18 | S93: 11 | T93: 51 | U93: 17 | V93: 10 | W93: 2 | X93: 5 | Y93: 0 | Z93: 18 | AA93: =AE93-(AE93/1.18) | AB93: =R93*0.05 | AC93: =R93*0.03 | AD93: 0 | AE93: 3999 | AF93: 10999 | AI93: 2199
A94: FBA76722 | B94: B0BLKDC4PP | C94: AM-C19 | D94: Microphone | E94: USB Microphone Kit - Tripod | F94: 0.11 | G94: AM-C19 | H94: 85181000 | I94: 12.52 | J94: ='Edit Parameters'!$B$2/('Edit Parameters'!$B$3/N94) | K94: 17.6 | L94: 15.1 | M94: 14.9 | N94: =(K94*L94*M94)/1000000 | O94: 15 | P94: =(I94+J94)*(O94%+(O94%*10%)) | Q94: =(I94+J94+P94)*'Edit Parameters'!B$1 | R94: =Q94*1.18 | S94: 11 | T94: 51 | U94: 17 | V94: 10 | W94: 2 | X94: 5 | Y94: 0 | Z94: 18 | AA94: =AE94-(AE94/1.18) | AB94: =R94*0.05 | AC94: =R94*0.03 | AD94: 0 | AE94: 1649 | AF94: 5199
A95: FBA78986 | B95: B0CF5WXWFH | C95: AB-01 | D95: Bundles | E95: Bundles | F95: 0.11 | G95: AB-01 | H95: 85181000 | I95: 32.5 | J95: ='Edit Parameters'!$B$2/('Edit Parameters'!$B$3/N95) | K95: 50.6 | L95: 21.5 | M95: 7.7 | N95: =(K95*L95*M95)/1000000 | O95: 15 | P95: =(I95+J95)*(O95%+(O95%*10%)) | Q95: =(I95+J95+P95)*'Edit Parameters'!B$1 | R95: =Q95*1.18 | S95: 11 | T95: 51 | U95: 22 | V95: 10 | W95: 2 | X95: 5 | Y95: 0 | Z95: 18 | AA95: =AE95-(AE95/1.18) | AB95: =R95*0.05 | AC95: =R95*0.03 | AD95: 0 | AE95: 5999 | AF95: 13999
A96: FBA79722 | B96: B0F2HYY7JF | C96: AM-W21 | D96: Microphone | E96: Wireless Lapel Microphone | F96: 0.11 | G96: AM-W21 | H96: 85181000 | I96: 21.5 | J96: ='Edit Parameters'!$B$2/('Edit Parameters'!$B$3/N96) | K96: 15.3 | L96: 12.1 | M96: 4.2 | N96: =(K96*L96*M96)/1000000 | O96: 15 | P96: =(I96+J96)*(O96%+(O96%*10%)) | Q96: =(I96+J96+P96)*'Edit Parameters'!B$1 | R96: =Q96*1.18 | S96: 11 | T96: 51 | U96: 17 | V96: 10 | W96: 2 | X96: 5 | Y96: 0 | Z96: 18 | AA96: =AE96-(AE96/1.18) | AB96: =R96*0.05 | AC96: =R96*0.03 | AD96: 0 | AE96: #N/A | AF96: #N/A | AI96: 3199
A97: FBA78205 | B97: B0C539RBGL | C97: AM-C32 | D97: Microphone | E97: RGB USB Microphone Kit - Tripod | F97: 0.11 | G97: AM-C32 | H97: 85181000 | I97: 20.5 | J97: ='Edit Parameters'!$B$2/('Edit Parameters'!$B$3/N97) | K97: 21.8 | L97: 12.6 | M97: 8.4 | N97: =(K97*L97*M97)/1000000 | O97: 15 | P97: =(I97+J97)*(O97%+(O97%*10%)) | Q97: =(I97+J97+P97)*'Edit Parameters'!B$1 | R97: =Q97*1.18 | S97: 11 | T97: 51 | U97: 17 | V97: 10 | W97: 2 | X97: 5 | Y97: 0 | Z97: 18 | AA97: =AE97-(AE97/1.18) | AB97: =R97*0.05 | AC97: =R97*0.03 | AD97: 0 | AE97: 3299 | AF97: 7499
A98: FBA78203 | B98: B0C4YTNJG7 | C98: AM-C30 | D98: Microphone | E98: RGB USB Microphone Kit - Tripod | F98: 0.11 | G98: AM-C30 | H98: 85181000 | I98: 25 | J98: ='Edit Parameters'!$B$2/('Edit Parameters'!$B$3/N98) | K98: 23.6 | L98: 18 | M98: 11.6 | N98: =(K98*L98*M98)/1000000 | O98: 15 | P98: =(I98+J98)*(O98%+(O98%*10%)) | Q98: =(I98+J98+P98)*'Edit Parameters'!B$1 | R98: =Q98*1.18 | S98: 11 | T98: 51 | U98: 17 | V98: 10 | W98: 2 | X98: 5 | Y98: 0 | Z98: 18 | AA98: =AE98-(AE98/1.18) | AB98: =R98*0.05 | AC98: =R98*0.03 | AD98: 0 | AE98: 3299 | AF98: 8999 | AI98: 2149
A99: FBA76744 | B99: B0BLK7VQ2N | C99: AM-K3 | D99: Microphone | E99: Instrument Microphone - Drum Kit | F99: 0.11 | G99: AM-K3 | H99: 85181000 | I99: 76.8 | J99: ='Edit Parameters'!$B$2/('Edit Parameters'!$B$3/N99) | K99: 42.9 | L99: 32.7 | M99: 9.7 | N99: =(K99*L99*M99)/1000000 | O99: 15 | P99: =(I99+J99)*(O99%+(O99%*10%)) | Q99: =(I99+J99+P99)*'Edit Parameters'!B$1 | R99: =Q99*1.18 | S99: 11 | T99: 51 | U99: 32 | V99: 10 | W99: 2 | X99: 5 | Y99: 0 | Z99: 18 | AA99: =AE99-(AE99/1.18) | AB99: =R99*0.05 | AC99: =R99*0.03 | AD99: 0 | AE99: 12499 | AF99: 29999
A100: FBK79708 | B100: B0FJS7JZ4V | C100: SB-01 | D100: Speaker | E100: Sound Bar | F100: 0.14 | G100: SB-01 | H100: 85182290 | I100: 0 | J100: ='Edit Parameters'!$B$2/('Edit Parameters'!$B$3/N100) | K100: 41 | L100: 12.2 | M100: 11.6 | N100: =(K100*L100*M100)/1000000 | O100: 0 | P100: =(I100+J100)*(O100%+(O100%*10%)) | Q100: =(I100+J100+P100)*'Edit Parameters'!B$1 | R100: =Q100*1.18 | S100: 14 | T100: 51 | U100: 115 | V100: 10 | W100: 2 | X100: 5 | Y100: 0 | Z100: 18 | AA100: =AE100-(AE100/1.18) | AB100: =R100*0.05 | AC100: =R100*0.03 | AD100: 0 | AE100: #N/A | AF100: #N/A | AI100: 1299
A101: FBA77011 | B101: B0BPMN89NG | C101: AM-C29 | D101: Microphone | E101: USB Microphone Kit - Tripod | F101: 0.11 | G101: AM-C29 | H101: 85181000 | I101: 27.5 | J101: ='Edit Parameters'!$B$2/('Edit Parameters'!$B$3/N101) | K101: 21.3 | L101: 13 | M101: 11.7 | N101: =(K101*L101*M101)/1000000 | O101: 15 | P101: =(I101+J101)*(O101%+(O101%*10%)) | Q101: =(I101+J101+P101)*'Edit Parameters'!B$1 | R101: =Q101*1.18 | S101: 11 | T101: 51 | U101: 17 | V101: 10 | W101: 2 | X101: 5 | Y101: 0 | Z101: 18 | AA101: =AE101-(AE101/1.18) | AB101: =R101*0.05 | AC101: =R101*0.03 | AD101: 0 | AE101: 4499 | AF101: 9999
A102: FBA76743 | B102: B0BLK8PXNY | C102: AM-K2 | D102: Microphone | E102: Instrument Microphone - Drum Kit | F102: 0.11 | G102: AM-K2 | H102: 85181000 | I102: 66.2 | J102: ='Edit Parameters'!$B$2/('Edit Parameters'!$B$3/N102) | K102: 33.8 | L102: 31.7 | M102: 10 | N102: =(K102*L102*M102)/1000000 | O102: 15 | P102: =(I102+J102)*(O102%+(O102%*10%)) | Q102: =(I102+J102+P102)*'Edit Parameters'!B$1 | R102: =Q102*1.18 | S102: 11 | T102: 51 | U102: 27 | V102: 10 | W102: 2 | X102: 5 | Y102: 0 | Z102: 18 | AA102: =AE102-(AE102/1.18) | AB102: =R102*0.05 | AC102: =R102*0.03 | AD102: 0 | AE102: 10499 | AF102: 24999
A103: FBA79070 | B103: B0CLH7G5WH | C103: AI-02 2x2| Metallic Red | D103: Audio Interface | E103: Audio Interface | F103: 0.11 | G103: AI-02 2x2| Metallic Red | H103: 85437029 | I103: 31 | J103: ='Edit Parameters'!$B$2/('Edit Parameters'!$B$3/N103) | K103: 22.9 | L103: 14.9 | M103: 5.9 | N103: =(K103*L103*M103)/1000000 | O103: 7.5 | P103: =(I103+J103)*(O103%+(O103%*10%)) | Q103: =(I103+J103+P103)*'Edit Parameters'!B$1 | R103: =Q103*1.18 | S103: 11 | T103: 51 | U103: 17 | V103: 10 | W103: 2 | X103: 5 | Y103: 0 | Z103: 18 | AA103: =AE103-(AE103/1.18) | AB103: =R103*0.05 | AC103: =R103*0.03 | AD103: 0 | AE103: 6499 | AF103: 12499
A104: FBA78420 | B104: B0C5957W3P | C104: AM-C33 | D104: Microphone | E104: WiredLavalier Microphone | F104: 0.045 | G104: AM-C33 | H104: 85181000 | I104: 3.85 | J104: ='Edit Parameters'!$B$2/('Edit Parameters'!$B$3/N104) | K104: 12.1 | L104: 9.2 | M104: 3.7 | N104: =(K104*L104*M104)/1000000 | O104: 15 | P104: =(I104+J104)*(O104%+(O104%*10%)) | Q104: =(I104+J104+P104)*'Edit Parameters'!B$1 | R104: =Q104*1.18 | S104: 4.5 | T104: 21 | U104: 17 | V104: 10 | W104: 2 | X104: 5 | Y104: 0 | Z104: 18 | AA104: =AE104-(AE104/1.18) | AB104: =R104*0.05 | AC104: =R104*0.03 | AD104: 0 | AE104: 499 | AF104: 1599
A105: FBA79814 | B105: - | C105: AH-50 Ear Cushion | D105: Headphone Accessories | E105: Headphone Accessories | F105: 0.11 | G105: AH-50 Ear Cushion | H105: 85189000 | I105: 0.45 | J105: ='Edit Parameters'!$B$2/('Edit Parameters'!$B$3/N105) | N105: =(K105*L105*M105)/1000000 | O105: 15 | P105: =(I105+J105)*(O105%+(O105%*10%)) | Q105: =(I105+J105+P105)*'Edit Parameters'!B$1 | R105: =Q105*1.18 | S105: 11 | U105: 0 | V105: 10 | W105: 2 | X105: 5 | Y105: 0 | Z105: 18 | AA105: =AE105-(AE105/1.18) | AB105: =R105*0.05 | AC105: =R105*0.03 | AD105: 0 | AE105: 499 | AF105: 799
A106: FBA75682 | B106: B0B4FVV78V | C106: AM-C8 | D106: Microphone | E106: USB Microphone Kit - Tripod | F106: 0.11 | G106: AM-C8 | H106: 85181000 | I106: 26.5 | J106: ='Edit Parameters'!$B$2/('Edit Parameters'!$B$3/N106) | K106: 26 | L106: 14.3 | M106: 10.9 | N106: =(K106*L106*M106)/1000000 | O106: 15 | P106: =(I106+J106)*(O106%+(O106%*10%)) | Q106: =(I106+J106+P106)*'Edit Parameters'!B$1 | R106: =Q106*1.18 | S106: 11 | T106: 51 | U106: 17 | V106: 10 | W106: 2 | X106: 5 | Y106: 0 | Z106: 18 | AA106: =AE106-(AE106/1.18) | AB106: =R106*0.05 | AC106: =R106*0.03 | AD106: 0 | AE106: 4999 | AF106: 9999
A107: FBA75685 | B107: B0B4FXDHXW | C107: AM-C9 | D107: Microphone | E107: USB Microphone Kit - Tripod | F107: 0.11 | G107: AM-C9 | H107: 85181000 | I107: 26 | J107: ='Edit Parameters'!$B$2/('Edit Parameters'!$B$3/N107) | K107: 17.8 | L107: 12.8 | M107: 12.7 | N107: =(K107*L107*M107)/1000000 | O107: 15 | P107: =(I107+J107)*(O107%+(O107%*10%)) | Q107: =(I107+J107+P107)*'Edit Parameters'!B$1 | R107: =Q107*1.18 | S107: 11 | T107: 51 | U107: 17 | V107: 10 | W107: 2 | X107: 5 | Y107: 0 | Z107: 18 | AA107: =AE107-(AE107/1.18) | AB107: =R107*0.05 | AC107: =R107*0.03 | AD107: 0 | AE107: 4499 | AF107: 9999
A108: FBA78425 | B108: B0C55QXL83 | C108: AM-C38 | D108: Microphone | E108: Condenser Shotgun Mic | F108: 0.11 | G108: AM-C38 | H108: 85181000 | I108: 10.32 | J108: ='Edit Parameters'!$B$2/('Edit Parameters'!$B$3/N108) | K108: 18.1 | L108: 14.2 | M108: 6 | N108: =(K108*L108*M108)/1000000 | O108: 15 | P108: =(I108+J108)*(O108%+(O108%*10%)) | Q108: =(I108+J108+P108)*'Edit Parameters'!B$1 | R108: =Q108*1.18 | S108: 11 | T108: 51 | U108: 17 | V108: 10 | W108: 2 | X108: 5 | Y108: 0 | Z108: 18 | AA108: =AE108-(AE108/1.18) | AB108: =R108*0.05 | AC108: =R108*0.03 | AD108: 0 | AE108: 1999 | AF108: 4399
A109: FBA76726 | B109: B0BLKD4815 | C109: AM-C23 | D109: Microphone | E109: USB Microphone Kit - Tripod | F109: 0.11 | G109: AM-C23 | H109: 85181000 | I109: 13.02 | J109: ='Edit Parameters'!$B$2/('Edit Parameters'!$B$3/N109) | K109: 24 | L109: 13.3 | M109: 11.9 | N109: =(K109*L109*M109)/1000000 | O109: 15 | P109: =(I109+J109)*(O109%+(O109%*10%)) | Q109: =(I109+J109+P109)*'Edit Parameters'!B$1 | R109: =Q109*1.18 | S109: 11 | T109: 51 | U109: 17 | V109: 10 | W109: 2 | X109: 5 | Y109: 0 | Z109: 18 | AA109: =AE109-(AE109/1.18) | AB109: =R109*0.05 | AC109: =R109*0.03 | AD109: 0 | AE109: 2399 | AF109: 5799
A110: FBA76739 | B110: B0BLRK37TB | C110: AA-12 | D110: Microphone Accessories | E110: Boom Arm | F110: 0.11 | G110: AA-12 | H110: 85189000 | I110: 11.67 | J110: ='Edit Parameters'!$B$2/('Edit Parameters'!$B$3/N110) | K110: 58.3 | L110: 20.7 | M110: 5.5 | N110: =(K110*L110*M110)/1000000 | O110: 15 | P110: =(I110+J110)*(O110%+(O110%*10%)) | Q110: =(I110+J110+P110)*'Edit Parameters'!B$1 | R110: =Q110*1.18 | S110: 11 | T110: 51 | U110: 22 | V110: 10 | W110: 2 | X110: 5 | Y110: 0 | Z110: 18 | AA110: =AE110-(AE110/1.18) | AB110: =R110*0.05 | AC110: =R110*0.03 | AD110: 0 | AE110: 2699 | AF110: 5399
A111: FBA79014 | B111: B0CH4WFQF6 | C111: AI-09 | D111: Pro Audio Tools | E111: DI box | F111: 0.11 | G111: AI-09 | H111: 85437029 | I111: 28.8 | J111: ='Edit Parameters'!$B$2/('Edit Parameters'!$B$3/N111) | K111: 22.1 | L111: 15 | M111: 8.2 | N111: =(K111*L111*M111)/1000000 | O111: 7.5 | P111: =(I111+J111)*(O111%+(O111%*10%)) | Q111: =(I111+J111+P111)*'Edit Parameters'!B$1 | R111: =Q111*1.18 | S111: 11 | T111: 51 | U111: 17 | V111: 10 | W111: 2 | X111: 5 | Y111: 0 | Z111: 18 | AA111: =AE111-(AE111/1.18) | AB111: =R111*0.05 | AC111: =R111*0.03 | AD111: 0 | AE111: 5499 | AF111: 14299
A112: FBA76718 | B112: B0BLKD8FVG | C112: AM-C15 | D112: Microphone | E112: WiredLavalier Microphone | F112: 0.11 | G112: AM-C15 | H112: 85181000 | I112: 11.11 | J112: ='Edit Parameters'!$B$2/('Edit Parameters'!$B$3/N112) | K112: 13.2 | L112: 9.6 | M112: 3.6 | N112: =(K112*L112*M112)/1000000 | O112: 15 | P112: =(I112+J112)*(O112%+(O112%*10%)) | Q112: =(I112+J112+P112)*'Edit Parameters'!B$1 | R112: =Q112*1.18 | S112: 11 | T112: 51 | U112: 17 | V112: 10 | W112: 2 | X112: 5 | Y112: 0 | Z112: 18 | AA112: =AE112-(AE112/1.18) | AB112: =R112*0.05 | AC112: =R112*0.03 | AD112: 0 | AE112: 1999 | AF112: 5399
A113: FBA76734 | B113: B0BLKHVCDX | C113: AA-07 | D113: Microphone Accessories | E113: Boom Arm | F113: 0.11 | G113: AA-07 | H113: 85189000 | I113: 8 | J113: ='Edit Parameters'!$B$2/('Edit Parameters'!$B$3/N113) | K113: 30.3 | L113: 18.9 | M113: 17.9 | N113: =(K113*L113*M113)/1000000 | O113: 15 | P113: =(I113+J113)*(O113%+(O113%*10%)) | Q113: =(I113+J113+P113)*'Edit Parameters'!B$1 | R113: =Q113*1.18 | S113: 11 | T113: 51 | U113: 27 | V113: 10 | W113: 2 | X113: 5 | Y113: 0 | Z113: 18 | AA113: =AE113-(AE113/1.18) | AB113: =R113*0.05 | AC113: =R113*0.03 | AD113: 0 | AE113: 2199 | AF113: 4699
A114: FBA78419 | B114: B0C55M2GBN | C114: AM-A1 | D114: Microphone Accessories | E114: Mic Activator | F114: 0.11 | G114: AM-A1 | H114: 85437029 | I114: 14.5 | J114: ='Edit Parameters'!$B$2/('Edit Parameters'!$B$3/N114) | K114: 13.1 | L114: 6.4 | M114: 5.7 | N114: =(K114*L114*M114)/1000000 | O114: 15 | P114: =(I114+J114)*(O114%+(O114%*10%)) | Q114: =(I114+J114+P114)*'Edit Parameters'!B$1 | R114: =Q114*1.18 | S114: 11 | T114: 51 | U114: 17 | V114: 10 | W114: 2 | X114: 5 | Y114: 0 | Z114: 18 | AA114: =AE114-(AE114/1.18) | AB114: =R114*0.05 | AC114: =R114*0.03 | AD114: 0 | AE114: 2199 | AF114: 5999
A115: FBA78972 | B115: B0CF5T89FT | C115: AA-18 | D115: Microphone Accessories | E115: Boom Arm | F115: 0.11 | G115: AA-18 | H115: 85189000 | I115: 13 | J115: ='Edit Parameters'!$B$2/('Edit Parameters'!$B$3/N115) | K115: 65.8 | L115: 17.6 | M115: 7 | N115: =(K115*L115*M115)/1000000 | O115: 15 | P115: =(I115+J115)*(O115%+(O115%*10%)) | Q115: =(I115+J115+P115)*'Edit Parameters'!B$1 | R115: =Q115*1.18 | S115: 11 | T115: 51 | U115: 22 | V115: 10 | W115: 2 | X115: 5 | Y115: 0 | Z115: 18 | AA115: =AE115-(AE115/1.18) | AB115: =R115*0.05 | AC115: =R115*0.03 | AD115: 0 | AE115: 3699 | AF115: 7399
A116: FBA78423 | B116: B0C598Q6PT | C116: AM-C36 | D116: Microphone | E116: WiredLavalier Microphone | F116: 0.055 | G116: AM-C36 | H116: 85181000 | I116: 3.52 | J116: ='Edit Parameters'!$B$2/('Edit Parameters'!$B$3/N116) | K116: 12.1 | L116: 9.2 | M116: 3.7 | N116: =(K116*L116*M116)/1000000 | O116: 15 | P116: =(I116+J116)*(O116%+(O116%*10%)) | Q116: =(I116+J116+P116)*'Edit Parameters'!B$1 | R116: =Q116*1.18 | S116: 5.5 | T116: 51 | U116: 17 | V116: 10 | W116: 2 | X116: 5 | Y116: 0 | Z116: 18 | AA116: =AE116-(AE116/1.18) | AB116: =R116*0.05 | AC116: =R116*0.03 | AD116: 0 | AE116: 699 | AF116: 1999
A117: FBA76715 | B117: B0BLK31PYH | C117: AM-C12 | D117: Microphone | E117: WiredLavalier Microphone | F117: 0.055 | G117: AM-C12 | H117: 85181000 | I117: 4.25 | J117: ='Edit Parameters'!$B$2/('Edit Parameters'!$B$3/N117) | K117: 13.2 | L117: 9.1 | M117: 4.7 | N117: =(K117*L117*M117)/1000000 | O117: 15 | P117: =(I117+J117)*(O117%+(O117%*10%)) | Q117: =(I117+J117+P117)*'Edit Parameters'!B$1 | R117: =Q117*1.18 | S117: 5.5 | T117: 51 | U117: 17 | V117: 10 | W117: 2 | X117: 5 | Y117: 0 | Z117: 18 | AA117: =AE117-(AE117/1.18) | AB117: =R117*0.05 | AC117: =R117*0.03 | AD117: 0 | AE117: 899 | AF117: 2999
... A119: FBA76735 | B119: B0BLKGPL4X | C119: AA-08 | D119: Microphone Accessories | E119: Sound Isolation Shield | F119: 0.11 | G119: AA-08 | H119: 85189000 | I119: 12.2 | J119: ='Edit Parameters'!$B$2/('Edit Parameters'!$B$3/N119) | K119: 30.3 | L119: 19 | M119: 18.2 | N119: =(K119*L119*M119)/1000000 | O119: 15 | P119: =(I119+J119)*(O119%+(O119%*10%)) | Q119: =(I119+J119+P119)*'Edit Parameters'!B$1 | R119: =Q119*1.18 | S119: 11 | T119: 51 | U119: 27 | V119: 10 | W119: 2 | X119: 5 | Y119: 0 | Z119: 18 | AA119: =AE119-(AE119/1.18) | AB119: =R119*0.05 | AC119: =R119*0.03 | AD119: 0 | AE119: 2399 | AF119: 5699
A120: FBA76732 | B120: B0BLKCB2JY | C120: AI-01 | D120: Audio Interface | E120: Audio Interface | F120: 0.06 | G120: AI-01 | H120: 85437029 | I120: 23.02 | J120: ='Edit Parameters'!$B$2/('Edit Parameters'!$B$3/N120) | K120: 28.5 | L120: 20.5 | M120: 6.8 | N120: =(K120*L120*M120)/1000000 | O120: 7.5 | P120: =(I120+J120)*(O120%+(O120%*10%)) | Q120: =(I120+J120+P120)*'Edit Parameters'!B$1 | R120: =Q120*1.18 | S120: 6 | T120: 51 | U120: 17 | V120: 10 | W120: 2 | X120: 5 | Y120: 0 | Z120: 18 | AA120: =AE120-(AE120/1.18) | AB120: =R120*0.05 | AC120: =R120*0.03 | AD120: 0 | AE120: #N/A | AF120: 8399
A121: FBA76720 | B121: B0BLKCWZQD | C121: AM-C17 | D121: Microphone | E121: WiredLavalier Microphone | F121: 0.045 | G121: AM-C17 | H121: 85181000 | I121: 2.9 | J121: ='Edit Parameters'!$B$2/('Edit Parameters'!$B$3/N121) | K121: 12 | L121: 9.1 | M121: 3.7 | N121: =(K121*L121*M121)/1000000 | O121: 15 | P121: =(I121+J121)*(O121%+(O121%*10%)) | Q121: =(I121+J121+P121)*'Edit Parameters'!B$1 | R121: =Q121*1.18 | S121: 4.5 | T121: 51 | U121: 17 | V121: 10 | W121: 2 | X121: 5 | Y121: 0 | Z121: 18 | AA121: =AE121-(AE121/1.18) | AB121: =R121*0.05 | AC121: =R121*0.03 | AD121: 0 | AE121: 425 | AF121: 1699
A122: FBA76725 | B122: B0BLKCSJ7Z | C122: AM-C22 | D122: Microphone | E122: USB Microphone Kit - Tripod | F122: 0.11 | G122: AM-C22 | H122: 85181000 | I122: 6.5 | J122: ='Edit Parameters'!$B$2/('Edit Parameters'!$B$3/N122) | K122: 19.5 | L122: 12.9 | M122: 6.7 | N122: =(K122*L122*M122)/1000000 | O122: 15 | P122: =(I122+J122)*(O122%+(O122%*10%)) | Q122: =(I122+J122+P122)*'Edit Parameters'!B$1 | R122: =Q122*1.18 | S122: 11 | T122: 51 | U122: 17 | V122: 10 | W122: 2 | X122: 5 | Y122: 0 | Z122: 18 | AA122: =AE122-(AE122/1.18) | AB122: =R122*0.05 | AC122: =R122*0.03 | AD122: 0 | AE122: 1499 | AF122: 5299
A123: FBA78422 | B123: B0C598MNMC | C123: AM-C35 | D123: Microphone | E123: WiredLavalier Microphone | F123: 0.045 | G123: AM-C35 | H123: 85181000 | I123: 2.82 | J123: ='Edit Parameters'!$B$2/('Edit Parameters'!$B$3/N123) | K123: 12.1 | L123: 9.2 | M123: 3.7 | N123: =(K123*L123*M123)/1000000 | O123: 15 | P123: =(I123+J123)*(O123%+(O123%*10%)) | Q123: =(I123+J123+P123)*'Edit Parameters'!B$1 | R123: =Q123*1.18 | S123: 4.5 | T123: 51 | U123: 17 | V123: 10 | W123: 2 | X123: 5 | Y123: 0 | Z123: 18 | AA123: =AE123-(AE123/1.18) | AB123: =R123*0.05 | AC123: =R123*0.03 | AD123: 0 | AE123: 599 | AF123: 1799
A124: FBA79013 | B124: B0CH4TDGPG | C124: AI-08 | D124: Pro Audio Tools | E124: Line Mixer | F124: 0.11 | G124: AI-08 | H124: 85437029 | I124: 11.3 | J124: ='Edit Parameters'!$B$2/('Edit Parameters'!$B$3/N124) | K124: 20 | L124: 13.6 | M124: 5.6 | N124: =(K124*L124*M124)/1000000 | O124: 7.5 | P124: =(I124+J124)*(O124%+(O124%*10%)) | Q124: =(I124+J124+P124)*'Edit Parameters'!B$1 | R124: =Q124*1.18 | S124: 11 | T124: 51 | U124: 17 | V124: 10 | W124: 2 | X124: 5 | Y124: 0 | Z124: 18 | AA124: =AE124-(AE124/1.18) | AB124: =R124*0.05 | AC124: =R124*0.03 | AD124: 0 | AE124: 2599 | AF124: 5599
...

Sheet Edit Parameters
A1: Dollar Conversion Rate | B1: 95
A2: 40HQ Freight+Clearance | B2: 2000
A3: 40HQ Usable CBM | B3: 68
A4: Fulfillment Rate/kg | B4: 40
A5: Surcharge | B5: 0.1
A6: Referral Fee (<15001) | B6: 0.15
A7: Referral Fee (>15000) | B7: 0.1
A8: AMS | B8: 0.15
A9: Returns and Repairs | B9: 0.05
A10: Overheads | B10: 0.05
A11: Finance | B11: 0.03
A12: Coupon | B12: 0.02
... A15: SMM | B15: 0
